Workbook

Sheet Instructions
A1: Monthly Budget Tracker — Instructions & Monthly Workflow
A3: A single-ledger cash-flow tracker. You record every income, expense and one-off item once on the Entries tab; the Monthly Summary and Dashboard rebuild themselves. This sheet is the manual — start with the checklist, details follow.
A5: THE TABS
A6: You edit three tabs: Entries (the ledger) · Budgets (your plan) · Categories (the master list).
A7: Read-only, automatic: Monthly Summary · Dashboard. Never type into these — they recalculate from the three above.
A8: Tool files that live in the same folder as this workbook: categorize_expenses.py · rules.csv (used in Step 2).
A10: YOUR MONTHLY ROUTINE — AT A GLANCE
A11: [ ] 1. Gather this month’s bank statement (.xlsx) and any credit-card bills you paid (.pdf).
A12: [ ] 2. Produce the categorised draft (send the files to Claude, or run the script).
A13: [ ] 3. Open the draft’s Validation tab (status must not be FAIL); fix amber flags, confirm categories, teach any new merchants.
A14: [ ] 4. Paste the draft’s "Entries draft" rows into the Entries tab.
A15: [ ] 5. (Nothing to do — Monthly Summary fills in the new month automatically.)
... A71: The bank parser is tuned to the UOB One Account layout and the bill parser to the UOB card format. A different bank or card bill needs a small parser addition — add a matching BANK_FORMATS / CARD_FORMATS entry (see the TEMPLATE blocks).

Sheet Dashboard
A1: Monthly Budget Tracker — Dashboard
A2: Everything updates from the Entries ledger. This sheet is locked (read-only).
A4: Latest month | C4: Cash saved (operating, cumulative) | E4: Rolling savings ratio (12m) | G4: Avg monthly spend (12m)
A5: =TEXT(LOOKUP(2,1/('Monthly Summary'!$C$2:$C$400<>""),'Monthly Summary'!$A$2:$A$400),"mmm yyyy") | C5: =LOOKUP(2,1/('Monthly Summary'!$C$2:$C$400<>""),'Monthly Summary'!$J$2:$J$400) | E5: =LOOKUP(2,1/('Monthly Summary'!$C$2:$C$400<>""),'Monthly Summary'!$M$2:$M$400) | G5: =LOOKUP(2,1/('Monthly Summary'!$C$2:$C$400<>""),'Monthly Summary'!$L$2:$L$400)
A39: Budget vs Actual — latest month (helper for chart)
A40: Category | B40: Actual | C40: Budget | E40: Latest month: | F40: =LOOKUP(2,1/('Monthly Summary'!$C$2:$C$400<>""),'Monthly Summary'!$A$2:$A$400)
A41: Daily Food | B41: =SUMIFS(Entries!$D$2:$D$5000,Entries!$C$2:$C$5000,"Actual",Entries!$A$2:$A$5000,$F$40,Entries!$B$2:$B$5000,$A41) | C41: =IFERROR(LOOKUP(2,1/((Budgets!$A$2:$A$200=$A41)*(Budgets!$B$2:$B$200<=$F$40)),Budgets!$C$2:$C$200),0)
A42: Transport | B42: =SUMIFS(Entries!$D$2:$D$5000,Entries!$C$2:$C$5000,"Actual",Entries!$A$2:$A$5000,$F$40,Entries!$B$2:$B$5000,$A42) | C42: =IFERROR(LOOKUP(2,1/((Budgets!$A$2:$A$200=$A42)*(Budgets!$B$2:$B$200<=$F$40)),Budgets!$C$2:$C$200),0)
A43: Credit Card | B43: =SUMIFS(Entries!$D$2:$D$5000,Entries!$C$2:$C$5000,"Actual",Entries!$A$2:$A$5000,$F$40,Entries!$B$2:$B$5000,$A43) | C43: =IFERROR(LOOKUP(2,1/((Budgets!$A$2:$A$200=$A43)*(Budgets!$B$2:$B$200<=$F$40)),Budgets!$C$2:$C$200),0)
A44: Household | B44: =SUMIFS(Entries!$D$2:$D$5000,Entries!$C$2:$C$5000,"Actual",Entries!$A$2:$A$5000,$F$40,Entries!$B$2:$B$5000,$A44) | C44: =IFERROR(LOOKUP(2,1/((Budgets!$A$2:$A$200=$A44)*(Budgets!$B$2:$B$200<=$F$40)),Budgets!$C$2:$C$200),0)
A45: Tax | B45: =SUMIFS(Entries!$D$2:$D$5000,Entries!$C$2:$C$5000,"Actual",Entries!$A$2:$A$5000,$F$40,Entries!$B$2:$B$5000,$A45) | C45: =IFERROR(LOOKUP(2,1/((Budgets!$A$2:$A$200=$A45)*(Budgets!$B$2:$B$200<=$F$40)),Budgets!$C$2:$C$200),0)
A46: Savings for holiday | B46: =SUMIFS(Entries!$D$2:$D$5000,Entries!$C$2:$C$5000,"Actual",Entries!$A$2:$A$5000,$F$40,Entries!$B$2:$B$5000,$A46) | C46: =IFERROR(LOOKUP(2,1/((Budgets!$A$2:$A$200=$A46)*(Budgets!$B$2:$B$200<=$F$40)),Budgets!$C$2:$C$200),0)
A47: Bills | B47: =SUMIFS(Entries!$D$2:$D$5000,Entries!$C$2:$C$5000,"Actual",Entries!$A$2:$A$5000,$F$40,Entries!$B$2:$B$5000,$A47) | C47: =IFERROR(LOOKUP(2,1/((Budgets!$A$2:$A$200=$A47)*(Budgets!$B$2:$B$200<=$F$40)),Budgets!$C$2:$C$200),0)
A48: Insurance | B48: =SUMIFS(Entries!$D$2:$D$5000,Entries!$C$2:$C$5000,"Actual",Entries!$A$2:$A$5000,$F$40,Entries!$B$2:$B$5000,$A48) | C48: =IFERROR(LOOKUP(2,1/((Budgets!$A$2:$A$200=$A48)*(Budgets!$B$2:$B$200<=$F$40)),Budgets!$C$2:$C$200),0)
A49: Donation | B49: =SUMIFS(Entries!$D$2:$D$5000,Entries!$C$2:$C$5000,"Actual",Entries!$A$2:$A$5000,$F$40,Entries!$B$2:$B$5000,$A49) | C49: =IFERROR(LOOKUP(2,1/((Budgets!$A$2:$A$200=$A49)*(Budgets!$B$2:$B$200<=$F$40)),Budgets!$C$2:$C$200),0)
A50: Groceries | B50: =SUMIFS(Entries!$D$2:$D$5000,Entries!$C$2:$C$5000,"Actual",Entries!$A$2:$A$5000,$F$40,Entries!$B$2:$B$5000,$A50) | C50: =IFERROR(LOOKUP(2,1/((Budgets!$A$2:$A$200=$A50)*(Budgets!$B$2:$B$200<=$F$40)),Budgets!$C$2:$C$200),0)
A51: Subscriptions | B51: =SUMIFS(Entries!$D$2:$D$5000,Entries!$C$2:$C$5000,"Actual",Entries!$A$2:$A$5000,$F$40,Entries!$B$2:$B$5000,$A51) | C51: =IFERROR(LOOKUP(2,1/((Budgets!$A$2:$A$200=$A51)*(Budgets!$B$2:$B$200<=$F$40)),Budgets!$C$2:$C$200),0)
A52: Shopping | B52: =SUMIFS(Entries!$D$2:$D$5000,Entries!$C$2:$C$5000,"Actual",Entries!$A$2:$A$5000,$F$40,Entries!$B$2:$B$5000,$A52) | C52: =IFERROR(LOOKUP(2,1/((Budgets!$A$2:$A$200=$A52)*(Budgets!$B$2:$B$200<=$F$40)),Budgets!$C$2:$C$200),0)
... A56: Household Help | B56: =SUMIFS(Entries!$D$2:$D$5000,Entries!$C$2:$C$5000,"Actual",Entries!$A$2:$A$5000,$F$40,Entries!$B$2:$B$5000,$A56) | C56: =IFERROR(LOOKUP(2,1/((Budgets!$A$2:$A$200=$A56)*(Budgets!$B$2:$B$200<=$F$40)),Budgets!$C$2:$C$200),0)

Sheet Monthly Summary
A1: Month | B1: Total Income | C1: Total Actual | D1: Total One-off | E1: Total Spend | F1: Total Budget | G1: Net Cash | H1: Cumulative Cash | I1: Capital Outflow | J1: Cumulative (operating) | K1: Rolling Income 12m | L1: Rolling Spend 12m | M1: Rolling Savings Ratio | O1: =IFERROR(INDEX(Categories!$A$2:$A$200,MATCH(1,Categories!$F$2:$F$200,0)),"") | P1: =IFERROR(INDEX(Categories!$A$2:$A$200,MATCH(2,Categories!$F$2:$F$200,0)),"") | Q1: =IFERROR(INDEX(Categories!$A$2:$A$200,MATCH(3,Categories!$F$2:$F$200,0)),"") | R1: =IFERROR(INDEX(Categories!$A$2:$A$200,MATCH(4,Categories!$F$2:$F$200,0)),"") | S1: =IFERROR(INDEX(Categories!$A$2:$A$200,MATCH(5,Categories!$F$2:$F$200,0)),"") | T1: =IFERROR(INDEX(Categories!$A$2:$A$200,MATCH(6,Categories!$F$2:$F$200,0)),"") | U1: =IFERROR(INDEX(Categories!$A$2:$A$200,MATCH(7,Categories!$F$2:$F$200,0)),"") | V1: =IFERROR(INDEX(Categories!$A$2:$A$200,MATCH(8,Categories!$F$2:$F$200,0)),"") | W1: =IFERROR(INDEX(Categories!$A$2:$A$200,MATCH(9,Categories!$F$2:$F$200,0)),"") | X1: =IFERROR(INDEX(Categories!$A$2:$A$200,MATCH(10,Categories!$F$2:$F$200,0)),"") | Y1: =IFERROR(INDEX(Categories!$A$2:$A$200,MATCH(11,Categories!$F$2:$F$200,0)),"") | Z1: =IFERROR(INDEX(Categories!$A$2:$A$200,MATCH(12,Categories!$F$2:$F$200,0)),"") | AA1: =IFERROR(INDEX(Categories!$A$2:$A$200,MATCH(13,Categories!$F$2:$F$200,0)),"") | AB1: =IFERROR(INDEX(Categories!$A$2:$A$200,MATCH(14,Categories!$F$2:$F$200,0)),"") | AC1: =IFERROR(INDEX(Categories!$A$2:$A$200,MATCH(15,Categories!$F$2:$F$200,0)),"") | AD1: =IFERROR(INDEX(Categories!$A$2:$A$200,MATCH(16,Categories!$F$2:$F$200,0)),"") | AE1: =IFERROR(INDEX(Categories!$A$2:$A$200,MATCH(17,Categories!$F$2:$F$200,0)),"") | AF1: =IFERROR(INDEX(Categories!$A$2:$A$200,MATCH(18,Categories!$F$2:$F$200,0)),"") | AG1: =IFERROR(INDEX(Categories!$A$2:$A$200,MATCH(19,Categories!$F$2:$F$200,0)),"") | AH1: =IFERROR(INDEX(Categories!$A$2:$A$200,MATCH(20,Categories!$F$2:$F$200,0)),"") | AJ1: =O$1 | AK1: =P$1 | AL1: =Q$1 | AM1: =R$1 | AN1: =S$1 | AO1: =T$1 | AP1: =U$1 | AQ1: =V$1 | ... BC1: =AH$1 | BE1: _active
A2: 39448 | B2: =IF($BE2=0,NA(),SUMIFS(Entries!$D$2:$D$5000,Entries!$C$2:$C$5000,"Income",Entries!$A$2:$A$5000,$A2)) | C2: =IF($BE2=0,"",SUMIFS(Entries!$D$2:$D$5000,Entries!$C$2:$C$5000,"Actual",Entries!$A$2:$A$5000,$A2)) | D2: =IF($BE2=0,"",SUMIFS(Entries!$D$2:$D$5000,Entries!$C$2:$C$5000,"One-off",Entries!$A$2:$A$5000,$A2)) | E2: =IF($BE2=0,NA(),C2+D2) | F2: =IF($BE2=0,"",SUM(AJ2:BC2)) | G2: =IF($BE2=0,"",B2-E2) | H2: =IF($BE2=0,"",SUM($G$2:G2)) | I2: =IF($BE2=0,"",SUMIFS(Entries!$F$2:$F$5000,Entries!$A$2:$A$5000,$A2)) | J2: =IF($BE2=0,NA(),H2+SUM($I$2:I2)) | K2: ="" | L2: ="" | M2: =NA() | O2: =IF(OR(O$1="",$BE2=0),"",SUMIFS(Entries!$D$2:$D$5000,Entries!$C$2:$C$5000,"Actual",Entries!$A$2:$A$5000,$A2,Entries!$B$2:$B$5000,O$1)) | P2: =IF(OR(P$1="",$BE2=0),"",SUMIFS(Entries!$D$2:$D$5000,Entries!$C$2:$C$5000,"Actual",Entries!$A$2:$A$5000,$A2,Entries!$B$2:$B$5000,P$1)) | Q2: =IF(OR(Q$1="",$BE2=0),"",SUMIFS(Entries!$D$2:$D$5000,Entries!$C$2:$C$5000,"Actual",Entries!$A$2:$A$5000,$A2,Entries!$B$2:$B$5000,Q$1)) | R2: =IF(OR(R$1="",$BE2=0),"",SUMIFS(Entries!$D$2:$D$5000,Entries!$C$2:$C$5000,"Actual",Entries!$A$2:$A$5000,$A2,Entries!$B$2:$B$5000,R$1)) | S2: =IF(OR(S$1="",$BE2=0),"",SUMIFS(Entries!$D$2:$D$5000,Entries!$C$2:$C$5000,"Actual",Entries!$A$2:$A$5000,$A2,Entries!$B$2:$B$5000,S$1)) | T2: =IF(OR(T$1="",$BE2=0),"",SUMIFS(Entries!$D$2:$D$5000,Entries!$C$2:$C$5000,"Actual",Entries!$A$2:$A$5000,$A2,Entries!$B$2:$B$5000,T$1)) | U2: =IF(OR(U$1="",$BE2=0),"",SUMIFS(Entries!$D$2:$D$5000,Entries!$C$2:$C$5000,"Actual",Entries!$A$2:$A$5000,$A2,Entries!$B$2:$B$5000,U$1)) | V2: =IF(OR(V$1="",$BE2=0),"",SUMIFS(Entries!$D$2:$D$5000,Entries!$C$2:$C$5000,"Actual",Entries!$A$2:$A$5000,$A2,Entries!$B$2:$B$5000,V$1)) | ... AH2: =IF(OR(AH$1="",$BE2=0),"",SUMIFS(Entries!$D$2:$D$5000,Entries!$C$2:$C$5000,"Actual",Entries!$A$2:$A$5000,$A2,Entries!$B$2:$B$5000,AH$1)) | AJ2: =IF(OR(AJ$1="",$BE2=0),"",IFERROR(LOOKUP(2,1/((Budgets!$A$2:$A$200=AJ$1)*(Budgets!$B$2:$B$200<=$A2)),Budgets!$C$2:$C$200),0)) | AK2: =IF(OR(AK$1="",$BE2=0),"",IFERROR(LOOKUP(2,1/((Budgets!$A$2:$A$200=AK$1)*(Budgets!$B$2:$B$200<=$A2)),Budgets!$C$2:$C$200),0)) | AL2: =IF(OR(AL$1="",$BE2=0),"",IFERROR(LOOKUP(2,1/((Budgets!$A$2:$A$200=AL$1)*(Budgets!$B$2:$B$200<=$A2)),Budgets!$C$2:$C$200),0)) | AM2: =IF(OR(AM$1="",$BE2=0),"",IFERROR(LOOKUP(2,1/((Budgets!$A$2:$A$200=AM$1)*(Budgets!$B$2:$B$200<=$A2)),Budgets!$C$2:$C$200),0)) | AN2: =IF(OR(AN$1="",$BE2=0),"",IFERROR(LOOKUP(2,1/((Budgets!$A$2:$A$200=AN$1)*(Budgets!$B$2:$B$200<=$A2)),Budgets!$C$2:$C$200),0)) | AO2: =IF(OR(AO$1="",$BE2=0),"",IFERROR(LOOKUP(2,1/((Budgets!$A$2:$A$200=AO$1)*(Budgets!$B$2:$B$200<=$A2)),Budgets!$C$2:$C$200),0)) | AP2: =IF(OR(AP$1="",$BE2=0),"",IFERROR(LOOKUP(2,1/((Budgets!$A$2:$A$200=AP$1)*(Budgets!$B$2:$B$200<=$A2)),Budgets!$C$2:$C$200),0)) | AQ2: =IF(OR(AQ$1="",$BE2=0),"",IFERROR(LOOKUP(2,1/((Budgets!$A$2:$A$200=AQ$1)*(Budgets!$B$2:$B$200<=$A2)),Budgets!$C$2:$C$200),0)) | ... BC2: =IF(OR(BC$1="",$BE2=0),"",IFERROR(LOOKUP(2,1/((Budgets!$A$2:$A$200=BC$1)*(Budgets!$B$2:$B$200<=$A2)),Budgets!$C$2:$C$200),0)) | BE2: =COUNTIFS(Entries!$A$2:$A$5000,$A2)
A3: 39479 | B3: =IF($BE3=0,NA(),SUMIFS(Entries!$D$2:$D$5000,Entries!$C$2:$C$5000,"Income",Entries!$A$2:$A$5000,$A3)) | C3: =IF($BE3=0,"",SUMIFS(Entries!$D$2:$D$5000,Entries!$C$2:$C$5000,"Actual",Entries!$A$2:$A$5000,$A3)) | D3: =IF($BE3=0,"",SUMIFS(Entries!$D$2:$D$5000,Entries!$C$2:$C$5000,"One-off",Entries!$A$2:$A$5000,$A3)) | E3: =IF($BE3=0,NA(),C3+D3) | F3: =IF($BE3=0,"",SUM(AJ3:BC3)) | G3: =IF($BE3=0,"",B3-E3) | H3: =IF($BE3=0,"",SUM($G$2:G3)) | I3: =IF($BE3=0,"",SUMIFS(Entries!$F$2:$F$5000,Entries!$A$2:$A$5000,$A3)) | J3: =IF($BE3=0,NA(),H3+SUM($I$2:I3)) | K3: ="" | L3: ="" | M3: =NA() | O3: =IF(OR(O$1="",$BE3=0),"",SUMIFS(Entries!$D$2:$D$5000,Entries!$C$2:$C$5000,"Actual",Entries!$A$2:$A$5000,$A3,Entries!$B$2:$B$5000,O$1)) | P3: =IF(OR(P$1="",$BE3=0),"",SUMIFS(Entries!$D$2:$D$5000,Entries!$C$2:$C$5000,"Actual",Entries!$A$2:$A$5000,$A3,Entries!$B$2:$B$5000,P$1)) | Q3: =IF(OR(Q$1="",$BE3=0),"",SUMIFS(Entries!$D$2:$D$5000,Entries!$C$2:$C$5000,"Actual",Entries!$A$2:$A$5000,$A3,Entries!$B$2:$B$5000,Q$1)) | R3: =IF(OR(R$1="",$BE3=0),"",SUMIFS(Entries!$D$2:$D$5000,Entries!$C$2:$C$5000,"Actual",Entries!$A$2:$A$5000,$A3,Entries!$B$2:$B$5000,R$1)) | S3: =IF(OR(S$1="",$BE3=0),"",SUMIFS(Entries!$D$2:$D$5000,Entries!$C$2:$C$5000,"Actual",Entries!$A$2:$A$5000,$A3,Entries!$B$2:$B$5000,S$1)) | T3: =IF(OR(T$1="",$BE3=0),"",SUMIFS(Entries!$D$2:$D$5000,Entries!$C$2:$C$5000,"Actual",Entries!$A$2:$A$5000,$A3,Entries!$B$2:$B$5000,T$1)) | U3: =IF(OR(U$1="",$BE3=0),"",SUMIFS(Entries!$D$2:$D$5000,Entries!$C$2:$C$5000,"Actual",Entries!$A$2:$A$5000,$A3,Entries!$B$2:$B$5000,U$1)) | V3: =IF(OR(V$1="",$BE3=0),"",SUMIFS(Entries!$D$2:$D$5000,Entries!$C$2:$C$5000,"Actual",Entries!$A$2:$A$5000,$A3,Entries!$B$2:$B$5000,V$1)) | ... AH3: =IF(OR(AH$1="",$BE3=0),"",SUMIFS(Entries!$D$2:$D$5000,Entries!$C$2:$C$5000,"Actual",Entries!$A$2:$A$5000,$A3,Entries!$B$2:$B$5000,AH$1)) | AJ3: =IF(OR(AJ$1="",$BE3=0),"",IFERROR(LOOKUP(2,1/((Budgets!$A$2:$A$200=AJ$1)*(Budgets!$B$2:$B$200<=$A3)),Budgets!$C$2:$C$200),0)) | AK3: =IF(OR(AK$1="",$BE3=0),"",IFERROR(LOOKUP(2,1/((Budgets!$A$2:$A$200=AK$1)*(Budgets!$B$2:$B$200<=$A3)),Budgets!$C$2:$C$200),0)) | AL3: =IF(OR(AL$1="",$BE3=0),"",IFERROR(LOOKUP(2,1/((Budgets!$A$2:$A$200=AL$1)*(Budgets!$B$2:$B$200<=$A3)),Budgets!$C$2:$C$200),0)) | AM3: =IF(OR(AM$1="",$BE3=0),"",IFERROR(LOOKUP(2,1/((Budgets!$A$2:$A$200=AM$1)*(Budgets!$B$2:$B$200<=$A3)),Budgets!$C$2:$C$200),0)) | AN3: =IF(OR(AN$1="",$BE3=0),"",IFERROR(LOOKUP(2,1/((Budgets!$A$2:$A$200=AN$1)*(Budgets!$B$2:$B$200<=$A3)),Budgets!$C$2:$C$200),0)) | AO3: =IF(OR(AO$1="",$BE3=0),"",IFERROR(LOOKUP(2,1/((Budgets!$A$2:$A$200=AO$1)*(Budgets!$B$2:$B$200<=$A3)),Budgets!$C$2:$C$200),0)) | AP3: =IF(OR(AP$1="",$BE3=0),"",IFERROR(LOOKUP(2,1/((Budgets!$A$2:$A$200=AP$1)*(Budgets!$B$2:$B$200<=$A3)),Budgets!$C$2:$C$200),0)) | AQ3: =IF(OR(AQ$1="",$BE3=0),"",IFERROR(LOOKUP(2,1/((Budgets!$A$2:$A$200=AQ$1)*(Budgets!$B$2:$B$200<=$A3)),Budgets!$C$2:$C$200),0)) | ... BC3: =IF(OR(BC$1="",$BE3=0),"",IFERROR(LOOKUP(2,1/((Budgets!$A$2:$A$200=BC$1)*(Budgets!$B$2:$B$200<=$A3)),Budgets!$C$2:$C$200),0)) | BE3: =COUNTIFS(Entries!$A$2:$A$5000,$A3)
A4: 39508 | B4: =IF($BE4=0,NA(),SUMIFS(Entries!$D$2:$D$5000,Entries!$C$2:$C$5000,"Income",Entries!$A$2:$A$5000,$A4)) | C4: =IF($BE4=0,"",SUMIFS(Entries!$D$2:$D$5000,Entries!$C$2:$C$5000,"Actual",Entries!$A$2:$A$5000,$A4)) | D4: =IF($BE4=0,"",SUMIFS(Entries!$D$2:$D$5000,Entries!$C$2:$C$5000,"One-off",Entries!$A$2:$A$5000,$A4)) | E4: =IF($BE4=0,NA(),C4+D4) | F4: =IF($BE4=0,"",SUM(AJ4:BC4)) | G4: =IF($BE4=0,"",B4-E4) | H4: =IF($BE4=0,"",SUM($G$2:G4)) | I4: =IF($BE4=0,"",SUMIFS(Entries!$F$2:$F$5000,Entries!$A$2:$A$5000,$A4)) | J4: =IF($BE4=0,NA(),H4+SUM($I$2:I4)) | K4: ="" | L4: ="" | M4: =NA() | O4: =IF(OR(O$1="",$BE4=0),"",SUMIFS(Entries!$D$2:$D$5000,Entries!$C$2:$C$5000,"Actual",Entries!$A$2:$A$5000,$A4,Entries!$B$2:$B$5000,O$1)) | P4: =IF(OR(P$1="",$BE4=0),"",SUMIFS(Entries!$D$2:$D$5000,Entries!$C$2:$C$5000,"Actual",Entries!$A$2:$A$5000,$A4,Entries!$B$2:$B$5000,P$1)) | Q4: =IF(OR(Q$1="",$BE4=0),"",SUMIFS(Entries!$D$2:$D$5000,Entries!$C$2:$C$5000,"Actual",Entries!$A$2:$A$5000,$A4,Entries!$B$2:$B$5000,Q$1)) | R4: =IF(OR(R$1="",$BE4=0),"",SUMIFS(Entries!$D$2:$D$5000,Entries!$C$2:$C$5000,"Actual",Entries!$A$2:$A$5000,$A4,Entries!$B$2:$B$5000,R$1)) | S4: =IF(OR(S$1="",$BE4=0),"",SUMIFS(Entries!$D$2:$D$5000,Entries!$C$2:$C$5000,"Actual",Entries!$A$2:$A$5000,$A4,Entries!$B$2:$B$5000,S$1)) | T4: =IF(OR(T$1="",$BE4=0),"",SUMIFS(Entries!$D$2:$D$5000,Entries!$C$2:$C$5000,"Actual",Entries!$A$2:$A$5000,$A4,Entries!$B$2:$B$5000,T$1)) | U4: =IF(OR(U$1="",$BE4=0),"",SUMIFS(Entries!$D$2:$D$5000,Entries!$C$2:$C$5000,"Actual",Entries!$A$2:$A$5000,$A4,Entries!$B$2:$B$5000,U$1)) | V4: =IF(OR(V$1="",$BE4=0),"",SUMIFS(Entries!$D$2:$D$5000,Entries!$C$2:$C$5000,"Actual",Entries!$A$2:$A$5000,$A4,Entries!$B$2:$B$5000,V$1)) | ... AH4: =IF(OR(AH$1="",$BE4=0),"",SUMIFS(Entries!$D$2:$D$5000,Entries!$C$2:$C$5000,"Actual",Entries!$A$2:$A$5000,$A4,Entries!$B$2:$B$5000,AH$1)) | AJ4: =IF(OR(AJ$1="",$BE4=0),"",IFERROR(LOOKUP(2,1/((Budgets!$A$2:$A$200=AJ$1)*(Budgets!$B$2:$B$200<=$A4)),Budgets!$C$2:$C$200),0)) | AK4: =IF(OR(AK$1="",$BE4=0),"",IFERROR(LOOKUP(2,1/((Budgets!$A$2:$A$200=AK$1)*(Budgets!$B$2:$B$200<=$A4)),Budgets!$C$2:$C$200),0)) | AL4: =IF(OR(AL$1="",$BE4=0),"",IFERROR(LOOKUP(2,1/((Budgets!$A$2:$A$200=AL$1)*(Budgets!$B$2:$B$200<=$A4)),Budgets!$C$2:$C$200),0)) | AM4: =IF(OR(AM$1="",$BE4=0),"",IFERROR(LOOKUP(2,1/((Budgets!$A$2:$A$200=AM$1)*(Budgets!$B$2:$B$200<=$A4)),Budgets!$C$2:$C$200),0)) | AN4: =IF(OR(AN$1="",$BE4=0),"",IFERROR(LOOKUP(2,1/((Budgets!$A$2:$A$200=AN$1)*(Budgets!$B$2:$B$200<=$A4)),Budgets!$C$2:$C$200),0)) | AO4: =IF(OR(AO$1="",$BE4=0),"",IFERROR(LOOKUP(2,1/((Budgets!$A$2:$A$200=AO$1)*(Budgets!$B$2:$B$200<=$A4)),Budgets!$C$2:$C$200),0)) | AP4: =IF(OR(AP$1="",$BE4=0),"",IFERROR(LOOKUP(2,1/((Budgets!$A$2:$A$200=AP$1)*(Budgets!$B$2:$B$200<=$A4)),Budgets!$C$2:$C$200),0)) | AQ4: =IF(OR(AQ$1="",$BE4=0),"",IFERROR(LOOKUP(2,1/((Budgets!$A$2:$A$200=AQ$1)*(Budgets!$B$2:$B$200<=$A4)),Budgets!$C$2:$C$200),0)) | ... BC4: =IF(OR(BC$1="",$BE4=0),"",IFERROR(LOOKUP(2,1/((Budgets!$A$2:$A$200=BC$1)*(Budgets!$B$2:$B$200<=$A4)),Budgets!$C$2:$C$200),0)) | BE4: =COUNTIFS(Entries!$A$2:$A$5000,$A4)
A5: 39539 | B5: =IF($BE5=0,NA(),SUMIFS(Entries!$D$2:$D$5000,Entries!$C$2:$C$5000,"Income",Entries!$A$2:$A$5000,$A5)) | C5: =IF($BE5=0,"",SUMIFS(Entries!$D$2:$D$5000,Entries!$C$2:$C$5000,"Actual",Entries!$A$2:$A$5000,$A5)) | D5: =IF($BE5=0,"",SUMIFS(Entries!$D$2:$D$5000,Entries!$C$2:$C$5000,"One-off",Entries!$A$2:$A$5000,$A5)) | E5: =IF($BE5=0,NA(),C5+D5) | F5: =IF($BE5=0,"",SUM(AJ5:BC5)) | G5: =IF($BE5=0,"",B5-E5) | H5: =IF($BE5=0,"",SUM($G$2:G5)) | I5: =IF($BE5=0,"",SUMIFS(Entries!$F$2:$F$5000,Entries!$A$2:$A$5000,$A5)) | J5: =IF($BE5=0,NA(),H5+SUM($I$2:I5)) | K5: ="" | L5: ="" | M5: =NA() | O5: =IF(OR(O$1="",$BE5=0),"",SUMIFS(Entries!$D$2:$D$5000,Entries!$C$2:$C$5000,"Actual",Entries!$A$2:$A$5000,$A5,Entries!$B$2:$B$5000,O$1)) | P5: =IF(OR(P$1="",$BE5=0),"",SUMIFS(Entries!$D$2:$D$5000,Entries!$C$2:$C$5000,"Actual",Entries!$A$2:$A$5000,$A5,Entries!$B$2:$B$5000,P$1)) | Q5: =IF(OR(Q$1="",$BE5=0),"",SUMIFS(Entries!$D$2:$D$5000,Entries!$C$2:$C$5000,"Actual",Entries!$A$2:$A$5000,$A5,Entries!$B$2:$B$5000,Q$1)) | R5: =IF(OR(R$1="",$BE5=0),"",SUMIFS(Entries!$D$2:$D$5000,Entries!$C$2:$C$5000,"Actual",Entries!$A$2:$A$5000,$A5,Entries!$B$2:$B$5000,R$1)) | S5: =IF(OR(S$1="",$BE5=0),"",SUMIFS(Entries!$D$2:$D$5000,Entries!$C$2:$C$5000,"Actual",Entries!$A$2:$A$5000,$A5,Entries!$B$2:$B$5000,S$1)) | T5: =IF(OR(T$1="",$BE5=0),"",SUMIFS(Entries!$D$2:$D$5000,Entries!$C$2:$C$5000,"Actual",Entries!$A$2:$A$5000,$A5,Entries!$B$2:$B$5000,T$1)) | U5: =IF(OR(U$1="",$BE5=0),"",SUMIFS(Entries!$D$2:$D$5000,Entries!$C$2:$C$5000,"Actual",Entries!$A$2:$A$5000,$A5,Entries!$B$2:$B$5000,U$1)) | V5: =IF(OR(V$1="",$BE5=0),"",SUMIFS(Entries!$D$2:$D$5000,Entries!$C$2:$C$5000,"Actual",Entries!$A$2:$A$5000,$A5,Entries!$B$2:$B$5000,V$1)) | ... AH5: =IF(OR(AH$1="",$BE5=0),"",SUMIFS(Entries!$D$2:$D$5000,Entries!$C$2:$C$5000,"Actual",Entries!$A$2:$A$5000,$A5,Entries!$B$2:$B$5000,AH$1)) | AJ5: =IF(OR(AJ$1="",$BE5=0),"",IFERROR(LOOKUP(2,1/((Budgets!$A$2:$A$200=AJ$1)*(Budgets!$B$2:$B$200<=$A5)),Budgets!$C$2:$C$200),0)) | AK5: =IF(OR(AK$1="",$BE5=0),"",IFERROR(LOOKUP(2,1/((Budgets!$A$2:$A$200=AK$1)*(Budgets!$B$2:$B$200<=$A5)),Budgets!$C$2:$C$200),0)) | AL5: =IF(OR(AL$1="",$BE5=0),"",IFERROR(LOOKUP(2,1/((Budgets!$A$2:$A$200=AL$1)*(Budgets!$B$2:$B$200<=$A5)),Budgets!$C$2:$C$200),0)) | AM5: =IF(OR(AM$1="",$BE5=0),"",IFERROR(LOOKUP(2,1/((Budgets!$A$2:$A$200=AM$1)*(Budgets!$B$2:$B$200<=$A5)),Budgets!$C$2:$C$200),0)) | AN5: =IF(OR(AN$1="",$BE5=0),"",IFERROR(LOOKUP(2,1/((Budgets!$A$2:$A$200=AN$1)*(Budgets!$B$2:$B$200<=$A5)),Budgets!$C$2:$C$200),0)) | AO5: =IF(OR(AO$1="",$BE5=0),"",IFERROR(LOOKUP(2,1/((Budgets!$A$2:$A$200=AO$1)*(Budgets!$B$2:$B$200<=$A5)),Budgets!$C$2:$C$200),0)) | AP5: =IF(OR(AP$1="",$BE5=0),"",IFERROR(LOOKUP(2,1/((Budgets!$A$2:$A$200=AP$1)*(Budgets!$B$2:$B$200<=$A5)),Budgets!$C$2:$C$200),0)) | AQ5: =IF(OR(AQ$1="",$BE5=0),"",IFERROR(LOOKUP(2,1/((Budgets!$A$2:$A$200=AQ$1)*(Budgets!$B$2:$B$200<=$A5)),Budgets!$C$2:$C$200),0)) | ... BC5: =IF(OR(BC$1="",$BE5=0),"",IFERROR(LOOKUP(2,1/((Budgets!$A$2:$A$200=BC$1)*(Budgets!$B$2:$B$200<=$A5)),Budgets!$C$2:$C$200),0)) | BE5: =COUNTIFS(Entries!$A$2:$A$5000,$A5)
A6: 39569 | B6: =IF($BE6=0,NA(),SUMIFS(Entries!$D$2:$D$5000,Entries!$C$2:$C$5000,"Income",Entries!$A$2:$A$5000,$A6)) | C6: =IF($BE6=0,"",SUMIFS(Entries!$D$2:$D$5000,Entries!$C$2:$C$5000,"Actual",Entries!$A$2:$A$5000,$A6)) | D6: =IF($BE6=0,"",SUMIFS(Entries!$D$2:$D$5000,Entries!$C$2:$C$5000,"One-off",Entries!$A$2:$A$5000,$A6)) | E6: =IF($BE6=0,NA(),C6+D6) | F6: =IF($BE6=0,"",SUM(AJ6:BC6)) | G6: =IF($BE6=0,"",B6-E6) | H6: =IF($BE6=0,"",SUM($G$2:G6)) | I6: =IF($BE6=0,"",SUMIFS(Entries!$F$2:$F$5000,Entries!$A$2:$A$5000,$A6)) | J6: =IF($BE6=0,NA(),H6+SUM($I$2:I6)) | K6: ="" | L6: ="" | M6: =NA() | O6: =IF(OR(O$1="",$BE6=0),"",SUMIFS(Entries!$D$2:$D$5000,Entries!$C$2:$C$5000,"Actual",Entries!$A$2:$A$5000,$A6,Entries!$B$2:$B$5000,O$1)) | P6: =IF(OR(P$1="",$BE6=0),"",SUMIFS(Entries!$D$2:$D$5000,Entries!$C$2:$C$5000,"Actual",Entries!$A$2:$A$5000,$A6,Entries!$B$2:$B$5000,P$1)) | Q6: =IF(OR(Q$1="",$BE6=0),"",SUMIFS(Entries!$D$2:$D$5000,Entries!$C$2:$C$5000,"Actual",Entries!$A$2:$A$5000,$A6,Entries!$B$2:$B$5000,Q$1)) | R6: =IF(OR(R$1="",$BE6=0),"",SUMIFS(Entries!$D$2:$D$5000,Entries!$C$2:$C$5000,"Actual",Entries!$A$2:$A$5000,$A6,Entries!$B$2:$B$5000,R$1)) | S6: =IF(OR(S$1="",$BE6=0),"",SUMIFS(Entries!$D$2:$D$5000,Entries!$C$2:$C$5000,"Actual",Entries!$A$2:$A$5000,$A6,Entries!$B$2:$B$5000,S$1)) | T6: =IF(OR(T$1="",$BE6=0),"",SUMIFS(Entries!$D$2:$D$5000,Entries!$C$2:$C$5000,"Actual",Entries!$A$2:$A$5000,$A6,Entries!$B$2:$B$5000,T$1)) | U6: =IF(OR(U$1="",$BE6=0),"",SUMIFS(Entries!$D$2:$D$5000,Entries!$C$2:$C$5000,"Actual",Entries!$A$2:$A$5000,$A6,Entries!$B$2:$B$5000,U$1)) | V6: =IF(OR(V$1="",$BE6=0),"",SUMIFS(Entries!$D$2:$D$5000,Entries!$C$2:$C$5000,"Actual",Entries!$A$2:$A$5000,$A6,Entries!$B$2:$B$5000,V$1)) | ... AH6: =IF(OR(AH$1="",$BE6=0),"",SUMIFS(Entries!$D$2:$D$5000,Entries!$C$2:$C$5000,"Actual",Entries!$A$2:$A$5000,$A6,Entries!$B$2:$B$5000,AH$1)) | AJ6: =IF(OR(AJ$1="",$BE6=0),"",IFERROR(LOOKUP(2,1/((Budgets!$A$2:$A$200=AJ$1)*(Budgets!$B$2:$B$200<=$A6)),Budgets!$C$2:$C$200),0)) | AK6: =IF(OR(AK$1="",$BE6=0),"",IFERROR(LOOKUP(2,1/((Budgets!$A$2:$A$200=AK$1)*(Budgets!$B$2:$B$200<=$A6)),Budgets!$C$2:$C$200),0)) | AL6: =IF(OR(AL$1="",$BE6=0),"",IFERROR(LOOKUP(2,1/((Budgets!$A$2:$A$200=AL$1)*(Budgets!$B$2:$B$200<=$A6)),Budgets!$C$2:$C$200),0)) | AM6: =IF(OR(AM$1="",$BE6=0),"",IFERROR(LOOKUP(2,1/((Budgets!$A$2:$A$200=AM$1)*(Budgets!$B$2:$B$200<=$A6)),Budgets!$C$2:$C$200),0)) | AN6: =IF(OR(AN$1="",$BE6=0),"",IFERROR(LOOKUP(2,1/((Budgets!$A$2:$A$200=AN$1)*(Budgets!$B$2:$B$200<=$A6)),Budgets!$C$2:$C$200),0)) | AO6: =IF(OR(AO$1="",$BE6=0),"",IFERROR(LOOKUP(2,1/((Budgets!$A$2:$A$200=AO$1)*(Budgets!$B$2:$B$200<=$A6)),Budgets!$C$2:$C$200),0)) | AP6: =IF(OR(AP$1="",$BE6=0),"",IFERROR(LOOKUP(2,1/((Budgets!$A$2:$A$200=AP$1)*(Budgets!$B$2:$B$200<=$A6)),Budgets!$C$2:$C$200),0)) | AQ6: =IF(OR(AQ$1="",$BE6=0),"",IFERROR(LOOKUP(2,1/((Budgets!$A$2:$A$200=AQ$1)*(Budgets!$B$2:$B$200<=$A6)),Budgets!$C$2:$C$200),0)) | ... BC6: =IF(OR(BC$1="",$BE6=0),"",IFERROR(LOOKUP(2,1/((Budgets!$A$2:$A$200=BC$1)*(Budgets!$B$2:$B$200<=$A6)),Budgets!$C$2:$C$200),0)) | BE6: =COUNTIFS(Entries!$A$2:$A$5000,$A6)
A7: 39600 | B7: =IF($BE7=0,NA(),SUMIFS(Entries!$D$2:$D$5000,Entries!$C$2:$C$5000,"Income",Entries!$A$2:$A$5000,$A7)) | C7: =IF($BE7=0,"",SUMIFS(Entries!$D$2:$D$5000,Entries!$C$2:$C$5000,"Actual",Entries!$A$2:$A$5000,$A7)) | D7: =IF($BE7=0,"",SUMIFS(Entries!$D$2:$D$5000,Entries!$C$2:$C$5000,"One-off",Entries!$A$2:$A$5000,$A7)) | E7: =IF($BE7=0,NA(),C7+D7) | F7: =IF($BE7=0,"",SUM(AJ7:BC7)) | G7: =IF($BE7=0,"",B7-E7) | H7: =IF($BE7=0,"",SUM($G$2:G7)) | I7: =IF($BE7=0,"",SUMIFS(Entries!$F$2:$F$5000,Entries!$A$2:$A$5000,$A7)) | J7: =IF($BE7=0,NA(),H7+SUM($I$2:I7)) | K7: ="" | L7: ="" | M7: =NA() | O7: =IF(OR(O$1="",$BE7=0),"",SUMIFS(Entries!$D$2:$D$5000,Entries!$C$2:$C$5000,"Actual",Entries!$A$2:$A$5000,$A7,Entries!$B$2:$B$5000,O$1)) | P7: =IF(OR(P$1="",$BE7=0),"",SUMIFS(Entries!$D$2:$D$5000,Entries!$C$2:$C$5000,"Actual",Entries!$A$2:$A$5000,$A7,Entries!$B$2:$B$5000,P$1)) | Q7: =IF(OR(Q$1="",$BE7=0),"",SUMIFS(Entries!$D$2:$D$5000,Entries!$C$2:$C$5000,"Actual",Entries!$A$2:$A$5000,$A7,Entries!$B$2:$B$5000,Q$1)) | R7: =IF(OR(R$1="",$BE7=0),"",SUMIFS(Entries!$D$2:$D$5000,Entries!$C$2:$C$5000,"Actual",Entries!$A$2:$A$5000,$A7,Entries!$B$2:$B$5000,R$1)) | S7: =IF(OR(S$1="",$BE7=0),"",SUMIFS(Entries!$D$2:$D$5000,Entries!$C$2:$C$5000,"Actual",Entries!$A$2:$A$5000,$A7,Entries!$B$2:$B$5000,S$1)) | T7: =IF(OR(T$1="",$BE7=0),"",SUMIFS(Entries!$D$2:$D$5000,Entries!$C$2:$C$5000,"Actual",Entries!$A$2:$A$5000,$A7,Entries!$B$2:$B$5000,T$1)) | U7: =IF(OR(U$1="",$BE7=0),"",SUMIFS(Entries!$D$2:$D$5000,Entries!$C$2:$C$5000,"Actual",Entries!$A$2:$A$5000,$A7,Entries!$B$2:$B$5000,U$1)) | V7: =IF(OR(V$1="",$BE7=0),"",SUMIFS(Entries!$D$2:$D$5000,Entries!$C$2:$C$5000,"Actual",Entries!$A$2:$A$5000,$A7,Entries!$B$2:$B$5000,V$1)) | ... AH7: =IF(OR(AH$1="",$BE7=0),"",SUMIFS(Entries!$D$2:$D$5000,Entries!$C$2:$C$5000,"Actual",Entries!$A$2:$A$5000,$A7,Entries!$B$2:$B$5000,AH$1)) | AJ7: =IF(OR(AJ$1="",$BE7=0),"",IFERROR(LOOKUP(2,1/((Budgets!$A$2:$A$200=AJ$1)*(Budgets!$B$2:$B$200<=$A7)),Budgets!$C$2:$C$200),0)) | AK7: =IF(OR(AK$1="",$BE7=0),"",IFERROR(LOOKUP(2,1/((Budgets!$A$2:$A$200=AK$1)*(Budgets!$B$2:$B$200<=$A7)),Budgets!$C$2:$C$200),0)) | AL7: =IF(OR(AL$1="",$BE7=0),"",IFERROR(LOOKUP(2,1/((Budgets!$A$2:$A$200=AL$1)*(Budgets!$B$2:$B$200<=$A7)),Budgets!$C$2:$C$200),0)) | AM7: =IF(OR(AM$1="",$BE7=0),"",IFERROR(LOOKUP(2,1/((Budgets!$A$2:$A$200=AM$1)*(Budgets!$B$2:$B$200<=$A7)),Budgets!$C$2:$C$200),0)) | AN7: =IF(OR(AN$1="",$BE7=0),"",IFERROR(LOOKUP(2,1/((Budgets!$A$2:$A$200=AN$1)*(Budgets!$B$2:$B$200<=$A7)),Budgets!$C$2:$C$200),0)) | AO7: =IF(OR(AO$1="",$BE7=0),"",IFERROR(LOOKUP(2,1/((Budgets!$A$2:$A$200=AO$1)*(Budgets!$B$2:$B$200<=$A7)),Budgets!$C$2:$C$200),0)) | AP7: =IF(OR(AP$1="",$BE7=0),"",IFERROR(LOOKUP(2,1/((Budgets!$A$2:$A$200=AP$1)*(Budgets!$B$2:$B$200<=$A7)),Budgets!$C$2:$C$200),0)) | AQ7: =IF(OR(AQ$1="",$BE7=0),"",IFERROR(LOOKUP(2,1/((Budgets!$A$2:$A$200=AQ$1)*(Budgets!$B$2:$B$200<=$A7)),Budgets!$C$2:$C$200),0)) | ... BC7: =IF(OR(BC$1="",$BE7=0),"",IFERROR(LOOKUP(2,1/((Budgets!$A$2:$A$200=BC$1)*(Budgets!$B$2:$B$200<=$A7)),Budgets!$C$2:$C$200),0)) | BE7: =COUNTIFS(Entries!$A$2:$A$5000,$A7)
A8: 39630 | B8: =IF($BE8=0,NA(),SUMIFS(Entries!$D$2:$D$5000,Entries!$C$2:$C$5000,"Income",Entries!$A$2:$A$5000,$A8)) | C8: =IF($BE8=0,"",SUMIFS(Entries!$D$2:$D$5000,Entries!$C$2:$C$5000,"Actual",Entries!$A$2:$A$5000,$A8)) | D8: =IF($BE8=0,"",SUMIFS(Entries!$D$2:$D$5000,Entries!$C$2:$C$5000,"One-off",Entries!$A$2:$A$5000,$A8)) | E8: =IF($BE8=0,NA(),C8+D8) | F8: =IF($BE8=0,"",SUM(AJ8:BC8)) | G8: =IF($BE8=0,"",B8-E8) | H8: =IF($BE8=0,"",SUM($G$2:G8)) | I8: =IF($BE8=0,"",SUMIFS(Entries!$F$2:$F$5000,Entries!$A$2:$A$5000,$A8)) | J8: =IF($BE8=0,NA(),H8+SUM($I$2:I8)) | K8: ="" | L8: ="" | M8: =NA() | O8: =IF(OR(O$1="",$BE8=0),"",SUMIFS(Entries!$D$2:$D$5000,Entries!$C$2:$C$5000,"Actual",Entries!$A$2:$A$5000,$A8,Entries!$B$2:$B$5000,O$1)) | P8: =IF(OR(P$1="",$BE8=0),"",SUMIFS(Entries!$D$2:$D$5000,Entries!$C$2:$C$5000,"Actual",Entries!$A$2:$A$5000,$A8,Entries!$B$2:$B$5000,P$1)) | Q8: =IF(OR(Q$1="",$BE8=0),"",SUMIFS(Entries!$D$2:$D$5000,Entries!$C$2:$C$5000,"Actual",Entries!$A$2:$A$5000,$A8,Entries!$B$2:$B$5000,Q$1)) | R8: =IF(OR(R$1="",$BE8=0),"",SUMIFS(Entries!$D$2:$D$5000,Entries!$C$2:$C$5000,"Actual",Entries!$A$2:$A$5000,$A8,Entries!$B$2:$B$5000,R$1)) | S8: =IF(OR(S$1="",$BE8=0),"",SUMIFS(Entries!$D$2:$D$5000,Entries!$C$2:$C$5000,"Actual",Entries!$A$2:$A$5000,$A8,Entries!$B$2:$B$5000,S$1)) | T8: =IF(OR(T$1="",$BE8=0),"",SUMIFS(Entries!$D$2:$D$5000,Entries!$C$2:$C$5000,"Actual",Entries!$A$2:$A$5000,$A8,Entries!$B$2:$B$5000,T$1)) | U8: =IF(OR(U$1="",$BE8=0),"",SUMIFS(Entries!$D$2:$D$5000,Entries!$C$2:$C$5000,"Actual",Entries!$A$2:$A$5000,$A8,Entries!$B$2:$B$5000,U$1)) | V8: =IF(OR(V$1="",$BE8=0),"",SUMIFS(Entries!$D$2:$D$5000,Entries!$C$2:$C$5000,"Actual",Entries!$A$2:$A$5000,$A8,Entries!$B$2:$B$5000,V$1)) | ... AH8: =IF(OR(AH$1="",$BE8=0),"",SUMIFS(Entries!$D$2:$D$5000,Entries!$C$2:$C$5000,"Actual",Entries!$A$2:$A$5000,$A8,Entries!$B$2:$B$5000,AH$1)) | AJ8: =IF(OR(AJ$1="",$BE8=0),"",IFERROR(LOOKUP(2,1/((Budgets!$A$2:$A$200=AJ$1)*(Budgets!$B$2:$B$200<=$A8)),Budgets!$C$2:$C$200),0)) | AK8: =IF(OR(AK$1="",$BE8=0),"",IFERROR(LOOKUP(2,1/((Budgets!$A$2:$A$200=AK$1)*(Budgets!$B$2:$B$200<=$A8)),Budgets!$C$2:$C$200),0)) | AL8: =IF(OR(AL$1="",$BE8=0),"",IFERROR(LOOKUP(2,1/((Budgets!$A$2:$A$200=AL$1)*(Budgets!$B$2:$B$200<=$A8)),Budgets!$C$2:$C$200),0)) | AM8: =IF(OR(AM$1="",$BE8=0),"",IFERROR(LOOKUP(2,1/((Budgets!$A$2:$A$200=AM$1)*(Budgets!$B$2:$B$200<=$A8)),Budgets!$C$2:$C$200),0)) | AN8: =IF(OR(AN$1="",$BE8=0),"",IFERROR(LOOKUP(2,1/((Budgets!$A$2:$A$200=AN$1)*(Budgets!$B$2:$B$200<=$A8)),Budgets!$C$2:$C$200),0)) | AO8: =IF(OR(AO$1="",$BE8=0),"",IFERROR(LOOKUP(2,1/((Budgets!$A$2:$A$200=AO$1)*(Budgets!$B$2:$B$200<=$A8)),Budgets!$C$2:$C$200),0)) | AP8: =IF(OR(AP$1="",$BE8=0),"",IFERROR(LOOKUP(2,1/((Budgets!$A$2:$A$200=AP$1)*(Budgets!$B$2:$B$200<=$A8)),Budgets!$C$2:$C$200),0)) | AQ8: =IF(OR(AQ$1="",$BE8=0),"",IFERROR(LOOKUP(2,1/((Budgets!$A$2:$A$200=AQ$1)*(Budgets!$B$2:$B$200<=$A8)),Budgets!$C$2:$C$200),0)) | ... BC8: =IF(OR(BC$1="",$BE8=0),"",IFERROR(LOOKUP(2,1/((Budgets!$A$2:$A$200=BC$1)*(Budgets!$B$2:$B$200<=$A8)),Budgets!$C$2:$C$200),0)) | BE8: =COUNTIFS(Entries!$A$2:$A$5000,$A8)
A9: 39661 | B9: =IF($BE9=0,NA(),SUMIFS(Entries!$D$2:$D$5000,Entries!$C$2:$C$5000,"Income",Entries!$A$2:$A$5000,$A9)) | C9: =IF($BE9=0,"",SUMIFS(Entries!$D$2:$D$5000,Entries!$C$2:$C$5000,"Actual",Entries!$A$2:$A$5000,$A9)) | D9: =IF($BE9=0,"",SUMIFS(Entries!$D$2:$D$5000,Entries!$C$2:$C$5000,"One-off",Entries!$A$2:$A$5000,$A9)) | E9: =IF($BE9=0,NA(),C9+D9) | F9: =IF($BE9=0,"",SUM(AJ9:BC9)) | G9: =IF($BE9=0,"",B9-E9) | H9: =IF($BE9=0,"",SUM($G$2:G9)) | I9: =IF($BE9=0,"",SUMIFS(Entries!$F$2:$F$5000,Entries!$A$2:$A$5000,$A9)) | J9: =IF($BE9=0,NA(),H9+SUM($I$2:I9)) | K9: ="" | L9: ="" | M9: =NA() | O9: =IF(OR(O$1="",$BE9=0),"",SUMIFS(Entries!$D$2:$D$5000,Entries!$C$2:$C$5000,"Actual",Entries!$A$2:$A$5000,$A9,Entries!$B$2:$B$5000,O$1)) | P9: =IF(OR(P$1="",$BE9=0),"",SUMIFS(Entries!$D$2:$D$5000,Entries!$C$2:$C$5000,"Actual",Entries!$A$2:$A$5000,$A9,Entries!$B$2:$B$5000,P$1)) | Q9: =IF(OR(Q$1="",$BE9=0),"",SUMIFS(Entries!$D$2:$D$5000,Entries!$C$2:$C$5000,"Actual",Entries!$A$2:$A$5000,$A9,Entries!$B$2:$B$5000,Q$1)) | R9: =IF(OR(R$1="",$BE9=0),"",SUMIFS(Entries!$D$2:$D$5000,Entries!$C$2:$C$5000,"Actual",Entries!$A$2:$A$5000,$A9,Entries!$B$2:$B$5000,R$1)) | S9: =IF(OR(S$1="",$BE9=0),"",SUMIFS(Entries!$D$2:$D$5000,Entries!$C$2:$C$5000,"Actual",Entries!$A$2:$A$5000,$A9,Entries!$B$2:$B$5000,S$1)) | T9: =IF(OR(T$1="",$BE9=0),"",SUMIFS(Entries!$D$2:$D$5000,Entries!$C$2:$C$5000,"Actual",Entries!$A$2:$A$5000,$A9,Entries!$B$2:$B$5000,T$1)) | U9: =IF(OR(U$1="",$BE9=0),"",SUMIFS(Entries!$D$2:$D$5000,Entries!$C$2:$C$5000,"Actual",Entries!$A$2:$A$5000,$A9,Entries!$B$2:$B$5000,U$1)) | V9: =IF(OR(V$1="",$BE9=0),"",SUMIFS(Entries!$D$2:$D$5000,Entries!$C$2:$C$5000,"Actual",Entries!$A$2:$A$5000,$A9,Entries!$B$2:$B$5000,V$1)) | ... AH9: =IF(OR(AH$1="",$BE9=0),"",SUMIFS(Entries!$D$2:$D$5000,Entries!$C$2:$C$5000,"Actual",Entries!$A$2:$A$5000,$A9,Entries!$B$2:$B$5000,AH$1)) | AJ9: =IF(OR(AJ$1="",$BE9=0),"",IFERROR(LOOKUP(2,1/((Budgets!$A$2:$A$200=AJ$1)*(Budgets!$B$2:$B$200<=$A9)),Budgets!$C$2:$C$200),0)) | AK9: =IF(OR(AK$1="",$BE9=0),"",IFERROR(LOOKUP(2,1/((Budgets!$A$2:$A$200=AK$1)*(Budgets!$B$2:$B$200<=$A9)),Budgets!$C$2:$C$200),0)) | AL9: =IF(OR(AL$1="",$BE9=0),"",IFERROR(LOOKUP(2,1/((Budgets!$A$2:$A$200=AL$1)*(Budgets!$B$2:$B$200<=$A9)),Budgets!$C$2:$C$200),0)) | AM9: =IF(OR(AM$1="",$BE9=0),"",IFERROR(LOOKUP(2,1/((Budgets!$A$2:$A$200=AM$1)*(Budgets!$B$2:$B$200<=$A9)),Budgets!$C$2:$C$200),0)) | AN9: =IF(OR(AN$1="",$BE9=0),"",IFERROR(LOOKUP(2,1/((Budgets!$A$2:$A$200=AN$1)*(Budgets!$B$2:$B$200<=$A9)),Budgets!$C$2:$C$200),0)) | AO9: =IF(OR(AO$1="",$BE9=0),"",IFERROR(LOOKUP(2,1/((Budgets!$A$2:$A$200=AO$1)*(Budgets!$B$2:$B$200<=$A9)),Budgets!$C$2:$C$200),0)) | AP9: =IF(OR(AP$1="",$BE9=0),"",IFERROR(LOOKUP(2,1/((Budgets!$A$2:$A$200=AP$1)*(Budgets!$B$2:$B$200<=$A9)),Budgets!$C$2:$C$200),0)) | AQ9: =IF(OR(AQ$1="",$BE9=0),"",IFERROR(LOOKUP(2,1/((Budgets!$A$2:$A$200=AQ$1)*(Budgets!$B$2:$B$200<=$A9)),Budgets!$C$2:$C$200),0)) | ... BC9: =IF(OR(BC$1="",$BE9=0),"",IFERROR(LOOKUP(2,1/((Budgets!$A$2:$A$200=BC$1)*(Budgets!$B$2:$B$200<=$A9)),Budgets!$C$2:$C$200),0)) | BE9: =COUNTIFS(Entries!$A$2:$A$5000,$A9)
A10: 39692 | B10: =IF($BE10=0,NA(),SUMIFS(Entries!$D$2:$D$5000,Entries!$C$2:$C$5000,"Income",Entries!$A$2:$A$5000,$A10)) | C10: =IF($BE10=0,"",SUMIFS(Entries!$D$2:$D$5000,Entries!$C$2:$C$5000,"Actual",Entries!$A$2:$A$5000,$A10)) | D10: =IF($BE10=0,"",SUMIFS(Entries!$D$2:$D$5000,Entries!$C$2:$C$5000,"One-off",Entries!$A$2:$A$5000,$A10)) | E10: =IF($BE10=0,NA(),C10+D10) | F10: =IF($BE10=0,"",SUM(AJ10:BC10)) | G10: =IF($BE10=0,"",B10-E10) | H10: =IF($BE10=0,"",SUM($G$2:G10)) | I10: =IF($BE10=0,"",SUMIFS(Entries!$F$2:$F$5000,Entries!$A$2:$A$5000,$A10)) | J10: =IF($BE10=0,NA(),H10+SUM($I$2:I10)) | K10: ="" | L10: ="" | M10: =NA() | O10: =IF(OR(O$1="",$BE10=0),"",SUMIFS(Entries!$D$2:$D$5000,Entries!$C$2:$C$5000,"Actual",Entries!$A$2:$A$5000,$A10,Entries!$B$2:$B$5000,O$1)) | P10: =IF(OR(P$1="",$BE10=0),"",SUMIFS(Entries!$D$2:$D$5000,Entries!$C$2:$C$5000,"Actual",Entries!$A$2:$A$5000,$A10,Entries!$B$2:$B$5000,P$1)) | Q10: =IF(OR(Q$1="",$BE10=0),"",SUMIFS(Entries!$D$2:$D$5000,Entries!$C$2:$C$5000,"Actual",Entries!$A$2:$A$5000,$A10,Entries!$B$2:$B$5000,Q$1)) | R10: =IF(OR(R$1="",$BE10=0),"",SUMIFS(Entries!$D$2:$D$5000,Entries!$C$2:$C$5000,"Actual",Entries!$A$2:$A$5000,$A10,Entries!$B$2:$B$5000,R$1)) | S10: =IF(OR(S$1="",$BE10=0),"",SUMIFS(Entries!$D$2:$D$5000,Entries!$C$2:$C$5000,"Actual",Entries!$A$2:$A$5000,$A10,Entries!$B$2:$B$5000,S$1)) | T10: =IF(OR(T$1="",$BE10=0),"",SUMIFS(Entries!$D$2:$D$5000,Entries!$C$2:$C$5000,"Actual",Entries!$A$2:$A$5000,$A10,Entries!$B$2:$B$5000,T$1)) | U10: =IF(OR(U$1="",$BE10=0),"",SUMIFS(Entries!$D$2:$D$5000,Entries!$C$2:$C$5000,"Actual",Entries!$A$2:$A$5000,$A10,Entries!$B$2:$B$5000,U$1)) | V10: =IF(OR(V$1="",$BE10=0),"",SUMIFS(Entries!$D$2:$D$5000,Entries!$C$2:$C$5000,"Actual",Entries!$A$2:$A$5000,$A10,Entries!$B$2:$B$5000,V$1)) | ... AH10: =IF(OR(AH$1="",$BE10=0),"",SUMIFS(Entries!$D$2:$D$5000,Entries!$C$2:$C$5000,"Actual",Entries!$A$2:$A$5000,$A10,Entries!$B$2:$B$5000,AH$1)) | AJ10: =IF(OR(AJ$1="",$BE10=0),"",IFERROR(LOOKUP(2,1/((Budgets!$A$2:$A$200=AJ$1)*(Budgets!$B$2:$B$200<=$A10)),Budgets!$C$2:$C$200),0)) | AK10: =IF(OR(AK$1="",$BE10=0),"",IFERROR(LOOKUP(2,1/((Budgets!$A$2:$A$200=AK$1)*(Budgets!$B$2:$B$200<=$A10)),Budgets!$C$2:$C$200),0)) | AL10: =IF(OR(AL$1="",$BE10=0),"",IFERROR(LOOKUP(2,1/((Budgets!$A$2:$A$200=AL$1)*(Budgets!$B$2:$B$200<=$A10)),Budgets!$C$2:$C$200),0)) | AM10: =IF(OR(AM$1="",$BE10=0),"",IFERROR(LOOKUP(2,1/((Budgets!$A$2:$A$200=AM$1)*(Budgets!$B$2:$B$200<=$A10)),Budgets!$C$2:$C$200),0)) | AN10: =IF(OR(AN$1="",$BE10=0),"",IFERROR(LOOKUP(2,1/((Budgets!$A$2:$A$200=AN$1)*(Budgets!$B$2:$B$200<=$A10)),Budgets!$C$2:$C$200),0)) | AO10: =IF(OR(AO$1="",$BE10=0),"",IFERROR(LOOKUP(2,1/((Budgets!$A$2:$A$200=AO$1)*(Budgets!$B$2:$B$200<=$A10)),Budgets!$C$2:$C$200),0)) | AP10: =IF(OR(AP$1="",$BE10=0),"",IFERROR(LOOKUP(2,1/((Budgets!$A$2:$A$200=AP$1)*(Budgets!$B$2:$B$200<=$A10)),Budgets!$C$2:$C$200),0)) | AQ10: =IF(OR(AQ$1="",$BE10=0),"",IFERROR(LOOKUP(2,1/((Budgets!$A$2:$A$200=AQ$1)*(Budgets!$B$2:$B$200<=$A10)),Budgets!$C$2:$C$200),0)) | ... BC10: =IF(OR(BC$1="",$BE10=0),"",IFERROR(LOOKUP(2,1/((Budgets!$A$2:$A$200=BC$1)*(Budgets!$B$2:$B$200<=$A10)),Budgets!$C$2:$C$200),0)) | BE10: =COUNTIFS(Entries!$A$2:$A$5000,$A10)
A11: 39722 | B11: =IF($BE11=0,NA(),SUMIFS(Entries!$D$2:$D$5000,Entries!$C$2:$C$5000,"Income",Entries!$A$2:$A$5000,$A11)) | C11: =IF($BE11=0,"",SUMIFS(Entries!$D$2:$D$5000,Entries!$C$2:$C$5000,"Actual",Entries!$A$2:$A$5000,$A11)) | D11: =IF($BE11=0,"",SUMIFS(Entries!$D$2:$D$5000,Entries!$C$2:$C$5000,"One-off",Entries!$A$2:$A$5000,$A11)) | E11: =IF($BE11=0,NA(),C11+D11) | F11: =IF($BE11=0,"",SUM(AJ11:BC11)) | G11: =IF($BE11=0,"",B11-E11) | H11: =IF($BE11=0,"",SUM($G$2:G11)) | I11: =IF($BE11=0,"",SUMIFS(Entries!$F$2:$F$5000,Entries!$A$2:$A$5000,$A11)) | J11: =IF($BE11=0,NA(),H11+SUM($I$2:I11)) | K11: ="" | L11: ="" | M11: =NA() | O11: =IF(OR(O$1="",$BE11=0),"",SUMIFS(Entries!$D$2:$D$5000,Entries!$C$2:$C$5000,"Actual",Entries!$A$2:$A$5000,$A11,Entries!$B$2:$B$5000,O$1)) | P11: =IF(OR(P$1="",$BE11=0),"",SUMIFS(Entries!$D$2:$D$5000,Entries!$C$2:$C$5000,"Actual",Entries!$A$2:$A$5000,$A11,Entries!$B$2:$B$5000,P$1)) | Q11: =IF(OR(Q$1="",$BE11=0),"",SUMIFS(Entries!$D$2:$D$5000,Entries!$C$2:$C$5000,"Actual",Entries!$A$2:$A$5000,$A11,Entries!$B$2:$B$5000,Q$1)) | R11: =IF(OR(R$1="",$BE11=0),"",SUMIFS(Entries!$D$2:$D$5000,Entries!$C$2:$C$5000,"Actual",Entries!$A$2:$A$5000,$A11,Entries!$B$2:$B$5000,R$1)) | S11: =IF(OR(S$1="",$BE11=0),"",SUMIFS(Entries!$D$2:$D$5000,Entries!$C$2:$C$5000,"Actual",Entries!$A$2:$A$5000,$A11,Entries!$B$2:$B$5000,S$1)) | T11: =IF(OR(T$1="",$BE11=0),"",SUMIFS(Entries!$D$2:$D$5000,Entries!$C$2:$C$5000,"Actual",Entries!$A$2:$A$5000,$A11,Entries!$B$2:$B$5000,T$1)) | U11: =IF(OR(U$1="",$BE11=0),"",SUMIFS(Entries!$D$2:$D$5000,Entries!$C$2:$C$5000,"Actual",Entries!$A$2:$A$5000,$A11,Entries!$B$2:$B$5000,U$1)) | V11: =IF(OR(V$1="",$BE11=0),"",SUMIFS(Entries!$D$2:$D$5000,Entries!$C$2:$C$5000,"Actual",Entries!$A$2:$A$5000,$A11,Entries!$B$2:$B$5000,V$1)) | ... AH11: =IF(OR(AH$1="",$BE11=0),"",SUMIFS(Entries!$D$2:$D$5000,Entries!$C$2:$C$5000,"Actual",Entries!$A$2:$A$5000,$A11,Entries!$B$2:$B$5000,AH$1)) | AJ11: =IF(OR(AJ$1="",$BE11=0),"",IFERROR(LOOKUP(2,1/((Budgets!$A$2:$A$200=AJ$1)*(Budgets!$B$2:$B$200<=$A11)),Budgets!$C$2:$C$200),0)) | AK11: =IF(OR(AK$1="",$BE11=0),"",IFERROR(LOOKUP(2,1/((Budgets!$A$2:$A$200=AK$1)*(Budgets!$B$2:$B$200<=$A11)),Budgets!$C$2:$C$200),0)) | AL11: =IF(OR(AL$1="",$BE11=0),"",IFERROR(LOOKUP(2,1/((Budgets!$A$2:$A$200=AL$1)*(Budgets!$B$2:$B$200<=$A11)),Budgets!$C$2:$C$200),0)) | AM11: =IF(OR(AM$1="",$BE11=0),"",IFERROR(LOOKUP(2,1/((Budgets!$A$2:$A$200=AM$1)*(Budgets!$B$2:$B$200<=$A11)),Budgets!$C$2:$C$200),0)) | AN11: =IF(OR(AN$1="",$BE11=0),"",IFERROR(LOOKUP(2,1/((Budgets!$A$2:$A$200=AN$1)*(Budgets!$B$2:$B$200<=$A11)),Budgets!$C$2:$C$200),0)) | AO11: =IF(OR(AO$1="",$BE11=0),"",IFERROR(LOOKUP(2,1/((Budgets!$A$2:$A$200=AO$1)*(Budgets!$B$2:$B$200<=$A11)),Budgets!$C$2:$C$200),0)) | AP11: =IF(OR(AP$1="",$BE11=0),"",IFERROR(LOOKUP(2,1/((Budgets!$A$2:$A$200=AP$1)*(Budgets!$B$2:$B$200<=$A11)),Budgets!$C$2:$C$200),0)) | AQ11: =IF(OR(AQ$1="",$BE11=0),"",IFERROR(LOOKUP(2,1/((Budgets!$A$2:$A$200=AQ$1)*(Budgets!$B$2:$B$200<=$A11)),Budgets!$C$2:$C$200),0)) | ... BC11: =IF(OR(BC$1="",$BE11=0),"",IFERROR(LOOKUP(2,1/((Budgets!$A$2:$A$200=BC$1)*(Budgets!$B$2:$B$200<=$A11)),Budgets!$C$2:$C$200),0)) | BE11: =COUNTIFS(Entries!$A$2:$A$5000,$A11)
A12: 39753 | B12: =IF($BE12=0,NA(),SUMIFS(Entries!$D$2:$D$5000,Entries!$C$2:$C$5000,"Income",Entries!$A$2:$A$5000,$A12)) | C12: =IF($BE12=0,"",SUMIFS(Entries!$D$2:$D$5000,Entries!$C$2:$C$5000,"Actual",Entries!$A$2:$A$5000,$A12)) | D12: =IF($BE12=0,"",SUMIFS(Entries!$D$2:$D$5000,Entries!$C$2:$C$5000,"One-off",Entries!$A$2:$A$5000,$A12)) | E12: =IF($BE12=0,NA(),C12+D12) | F12: =IF($BE12=0,"",SUM(AJ12:BC12)) | G12: =IF($BE12=0,"",B12-E12) | H12: =IF($BE12=0,"",SUM($G$2:G12)) | I12: =IF($BE12=0,"",SUMIFS(Entries!$F$2:$F$5000,Entries!$A$2:$A$5000,$A12)) | J12: =IF($BE12=0,NA(),H12+SUM($I$2:I12)) | K12: ="" | L12: ="" | M12: =NA() | O12: =IF(OR(O$1="",$BE12=0),"",SUMIFS(Entries!$D$2:$D$5000,Entries!$C$2:$C$5000,"Actual",Entries!$A$2:$A$5000,$A12,Entries!$B$2:$B$5000,O$1)) | P12: =IF(OR(P$1="",$BE12=0),"",SUMIFS(Entries!$D$2:$D$5000,Entries!$C$2:$C$5000,"Actual",Entries!$A$2:$A$5000,$A12,Entries!$B$2:$B$5000,P$1)) | Q12: =IF(OR(Q$1="",$BE12=0),"",SUMIFS(Entries!$D$2:$D$5000,Entries!$C$2:$C$5000,"Actual",Entries!$A$2:$A$5000,$A12,Entries!$B$2:$B$5000,Q$1)) | R12: =IF(OR(R$1="",$BE12=0),"",SUMIFS(Entries!$D$2:$D$5000,Entries!$C$2:$C$5000,"Actual",Entries!$A$2:$A$5000,$A12,Entries!$B$2:$B$5000,R$1)) | S12: =IF(OR(S$1="",$BE12=0),"",SUMIFS(Entries!$D$2:$D$5000,Entries!$C$2:$C$5000,"Actual",Entries!$A$2:$A$5000,$A12,Entries!$B$2:$B$5000,S$1)) | T12: =IF(OR(T$1="",$BE12=0),"",SUMIFS(Entries!$D$2:$D$5000,Entries!$C$2:$C$5000,"Actual",Entries!$A$2:$A$5000,$A12,Entries!$B$2:$B$5000,T$1)) | U12: =IF(OR(U$1="",$BE12=0),"",SUMIFS(Entries!$D$2:$D$5000,Entries!$C$2:$C$5000,"Actual",Entries!$A$2:$A$5000,$A12,Entries!$B$2:$B$5000,U$1)) | V12: =IF(OR(V$1="",$BE12=0),"",SUMIFS(Entries!$D$2:$D$5000,Entries!$C$2:$C$5000,"Actual",Entries!$A$2:$A$5000,$A12,Entries!$B$2:$B$5000,V$1)) | ... AH12: =IF(OR(AH$1="",$BE12=0),"",SUMIFS(Entries!$D$2:$D$5000,Entries!$C$2:$C$5000,"Actual",Entries!$A$2:$A$5000,$A12,Entries!$B$2:$B$5000,AH$1)) | AJ12: =IF(OR(AJ$1="",$BE12=0),"",IFERROR(LOOKUP(2,1/((Budgets!$A$2:$A$200=AJ$1)*(Budgets!$B$2:$B$200<=$A12)),Budgets!$C$2:$C$200),0)) | AK12: =IF(OR(AK$1="",$BE12=0),"",IFERROR(LOOKUP(2,1/((Budgets!$A$2:$A$200=AK$1)*(Budgets!$B$2:$B$200<=$A12)),Budgets!$C$2:$C$200),0)) | AL12: =IF(OR(AL$1="",$BE12=0),"",IFERROR(LOOKUP(2,1/((Budgets!$A$2:$A$200=AL$1)*(Budgets!$B$2:$B$200<=$A12)),Budgets!$C$2:$C$200),0)) | AM12: =IF(OR(AM$1="",$BE12=0),"",IFERROR(LOOKUP(2,1/((Budgets!$A$2:$A$200=AM$1)*(Budgets!$B$2:$B$200<=$A12)),Budgets!$C$2:$C$200),0)) | AN12: =IF(OR(AN$1="",$BE12=0),"",IFERROR(LOOKUP(2,1/((Budgets!$A$2:$A$200=AN$1)*(Budgets!$B$2:$B$200<=$A12)),Budgets!$C$2:$C$200),0)) | AO12: =IF(OR(AO$1="",$BE12=0),"",IFERROR(LOOKUP(2,1/((Budgets!$A$2:$A$200=AO$1)*(Budgets!$B$2:$B$200<=$A12)),Budgets!$C$2:$C$200),0)) | AP12: =IF(OR(AP$1="",$BE12=0),"",IFERROR(LOOKUP(2,1/((Budgets!$A$2:$A$200=AP$1)*(Budgets!$B$2:$B$200<=$A12)),Budgets!$C$2:$C$200),0)) | AQ12: =IF(OR(AQ$1="",$BE12=0),"",IFERROR(LOOKUP(2,1/((Budgets!$A$2:$A$200=AQ$1)*(Budgets!$B$2:$B$200<=$A12)),Budgets!$C$2:$C$200),0)) | ... BC12: =IF(OR(BC$1="",$BE12=0),"",IFERROR(LOOKUP(2,1/((Budgets!$A$2:$A$200=BC$1)*(Budgets!$B$2:$B$200<=$A12)),Budgets!$C$2:$C$200),0)) | BE12: =COUNTIFS(Entries!$A$2:$A$5000,$A12)
A13: 39783 | B13: =IF($BE13=0,NA(),SUMIFS(Entries!$D$2:$D$5000,Entries!$C$2:$C$5000,"Income",Entries!$A$2:$A$5000,$A13)) | C13: =IF($BE13=0,"",SUMIFS(Entries!$D$2:$D$5000,Entries!$C$2:$C$5000,"Actual",Entries!$A$2:$A$5000,$A13)) | D13: =IF($BE13=0,"",SUMIFS(Entries!$D$2:$D$5000,Entries!$C$2:$C$5000,"One-off",Entries!$A$2:$A$5000,$A13)) | E13: =IF($BE13=0,NA(),C13+D13) | F13: =IF($BE13=0,"",SUM(AJ13:BC13)) | G13: =IF($BE13=0,"",B13-E13) | H13: =IF($BE13=0,"",SUM($G$2:G13)) | I13: =IF($BE13=0,"",SUMIFS(Entries!$F$2:$F$5000,Entries!$A$2:$A$5000,$A13)) | J13: =IF($BE13=0,NA(),H13+SUM($I$2:I13)) | K13: =IF($BE13=0,"",SUMIFS(Entries!$D$2:$D$5000,Entries!$C$2:$C$5000,"Income",Entries!$A$2:$A$5000,">="&EDATE($A13,-11),Entries!$A$2:$A$5000,"<="&$A13)/12) | L13: =IF($BE13=0,"",(SUMIFS(Entries!$D$2:$D$5000,Entries!$C$2:$C$5000,"Actual",Entries!$A$2:$A$5000,">="&EDATE($A13,-11),Entries!$A$2:$A$5000,"<="&$A13)+SUMIFS(Entries!$D$2:$D$5000,Entries!$C$2:$C$5000,"One-off",Entries!$A$2:$A$5000,">="&EDATE($A13,-11),Entries!$A$2:$A$5000,"<="&$A13))/12) | M13: =IF($BE13=0,NA(),IFERROR((K13-L13)/K13,0)) | O13: =IF(OR(O$1="",$BE13=0),"",SUMIFS(Entries!$D$2:$D$5000,Entries!$C$2:$C$5000,"Actual",Entries!$A$2:$A$5000,$A13,Entries!$B$2:$B$5000,O$1)) | P13: =IF(OR(P$1="",$BE13=0),"",SUMIFS(Entries!$D$2:$D$5000,Entries!$C$2:$C$5000,"Actual",Entries!$A$2:$A$5000,$A13,Entries!$B$2:$B$5000,P$1)) | Q13: =IF(OR(Q$1="",$BE13=0),"",SUMIFS(Entries!$D$2:$D$5000,Entries!$C$2:$C$5000,"Actual",Entries!$A$2:$A$5000,$A13,Entries!$B$2:$B$5000,Q$1)) | R13: =IF(OR(R$1="",$BE13=0),"",SUMIFS(Entries!$D$2:$D$5000,Entries!$C$2:$C$5000,"Actual",Entries!$A$2:$A$5000,$A13,Entries!$B$2:$B$5000,R$1)) | S13: =IF(OR(S$1="",$BE13=0),"",SUMIFS(Entries!$D$2:$D$5000,Entries!$C$2:$C$5000,"Actual",Entries!$A$2:$A$5000,$A13,Entries!$B$2:$B$5000,S$1)) | T13: =IF(OR(T$1="",$BE13=0),"",SUMIFS(Entries!$D$2:$D$5000,Entries!$C$2:$C$5000,"Actual",Entries!$A$2:$A$5000,$A13,Entries!$B$2:$B$5000,T$1)) | U13: =IF(OR(U$1="",$BE13=0),"",SUMIFS(Entries!$D$2:$D$5000,Entries!$C$2:$C$5000,"Actual",Entries!$A$2:$A$5000,$A13,Entries!$B$2:$B$5000,U$1)) | V13: =IF(OR(V$1="",$BE13=0),"",SUMIFS(Entries!$D$2:$D$5000,Entries!$C$2:$C$5000,"Actual",Entries!$A$2:$A$5000,$A13,Entries!$B$2:$B$5000,V$1)) | ... AH13: =IF(OR(AH$1="",$BE13=0),"",SUMIFS(Entries!$D$2:$D$5000,Entries!$C$2:$C$5000,"Actual",Entries!$A$2:$A$5000,$A13,Entries!$B$2:$B$5000,AH$1)) | AJ13: =IF(OR(AJ$1="",$BE13=0),"",IFERROR(LOOKUP(2,1/((Budgets!$A$2:$A$200=AJ$1)*(Budgets!$B$2:$B$200<=$A13)),Budgets!$C$2:$C$200),0)) | AK13: =IF(OR(AK$1="",$BE13=0),"",IFERROR(LOOKUP(2,1/((Budgets!$A$2:$A$200=AK$1)*(Budgets!$B$2:$B$200<=$A13)),Budgets!$C$2:$C$200),0)) | AL13: =IF(OR(AL$1="",$BE13=0),"",IFERROR(LOOKUP(2,1/((Budgets!$A$2:$A$200=AL$1)*(Budgets!$B$2:$B$200<=$A13)),Budgets!$C$2:$C$200),0)) | AM13: =IF(OR(AM$1="",$BE13=0),"",IFERROR(LOOKUP(2,1/((Budgets!$A$2:$A$200=AM$1)*(Budgets!$B$2:$B$200<=$A13)),Budgets!$C$2:$C$200),0)) | AN13: =IF(OR(AN$1="",$BE13=0),"",IFERROR(LOOKUP(2,1/((Budgets!$A$2:$A$200=AN$1)*(Budgets!$B$2:$B$200<=$A13)),Budgets!$C$2:$C$200),0)) | AO13: =IF(OR(AO$1="",$BE13=0),"",IFERROR(LOOKUP(2,1/((Budgets!$A$2:$A$200=AO$1)*(Budgets!$B$2:$B$200<=$A13)),Budgets!$C$2:$C$200),0)) | AP13: =IF(OR(AP$1="",$BE13=0),"",IFERROR(LOOKUP(2,1/((Budgets!$A$2:$A$200=AP$1)*(Budgets!$B$2:$B$200<=$A13)),Budgets!$C$2:$C$200),0)) | AQ13: =IF(OR(AQ$1="",$BE13=0),"",IFERROR(LOOKUP(2,1/((Budgets!$A$2:$A$200=AQ$1)*(Budgets!$B$2:$B$200<=$A13)),Budgets!$C$2:$C$200),0)) | ... BC13: =IF(OR(BC$1="",$BE13=0),"",IFERROR(LOOKUP(2,1/((Budgets!$A$2:$A$200=BC$1)*(Budgets!$B$2:$B$200<=$A13)),Budgets!$C$2:$C$200),0)) | BE13: =COUNTIFS(Entries!$A$2:$A$5000,$A13)
A14: 39814 | B14: =IF($BE14=0,NA(),SUMIFS(Entries!$D$2:$D$5000,Entries!$C$2:$C$5000,"Income",Entries!$A$2:$A$5000,$A14)) | C14: =IF($BE14=0,"",SUMIFS(Entries!$D$2:$D$5000,Entries!$C$2:$C$5000,"Actual",Entries!$A$2:$A$5000,$A14)) | D14: =IF($BE14=0,"",SUMIFS(Entries!$D$2:$D$5000,Entries!$C$2:$C$5000,"One-off",Entries!$A$2:$A$5000,$A14)) | E14: =IF($BE14=0,NA(),C14+D14) | F14: =IF($BE14=0,"",SUM(AJ14:BC14)) | G14: =IF($BE14=0,"",B14-E14) | H14: =IF($BE14=0,"",SUM($G$2:G14)) | I14: =IF($BE14=0,"",SUMIFS(Entries!$F$2:$F$5000,Entries!$A$2:$A$5000,$A14)) | J14: =IF($BE14=0,NA(),H14+SUM($I$2:I14)) | K14: =IF($BE14=0,"",SUMIFS(Entries!$D$2:$D$5000,Entries!$C$2:$C$5000,"Income",Entries!$A$2:$A$5000,">="&EDATE($A14,-11),Entries!$A$2:$A$5000,"<="&$A14)/12) | L14: =IF($BE14=0,"",(SUMIFS(Entries!$D$2:$D$5000,Entries!$C$2:$C$5000,"Actual",Entries!$A$2:$A$5000,">="&EDATE($A14,-11),Entries!$A$2:$A$5000,"<="&$A14)+SUMIFS(Entries!$D$2:$D$5000,Entries!$C$2:$C$5000,"One-off",Entries!$A$2:$A$5000,">="&EDATE($A14,-11),Entries!$A$2:$A$5000,"<="&$A14))/12) | M14: =IF($BE14=0,NA(),IFERROR((K14-L14)/K14,0)) | O14: =IF(OR(O$1="",$BE14=0),"",SUMIFS(Entries!$D$2:$D$5000,Entries!$C$2:$C$5000,"Actual",Entries!$A$2:$A$5000,$A14,Entries!$B$2:$B$5000,O$1)) | P14: =IF(OR(P$1="",$BE14=0),"",SUMIFS(Entries!$D$2:$D$5000,Entries!$C$2:$C$5000,"Actual",Entries!$A$2:$A$5000,$A14,Entries!$B$2:$B$5000,P$1)) | Q14: =IF(OR(Q$1="",$BE14=0),"",SUMIFS(Entries!$D$2:$D$5000,Entries!$C$2:$C$5000,"Actual",Entries!$A$2:$A$5000,$A14,Entries!$B$2:$B$5000,Q$1)) | R14: =IF(OR(R$1="",$BE14=0),"",SUMIFS(Entries!$D$2:$D$5000,Entries!$C$2:$C$5000,"Actual",Entries!$A$2:$A$5000,$A14,Entries!$B$2:$B$5000,R$1)) | S14: =IF(OR(S$1="",$BE14=0),"",SUMIFS(Entries!$D$2:$D$5000,Entries!$C$2:$C$5000,"Actual",Entries!$A$2:$A$5000,$A14,Entries!$B$2:$B$5000,S$1)) | T14: =IF(OR(T$1="",$BE14=0),"",SUMIFS(Entries!$D$2:$D$5000,Entries!$C$2:$C$5000,"Actual",Entries!$A$2:$A$5000,$A14,Entries!$B$2:$B$5000,T$1)) | U14: =IF(OR(U$1="",$BE14=0),"",SUMIFS(Entries!$D$2:$D$5000,Entries!$C$2:$C$5000,"Actual",Entries!$A$2:$A$5000,$A14,Entries!$B$2:$B$5000,U$1)) | V14: =IF(OR(V$1="",$BE14=0),"",SUMIFS(Entries!$D$2:$D$5000,Entries!$C$2:$C$5000,"Actual",Entries!$A$2:$A$5000,$A14,Entries!$B$2:$B$5000,V$1)) | ... AH14: =IF(OR(AH$1="",$BE14=0),"",SUMIFS(Entries!$D$2:$D$5000,Entries!$C$2:$C$5000,"Actual",Entries!$A$2:$A$5000,$A14,Entries!$B$2:$B$5000,AH$1)) | AJ14: =IF(OR(AJ$1="",$BE14=0),"",IFERROR(LOOKUP(2,1/((Budgets!$A$2:$A$200=AJ$1)*(Budgets!$B$2:$B$200<=$A14)),Budgets!$C$2:$C$200),0)) | AK14: =IF(OR(AK$1="",$BE14=0),"",IFERROR(LOOKUP(2,1/((Budgets!$A$2:$A$200=AK$1)*(Budgets!$B$2:$B$200<=$A14)),Budgets!$C$2:$C$200),0)) | AL14: =IF(OR(AL$1="",$BE14=0),"",IFERROR(LOOKUP(2,1/((Budgets!$A$2:$A$200=AL$1)*(Budgets!$B$2:$B$200<=$A14)),Budgets!$C$2:$C$200),0)) | AM14: =IF(OR(AM$1="",$BE14=0),"",IFERROR(LOOKUP(2,1/((Budgets!$A$2:$A$200=AM$1)*(Budgets!$B$2:$B$200<=$A14)),Budgets!$C$2:$C$200),0)) | AN14: =IF(OR(AN$1="",$BE14=0),"",IFERROR(LOOKUP(2,1/((Budgets!$A$2:$A$200=AN$1)*(Budgets!$B$2:$B$200<=$A14)),Budgets!$C$2:$C$200),0)) | AO14: =IF(OR(AO$1="",$BE14=0),"",IFERROR(LOOKUP(2,1/((Budgets!$A$2:$A$200=AO$1)*(Budgets!$B$2:$B$200<=$A14)),Budgets!$C$2:$C$200),0)) | AP14: =IF(OR(AP$1="",$BE14=0),"",IFERROR(LOOKUP(2,1/((Budgets!$A$2:$A$200=AP$1)*(Budgets!$B$2:$B$200<=$A14)),Budgets!$C$2:$C$200),0)) | AQ14: =IF(OR(AQ$1="",$BE14=0),"",IFERROR(LOOKUP(2,1/((Budgets!$A$2:$A$200=AQ$1)*(Budgets!$B$2:$B$200<=$A14)),Budgets!$C$2:$C$200),0)) | ... BC14: =IF(OR(BC$1="",$BE14=0),"",IFERROR(LOOKUP(2,1/((Budgets!$A$2:$A$200=BC$1)*(Budgets!$B$2:$B$200<=$A14)),Budgets!$C$2:$C$200),0)) | BE14: =COUNTIFS(Entries!$A$2:$A$5000,$A14)
A15: 39845 | B15: =IF($BE15=0,NA(),SUMIFS(Entries!$D$2:$D$5000,Entries!$C$2:$C$5000,"Income",Entries!$A$2:$A$5000,$A15)) | C15: =IF($BE15=0,"",SUMIFS(Entries!$D$2:$D$5000,Entries!$C$2:$C$5000,"Actual",Entries!$A$2:$A$5000,$A15)) | D15: =IF($BE15=0,"",SUMIFS(Entries!$D$2:$D$5000,Entries!$C$2:$C$5000,"One-off",Entries!$A$2:$A$5000,$A15)) | E15: =IF($BE15=0,NA(),C15+D15) | F15: =IF($BE15=0,"",SUM(AJ15:BC15)) | G15: =IF($BE15=0,"",B15-E15) | H15: =IF($BE15=0,"",SUM($G$2:G15)) | I15: =IF($BE15=0,"",SUMIFS(Entries!$F$2:$F$5000,Entries!$A$2:$A$5000,$A15)) | J15: =IF($BE15=0,NA(),H15+SUM($I$2:I15)) | K15: =IF($BE15=0,"",SUMIFS(Entries!$D$2:$D$5000,Entries!$C$2:$C$5000,"Income",Entries!$A$2:$A$5000,">="&EDATE($A15,-11),Entries!$A$2:$A$5000,"<="&$A15)/12) | L15: =IF($BE15=0,"",(SUMIFS(Entries!$D$2:$D$5000,Entries!$C$2:$C$5000,"Actual",Entries!$A$2:$A$5000,">="&EDATE($A15,-11),Entries!$A$2:$A$5000,"<="&$A15)+SUMIFS(Entries!$D$2:$D$5000,Entries!$C$2:$C$5000,"One-off",Entries!$A$2:$A$5000,">="&EDATE($A15,-11),Entries!$A$2:$A$5000,"<="&$A15))/12) | M15: =IF($BE15=0,NA(),IFERROR((K15-L15)/K15,0)) | O15: =IF(OR(O$1="",$BE15=0),"",SUMIFS(Entries!$D$2:$D$5000,Entries!$C$2:$C$5000,"Actual",Entries!$A$2:$A$5000,$A15,Entries!$B$2:$B$5000,O$1)) | P15: =IF(OR(P$1="",$BE15=0),"",SUMIFS(Entries!$D$2:$D$5000,Entries!$C$2:$C$5000,"Actual",Entries!$A$2:$A$5000,$A15,Entries!$B$2:$B$5000,P$1)) | Q15: =IF(OR(Q$1="",$BE15=0),"",SUMIFS(Entries!$D$2:$D$5000,Entries!$C$2:$C$5000,"Actual",Entries!$A$2:$A$5000,$A15,Entries!$B$2:$B$5000,Q$1)) | R15: =IF(OR(R$1="",$BE15=0),"",SUMIFS(Entries!$D$2:$D$5000,Entries!$C$2:$C$5000,"Actual",Entries!$A$2:$A$5000,$A15,Entries!$B$2:$B$5000,R$1)) | S15: =IF(OR(S$1="",$BE15=0),"",SUMIFS(Entries!$D$2:$D$5000,Entries!$C$2:$C$5000,"Actual",Entries!$A$2:$A$5000,$A15,Entries!$B$2:$B$5000,S$1)) | T15: =IF(OR(T$1="",$BE15=0),"",SUMIFS(Entries!$D$2:$D$5000,Entries!$C$2:$C$5000,"Actual",Entries!$A$2:$A$5000,$A15,Entries!$B$2:$B$5000,T$1)) | U15: =IF(OR(U$1="",$BE15=0),"",SUMIFS(Entries!$D$2:$D$5000,Entries!$C$2:$C$5000,"Actual",Entries!$A$2:$A$5000,$A15,Entries!$B$2:$B$5000,U$1)) | V15: =IF(OR(V$1="",$BE15=0),"",SUMIFS(Entries!$D$2:$D$5000,Entries!$C$2:$C$5000,"Actual",Entries!$A$2:$A$5000,$A15,Entries!$B$2:$B$5000,V$1)) | ... AH15: =IF(OR(AH$1="",$BE15=0),"",SUMIFS(Entries!$D$2:$D$5000,Entries!$C$2:$C$5000,"Actual",Entries!$A$2:$A$5000,$A15,Entries!$B$2:$B$5000,AH$1)) | AJ15: =IF(OR(AJ$1="",$BE15=0),"",IFERROR(LOOKUP(2,1/((Budgets!$A$2:$A$200=AJ$1)*(Budgets!$B$2:$B$200<=$A15)),Budgets!$C$2:$C$200),0)) | AK15: =IF(OR(AK$1="",$BE15=0),"",IFERROR(LOOKUP(2,1/((Budgets!$A$2:$A$200=AK$1)*(Budgets!$B$2:$B$200<=$A15)),Budgets!$C$2:$C$200),0)) | AL15: =IF(OR(AL$1="",$BE15=0),"",IFERROR(LOOKUP(2,1/((Budgets!$A$2:$A$200=AL$1)*(Budgets!$B$2:$B$200<=$A15)),Budgets!$C$2:$C$200),0)) | AM15: =IF(OR(AM$1="",$BE15=0),"",IFERROR(LOOKUP(2,1/((Budgets!$A$2:$A$200=AM$1)*(Budgets!$B$2:$B$200<=$A15)),Budgets!$C$2:$C$200),0)) | AN15: =IF(OR(AN$1="",$BE15=0),"",IFERROR(LOOKUP(2,1/((Budgets!$A$2:$A$200=AN$1)*(Budgets!$B$2:$B$200<=$A15)),Budgets!$C$2:$C$200),0)) | AO15: =IF(OR(AO$1="",$BE15=0),"",IFERROR(LOOKUP(2,1/((Budgets!$A$2:$A$200=AO$1)*(Budgets!$B$2:$B$200<=$A15)),Budgets!$C$2:$C$200),0)) | AP15: =IF(OR(AP$1="",$BE15=0),"",IFERROR(LOOKUP(2,1/((Budgets!$A$2:$A$200=AP$1)*(Budgets!$B$2:$B$200<=$A15)),Budgets!$C$2:$C$200),0)) | AQ15: =IF(OR(AQ$1="",$BE15=0),"",IFERROR(LOOKUP(2,1/((Budgets!$A$2:$A$200=AQ$1)*(Budgets!$B$2:$B$200<=$A15)),Budgets!$C$2:$C$200),0)) | ... BC15: =IF(OR(BC$1="",$BE15=0),"",IFERROR(LOOKUP(2,1/((Budgets!$A$2:$A$200=BC$1)*(Budgets!$B$2:$B$200<=$A15)),Budgets!$C$2:$C$200),0)) | BE15: =COUNTIFS(Entries!$A$2:$A$5000,$A15)
A16: 39873 | B16: =IF($BE16=0,NA(),SUMIFS(Entries!$D$2:$D$5000,Entries!$C$2:$C$5000,"Income",Entries!$A$2:$A$5000,$A16)) | C16: =IF($BE16=0,"",SUMIFS(Entries!$D$2:$D$5000,Entries!$C$2:$C$5000,"Actual",Entries!$A$2:$A$5000,$A16)) | D16: =IF($BE16=0,"",SUMIFS(Entries!$D$2:$D$5000,Entries!$C$2:$C$5000,"One-off",Entries!$A$2:$A$5000,$A16)) | E16: =IF($BE16=0,NA(),C16+D16) | F16: =IF($BE16=0,"",SUM(AJ16:BC16)) | G16: =IF($BE16=0,"",B16-E16) | H16: =IF($BE16=0,"",SUM($G$2:G16)) | I16: =IF($BE16=0,"",SUMIFS(Entries!$F$2:$F$5000,Entries!$A$2:$A$5000,$A16)) | J16: =IF($BE16=0,NA(),H16+SUM($I$2:I16)) | K16: =IF($BE16=0,"",SUMIFS(Entries!$D$2:$D$5000,Entries!$C$2:$C$5000,"Income",Entries!$A$2:$A$5000,">="&EDATE($A16,-11),Entries!$A$2:$A$5000,"<="&$A16)/12) | L16: =IF($BE16=0,"",(SUMIFS(Entries!$D$2:$D$5000,Entries!$C$2:$C$5000,"Actual",Entries!$A$2:$A$5000,">="&EDATE($A16,-11),Entries!$A$2:$A$5000,"<="&$A16)+SUMIFS(Entries!$D$2:$D$5000,Entries!$C$2:$C$5000,"One-off",Entries!$A$2:$A$5000,">="&EDATE($A16,-11),Entries!$A$2:$A$5000,"<="&$A16))/12) | M16: =IF($BE16=0,NA(),IFERROR((K16-L16)/K16,0)) | O16: =IF(OR(O$1="",$BE16=0),"",SUMIFS(Entries!$D$2:$D$5000,Entries!$C$2:$C$5000,"Actual",Entries!$A$2:$A$5000,$A16,Entries!$B$2:$B$5000,O$1)) | P16: =IF(OR(P$1="",$BE16=0),"",SUMIFS(Entries!$D$2:$D$5000,Entries!$C$2:$C$5000,"Actual",Entries!$A$2:$A$5000,$A16,Entries!$B$2:$B$5000,P$1)) | Q16: =IF(OR(Q$1="",$BE16=0),"",SUMIFS(Entries!$D$2:$D$5000,Entries!$C$2:$C$5000,"Actual",Entries!$A$2:$A$5000,$A16,Entries!$B$2:$B$5000,Q$1)) | R16: =IF(OR(R$1="",$BE16=0),"",SUMIFS(Entries!$D$2:$D$5000,Entries!$C$2:$C$5000,"Actual",Entries!$A$2:$A$5000,$A16,Entries!$B$2:$B$5000,R$1)) | S16: =IF(OR(S$1="",$BE16=0),"",SUMIFS(Entries!$D$2:$D$5000,Entries!$C$2:$C$5000,"Actual",Entries!$A$2:$A$5000,$A16,Entries!$B$2:$B$5000,S$1)) | T16: =IF(OR(T$1="",$BE16=0),"",SUMIFS(Entries!$D$2:$D$5000,Entries!$C$2:$C$5000,"Actual",Entries!$A$2:$A$5000,$A16,Entries!$B$2:$B$5000,T$1)) | U16: =IF(OR(U$1="",$BE16=0),"",SUMIFS(Entries!$D$2:$D$5000,Entries!$C$2:$C$5000,"Actual",Entries!$A$2:$A$5000,$A16,Entries!$B$2:$B$5000,U$1)) | V16: =IF(OR(V$1="",$BE16=0),"",SUMIFS(Entries!$D$2:$D$5000,Entries!$C$2:$C$5000,"Actual",Entries!$A$2:$A$5000,$A16,Entries!$B$2:$B$5000,V$1)) | ... AH16: =IF(OR(AH$1="",$BE16=0),"",SUMIFS(Entries!$D$2:$D$5000,Entries!$C$2:$C$5000,"Actual",Entries!$A$2:$A$5000,$A16,Entries!$B$2:$B$5000,AH$1)) | AJ16: =IF(OR(AJ$1="",$BE16=0),"",IFERROR(LOOKUP(2,1/((Budgets!$A$2:$A$200=AJ$1)*(Budgets!$B$2:$B$200<=$A16)),Budgets!$C$2:$C$200),0)) | AK16: =IF(OR(AK$1="",$BE16=0),"",IFERROR(LOOKUP(2,1/((Budgets!$A$2:$A$200=AK$1)*(Budgets!$B$2:$B$200<=$A16)),Budgets!$C$2:$C$200),0)) | AL16: =IF(OR(AL$1="",$BE16=0),"",IFERROR(LOOKUP(2,1/((Budgets!$A$2:$A$200=AL$1)*(Budgets!$B$2:$B$200<=$A16)),Budgets!$C$2:$C$200),0)) | AM16: =IF(OR(AM$1="",$BE16=0),"",IFERROR(LOOKUP(2,1/((Budgets!$A$2:$A$200=AM$1)*(Budgets!$B$2:$B$200<=$A16)),Budgets!$C$2:$C$200),0)) | AN16: =IF(OR(AN$1="",$BE16=0),"",IFERROR(LOOKUP(2,1/((Budgets!$A$2:$A$200=AN$1)*(Budgets!$B$2:$B$200<=$A16)),Budgets!$C$2:$C$200),0)) | AO16: =IF(OR(AO$1="",$BE16=0),"",IFERROR(LOOKUP(2,1/((Budgets!$A$2:$A$200=AO$1)*(Budgets!$B$2:$B$200<=$A16)),Budgets!$C$2:$C$200),0)) | AP16: =IF(OR(AP$1="",$BE16=0),"",IFERROR(LOOKUP(2,1/((Budgets!$A$2:$A$200=AP$1)*(Budgets!$B$2:$B$200<=$A16)),Budgets!$C$2:$C$200),0)) | AQ16: =IF(OR(AQ$1="",$BE16=0),"",IFERROR(LOOKUP(2,1/((Budgets!$A$2:$A$200=AQ$1)*(Budgets!$B$2:$B$200<=$A16)),Budgets!$C$2:$C$200),0)) | ... BC16: =IF(OR(BC$1="",$BE16=0),"",IFERROR(LOOKUP(2,1/((Budgets!$A$2:$A$200=BC$1)*(Budgets!$B$2:$B$200<=$A16)),Budgets!$C$2:$C$200),0)) | BE16: =COUNTIFS(Entries!$A$2:$A$5000,$A16)
A17: 39904 | B17: =IF($BE17=0,NA(),SUMIFS(Entries!$D$2:$D$5000,Entries!$C$2:$C$5000,"Income",Entries!$A$2:$A$5000,$A17)) | C17: =IF($BE17=0,"",SUMIFS(Entries!$D$2:$D$5000,Entries!$C$2:$C$5000,"Actual",Entries!$A$2:$A$5000,$A17)) | D17: =IF($BE17=0,"",SUMIFS(Entries!$D$2:$D$5000,Entries!$C$2:$C$5000,"One-off",Entries!$A$2:$A$5000,$A17)) | E17: =IF($BE17=0,NA(),C17+D17) | F17: =IF($BE17=0,"",SUM(AJ17:BC17)) | G17: =IF($BE17=0,"",B17-E17) | H17: =IF($BE17=0,"",SUM($G$2:G17)) | I17: =IF($BE17=0,"",SUMIFS(Entries!$F$2:$F$5000,Entries!$A$2:$A$5000,$A17)) | J17: =IF($BE17=0,NA(),H17+SUM($I$2:I17)) | K17: =IF($BE17=0,"",SUMIFS(Entries!$D$2:$D$5000,Entries!$C$2:$C$5000,"Income",Entries!$A$2:$A$5000,">="&EDATE($A17,-11),Entries!$A$2:$A$5000,"<="&$A17)/12) | L17: =IF($BE17=0,"",(SUMIFS(Entries!$D$2:$D$5000,Entries!$C$2:$C$5000,"Actual",Entries!$A$2:$A$5000,">="&EDATE($A17,-11),Entries!$A$2:$A$5000,"<="&$A17)+SUMIFS(Entries!$D$2:$D$5000,Entries!$C$2:$C$5000,"One-off",Entries!$A$2:$A$5000,">="&EDATE($A17,-11),Entries!$A$2:$A$5000,"<="&$A17))/12) | M17: =IF($BE17=0,NA(),IFERROR((K17-L17)/K17,0)) | O17: =IF(OR(O$1="",$BE17=0),"",SUMIFS(Entries!$D$2:$D$5000,Entries!$C$2:$C$5000,"Actual",Entries!$A$2:$A$5000,$A17,Entries!$B$2:$B$5000,O$1)) | P17: =IF(OR(P$1="",$BE17=0),"",SUMIFS(Entries!$D$2:$D$5000,Entries!$C$2:$C$5000,"Actual",Entries!$A$2:$A$5000,$A17,Entries!$B$2:$B$5000,P$1)) | Q17: =IF(OR(Q$1="",$BE17=0),"",SUMIFS(Entries!$D$2:$D$5000,Entries!$C$2:$C$5000,"Actual",Entries!$A$2:$A$5000,$A17,Entries!$B$2:$B$5000,Q$1)) | R17: =IF(OR(R$1="",$BE17=0),"",SUMIFS(Entries!$D$2:$D$5000,Entries!$C$2:$C$5000,"Actual",Entries!$A$2:$A$5000,$A17,Entries!$B$2:$B$5000,R$1)) | S17: =IF(OR(S$1="",$BE17=0),"",SUMIFS(Entries!$D$2:$D$5000,Entries!$C$2:$C$5000,"Actual",Entries!$A$2:$A$5000,$A17,Entries!$B$2:$B$5000,S$1)) | T17: =IF(OR(T$1="",$BE17=0),"",SUMIFS(Entries!$D$2:$D$5000,Entries!$C$2:$C$5000,"Actual",Entries!$A$2:$A$5000,$A17,Entries!$B$2:$B$5000,T$1)) | U17: =IF(OR(U$1="",$BE17=0),"",SUMIFS(Entries!$D$2:$D$5000,Entries!$C$2:$C$5000,"Actual",Entries!$A$2:$A$5000,$A17,Entries!$B$2:$B$5000,U$1)) | V17: =IF(OR(V$1="",$BE17=0),"",SUMIFS(Entries!$D$2:$D$5000,Entries!$C$2:$C$5000,"Actual",Entries!$A$2:$A$5000,$A17,Entries!$B$2:$B$5000,V$1)) | ... AH17: =IF(OR(AH$1="",$BE17=0),"",SUMIFS(Entries!$D$2:$D$5000,Entries!$C$2:$C$5000,"Actual",Entries!$A$2:$A$5000,$A17,Entries!$B$2:$B$5000,AH$1)) | AJ17: =IF(OR(AJ$1="",$BE17=0),"",IFERROR(LOOKUP(2,1/((Budgets!$A$2:$A$200=AJ$1)*(Budgets!$B$2:$B$200<=$A17)),Budgets!$C$2:$C$200),0)) | AK17: =IF(OR(AK$1="",$BE17=0),"",IFERROR(LOOKUP(2,1/((Budgets!$A$2:$A$200=AK$1)*(Budgets!$B$2:$B$200<=$A17)),Budgets!$C$2:$C$200),0)) | AL17: =IF(OR(AL$1="",$BE17=0),"",IFERROR(LOOKUP(2,1/((Budgets!$A$2:$A$200=AL$1)*(Budgets!$B$2:$B$200<=$A17)),Budgets!$C$2:$C$200),0)) | AM17: =IF(OR(AM$1="",$BE17=0),"",IFERROR(LOOKUP(2,1/((Budgets!$A$2:$A$200=AM$1)*(Budgets!$B$2:$B$200<=$A17)),Budgets!$C$2:$C$200),0)) | AN17: =IF(OR(AN$1="",$BE17=0),"",IFERROR(LOOKUP(2,1/((Budgets!$A$2:$A$200=AN$1)*(Budgets!$B$2:$B$200<=$A17)),Budgets!$C$2:$C$200),0)) | AO17: =IF(OR(AO$1="",$BE17=0),"",IFERROR(LOOKUP(2,1/((Budgets!$A$2:$A$200=AO$1)*(Budgets!$B$2:$B$200<=$A17)),Budgets!$C$2:$C$200),0)) | AP17: =IF(OR(AP$1="",$BE17=0),"",IFERROR(LOOKUP(2,1/((Budgets!$A$2:$A$200=AP$1)*(Budgets!$B$2:$B$200<=$A17)),Budgets!$C$2:$C$200),0)) | AQ17: =IF(OR(AQ$1="",$BE17=0),"",IFERROR(LOOKUP(2,1/((Budgets!$A$2:$A$200=AQ$1)*(Budgets!$B$2:$B$200<=$A17)),Budgets!$C$2:$C$200),0)) | ... BC17: =IF(OR(BC$1="",$BE17=0),"",IFERROR(LOOKUP(2,1/((Budgets!$A$2:$A$200=BC$1)*(Budgets!$B$2:$B$200<=$A17)),Budgets!$C$2:$C$200),0)) | BE17: =COUNTIFS(Entries!$A$2:$A$5000,$A17)
A18: 39934 | B18: =IF($BE18=0,NA(),SUMIFS(Entries!$D$2:$D$5000,Entries!$C$2:$C$5000,"Income",Entries!$A$2:$A$5000,$A18)) | C18: =IF($BE18=0,"",SUMIFS(Entries!$D$2:$D$5000,Entries!$C$2:$C$5000,"Actual",Entries!$A$2:$A$5000,$A18)) | D18: =IF($BE18=0,"",SUMIFS(Entries!$D$2:$D$5000,Entries!$C$2:$C$5000,"One-off",Entries!$A$2:$A$5000,$A18)) | E18: =IF($BE18=0,NA(),C18+D18) | F18: =IF($BE18=0,"",SUM(AJ18:BC18)) | G18: =IF($BE18=0,"",B18-E18) | H18: =IF($BE18=0,"",SUM($G$2:G18)) | I18: =IF($BE18=0,"",SUMIFS(Entries!$F$2:$F$5000,Entries!$A$2:$A$5000,$A18)) | J18: =IF($BE18=0,NA(),H18+SUM($I$2:I18)) | K18: =IF($BE18=0,"",SUMIFS(Entries!$D$2:$D$5000,Entries!$C$2:$C$5000,"Income",Entries!$A$2:$A$5000,">="&EDATE($A18,-11),Entries!$A$2:$A$5000,"<="&$A18)/12) | L18: =IF($BE18=0,"",(SUMIFS(Entries!$D$2:$D$5000,Entries!$C$2:$C$5000,"Actual",Entries!$A$2:$A$5000,">="&EDATE($A18,-11),Entries!$A$2:$A$5000,"<="&$A18)+SUMIFS(Entries!$D$2:$D$5000,Entries!$C$2:$C$5000,"One-off",Entries!$A$2:$A$5000,">="&EDATE($A18,-11),Entries!$A$2:$A$5000,"<="&$A18))/12) | M18: =IF($BE18=0,NA(),IFERROR((K18-L18)/K18,0)) | O18: =IF(OR(O$1="",$BE18=0),"",SUMIFS(Entries!$D$2:$D$5000,Entries!$C$2:$C$5000,"Actual",Entries!$A$2:$A$5000,$A18,Entries!$B$2:$B$5000,O$1)) | P18: =IF(OR(P$1="",$BE18=0),"",SUMIFS(Entries!$D$2:$D$5000,Entries!$C$2:$C$5000,"Actual",Entries!$A$2:$A$5000,$A18,Entries!$B$2:$B$5000,P$1)) | Q18: =IF(OR(Q$1="",$BE18=0),"",SUMIFS(Entries!$D$2:$D$5000,Entries!$C$2:$C$5000,"Actual",Entries!$A$2:$A$5000,$A18,Entries!$B$2:$B$5000,Q$1)) | R18: =IF(OR(R$1="",$BE18=0),"",SUMIFS(Entries!$D$2:$D$5000,Entries!$C$2:$C$5000,"Actual",Entries!$A$2:$A$5000,$A18,Entries!$B$2:$B$5000,R$1)) | S18: =IF(OR(S$1="",$BE18=0),"",SUMIFS(Entries!$D$2:$D$5000,Entries!$C$2:$C$5000,"Actual",Entries!$A$2:$A$5000,$A18,Entries!$B$2:$B$5000,S$1)) | T18: =IF(OR(T$1="",$BE18=0),"",SUMIFS(Entries!$D$2:$D$5000,Entries!$C$2:$C$5000,"Actual",Entries!$A$2:$A$5000,$A18,Entries!$B$2:$B$5000,T$1)) | U18: =IF(OR(U$1="",$BE18=0),"",SUMIFS(Entries!$D$2:$D$5000,Entries!$C$2:$C$5000,"Actual",Entries!$A$2:$A$5000,$A18,Entries!$B$2:$B$5000,U$1)) | V18: =IF(OR(V$1="",$BE18=0),"",SUMIFS(Entries!$D$2:$D$5000,Entries!$C$2:$C$5000,"Actual",Entries!$A$2:$A$5000,$A18,Entries!$B$2:$B$5000,V$1)) | ... AH18: =IF(OR(AH$1="",$BE18=0),"",SUMIFS(Entries!$D$2:$D$5000,Entries!$C$2:$C$5000,"Actual",Entries!$A$2:$A$5000,$A18,Entries!$B$2:$B$5000,AH$1)) | AJ18: =IF(OR(AJ$1="",$BE18=0),"",IFERROR(LOOKUP(2,1/((Budgets!$A$2:$A$200=AJ$1)*(Budgets!$B$2:$B$200<=$A18)),Budgets!$C$2:$C$200),0)) | AK18: =IF(OR(AK$1="",$BE18=0),"",IFERROR(LOOKUP(2,1/((Budgets!$A$2:$A$200=AK$1)*(Budgets!$B$2:$B$200<=$A18)),Budgets!$C$2:$C$200),0)) | AL18: =IF(OR(AL$1="",$BE18=0),"",IFERROR(LOOKUP(2,1/((Budgets!$A$2:$A$200=AL$1)*(Budgets!$B$2:$B$200<=$A18)),Budgets!$C$2:$C$200),0)) | AM18: =IF(OR(AM$1="",$BE18=0),"",IFERROR(LOOKUP(2,1/((Budgets!$A$2:$A$200=AM$1)*(Budgets!$B$2:$B$200<=$A18)),Budgets!$C$2:$C$200),0)) | AN18: =IF(OR(AN$1="",$BE18=0),"",IFERROR(LOOKUP(2,1/((Budgets!$A$2:$A$200=AN$1)*(Budgets!$B$2:$B$200<=$A18)),Budgets!$C$2:$C$200),0)) | AO18: =IF(OR(AO$1="",$BE18=0),"",IFERROR(LOOKUP(2,1/((Budgets!$A$2:$A$200=AO$1)*(Budgets!$B$2:$B$200<=$A18)),Budgets!$C$2:$C$200),0)) | AP18: =IF(OR(AP$1="",$BE18=0),"",IFERROR(LOOKUP(2,1/((Budgets!$A$2:$A$200=AP$1)*(Budgets!$B$2:$B$200<=$A18)),Budgets!$C$2:$C$200),0)) | AQ18: =IF(OR(AQ$1="",$BE18=0),"",IFERROR(LOOKUP(2,1/((Budgets!$A$2:$A$200=AQ$1)*(Budgets!$B$2:$B$200<=$A18)),Budgets!$C$2:$C$200),0)) | ... BC18: =IF(OR(BC$1="",$BE18=0),"",IFERROR(LOOKUP(2,1/((Budgets!$A$2:$A$200=BC$1)*(Budgets!$B$2:$B$200<=$A18)),Budgets!$C$2:$C$200),0)) | BE18: =COUNTIFS(Entries!$A$2:$A$5000,$A18)
A19: 39965 | B19: =IF($BE19=0,NA(),SUMIFS(Entries!$D$2:$D$5000,Entries!$C$2:$C$5000,"Income",Entries!$A$2:$A$5000,$A19)) | C19: =IF($BE19=0,"",SUMIFS(Entries!$D$2:$D$5000,Entries!$C$2:$C$5000,"Actual",Entries!$A$2:$A$5000,$A19)) | D19: =IF($BE19=0,"",SUMIFS(Entries!$D$2:$D$5000,Entries!$C$2:$C$5000,"One-off",Entries!$A$2:$A$5000,$A19)) | E19: =IF($BE19=0,NA(),C19+D19) | F19: =IF($BE19=0,"",SUM(AJ19:BC19)) | G19: =IF($BE19=0,"",B19-E19) | H19: =IF($BE19=0,"",SUM($G$2:G19)) | I19: =IF($BE19=0,"",SUMIFS(Entries!$F$2:$F$5000,Entries!$A$2:$A$5000,$A19)) | J19: =IF($BE19=0,NA(),H19+SUM($I$2:I19)) | K19: =IF($BE19=0,"",SUMIFS(Entries!$D$2:$D$5000,Entries!$C$2:$C$5000,"Income",Entries!$A$2:$A$5000,">="&EDATE($A19,-11),Entries!$A$2:$A$5000,"<="&$A19)/12) | L19: =IF($BE19=0,"",(SUMIFS(Entries!$D$2:$D$5000,Entries!$C$2:$C$5000,"Actual",Entries!$A$2:$A$5000,">="&EDATE($A19,-11),Entries!$A$2:$A$5000,"<="&$A19)+SUMIFS(Entries!$D$2:$D$5000,Entries!$C$2:$C$5000,"One-off",Entries!$A$2:$A$5000,">="&EDATE($A19,-11),Entries!$A$2:$A$5000,"<="&$A19))/12) | M19: =IF($BE19=0,NA(),IFERROR((K19-L19)/K19,0)) | O19: =IF(OR(O$1="",$BE19=0),"",SUMIFS(Entries!$D$2:$D$5000,Entries!$C$2:$C$5000,"Actual",Entries!$A$2:$A$5000,$A19,Entries!$B$2:$B$5000,O$1)) | P19: =IF(OR(P$1="",$BE19=0),"",SUMIFS(Entries!$D$2:$D$5000,Entries!$C$2:$C$5000,"Actual",Entries!$A$2:$A$5000,$A19,Entries!$B$2:$B$5000,P$1)) | Q19: =IF(OR(Q$1="",$BE19=0),"",SUMIFS(Entries!$D$2:$D$5000,Entries!$C$2:$C$5000,"Actual",Entries!$A$2:$A$5000,$A19,Entries!$B$2:$B$5000,Q$1)) | R19: =IF(OR(R$1="",$BE19=0),"",SUMIFS(Entries!$D$2:$D$5000,Entries!$C$2:$C$5000,"Actual",Entries!$A$2:$A$5000,$A19,Entries!$B$2:$B$5000,R$1)) | S19: =IF(OR(S$1="",$BE19=0),"",SUMIFS(Entries!$D$2:$D$5000,Entries!$C$2:$C$5000,"Actual",Entries!$A$2:$A$5000,$A19,Entries!$B$2:$B$5000,S$1)) | T19: =IF(OR(T$1="",$BE19=0),"",SUMIFS(Entries!$D$2:$D$5000,Entries!$C$2:$C$5000,"Actual",Entries!$A$2:$A$5000,$A19,Entries!$B$2:$B$5000,T$1)) | U19: =IF(OR(U$1="",$BE19=0),"",SUMIFS(Entries!$D$2:$D$5000,Entries!$C$2:$C$5000,"Actual",Entries!$A$2:$A$5000,$A19,Entries!$B$2:$B$5000,U$1)) | V19: =IF(OR(V$1="",$BE19=0),"",SUMIFS(Entries!$D$2:$D$5000,Entries!$C$2:$C$5000,"Actual",Entries!$A$2:$A$5000,$A19,Entries!$B$2:$B$5000,V$1)) | ... AH19: =IF(OR(AH$1="",$BE19=0),"",SUMIFS(Entries!$D$2:$D$5000,Entries!$C$2:$C$5000,"Actual",Entries!$A$2:$A$5000,$A19,Entries!$B$2:$B$5000,AH$1)) | AJ19: =IF(OR(AJ$1="",$BE19=0),"",IFERROR(LOOKUP(2,1/((Budgets!$A$2:$A$200=AJ$1)*(Budgets!$B$2:$B$200<=$A19)),Budgets!$C$2:$C$200),0)) | AK19: =IF(OR(AK$1="",$BE19=0),"",IFERROR(LOOKUP(2,1/((Budgets!$A$2:$A$200=AK$1)*(Budgets!$B$2:$B$200<=$A19)),Budgets!$C$2:$C$200),0)) | AL19: =IF(OR(AL$1="",$BE19=0),"",IFERROR(LOOKUP(2,1/((Budgets!$A$2:$A$200=AL$1)*(Budgets!$B$2:$B$200<=$A19)),Budgets!$C$2:$C$200),0)) | AM19: =IF(OR(AM$1="",$BE19=0),"",IFERROR(LOOKUP(2,1/((Budgets!$A$2:$A$200=AM$1)*(Budgets!$B$2:$B$200<=$A19)),Budgets!$C$2:$C$200),0)) | AN19: =IF(OR(AN$1="",$BE19=0),"",IFERROR(LOOKUP(2,1/((Budgets!$A$2:$A$200=AN$1)*(Budgets!$B$2:$B$200<=$A19)),Budgets!$C$2:$C$200),0)) | AO19: =IF(OR(AO$1="",$BE19=0),"",IFERROR(LOOKUP(2,1/((Budgets!$A$2:$A$200=AO$1)*(Budgets!$B$2:$B$200<=$A19)),Budgets!$C$2:$C$200),0)) | AP19: =IF(OR(AP$1="",$BE19=0),"",IFERROR(LOOKUP(2,1/((Budgets!$A$2:$A$200=AP$1)*(Budgets!$B$2:$B$200<=$A19)),Budgets!$C$2:$C$200),0)) | AQ19: =IF(OR(AQ$1="",$BE19=0),"",IFERROR(LOOKUP(2,1/((Budgets!$A$2:$A$200=AQ$1)*(Budgets!$B$2:$B$200<=$A19)),Budgets!$C$2:$C$200),0)) | ... BC19: =IF(OR(BC$1="",$BE19=0),"",IFERROR(LOOKUP(2,1/((Budgets!$A$2:$A$200=BC$1)*(Budgets!$B$2:$B$200<=$A19)),Budgets!$C$2:$C$200),0)) | BE19: =COUNTIFS(Entries!$A$2:$A$5000,$A19)
A20: 39995 | B20: =IF($BE20=0,NA(),SUMIFS(Entries!$D$2:$D$5000,Entries!$C$2:$C$5000,"Income",Entries!$A$2:$A$5000,$A20)) | C20: =IF($BE20=0,"",SUMIFS(Entries!$D$2:$D$5000,Entries!$C$2:$C$5000,"Actual",Entries!$A$2:$A$5000,$A20)) | D20: =IF($BE20=0,"",SUMIFS(Entries!$D$2:$D$5000,Entries!$C$2:$C$5000,"One-off",Entries!$A$2:$A$5000,$A20)) | E20: =IF($BE20=0,NA(),C20+D20) | F20: =IF($BE20=0,"",SUM(AJ20:BC20)) | G20: =IF($BE20=0,"",B20-E20) | H20: =IF($BE20=0,"",SUM($G$2:G20)) | I20: =IF($BE20=0,"",SUMIFS(Entries!$F$2:$F$5000,Entries!$A$2:$A$5000,$A20)) | J20: =IF($BE20=0,NA(),H20+SUM($I$2:I20)) | K20: =IF($BE20=0,"",SUMIFS(Entries!$D$2:$D$5000,Entries!$C$2:$C$5000,"Income",Entries!$A$2:$A$5000,">="&EDATE($A20,-11),Entries!$A$2:$A$5000,"<="&$A20)/12) | L20: =IF($BE20=0,"",(SUMIFS(Entries!$D$2:$D$5000,Entries!$C$2:$C$5000,"Actual",Entries!$A$2:$A$5000,">="&EDATE($A20,-11),Entries!$A$2:$A$5000,"<="&$A20)+SUMIFS(Entries!$D$2:$D$5000,Entries!$C$2:$C$5000,"One-off",Entries!$A$2:$A$5000,">="&EDATE($A20,-11),Entries!$A$2:$A$5000,"<="&$A20))/12) | M20: =IF($BE20=0,NA(),IFERROR((K20-L20)/K20,0)) | O20: =IF(OR(O$1="",$BE20=0),"",SUMIFS(Entries!$D$2:$D$5000,Entries!$C$2:$C$5000,"Actual",Entries!$A$2:$A$5000,$A20,Entries!$B$2:$B$5000,O$1)) | P20: =IF(OR(P$1="",$BE20=0),"",SUMIFS(Entries!$D$2:$D$5000,Entries!$C$2:$C$5000,"Actual",Entries!$A$2:$A$5000,$A20,Entries!$B$2:$B$5000,P$1)) | Q20: =IF(OR(Q$1="",$BE20=0),"",SUMIFS(Entries!$D$2:$D$5000,Entries!$C$2:$C$5000,"Actual",Entries!$A$2:$A$5000,$A20,Entries!$B$2:$B$5000,Q$1)) | R20: =IF(OR(R$1="",$BE20=0),"",SUMIFS(Entries!$D$2:$D$5000,Entries!$C$2:$C$5000,"Actual",Entries!$A$2:$A$5000,$A20,Entries!$B$2:$B$5000,R$1)) | S20: =IF(OR(S$1="",$BE20=0),"",SUMIFS(Entries!$D$2:$D$5000,Entries!$C$2:$C$5000,"Actual",Entries!$A$2:$A$5000,$A20,Entries!$B$2:$B$5000,S$1)) | T20: =IF(OR(T$1="",$BE20=0),"",SUMIFS(Entries!$D$2:$D$5000,Entries!$C$2:$C$5000,"Actual",Entries!$A$2:$A$5000,$A20,Entries!$B$2:$B$5000,T$1)) | U20: =IF(OR(U$1="",$BE20=0),"",SUMIFS(Entries!$D$2:$D$5000,Entries!$C$2:$C$5000,"Actual",Entries!$A$2:$A$5000,$A20,Entries!$B$2:$B$5000,U$1)) | V20: =IF(OR(V$1="",$BE20=0),"",SUMIFS(Entries!$D$2:$D$5000,Entries!$C$2:$C$5000,"Actual",Entries!$A$2:$A$5000,$A20,Entries!$B$2:$B$5000,V$1)) | ... AH20: =IF(OR(AH$1="",$BE20=0),"",SUMIFS(Entries!$D$2:$D$5000,Entries!$C$2:$C$5000,"Actual",Entries!$A$2:$A$5000,$A20,Entries!$B$2:$B$5000,AH$1)) | AJ20: =IF(OR(AJ$1="",$BE20=0),"",IFERROR(LOOKUP(2,1/((Budgets!$A$2:$A$200=AJ$1)*(Budgets!$B$2:$B$200<=$A20)),Budgets!$C$2:$C$200),0)) | AK20: =IF(OR(AK$1="",$BE20=0),"",IFERROR(LOOKUP(2,1/((Budgets!$A$2:$A$200=AK$1)*(Budgets!$B$2:$B$200<=$A20)),Budgets!$C$2:$C$200),0)) | AL20: =IF(OR(AL$1="",$BE20=0),"",IFERROR(LOOKUP(2,1/((Budgets!$A$2:$A$200=AL$1)*(Budgets!$B$2:$B$200<=$A20)),Budgets!$C$2:$C$200),0)) | AM20: =IF(OR(AM$1="",$BE20=0),"",IFERROR(LOOKUP(2,1/((Budgets!$A$2:$A$200=AM$1)*(Budgets!$B$2:$B$200<=$A20)),Budgets!$C$2:$C$200),0)) | AN20: =IF(OR(AN$1="",$BE20=0),"",IFERROR(LOOKUP(2,1/((Budgets!$A$2:$A$200=AN$1)*(Budgets!$B$2:$B$200<=$A20)),Budgets!$C$2:$C$200),0)) | AO20: =IF(OR(AO$1="",$BE20=0),"",IFERROR(LOOKUP(2,1/((Budgets!$A$2:$A$200=AO$1)*(Budgets!$B$2:$B$200<=$A20)),Budgets!$C$2:$C$200),0)) | AP20: =IF(OR(AP$1="",$BE20=0),"",IFERROR(LOOKUP(2,1/((Budgets!$A$2:$A$200=AP$1)*(Budgets!$B$2:$B$200<=$A20)),Budgets!$C$2:$C$200),0)) | AQ20: =IF(OR(AQ$1="",$BE20=0),"",IFERROR(LOOKUP(2,1/((Budgets!$A$2:$A$200=AQ$1)*(Budgets!$B$2:$B$200<=$A20)),Budgets!$C$2:$C$200),0)) | ... BC20: =IF(OR(BC$1="",$BE20=0),"",IFERROR(LOOKUP(2,1/((Budgets!$A$2:$A$200=BC$1)*(Budgets!$B$2:$B$200<=$A20)),Budgets!$C$2:$C$200),0)) | BE20: =COUNTIFS(Entries!$A$2:$A$5000,$A20)
A21: 40026 | B21: =IF($BE21=0,NA(),SUMIFS(Entries!$D$2:$D$5000,Entries!$C$2:$C$5000,"Income",Entries!$A$2:$A$5000,$A21)) | C21: =IF($BE21=0,"",SUMIFS(Entries!$D$2:$D$5000,Entries!$C$2:$C$5000,"Actual",Entries!$A$2:$A$5000,$A21)) | D21: =IF($BE21=0,"",SUMIFS(Entries!$D$2:$D$5000,Entries!$C$2:$C$5000,"One-off",Entries!$A$2:$A$5000,$A21)) | E21: =IF($BE21=0,NA(),C21+D21) | F21: =IF($BE21=0,"",SUM(AJ21:BC21)) | G21: =IF($BE21=0,"",B21-E21) | H21: =IF($BE21=0,"",SUM($G$2:G21)) | I21: =IF($BE21=0,"",SUMIFS(Entries!$F$2:$F$5000,Entries!$A$2:$A$5000,$A21)) | J21: =IF($BE21=0,NA(),H21+SUM($I$2:I21)) | K21: =IF($BE21=0,"",SUMIFS(Entries!$D$2:$D$5000,Entries!$C$2:$C$5000,"Income",Entries!$A$2:$A$5000,">="&EDATE($A21,-11),Entries!$A$2:$A$5000,"<="&$A21)/12) | L21: =IF($BE21=0,"",(SUMIFS(Entries!$D$2:$D$5000,Entries!$C$2:$C$5000,"Actual",Entries!$A$2:$A$5000,">="&EDATE($A21,-11),Entries!$A$2:$A$5000,"<="&$A21)+SUMIFS(Entries!$D$2:$D$5000,Entries!$C$2:$C$5000,"One-off",Entries!$A$2:$A$5000,">="&EDATE($A21,-11),Entries!$A$2:$A$5000,"<="&$A21))/12) | M21: =IF($BE21=0,NA(),IFERROR((K21-L21)/K21,0)) | O21: =IF(OR(O$1="",$BE21=0),"",SUMIFS(Entries!$D$2:$D$5000,Entries!$C$2:$C$5000,"Actual",Entries!$A$2:$A$5000,$A21,Entries!$B$2:$B$5000,O$1)) | P21: =IF(OR(P$1="",$BE21=0),"",SUMIFS(Entries!$D$2:$D$5000,Entries!$C$2:$C$5000,"Actual",Entries!$A$2:$A$5000,$A21,Entries!$B$2:$B$5000,P$1)) | Q21: =IF(OR(Q$1="",$BE21=0),"",SUMIFS(Entries!$D$2:$D$5000,Entries!$C$2:$C$5000,"Actual",Entries!$A$2:$A$5000,$A21,Entries!$B$2:$B$5000,Q$1)) | R21: =IF(OR(R$1="",$BE21=0),"",SUMIFS(Entries!$D$2:$D$5000,Entries!$C$2:$C$5000,"Actual",Entries!$A$2:$A$5000,$A21,Entries!$B$2:$B$5000,R$1)) | S21: =IF(OR(S$1="",$BE21=0),"",SUMIFS(Entries!$D$2:$D$5000,Entries!$C$2:$C$5000,"Actual",Entries!$A$2:$A$5000,$A21,Entries!$B$2:$B$5000,S$1)) | T21: =IF(OR(T$1="",$BE21=0),"",SUMIFS(Entries!$D$2:$D$5000,Entries!$C$2:$C$5000,"Actual",Entries!$A$2:$A$5000,$A21,Entries!$B$2:$B$5000,T$1)) | U21: =IF(OR(U$1="",$BE21=0),"",SUMIFS(Entries!$D$2:$D$5000,Entries!$C$2:$C$5000,"Actual",Entries!$A$2:$A$5000,$A21,Entries!$B$2:$B$5000,U$1)) | V21: =IF(OR(V$1="",$BE21=0),"",SUMIFS(Entries!$D$2:$D$5000,Entries!$C$2:$C$5000,"Actual",Entries!$A$2:$A$5000,$A21,Entries!$B$2:$B$5000,V$1)) | ... AH21: =IF(OR(AH$1="",$BE21=0),"",SUMIFS(Entries!$D$2:$D$5000,Entries!$C$2:$C$5000,"Actual",Entries!$A$2:$A$5000,$A21,Entries!$B$2:$B$5000,AH$1)) | AJ21: =IF(OR(AJ$1="",$BE21=0),"",IFERROR(LOOKUP(2,1/((Budgets!$A$2:$A$200=AJ$1)*(Budgets!$B$2:$B$200<=$A21)),Budgets!$C$2:$C$200),0)) | AK21: =IF(OR(AK$1="",$BE21=0),"",IFERROR(LOOKUP(2,1/((Budgets!$A$2:$A$200=AK$1)*(Budgets!$B$2:$B$200<=$A21)),Budgets!$C$2:$C$200),0)) | AL21: =IF(OR(AL$1="",$BE21=0),"",IFERROR(LOOKUP(2,1/((Budgets!$A$2:$A$200=AL$1)*(Budgets!$B$2:$B$200<=$A21)),Budgets!$C$2:$C$200),0)) | AM21: =IF(OR(AM$1="",$BE21=0),"",IFERROR(LOOKUP(2,1/((Budgets!$A$2:$A$200=AM$1)*(Budgets!$B$2:$B$200<=$A21)),Budgets!$C$2:$C$200),0)) | AN21: =IF(OR(AN$1="",$BE21=0),"",IFERROR(LOOKUP(2,1/((Budgets!$A$2:$A$200=AN$1)*(Budgets!$B$2:$B$200<=$A21)),Budgets!$C$2:$C$200),0)) | AO21: =IF(OR(AO$1="",$BE21=0),"",IFERROR(LOOKUP(2,1/((Budgets!$A$2:$A$200=AO$1)*(Budgets!$B$2:$B$200<=$A21)),Budgets!$C$2:$C$200),0)) | AP21: =IF(OR(AP$1="",$BE21=0),"",IFERROR(LOOKUP(2,1/((Budgets!$A$2:$A$200=AP$1)*(Budgets!$B$2:$B$200<=$A21)),Budgets!$C$2:$C$200),0)) | AQ21: =IF(OR(AQ$1="",$BE21=0),"",IFERROR(LOOKUP(2,1/((Budgets!$A$2:$A$200=AQ$1)*(Budgets!$B$2:$B$200<=$A21)),Budgets!$C$2:$C$200),0)) | ... BC21: =IF(OR(BC$1="",$BE21=0),"",IFERROR(LOOKUP(2,1/((Budgets!$A$2:$A$200=BC$1)*(Budgets!$B$2:$B$200<=$A21)),Budgets!$C$2:$C$200),0)) | BE21: =COUNTIFS(Entries!$A$2:$A$5000,$A21)
A22: 40057 | B22: =IF($BE22=0,NA(),SUMIFS(Entries!$D$2:$D$5000,Entries!$C$2:$C$5000,"Income",Entries!$A$2:$A$5000,$A22)) | C22: =IF($BE22=0,"",SUMIFS(Entries!$D$2:$D$5000,Entries!$C$2:$C$5000,"Actual",Entries!$A$2:$A$5000,$A22)) | D22: =IF($BE22=0,"",SUMIFS(Entries!$D$2:$D$5000,Entries!$C$2:$C$5000,"One-off",Entries!$A$2:$A$5000,$A22)) | E22: =IF($BE22=0,NA(),C22+D22) | F22: =IF($BE22=0,"",SUM(AJ22:BC22)) | G22: =IF($BE22=0,"",B22-E22) | H22: =IF($BE22=0,"",SUM($G$2:G22)) | I22: =IF($BE22=0,"",SUMIFS(Entries!$F$2:$F$5000,Entries!$A$2:$A$5000,$A22)) | J22: =IF($BE22=0,NA(),H22+SUM($I$2:I22)) | K22: =IF($BE22=0,"",SUMIFS(Entries!$D$2:$D$5000,Entries!$C$2:$C$5000,"Income",Entries!$A$2:$A$5000,">="&EDATE($A22,-11),Entries!$A$2:$A$5000,"<="&$A22)/12) | L22: =IF($BE22=0,"",(SUMIFS(Entries!$D$2:$D$5000,Entries!$C$2:$C$5000,"Actual",Entries!$A$2:$A$5000,">="&EDATE($A22,-11),Entries!$A$2:$A$5000,"<="&$A22)+SUMIFS(Entries!$D$2:$D$5000,Entries!$C$2:$C$5000,"One-off",Entries!$A$2:$A$5000,">="&EDATE($A22,-11),Entries!$A$2:$A$5000,"<="&$A22))/12) | M22: =IF($BE22=0,NA(),IFERROR((K22-L22)/K22,0)) | O22: =IF(OR(O$1="",$BE22=0),"",SUMIFS(Entries!$D$2:$D$5000,Entries!$C$2:$C$5000,"Actual",Entries!$A$2:$A$5000,$A22,Entries!$B$2:$B$5000,O$1)) | P22: =IF(OR(P$1="",$BE22=0),"",SUMIFS(Entries!$D$2:$D$5000,Entries!$C$2:$C$5000,"Actual",Entries!$A$2:$A$5000,$A22,Entries!$B$2:$B$5000,P$1)) | Q22: =IF(OR(Q$1="",$BE22=0),"",SUMIFS(Entries!$D$2:$D$5000,Entries!$C$2:$C$5000,"Actual",Entries!$A$2:$A$5000,$A22,Entries!$B$2:$B$5000,Q$1)) | R22: =IF(OR(R$1="",$BE22=0),"",SUMIFS(Entries!$D$2:$D$5000,Entries!$C$2:$C$5000,"Actual",Entries!$A$2:$A$5000,$A22,Entries!$B$2:$B$5000,R$1)) | S22: =IF(OR(S$1="",$BE22=0),"",SUMIFS(Entries!$D$2:$D$5000,Entries!$C$2:$C$5000,"Actual",Entries!$A$2:$A$5000,$A22,Entries!$B$2:$B$5000,S$1)) | T22: =IF(OR(T$1="",$BE22=0),"",SUMIFS(Entries!$D$2:$D$5000,Entries!$C$2:$C$5000,"Actual",Entries!$A$2:$A$5000,$A22,Entries!$B$2:$B$5000,T$1)) | U22: =IF(OR(U$1="",$BE22=0),"",SUMIFS(Entries!$D$2:$D$5000,Entries!$C$2:$C$5000,"Actual",Entries!$A$2:$A$5000,$A22,Entries!$B$2:$B$5000,U$1)) | V22: =IF(OR(V$1="",$BE22=0),"",SUMIFS(Entries!$D$2:$D$5000,Entries!$C$2:$C$5000,"Actual",Entries!$A$2:$A$5000,$A22,Entries!$B$2:$B$5000,V$1)) | ... AH22: =IF(OR(AH$1="",$BE22=0),"",SUMIFS(Entries!$D$2:$D$5000,Entries!$C$2:$C$5000,"Actual",Entries!$A$2:$A$5000,$A22,Entries!$B$2:$B$5000,AH$1)) | AJ22: =IF(OR(AJ$1="",$BE22=0),"",IFERROR(LOOKUP(2,1/((Budgets!$A$2:$A$200=AJ$1)*(Budgets!$B$2:$B$200<=$A22)),Budgets!$C$2:$C$200),0)) | AK22: =IF(OR(AK$1="",$BE22=0),"",IFERROR(LOOKUP(2,1/((Budgets!$A$2:$A$200=AK$1)*(Budgets!$B$2:$B$200<=$A22)),Budgets!$C$2:$C$200),0)) | AL22: =IF(OR(AL$1="",$BE22=0),"",IFERROR(LOOKUP(2,1/((Budgets!$A$2:$A$200=AL$1)*(Budgets!$B$2:$B$200<=$A22)),Budgets!$C$2:$C$200),0)) | AM22: =IF(OR(AM$1="",$BE22=0),"",IFERROR(LOOKUP(2,1/((Budgets!$A$2:$A$200=AM$1)*(Budgets!$B$2:$B$200<=$A22)),Budgets!$C$2:$C$200),0)) | AN22: =IF(OR(AN$1="",$BE22=0),"",IFERROR(LOOKUP(2,1/((Budgets!$A$2:$A$200=AN$1)*(Budgets!$B$2:$B$200<=$A22)),Budgets!$C$2:$C$200),0)) | AO22: =IF(OR(AO$1="",$BE22=0),"",IFERROR(LOOKUP(2,1/((Budgets!$A$2:$A$200=AO$1)*(Budgets!$B$2:$B$200<=$A22)),Budgets!$C$2:$C$200),0)) | AP22: =IF(OR(AP$1="",$BE22=0),"",IFERROR(LOOKUP(2,1/((Budgets!$A$2:$A$200=AP$1)*(Budgets!$B$2:$B$200<=$A22)),Budgets!$C$2:$C$200),0)) | AQ22: =IF(OR(AQ$1="",$BE22=0),"",IFERROR(LOOKUP(2,1/((Budgets!$A$2:$A$200=AQ$1)*(Budgets!$B$2:$B$200<=$A22)),Budgets!$C$2:$C$200),0)) | ... BC22: =IF(OR(BC$1="",$BE22=0),"",IFERROR(LOOKUP(2,1/((Budgets!$A$2:$A$200=BC$1)*(Budgets!$B$2:$B$200<=$A22)),Budgets!$C$2:$C$200),0)) | BE22: =COUNTIFS(Entries!$A$2:$A$5000,$A22)
A23: 40087 | B23: =IF($BE23=0,NA(),SUMIFS(Entries!$D$2:$D$5000,Entries!$C$2:$C$5000,"Income",Entries!$A$2:$A$5000,$A23)) | C23: =IF($BE23=0,"",SUMIFS(Entries!$D$2:$D$5000,Entries!$C$2:$C$5000,"Actual",Entries!$A$2:$A$5000,$A23)) | D23: =IF($BE23=0,"",SUMIFS(Entries!$D$2:$D$5000,Entries!$C$2:$C$5000,"One-off",Entries!$A$2:$A$5000,$A23)) | E23: =IF($BE23=0,NA(),C23+D23) | F23: =IF($BE23=0,"",SUM(AJ23:BC23)) | G23: =IF($BE23=0,"",B23-E23) | H23: =IF($BE23=0,"",SUM($G$2:G23)) | I23: =IF($BE23=0,"",SUMIFS(Entries!$F$2:$F$5000,Entries!$A$2:$A$5000,$A23)) | J23: =IF($BE23=0,NA(),H23+SUM($I$2:I23)) | K23: =IF($BE23=0,"",SUMIFS(Entries!$D$2:$D$5000,Entries!$C$2:$C$5000,"Income",Entries!$A$2:$A$5000,">="&EDATE($A23,-11),Entries!$A$2:$A$5000,"<="&$A23)/12) | L23: =IF($BE23=0,"",(SUMIFS(Entries!$D$2:$D$5000,Entries!$C$2:$C$5000,"Actual",Entries!$A$2:$A$5000,">="&EDATE($A23,-11),Entries!$A$2:$A$5000,"<="&$A23)+SUMIFS(Entries!$D$2:$D$5000,Entries!$C$2:$C$5000,"One-off",Entries!$A$2:$A$5000,">="&EDATE($A23,-11),Entries!$A$2:$A$5000,"<="&$A23))/12) | M23: =IF($BE23=0,NA(),IFERROR((K23-L23)/K23,0)) | O23: =IF(OR(O$1="",$BE23=0),"",SUMIFS(Entries!$D$2:$D$5000,Entries!$C$2:$C$5000,"Actual",Entries!$A$2:$A$5000,$A23,Entries!$B$2:$B$5000,O$1)) | P23: =IF(OR(P$1="",$BE23=0),"",SUMIFS(Entries!$D$2:$D$5000,Entries!$C$2:$C$5000,"Actual",Entries!$A$2:$A$5000,$A23,Entries!$B$2:$B$5000,P$1)) | Q23: =IF(OR(Q$1="",$BE23=0),"",SUMIFS(Entries!$D$2:$D$5000,Entries!$C$2:$C$5000,"Actual",Entries!$A$2:$A$5000,$A23,Entries!$B$2:$B$5000,Q$1)) | R23: =IF(OR(R$1="",$BE23=0),"",SUMIFS(Entries!$D$2:$D$5000,Entries!$C$2:$C$5000,"Actual",Entries!$A$2:$A$5000,$A23,Entries!$B$2:$B$5000,R$1)) | S23: =IF(OR(S$1="",$BE23=0),"",SUMIFS(Entries!$D$2:$D$5000,Entries!$C$2:$C$5000,"Actual",Entries!$A$2:$A$5000,$A23,Entries!$B$2:$B$5000,S$1)) | T23: =IF(OR(T$1="",$BE23=0),"",SUMIFS(Entries!$D$2:$D$5000,Entries!$C$2:$C$5000,"Actual",Entries!$A$2:$A$5000,$A23,Entries!$B$2:$B$5000,T$1)) | U23: =IF(OR(U$1="",$BE23=0),"",SUMIFS(Entries!$D$2:$D$5000,Entries!$C$2:$C$5000,"Actual",Entries!$A$2:$A$5000,$A23,Entries!$B$2:$B$5000,U$1)) | V23: =IF(OR(V$1="",$BE23=0),"",SUMIFS(Entries!$D$2:$D$5000,Entries!$C$2:$C$5000,"Actual",Entries!$A$2:$A$5000,$A23,Entries!$B$2:$B$5000,V$1)) | ... AH23: =IF(OR(AH$1="",$BE23=0),"",SUMIFS(Entries!$D$2:$D$5000,Entries!$C$2:$C$5000,"Actual",Entries!$A$2:$A$5000,$A23,Entries!$B$2:$B$5000,AH$1)) | AJ23: =IF(OR(AJ$1="",$BE23=0),"",IFERROR(LOOKUP(2,1/((Budgets!$A$2:$A$200=AJ$1)*(Budgets!$B$2:$B$200<=$A23)),Budgets!$C$2:$C$200),0)) | AK23: =IF(OR(AK$1="",$BE23=0),"",IFERROR(LOOKUP(2,1/((Budgets!$A$2:$A$200=AK$1)*(Budgets!$B$2:$B$200<=$A23)),Budgets!$C$2:$C$200),0)) | AL23: =IF(OR(AL$1="",$BE23=0),"",IFERROR(LOOKUP(2,1/((Budgets!$A$2:$A$200=AL$1)*(Budgets!$B$2:$B$200<=$A23)),Budgets!$C$2:$C$200),0)) | AM23: =IF(OR(AM$1="",$BE23=0),"",IFERROR(LOOKUP(2,1/((Budgets!$A$2:$A$200=AM$1)*(Budgets!$B$2:$B$200<=$A23)),Budgets!$C$2:$C$200),0)) | AN23: =IF(OR(AN$1="",$BE23=0),"",IFERROR(LOOKUP(2,1/((Budgets!$A$2:$A$200=AN$1)*(Budgets!$B$2:$B$200<=$A23)),Budgets!$C$2:$C$200),0)) | AO23: =IF(OR(AO$1="",$BE23=0),"",IFERROR(LOOKUP(2,1/((Budgets!$A$2:$A$200=AO$1)*(Budgets!$B$2:$B$200<=$A23)),Budgets!$C$2:$C$200),0)) | AP23: =IF(OR(AP$1="",$BE23=0),"",IFERROR(LOOKUP(2,1/((Budgets!$A$2:$A$200=AP$1)*(Budgets!$B$2:$B$200<=$A23)),Budgets!$C$2:$C$200),0)) | AQ23: =IF(OR(AQ$1="",$BE23=0),"",IFERROR(LOOKUP(2,1/((Budgets!$A$2:$A$200=AQ$1)*(Budgets!$B$2:$B$200<=$A23)),Budgets!$C$2:$C$200),0)) | ... BC23: =IF(OR(BC$1="",$BE23=0),"",IFERROR(LOOKUP(2,1/((Budgets!$A$2:$A$200=BC$1)*(Budgets!$B$2:$B$200<=$A23)),Budgets!$C$2:$C$200),0)) | BE23: =COUNTIFS(Entries!$A$2:$A$5000,$A23)
A24: 40118 | B24: =IF($BE24=0,NA(),SUMIFS(Entries!$D$2:$D$5000,Entries!$C$2:$C$5000,"Income",Entries!$A$2:$A$5000,$A24)) | C24: =IF($BE24=0,"",SUMIFS(Entries!$D$2:$D$5000,Entries!$C$2:$C$5000,"Actual",Entries!$A$2:$A$5000,$A24)) | D24: =IF($BE24=0,"",SUMIFS(Entries!$D$2:$D$5000,Entries!$C$2:$C$5000,"One-off",Entries!$A$2:$A$5000,$A24)) | E24: =IF($BE24=0,NA(),C24+D24) | F24: =IF($BE24=0,"",SUM(AJ24:BC24)) | G24: =IF($BE24=0,"",B24-E24) | H24: =IF($BE24=0,"",SUM($G$2:G24)) | I24: =IF($BE24=0,"",SUMIFS(Entries!$F$2:$F$5000,Entries!$A$2:$A$5000,$A24)) | J24: =IF($BE24=0,NA(),H24+SUM($I$2:I24)) | K24: =IF($BE24=0,"",SUMIFS(Entries!$D$2:$D$5000,Entries!$C$2:$C$5000,"Income",Entries!$A$2:$A$5000,">="&EDATE($A24,-11),Entries!$A$2:$A$5000,"<="&$A24)/12) | L24: =IF($BE24=0,"",(SUMIFS(Entries!$D$2:$D$5000,Entries!$C$2:$C$5000,"Actual",Entries!$A$2:$A$5000,">="&EDATE($A24,-11),Entries!$A$2:$A$5000,"<="&$A24)+SUMIFS(Entries!$D$2:$D$5000,Entries!$C$2:$C$5000,"One-off",Entries!$A$2:$A$5000,">="&EDATE($A24,-11),Entries!$A$2:$A$5000,"<="&$A24))/12) | M24: =IF($BE24=0,NA(),IFERROR((K24-L24)/K24,0)) | O24: =IF(OR(O$1="",$BE24=0),"",SUMIFS(Entries!$D$2:$D$5000,Entries!$C$2:$C$5000,"Actual",Entries!$A$2:$A$5000,$A24,Entries!$B$2:$B$5000,O$1)) | P24: =IF(OR(P$1="",$BE24=0),"",SUMIFS(Entries!$D$2:$D$5000,Entries!$C$2:$C$5000,"Actual",Entries!$A$2:$A$5000,$A24,Entries!$B$2:$B$5000,P$1)) | Q24: =IF(OR(Q$1="",$BE24=0),"",SUMIFS(Entries!$D$2:$D$5000,Entries!$C$2:$C$5000,"Actual",Entries!$A$2:$A$5000,$A24,Entries!$B$2:$B$5000,Q$1)) | R24: =IF(OR(R$1="",$BE24=0),"",SUMIFS(Entries!$D$2:$D$5000,Entries!$C$2:$C$5000,"Actual",Entries!$A$2:$A$5000,$A24,Entries!$B$2:$B$5000,R$1)) | S24: =IF(OR(S$1="",$BE24=0),"",SUMIFS(Entries!$D$2:$D$5000,Entries!$C$2:$C$5000,"Actual",Entries!$A$2:$A$5000,$A24,Entries!$B$2:$B$5000,S$1)) | T24: =IF(OR(T$1="",$BE24=0),"",SUMIFS(Entries!$D$2:$D$5000,Entries!$C$2:$C$5000,"Actual",Entries!$A$2:$A$5000,$A24,Entries!$B$2:$B$5000,T$1)) | U24: =IF(OR(U$1="",$BE24=0),"",SUMIFS(Entries!$D$2:$D$5000,Entries!$C$2:$C$5000,"Actual",Entries!$A$2:$A$5000,$A24,Entries!$B$2:$B$5000,U$1)) | V24: =IF(OR(V$1="",$BE24=0),"",SUMIFS(Entries!$D$2:$D$5000,Entries!$C$2:$C$5000,"Actual",Entries!$A$2:$A$5000,$A24,Entries!$B$2:$B$5000,V$1)) | ... AH24: =IF(OR(AH$1="",$BE24=0),"",SUMIFS(Entries!$D$2:$D$5000,Entries!$C$2:$C$5000,"Actual",Entries!$A$2:$A$5000,$A24,Entries!$B$2:$B$5000,AH$1)) | AJ24: =IF(OR(AJ$1="",$BE24=0),"",IFERROR(LOOKUP(2,1/((Budgets!$A$2:$A$200=AJ$1)*(Budgets!$B$2:$B$200<=$A24)),Budgets!$C$2:$C$200),0)) | AK24: =IF(OR(AK$1="",$BE24=0),"",IFERROR(LOOKUP(2,1/((Budgets!$A$2:$A$200=AK$1)*(Budgets!$B$2:$B$200<=$A24)),Budgets!$C$2:$C$200),0)) | AL24: =IF(OR(AL$1="",$BE24=0),"",IFERROR(LOOKUP(2,1/((Budgets!$A$2:$A$200=AL$1)*(Budgets!$B$2:$B$200<=$A24)),Budgets!$C$2:$C$200),0)) | AM24: =IF(OR(AM$1="",$BE24=0),"",IFERROR(LOOKUP(2,1/((Budgets!$A$2:$A$200=AM$1)*(Budgets!$B$2:$B$200<=$A24)),Budgets!$C$2:$C$200),0)) | AN24: =IF(OR(AN$1="",$BE24=0),"",IFERROR(LOOKUP(2,1/((Budgets!$A$2:$A$200=AN$1)*(Budgets!$B$2:$B$200<=$A24)),Budgets!$C$2:$C$200),0)) | AO24: =IF(OR(AO$1="",$BE24=0),"",IFERROR(LOOKUP(2,1/((Budgets!$A$2:$A$200=AO$1)*(Budgets!$B$2:$B$200<=$A24)),Budgets!$C$2:$C$200),0)) | AP24: =IF(OR(AP$1="",$BE24=0),"",IFERROR(LOOKUP(2,1/((Budgets!$A$2:$A$200=AP$1)*(Budgets!$B$2:$B$200<=$A24)),Budgets!$C$2:$C$200),0)) | AQ24: =IF(OR(AQ$1="",$BE24=0),"",IFERROR(LOOKUP(2,1/((Budgets!$A$2:$A$200=AQ$1)*(Budgets!$B$2:$B$200<=$A24)),Budgets!$C$2:$C$200),0)) | ... BC24: =IF(OR(BC$1="",$BE24=0),"",IFERROR(LOOKUP(2,1/((Budgets!$A$2:$A$200=BC$1)*(Budgets!$B$2:$B$200<=$A24)),Budgets!$C$2:$C$200),0)) | BE24: =COUNTIFS(Entries!$A$2:$A$5000,$A24)
... A301: 48549 | B301: =IF($BE301=0,NA(),SUMIFS(Entries!$D$2:$D$5000,Entries!$C$2:$C$5000,"Income",Entries!$A$2:$A$5000,$A301)) | C301: =IF($BE301=0,"",SUMIFS(Entries!$D$2:$D$5000,Entries!$C$2:$C$5000,"Actual",Entries!$A$2:$A$5000,$A301)) | D301: =IF($BE301=0,"",SUMIFS(Entries!$D$2:$D$5000,Entries!$C$2:$C$5000,"One-off",Entries!$A$2:$A$5000,$A301)) | E301: =IF($BE301=0,NA(),C301+D301) | F301: =IF($BE301=0,"",SUM(AJ301:BC301)) | G301: =IF($BE301=0,"",B301-E301) | H301: =IF($BE301=0,"",SUM($G$2:G301)) | I301: =IF($BE301=0,"",SUMIFS(Entries!$F$2:$F$5000,Entries!$A$2:$A$5000,$A301)) | J301: =IF($BE301=0,NA(),H301+SUM($I$2:I301)) | K301: =IF($BE301=0,"",SUMIFS(Entries!$D$2:$D$5000,Entries!$C$2:$C$5000,"Income",Entries!$A$2:$A$5000,">="&EDATE($A301,-11),Entries!$A$2:$A$5000,"<="&$A301)/12) | L301: =IF($BE301=0,"",(SUMIFS(Entries!$D$2:$D$5000,Entries!$C$2:$C$5000,"Actual",Entries!$A$2:$A$5000,">="&EDATE($A301,-11),Entries!$A$2:$A$5000,"<="&$A301)+SUMIFS(Entries!$D$2:$D$5000,Entries!$C$2:$C$5000,"One-off",Entries!$A$2:$A$5000,">="&EDATE($A301,-11),Entries!$A$2:$A$5000,"<="&$A301))/12) | M301: =IF($BE301=0,NA(),IFERROR((K301-L301)/K301,0)) | O301: =IF(OR(O$1="",$BE301=0),"",SUMIFS(Entries!$D$2:$D$5000,Entries!$C$2:$C$5000,"Actual",Entries!$A$2:$A$5000,$A301,Entries!$B$2:$B$5000,O$1)) | P301: =IF(OR(P$1="",$BE301=0),"",SUMIFS(Entries!$D$2:$D$5000,Entries!$C$2:$C$5000,"Actual",Entries!$A$2:$A$5000,$A301,Entries!$B$2:$B$5000,P$1)) | Q301: =IF(OR(Q$1="",$BE301=0),"",SUMIFS(Entries!$D$2:$D$5000,Entries!$C$2:$C$5000,"Actual",Entries!$A$2:$A$5000,$A301,Entries!$B$2:$B$5000,Q$1)) | R301: =IF(OR(R$1="",$BE301=0),"",SUMIFS(Entries!$D$2:$D$5000,Entries!$C$2:$C$5000,"Actual",Entries!$A$2:$A$5000,$A301,Entries!$B$2:$B$5000,R$1)) | S301: =IF(OR(S$1="",$BE301=0),"",SUMIFS(Entries!$D$2:$D$5000,Entries!$C$2:$C$5000,"Actual",Entries!$A$2:$A$5000,$A301,Entries!$B$2:$B$5000,S$1)) | T301: =IF(OR(T$1="",$BE301=0),"",SUMIFS(Entries!$D$2:$D$5000,Entries!$C$2:$C$5000,"Actual",Entries!$A$2:$A$5000,$A301,Entries!$B$2:$B$5000,T$1)) | U301: =IF(OR(U$1="",$BE301=0),"",SUMIFS(Entries!$D$2:$D$5000,Entries!$C$2:$C$5000,"Actual",Entries!$A$2:$A$5000,$A301,Entries!$B$2:$B$5000,U$1)) | V301: =IF(OR(V$1="",$BE301=0),"",SUMIFS(Entries!$D$2:$D$5000,Entries!$C$2:$C$5000,"Actual",Entries!$A$2:$A$5000,$A301,Entries!$B$2:$B$5000,V$1)) | ... AH301: =IF(OR(AH$1="",$BE301=0),"",SUMIFS(Entries!$D$2:$D$5000,Entries!$C$2:$C$5000,"Actual",Entries!$A$2:$A$5000,$A301,Entries!$B$2:$B$5000,AH$1)) | AJ301: =IF(OR(AJ$1="",$BE301=0),"",IFERROR(LOOKUP(2,1/((Budgets!$A$2:$A$200=AJ$1)*(Budgets!$B$2:$B$200<=$A301)),Budgets!$C$2:$C$200),0)) | AK301: =IF(OR(AK$1="",$BE301=0),"",IFERROR(LOOKUP(2,1/((Budgets!$A$2:$A$200=AK$1)*(Budgets!$B$2:$B$200<=$A301)),Budgets!$C$2:$C$200),0)) | AL301: =IF(OR(AL$1="",$BE301=0),"",IFERROR(LOOKUP(2,1/((Budgets!$A$2:$A$200=AL$1)*(Budgets!$B$2:$B$200<=$A301)),Budgets!$C$2:$C$200),0)) | AM301: =IF(OR(AM$1="",$BE301=0),"",IFERROR(LOOKUP(2,1/((Budgets!$A$2:$A$200=AM$1)*(Budgets!$B$2:$B$200<=$A301)),Budgets!$C$2:$C$200),0)) | AN301: =IF(OR(AN$1="",$BE301=0),"",IFERROR(LOOKUP(2,1/((Budgets!$A$2:$A$200=AN$1)*(Budgets!$B$2:$B$200<=$A301)),Budgets!$C$2:$C$200),0)) | AO301: =IF(OR(AO$1="",$BE301=0),"",IFERROR(LOOKUP(2,1/((Budgets!$A$2:$A$200=AO$1)*(Budgets!$B$2:$B$200<=$A301)),Budgets!$C$2:$C$200),0)) | AP301: =IF(OR(AP$1="",$BE301=0),"",IFERROR(LOOKUP(2,1/((Budgets!$A$2:$A$200=AP$1)*(Budgets!$B$2:$B$200<=$A301)),Budgets!$C$2:$C$200),0)) | AQ301: =IF(OR(AQ$1="",$BE301=0),"",IFERROR(LOOKUP(2,1/((Budgets!$A$2:$A$200=AQ$1)*(Budgets!$B$2:$B$200<=$A301)),Budgets!$C$2:$C$200),0)) | ... BC301: =IF(OR(BC$1="",$BE301=0),"",IFERROR(LOOKUP(2,1/((Budgets!$A$2:$A$200=BC$1)*(Budgets!$B$2:$B$200<=$A301)),Budgets!$C$2:$C$200),0)) | BE301: =COUNTIFS(Entries!$A$2:$A$5000,$A301)

Sheet Entries
A1: Date | B1: Category | C1: Type | D1: Amount | E1: Note | F1: Capital (auto)
A2: 39448 | B2: Interest | C2: Income | D2: 20 | F2: =IF(AND(C2="One-off",IFERROR(INDEX(Categories!$C$2:$C$200,MATCH(B2,Categories!$A$2:$A$200,0)),"N")="Y"),D2,0)
A3: 39448 | B3: Salary | C3: Income | D3: 3000 | F3: =IF(AND(C3="One-off",IFERROR(INDEX(Categories!$C$2:$C$200,MATCH(B3,Categories!$A$2:$A$200,0)),"N")="Y"),D3,0)
A4: 39448 | B4: Uncategorised | C4: Actual | D4: 2000 | E4: Historical monthly total (pre per-category tracking) | F4: =IF(AND(C4="One-off",IFERROR(INDEX(Categories!$C$2:$C$200,MATCH(B4,Categories!$A$2:$A$200,0)),"N")="Y"),D4,0)
A5: 39479 | B5: Interest | C5: Income | D5: 20 | F5: =IF(AND(C5="One-off",IFERROR(INDEX(Categories!$C$2:$C$200,MATCH(B5,Categories!$A$2:$A$200,0)),"N")="Y"),D5,0)
A6: 39479 | B6: Salary | C6: Income | D6: 3050 | F6: =IF(AND(C6="One-off",IFERROR(INDEX(Categories!$C$2:$C$200,MATCH(B6,Categories!$A$2:$A$200,0)),"N")="Y"),D6,0)
A7: 39479 | B7: Uncategorised | C7: Actual | D7: 2120 | E7: Historical monthly total (pre per-category tracking) | F7: =IF(AND(C7="One-off",IFERROR(INDEX(Categories!$C$2:$C$200,MATCH(B7,Categories!$A$2:$A$200,0)),"N")="Y"),D7,0)
A8: 39508 | B8: Dividends | C8: Income | D8: 150 | F8: =IF(AND(C8="One-off",IFERROR(INDEX(Categories!$C$2:$C$200,MATCH(B8,Categories!$A$2:$A$200,0)),"N")="Y"),D8,0)
A9: 39508 | B9: Interest | C9: Income | D9: 20 | F9: =IF(AND(C9="One-off",IFERROR(INDEX(Categories!$C$2:$C$200,MATCH(B9,Categories!$A$2:$A$200,0)),"N")="Y"),D9,0)
A10: 39508 | B10: Salary | C10: Income | D10: 3100 | F10: =IF(AND(C10="One-off",IFERROR(INDEX(Categories!$C$2:$C$200,MATCH(B10,Categories!$A$2:$A$200,0)),"N")="Y"),D10,0)
A11: 39508 | B11: Uncategorised | C11: Actual | D11: 2240 | E11: Historical monthly total (pre per-category tracking) | F11: =IF(AND(C11="One-off",IFERROR(INDEX(Categories!$C$2:$C$200,MATCH(B11,Categories!$A$2:$A$200,0)),"N")="Y"),D11,0)
A12: 39539 | B12: Interest | C12: Income | D12: 20 | F12: =IF(AND(C12="One-off",IFERROR(INDEX(Categories!$C$2:$C$200,MATCH(B12,Categories!$A$2:$A$200,0)),"N")="Y"),D12,0)
A13: 39539 | B13: Salary | C13: Income | D13: 3150 | F13: =IF(AND(C13="One-off",IFERROR(INDEX(Categories!$C$2:$C$200,MATCH(B13,Categories!$A$2:$A$200,0)),"N")="Y"),D13,0)
A14: 39539 | B14: Uncategorised | C14: Actual | D14: 2360 | E14: Historical monthly total (pre per-category tracking) | F14: =IF(AND(C14="One-off",IFERROR(INDEX(Categories!$C$2:$C$200,MATCH(B14,Categories!$A$2:$A$200,0)),"N")="Y"),D14,0)
A15: 39569 | B15: Interest | C15: Income | D15: 20 | F15: =IF(AND(C15="One-off",IFERROR(INDEX(Categories!$C$2:$C$200,MATCH(B15,Categories!$A$2:$A$200,0)),"N")="Y"),D15,0)
A16: 39569 | B16: Salary | C16: Income | D16: 3200 | F16: =IF(AND(C16="One-off",IFERROR(INDEX(Categories!$C$2:$C$200,MATCH(B16,Categories!$A$2:$A$200,0)),"N")="Y"),D16,0)
A17: 39569 | B17: Uncategorised | C17: Actual | D17: 2480 | E17: Historical monthly total (pre per-category tracking) | F17: =IF(AND(C17="One-off",IFERROR(INDEX(Categories!$C$2:$C$200,MATCH(B17,Categories!$A$2:$A$200,0)),"N")="Y"),D17,0)
A18: 39600 | B18: Dividends | C18: Income | D18: 150 | F18: =IF(AND(C18="One-off",IFERROR(INDEX(Categories!$C$2:$C$200,MATCH(B18,Categories!$A$2:$A$200,0)),"N")="Y"),D18,0)
A19: 39600 | B19: Interest | C19: Income | D19: 20 | F19: =IF(AND(C19="One-off",IFERROR(INDEX(Categories!$C$2:$C$200,MATCH(B19,Categories!$A$2:$A$200,0)),"N")="Y"),D19,0)
A20: 39600 | B20: Salary | C20: Income | D20: 3250 | F20: =IF(AND(C20="One-off",IFERROR(INDEX(Categories!$C$2:$C$200,MATCH(B20,Categories!$A$2:$A$200,0)),"N")="Y"),D20,0)
A21: 39600 | B21: Uncategorised | C21: Actual | D21: 2000 | E21: Historical monthly total (pre per-category tracking) | F21: =IF(AND(C21="One-off",IFERROR(INDEX(Categories!$C$2:$C$200,MATCH(B21,Categories!$A$2:$A$200,0)),"N")="Y"),D21,0)
A22: 39630 | B22: Interest | C22: Income | D22: 20 | F22: =IF(AND(C22="One-off",IFERROR(INDEX(Categories!$C$2:$C$200,MATCH(B22,Categories!$A$2:$A$200,0)),"N")="Y"),D22,0)
A23: 39630 | B23: Salary | C23: Income | D23: 3000 | F23: =IF(AND(C23="One-off",IFERROR(INDEX(Categories!$C$2:$C$200,MATCH(B23,Categories!$A$2:$A$200,0)),"N")="Y"),D23,0)
A24: 39630 | B24: Uncategorised | C24: Actual | D24: 2120 | E24: Historical monthly total (pre per-category tracking) | F24: =IF(AND(C24="One-off",IFERROR(INDEX(Categories!$C$2:$C$200,MATCH(B24,Categories!$A$2:$A$200,0)),"N")="Y"),D24,0)
A25: 39661 | B25: Interest | C25: Income | D25: 20 | F25: =IF(AND(C25="One-off",IFERROR(INDEX(Categories!$C$2:$C$200,MATCH(B25,Categories!$A$2:$A$200,0)),"N")="Y"),D25,0)
A26: 39661 | B26: Salary | C26: Income | D26: 3050 | F26: =IF(AND(C26="One-off",IFERROR(INDEX(Categories!$C$2:$C$200,MATCH(B26,Categories!$A$2:$A$200,0)),"N")="Y"),D26,0)
A27: 39661 | B27: Uncategorised | C27: Actual | D27: 2240 | E27: Historical monthly total (pre per-category tracking) | F27: =IF(AND(C27="One-off",IFERROR(INDEX(Categories!$C$2:$C$200,MATCH(B27,Categories!$A$2:$A$200,0)),"N")="Y"),D27,0)
A28: 39692 | B28: Dividends | C28: Income | D28: 150 | F28: =IF(AND(C28="One-off",IFERROR(INDEX(Categories!$C$2:$C$200,MATCH(B28,Categories!$A$2:$A$200,0)),"N")="Y"),D28,0)
A29: 39692 | B29: Interest | C29: Income | D29: 20 | F29: =IF(AND(C29="One-off",IFERROR(INDEX(Categories!$C$2:$C$200,MATCH(B29,Categories!$A$2:$A$200,0)),"N")="Y"),D29,0)
A30: 39692 | B30: Salary | C30: Income | D30: 3100 | F30: =IF(AND(C30="One-off",IFERROR(INDEX(Categories!$C$2:$C$200,MATCH(B30,Categories!$A$2:$A$200,0)),"N")="Y"),D30,0)
A31: 39692 | B31: Uncategorised | C31: Actual | D31: 2360 | E31: Historical monthly total (pre per-category tracking) | F31: =IF(AND(C31="One-off",IFERROR(INDEX(Categories!$C$2:$C$200,MATCH(B31,Categories!$A$2:$A$200,0)),"N")="Y"),D31,0)
A32: 39722 | B32: Interest | C32: Income | D32: 20 | F32: =IF(AND(C32="One-off",IFERROR(INDEX(Categories!$C$2:$C$200,MATCH(B32,Categories!$A$2:$A$200,0)),"N")="Y"),D32,0)
A33: 39722 | B33: Salary | C33: Income | D33: 3150 | F33: =IF(AND(C33="One-off",IFERROR(INDEX(Categories!$C$2:$C$200,MATCH(B33,Categories!$A$2:$A$200,0)),"N")="Y"),D33,0)
A34: 39722 | B34: Uncategorised | C34: Actual | D34: 2480 | E34: Historical monthly total (pre per-category tracking) | F34: =IF(AND(C34="One-off",IFERROR(INDEX(Categories!$C$2:$C$200,MATCH(B34,Categories!$A$2:$A$200,0)),"N")="Y"),D34,0)
A35: 39753 | B35: Interest | C35: Income | D35: 20 | F35: =IF(AND(C35="One-off",IFERROR(INDEX(Categories!$C$2:$C$200,MATCH(B35,Categories!$A$2:$A$200,0)),"N")="Y"),D35,0)
A36: 39753 | B36: Salary | C36: Income | D36: 3200 | F36: =IF(AND(C36="One-off",IFERROR(INDEX(Categories!$C$2:$C$200,MATCH(B36,Categories!$A$2:$A$200,0)),"N")="Y"),D36,0)
A37: 39753 | B37: Uncategorised | C37: Actual | D37: 2000 | E37: Historical monthly total (pre per-category tracking) | F37: =IF(AND(C37="One-off",IFERROR(INDEX(Categories!$C$2:$C$200,MATCH(B37,Categories!$A$2:$A$200,0)),"N")="Y"),D37,0)
A38: 39783 | B38: Bonus/Claims | C38: Income | D38: 3250 | F38: =IF(AND(C38="One-off",IFERROR(INDEX(Categories!$C$2:$C$200,MATCH(B38,Categories!$A$2:$A$200,0)),"N")="Y"),D38,0)
A39: 39783 | B39: Dividends | C39: Income | D39: 150 | F39: =IF(AND(C39="One-off",IFERROR(INDEX(Categories!$C$2:$C$200,MATCH(B39,Categories!$A$2:$A$200,0)),"N")="Y"),D39,0)
A40: 39783 | B40: Interest | C40: Income | D40: 20 | F40: =IF(AND(C40="One-off",IFERROR(INDEX(Categories!$C$2:$C$200,MATCH(B40,Categories!$A$2:$A$200,0)),"N")="Y"),D40,0)
A41: 39783 | B41: Salary | C41: Income | D41: 3250 | F41: =IF(AND(C41="One-off",IFERROR(INDEX(Categories!$C$2:$C$200,MATCH(B41,Categories!$A$2:$A$200,0)),"N")="Y"),D41,0)
A42: 39783 | B42: Uncategorised | C42: Actual | D42: 2120 | E42: Historical monthly total (pre per-category tracking) | F42: =IF(AND(C42="One-off",IFERROR(INDEX(Categories!$C$2:$C$200,MATCH(B42,Categories!$A$2:$A$200,0)),"N")="Y"),D42,0)
A43: 39814 | B43: Interest | C43: Income | D43: 20 | F43: =IF(AND(C43="One-off",IFERROR(INDEX(Categories!$C$2:$C$200,MATCH(B43,Categories!$A$2:$A$200,0)),"N")="Y"),D43,0)
A44: 39814 | B44: Salary | C44: Income | D44: 3180 | F44: =IF(AND(C44="One-off",IFERROR(INDEX(Categories!$C$2:$C$200,MATCH(B44,Categories!$A$2:$A$200,0)),"N")="Y"),D44,0)
A45: 39814 | B45: Uncategorised | C45: Actual | D45: 2320 | E45: Historical monthly total (pre per-category tracking) | F45: =IF(AND(C45="One-off",IFERROR(INDEX(Categories!$C$2:$C$200,MATCH(B45,Categories!$A$2:$A$200,0)),"N")="Y"),D45,0)
A46: 39845 | B46: Interest | C46: Income | D46: 20 | F46: =IF(AND(C46="One-off",IFERROR(INDEX(Categories!$C$2:$C$200,MATCH(B46,Categories!$A$2:$A$200,0)),"N")="Y"),D46,0)
A47: 39845 | B47: Salary | C47: Income | D47: 3230 | F47: =IF(AND(C47="One-off",IFERROR(INDEX(Categories!$C$2:$C$200,MATCH(B47,Categories!$A$2:$A$200,0)),"N")="Y"),D47,0)
A48: 39845 | B48: Uncategorised | C48: Actual | D48: 2440 | E48: Historical monthly total (pre per-category tracking) | F48: =IF(AND(C48="One-off",IFERROR(INDEX(Categories!$C$2:$C$200,MATCH(B48,Categories!$A$2:$A$200,0)),"N")="Y"),D48,0)
A49: 39873 | B49: Dividends | C49: Income | D49: 150 | F49: =IF(AND(C49="One-off",IFERROR(INDEX(Categories!$C$2:$C$200,MATCH(B49,Categories!$A$2:$A$200,0)),"N")="Y"),D49,0)
A50: 39873 | B50: Interest | C50: Income | D50: 20 | F50: =IF(AND(C50="One-off",IFERROR(INDEX(Categories!$C$2:$C$200,MATCH(B50,Categories!$A$2:$A$200,0)),"N")="Y"),D50,0)
A51: 39873 | B51: Salary | C51: Income | D51: 3280 | F51: =IF(AND(C51="One-off",IFERROR(INDEX(Categories!$C$2:$C$200,MATCH(B51,Categories!$A$2:$A$200,0)),"N")="Y"),D51,0)
A52: 39873 | B52: Uncategorised | C52: Actual | D52: 2560 | E52: Historical monthly total (pre per-category tracking) | F52: =IF(AND(C52="One-off",IFERROR(INDEX(Categories!$C$2:$C$200,MATCH(B52,Categories!$A$2:$A$200,0)),"N")="Y"),D52,0)
A53: 39904 | B53: Interest | C53: Income | D53: 20 | F53: =IF(AND(C53="One-off",IFERROR(INDEX(Categories!$C$2:$C$200,MATCH(B53,Categories!$A$2:$A$200,0)),"N")="Y"),D53,0)
A54: 39904 | B54: Salary | C54: Income | D54: 3330 | F54: =IF(AND(C54="One-off",IFERROR(INDEX(Categories!$C$2:$C$200,MATCH(B54,Categories!$A$2:$A$200,0)),"N")="Y"),D54,0)
A55: 39904 | B55: Uncategorised | C55: Actual | D55: 2080 | E55: Historical monthly total (pre per-category tracking) | F55: =IF(AND(C55="One-off",IFERROR(INDEX(Categories!$C$2:$C$200,MATCH(B55,Categories!$A$2:$A$200,0)),"N")="Y"),D55,0)
A56: 39934 | B56: Interest | C56: Income | D56: 20 | F56: =IF(AND(C56="One-off",IFERROR(INDEX(Categories!$C$2:$C$200,MATCH(B56,Categories!$A$2:$A$200,0)),"N")="Y"),D56,0)
A57: 39934 | B57: Salary | C57: Income | D57: 3380 | F57: =IF(AND(C57="One-off",IFERROR(INDEX(Categories!$C$2:$C$200,MATCH(B57,Categories!$A$2:$A$200,0)),"N")="Y"),D57,0)
A58: 39934 | B58: Uncategorised | C58: Actual | D58: 2200 | E58: Historical monthly total (pre per-category tracking) | F58: =IF(AND(C58="One-off",IFERROR(INDEX(Categories!$C$2:$C$200,MATCH(B58,Categories!$A$2:$A$200,0)),"N")="Y"),D58,0)
A59: 39965 | B59: Dividends | C59: Income | D59: 150 | F59: =IF(AND(C59="One-off",IFERROR(INDEX(Categories!$C$2:$C$200,MATCH(B59,Categories!$A$2:$A$200,0)),"N")="Y"),D59,0)
A60: 39965 | B60: Interest | C60: Income | D60: 20 | F60: =IF(AND(C60="One-off",IFERROR(INDEX(Categories!$C$2:$C$200,MATCH(B60,Categories!$A$2:$A$200,0)),"N")="Y"),D60,0)
A61: 39965 | B61: Salary | C61: Income | D61: 3430 | F61: =IF(AND(C61="One-off",IFERROR(INDEX(Categories!$C$2:$C$200,MATCH(B61,Categories!$A$2:$A$200,0)),"N")="Y"),D61,0)
A62: 39965 | B62: Uncategorised | C62: Actual | D62: 2320 | E62: Historical monthly total (pre per-category tracking) | F62: =IF(AND(C62="One-off",IFERROR(INDEX(Categories!$C$2:$C$200,MATCH(B62,Categories!$A$2:$A$200,0)),"N")="Y"),D62,0)
A63: 39995 | B63: Interest | C63: Income | D63: 20 | F63: =IF(AND(C63="One-off",IFERROR(INDEX(Categories!$C$2:$C$200,MATCH(B63,Categories!$A$2:$A$200,0)),"N")="Y"),D63,0)
A64: 39995 | B64: Salary | C64: Income | D64: 3180 | F64: =IF(AND(C64="One-off",IFERROR(INDEX(Categories!$C$2:$C$200,MATCH(B64,Categories!$A$2:$A$200,0)),"N")="Y"),D64,0)
A65: 39995 | B65: Uncategorised | C65: Actual | D65: 2440 | E65: Historical monthly total (pre per-category tracking) | F65: =IF(AND(C65="One-off",IFERROR(INDEX(Categories!$C$2:$C$200,MATCH(B65,Categories!$A$2:$A$200,0)),"N")="Y"),D65,0)
A66: 40026 | B66: Interest | C66: Income | D66: 20 | F66: =IF(AND(C66="One-off",IFERROR(INDEX(Categories!$C$2:$C$200,MATCH(B66,Categories!$A$2:$A$200,0)),"N")="Y"),D66,0)
A67: 40026 | B67: Salary | C67: Income | D67: 3230 | F67: =IF(AND(C67="One-off",IFERROR(INDEX(Categories!$C$2:$C$200,MATCH(B67,Categories!$A$2:$A$200,0)),"N")="Y"),D67,0)
A68: 40026 | B68: Uncategorised | C68: Actual | D68: 2560 | E68: Historical monthly total (pre per-category tracking) | F68: =IF(AND(C68="One-off",IFERROR(INDEX(Categories!$C$2:$C$200,MATCH(B68,Categories!$A$2:$A$200,0)),"N")="Y"),D68,0)
A69: 40057 | B69: Dividends | C69: Income | D69: 150 | F69: =IF(AND(C69="One-off",IFERROR(INDEX(Categories!$C$2:$C$200,MATCH(B69,Categories!$A$2:$A$200,0)),"N")="Y"),D69,0)
A70: 40057 | B70: Interest | C70: Income | D70: 20 | F70: =IF(AND(C70="One-off",IFERROR(INDEX(Categories!$C$2:$C$200,MATCH(B70,Categories!$A$2:$A$200,0)),"N")="Y"),D70,0)
A71: 40057 | B71: Salary | C71: Income | D71: 3280 | F71: =IF(AND(C71="One-off",IFERROR(INDEX(Categories!$C$2:$C$200,MATCH(B71,Categories!$A$2:$A$200,0)),"N")="Y"),D71,0)
A72: 40057 | B72: Uncategorised | C72: Actual | D72: 2080 | E72: Historical monthly total (pre per-category tracking) | F72: =IF(AND(C72="One-off",IFERROR(INDEX(Categories!$C$2:$C$200,MATCH(B72,Categories!$A$2:$A$200,0)),"N")="Y"),D72,0)
A73: 40087 | B73: Interest | C73: Income | D73: 20 | F73: =IF(AND(C73="One-off",IFERROR(INDEX(Categories!$C$2:$C$200,MATCH(B73,Categories!$A$2:$A$200,0)),"N")="Y"),D73,0)
A74: 40087 | B74: Salary | C74: Income | D74: 3330 | F74: =IF(AND(C74="One-off",IFERROR(INDEX(Categories!$C$2:$C$200,MATCH(B74,Categories!$A$2:$A$200,0)),"N")="Y"),D74,0)
A75: 40087 | B75: Uncategorised | C75: Actual | D75: 2200 | E75: Historical monthly total (pre per-category tracking) | F75: =IF(AND(C75="One-off",IFERROR(INDEX(Categories!$C$2:$C$200,MATCH(B75,Categories!$A$2:$A$200,0)),"N")="Y"),D75,0)
A76: 40118 | B76: Interest | C76: Income | D76: 20 | F76: =IF(AND(C76="One-off",IFERROR(INDEX(Categories!$C$2:$C$200,MATCH(B76,Categories!$A$2:$A$200,0)),"N")="Y"),D76,0)
A77: 40118 | B77: Salary | C77: Income | D77: 3380 | F77: =IF(AND(C77="One-off",IFERROR(INDEX(Categories!$C$2:$C$200,MATCH(B77,Categories!$A$2:$A$200,0)),"N")="Y"),D77,0)
A78: 40118 | B78: Uncategorised | C78: Actual | D78: 2320 | E78: Historical monthly total (pre per-category tracking) | F78: =IF(AND(C78="One-off",IFERROR(INDEX(Categories!$C$2:$C$200,MATCH(B78,Categories!$A$2:$A$200,0)),"N")="Y"),D78,0)
A79: 40148 | B79: Bonus/Claims | C79: Income | D79: 3430 | F79: =IF(AND(C79="One-off",IFERROR(INDEX(Categories!$C$2:$C$200,MATCH(B79,Categories!$A$2:$A$200,0)),"N")="Y"),D79,0)
A80: 40148 | B80: Dividends | C80: Income | D80: 150 | F80: =IF(AND(C80="One-off",IFERROR(INDEX(Categories!$C$2:$C$200,MATCH(B80,Categories!$A$2:$A$200,0)),"N")="Y"),D80,0)
A81: 40148 | B81: Interest | C81: Income | D81: 20 | F81: =IF(AND(C81="One-off",IFERROR(INDEX(Categories!$C$2:$C$200,MATCH(B81,Categories!$A$2:$A$200,0)),"N")="Y"),D81,0)
A82: 40148 | B82: Salary | C82: Income | D82: 3430 | F82: =IF(AND(C82="One-off",IFERROR(INDEX(Categories!$C$2:$C$200,MATCH(B82,Categories!$A$2:$A$200,0)),"N")="Y"),D82,0)
A83: 40148 | B83: Uncategorised | C83: Actual | D83: 2440 | E83: Historical monthly total (pre per-category tracking) | F83: =IF(AND(C83="One-off",IFERROR(INDEX(Categories!$C$2:$C$200,MATCH(B83,Categories!$A$2:$A$200,0)),"N")="Y"),D83,0)
A84: 40179 | B84: Interest | C84: Income | D84: 20 | F84: =IF(AND(C84="One-off",IFERROR(INDEX(Categories!$C$2:$C$200,MATCH(B84,Categories!$A$2:$A$200,0)),"N")="Y"),D84,0)
A85: 40179 | B85: Salary | C85: Income | D85: 3360 | F85: =IF(AND(C85="One-off",IFERROR(INDEX(Categories!$C$2:$C$200,MATCH(B85,Categories!$A$2:$A$200,0)),"N")="Y"),D85,0)
A86: 40179 | B86: Uncategorised | C86: Actual | D86: 2640 | E86: Historical monthly total (pre per-category tracking) | F86: =IF(AND(C86="One-off",IFERROR(INDEX(Categories!$C$2:$C$200,MATCH(B86,Categories!$A$2:$A$200,0)),"N")="Y"),D86,0)
A87: 40210 | B87: Interest | C87: Income | D87: 20 | F87: =IF(AND(C87="One-off",IFERROR(INDEX(Categories!$C$2:$C$200,MATCH(B87,Categories!$A$2:$A$200,0)),"N")="Y"),D87,0)
A88: 40210 | B88: Salary | C88: Income | D88: 3410 | F88: =IF(AND(C88="One-off",IFERROR(INDEX(Categories!$C$2:$C$200,MATCH(B88,Categories!$A$2:$A$200,0)),"N")="Y"),D88,0)
A89: 40210 | B89: Uncategorised | C89: Actual | D89: 2160 | E89: Historical monthly total (pre per-category tracking) | F89: =IF(AND(C89="One-off",IFERROR(INDEX(Categories!$C$2:$C$200,MATCH(B89,Categories!$A$2:$A$200,0)),"N")="Y"),D89,0)
A90: 40238 | B90: Dividends | C90: Income | D90: 150 | F90: =IF(AND(C90="One-off",IFERROR(INDEX(Categories!$C$2:$C$200,MATCH(B90,Categories!$A$2:$A$200,0)),"N")="Y"),D90,0)
A91: 40238 | B91: Interest | C91: Income | D91: 20 | F91: =IF(AND(C91="One-off",IFERROR(INDEX(Categories!$C$2:$C$200,MATCH(B91,Categories!$A$2:$A$200,0)),"N")="Y"),D91,0)
A92: 40238 | B92: Salary | C92: Income | D92: 3460 | F92: =IF(AND(C92="One-off",IFERROR(INDEX(Categories!$C$2:$C$200,MATCH(B92,Categories!$A$2:$A$200,0)),"N")="Y"),D92,0)
A93: 40238 | B93: Uncategorised | C93: Actual | D93: 2280 | E93: Historical monthly total (pre per-category tracking) | F93: =IF(AND(C93="One-off",IFERROR(INDEX(Categories!$C$2:$C$200,MATCH(B93,Categories!$A$2:$A$200,0)),"N")="Y"),D93,0)
A94: 40269 | B94: Interest | C94: Income | D94: 20 | F94: =IF(AND(C94="One-off",IFERROR(INDEX(Categories!$C$2:$C$200,MATCH(B94,Categories!$A$2:$A$200,0)),"N")="Y"),D94,0)
A95: 40269 | B95: Salary | C95: Income | D95: 3510 | F95: =IF(AND(C95="One-off",IFERROR(INDEX(Categories!$C$2:$C$200,MATCH(B95,Categories!$A$2:$A$200,0)),"N")="Y"),D95,0)
A96: 40269 | B96: Uncategorised | C96: Actual | D96: 2400 | E96: Historical monthly total (pre per-category tracking) | F96: =IF(AND(C96="One-off",IFERROR(INDEX(Categories!$C$2:$C$200,MATCH(B96,Categories!$A$2:$A$200,0)),"N")="Y"),D96,0)
A97: 40299 | B97: Interest | C97: Income | D97: 20 | F97: =IF(AND(C97="One-off",IFERROR(INDEX(Categories!$C$2:$C$200,MATCH(B97,Categories!$A$2:$A$200,0)),"N")="Y"),D97,0)
A98: 40299 | B98: Salary | C98: Income | D98: 3560 | F98: =IF(AND(C98="One-off",IFERROR(INDEX(Categories!$C$2:$C$200,MATCH(B98,Categories!$A$2:$A$200,0)),"N")="Y"),D98,0)
A99: 40299 | B99: Uncategorised | C99: Actual | D99: 2520 | E99: Historical monthly total (pre per-category tracking) | F99: =IF(AND(C99="One-off",IFERROR(INDEX(Categories!$C$2:$C$200,MATCH(B99,Categories!$A$2:$A$200,0)),"N")="Y"),D99,0)
A100: 40330 | B100: Dividends | C100: Income | D100: 150 | F100: =IF(AND(C100="One-off",IFERROR(INDEX(Categories!$C$2:$C$200,MATCH(B100,Categories!$A$2:$A$200,0)),"N")="Y"),D100,0)
...

Sheet Budgets
A1: Category | B1: Effective From | C1: Monthly Budget
A2: Daily Food | B2: 39448 | C2: 400
A3: Daily Food | B3: 42005 | C3: 500
A4: Daily Food | B4: 44927 | C4: 600
A5: Transport | B5: 39448 | C5: 250
A6: Transport | B6: 43101 | C6: 300
A7: Groceries | B7: 39448 | C7: 350
A8: Groceries | B8: 43101 | C8: 450
A9: Groceries | B9: 44927 | C9: 500
A10: Bills | B10: 39448 | C10: 120
A11: Bills | B11: 42370 | C11: 180
A12: Bills | B12: 44927 | C12: 200
A13: Insurance | B13: 39448 | C13: 200
... A22: Shopping | B22: 44927 | C22: 150
A24: To revise a budget, add a NEW row for the category with a later 'Effective From' date. Blue = you edit.

Sheet Categories
A1: Category | B1: Group | C1: Invested (Y/N) | D1: Active | F1: ExpenseOrder (auto)
A2: Salary | B2: Income | C2: N | D2: Y | F2: =IF(AND($B2="Expense",$D2="Y"),COUNTIFS($B$2:$B2,"Expense",$D$2:$D2,"Y"),"")
A3: Interest | B3: Income | C3: N | D3: Y | F3: =IF(AND($B3="Expense",$D3="Y"),COUNTIFS($B$2:$B3,"Expense",$D$2:$D3,"Y"),"")
A4: Dividends | B4: Income | C4: N | D4: Y | F4: =IF(AND($B4="Expense",$D4="Y"),COUNTIFS($B$2:$B4,"Expense",$D$2:$D4,"Y"),"")
A5: Bonus/Claims | B5: Income | C5: N | D5: Y | F5: =IF(AND($B5="Expense",$D5="Y"),COUNTIFS($B$2:$B5,"Expense",$D$2:$D5,"Y"),"")
A6: Daily Food | B6: Expense | C6: N | D6: Y | F6: =IF(AND($B6="Expense",$D6="Y"),COUNTIFS($B$2:$B6,"Expense",$D$2:$D6,"Y"),"")
A7: Transport | B7: Expense | C7: N | D7: Y | F7: =IF(AND($B7="Expense",$D7="Y"),COUNTIFS($B$2:$B7,"Expense",$D$2:$D7,"Y"),"")
A8: Credit Card | B8: Expense | C8: N | D8: Y | F8: =IF(AND($B8="Expense",$D8="Y"),COUNTIFS($B$2:$B8,"Expense",$D$2:$D8,"Y"),"")
A9: Household | B9: Expense | C9: N | D9: Y | F9: =IF(AND($B9="Expense",$D9="Y"),COUNTIFS($B$2:$B9,"Expense",$D$2:$D9,"Y"),"")
A10: Tax | B10: Expense | C10: N | D10: Y | F10: =IF(AND($B10="Expense",$D10="Y"),COUNTIFS($B$2:$B10,"Expense",$D$2:$D10,"Y"),"")
A11: Savings for holiday | B11: Expense | C11: N | D11: Y | F11: =IF(AND($B11="Expense",$D11="Y"),COUNTIFS($B$2:$B11,"Expense",$D$2:$D11,"Y"),"")
A12: Bills | B12: Expense | C12: N | D12: Y | F12: =IF(AND($B12="Expense",$D12="Y"),COUNTIFS($B$2:$B12,"Expense",$D$2:$D12,"Y"),"")
A13: Insurance | B13: Expense | C13: N | D13: Y | F13: =IF(AND($B13="Expense",$D13="Y"),COUNTIFS($B$2:$B13,"Expense",$D$2:$D13,"Y"),"")
... A25: Household Help | B25: Expense | C25: N | D25: Y | F25: =IF(AND($B25="Expense",$D25="Y"),COUNTIFS($B$2:$B25,"Expense",$D$2:$D25,"Y"),"")
F26: =IF(AND($B26="Expense",$D26="Y"),COUNTIFS($B$2:$B26,"Expense",$D$2:$D26,"Y"),"")
F27: =IF(AND($B27="Expense",$D27="Y"),COUNTIFS($B$2:$B27,"Expense",$D$2:$D27,"Y"),"")
F28: =IF(AND($B28="Expense",$D28="Y"),COUNTIFS($B$2:$B28,"Expense",$D$2:$D28,"Y"),"")
F29: =IF(AND($B29="Expense",$D29="Y"),COUNTIFS($B$2:$B29,"Expense",$D$2:$D29,"Y"),"")
F30: =IF(AND($B30="Expense",$D30="Y"),COUNTIFS($B$2:$B30,"Expense",$D$2:$D30,"Y"),"")
F31: =IF(AND($B31="Expense",$D31="Y"),COUNTIFS($B$2:$B31,"Expense",$D$2:$D31,"Y"),"")
F32: =IF(AND($B32="Expense",$D32="Y"),COUNTIFS($B$2:$B32,"Expense",$D$2:$D32,"Y"),"")
F33: =IF(AND($B33="Expense",$D33="Y"),COUNTIFS($B$2:$B33,"Expense",$D$2:$D33,"Y"),"")
F34: =IF(AND($B34="Expense",$D34="Y"),COUNTIFS($B$2:$B34,"Expense",$D$2:$D34,"Y"),"")
F35: =IF(AND($B35="Expense",$D35="Y"),COUNTIFS($B$2:$B35,"Expense",$D$2:$D35,"Y"),"")
F36: =IF(AND($B36="Expense",$D36="Y"),COUNTIFS($B$2:$B36,"Expense",$D$2:$D36,"Y"),"")
F37: =IF(AND($B37="Expense",$D37="Y"),COUNTIFS($B$2:$B37,"Expense",$D$2:$D37,"Y"),"")
... F60: =IF(AND($B60="Expense",$D60="Y"),COUNTIFS($B$2:$B60,"Expense",$D$2:$D60,"Y"),"")
A62: Add a category by typing in the next empty (yellow) row. Group = Income / Expense / One-off. Invested = Y for capital that becomes an asset. Active = Y to include it in the Monthly Summary. It appears in the per-category breakdown automatically — no formula editing.
