Workbook
Name ColumnTitle1: Loan[[#Headers],[Pmt no.]]
Name EndingBalance: -FV(InterestRate/12,PaymentNumber,-MonthlyPayment,LoanAmount)
Name HeaderRow: ROW('Loan Calculator'!$16:$16)
Name InterestAmt: -IPMT(InterestRate/12,PaymentNumber,NumberOfPayments,LoanAmount)
Name InterestRate: 'Loan Calculator'!$D$6
Name LastCol: COUNTA('Loan Calculator'!$16:$16)
Name LastRow: MATCH(9.99E+307,'Loan Calculator'!$B:$B)
Name LoanAmount: 'Loan Calculator'!$D$5
Name LoanIsGood: IF(LoanAmount*InterestRate*LoanYears*LoanStartDate>0,1,0)
Name LoanIsNotPaid: IF(PaymentNumber<=NumberOfPayments,1,0)
Name LoanStartDate: 'Loan Calculator'!$D$8
Name LoanValue: -FV(InterestRate/12,PaymentNumber-1,-MonthlyPayment,LoanAmount)
Name LoanYears: 'Loan Calculator'!$D$7
Name MonthlyPayment: -PMT(InterestRate/12,NumberOfPayments,LoanAmount)
Name NumberOfPayments: 'Loan Calculator'!$D$12
Name PaymentDate: DATE(YEAR(LoanStartDate),MONTH(LoanStartDate)+PaymentNumber,DAY(LoanStartDate))
Name PaymentNumber: ROW()-HeaderRow
Name Principal: -PPMT(InterestRate/12,PaymentNumber,NumberOfPayments,LoanAmount)
Name PrintArea_SET: OFFSET('Loan Calculator'!$B$2,,,LastRow,LastCol)
Name RowTitleRegion1..D6: 'Loan Calculator'!$B$5
Name RowTitleRegion2..H6: 'Loan Calculator'!$B$11
Name Total_Interest: 'Loan Calculator'!$D$13
Name TotalLoanCost: 'Loan Calculator'!$D$14

Sheet Start Here
B1: PERSONAL FINANCE TRACKER
B2: A free template that grows with you — from basic financial planning to full portfolio management.
B4: HOW THIS WORKBOOK IS ORGANISED
B5: The tabs are colour-coded by level. Start with GREEN, add BLUE when you're ready, and graduate to PURPLE. GREY tabs are the engine room — they calculate everything automatically. Every tab: yellow cells are yours to edit, everything else is formulas.
B7: LEVEL 1 — FOUNDATIONS · know where you stand (≈15 minutes)
B8: 1. Settings — your age, savings, growth & inflation assumptions, FX rates. Everything reads from here.
B9: 2. Balance Sheet — list your accounts, investments, CPF and property. It totals your net worth and allocation.
B10: 3. Cash Flow — one row per month: income and expenses. This measures your real savings rate.
B11: 4. Net Worth History — one row per month with your latest net worth (from Balance Sheet E68).
B12: ✓ Payoff: the Dashboard shows your net worth, asset allocation, emergency-fund months and savings-rate checks — red/amber/green.
B13: Heads-up: a few Balance Sheet lines pull from Insurance, Housing and the stock ledger (Levels 2–3), so sample values linger there until you reset those tabs too — see RESETTING THE SAMPLE DATA at the bottom of this sheet.
B14: LEVEL 2 — LIFE PLANNING · protect and project
... B73: Why a checklist and not fully automatic: the held-ticker list is derived live, but rows are not auto-inserted — that would reshuffle the list and pull your hand-typed prices out of line. The panel simply points you to the one row to add or remove.

Sheet Dashboard
A1: DASHBOARD
A2: A live snapshot. Numbers flow from the other tabs — update those and this refreshes automatically.
A4: NET WORTH | D4: ASSET ALLOCATION
A5: Net Worth | B5: ='Balance Sheet'!E68 -> 1228147.5 | D5: Class | E5: Value
A6: Assets (excl. home & car) | B6: ='Balance Sheet'!B68 -> 952364.44 | D6: ='Balance Sheet'!J32 -> Cash | E6: ='Balance Sheet'!K32 -> 137500
A7: Total Assets | B7: ='Balance Sheet'!B67 -> 1822364.4 | D7: ='Balance Sheet'!J33 -> Investments (Cap Protected 2-3%) | E7: ='Balance Sheet'!K33 -> 317000
A8: Total Liabilities | B8: ='Balance Sheet'!E67 -> 594216.97 | D8: ='Balance Sheet'!J34 -> Crypto | E8: ='Balance Sheet'!K34 -> 13252.532
A9: Liquid / Emergency Cash | B9: ='Balance Sheet'!B18 -> 137500 | D9: ='Balance Sheet'!J35 -> Small Cap | E9: ='Balance Sheet'!K35 -> 8150
A10: Liquid as % of Net Worth | B10: =IFERROR('Balance Sheet'!B18/'Balance Sheet'!E68,"") -> 0.11195724 | D10: ='Balance Sheet'!J36 -> US/HK Growth | E10: ='Balance Sheet'!K36 -> 39594.911
D11: ='Balance Sheet'!J37 -> Reit/Dividend | E11: ='Balance Sheet'!K37 -> 38740
A12: RETIREMENT | D12: ='Balance Sheet'!J38 -> Bonds | E12: ='Balance Sheet'!K38 -> 40000
A13: Planned retirement age | B13: =Settings!B7 -> 60 | D13: ='Balance Sheet'!J39 -> Gold/Silver | E13: ='Balance Sheet'!K39 -> 78127
A14: Projected portfolio @ retirement (5%) | B14: =INDEX('Retirement Plan'!I15:I58,MATCH(Settings!B7,'Retirement Plan'!A15:A58,0)) -> 3799654.9 | D14: ='Balance Sheet'!J40 -> Commodities | E14: ='Balance Sheet'!K40 -> 0
A15: Projected dividend income/yr (5%) | B15: =INDEX('Retirement Plan'!K15:K58,MATCH(Settings!B7,'Retirement Plan'!A15:A58,0)) -> 101637.24 | D15: ='Balance Sheet'!J41 -> CPF OA (2.5%) | E15: ='Balance Sheet'!K41 -> 95000
A16: Target annual retirement sum | B16: =Settings!B18 -> 60000 | D16: ='Balance Sheet'!J42 -> CPF SA Medisave | E16: ='Balance Sheet'!K42 -> 180000
D17: ='Balance Sheet'!J43 -> Real Properties | E17: ='Balance Sheet'!K43 -> 246733.03
A18: INSURANCE | D18: ='Balance Sheet'!J44 -> Personal Loan to Friend | E18: ='Balance Sheet'!K44 -> 5000
A19: Life / death coverage | B19: =Insurance!B8 -> 710000
A20: Critical illness coverage | B20: =Insurance!B10 -> 410000
A21: Total annual premium | B21: =Insurance!B7 -> 5048.88
A22: Insurance cash value (in net worth) | B22: =Insurance!B5 -> 135000
A24: HOUSING
A25: Property value (your share) | B25: =Housing!B20 -> 825000
A26: Mortgage (your share) | B26: =Housing!B21 -> 578266.97
A27: Home equity (your share) | B27: =Housing!B22 -> 246733.03
A29: STATUS CHECKS
A30: Emergency fund (months of expenses) | B30: =IFERROR('Balance Sheet'!B18/Settings!B31,"") -> 27.5 | C30: target ≥ 6
A31: Top holding concentration (stocks) | B31: ='Stock Dashboard'!B12 -> 0.43925024 | C31: target < 10%
A32: FI number (target income ÷ safe withdrawal rate) | B32: =IFERROR(Settings!B18/Settings!B32,"") -> 1500000
A33: Retirement readiness (proj @5% ÷ FI number) | B33: =IFERROR(B14/B32,"") -> 2.5331033 | C33: target ≥ 100%
A34: Actual savings rate (Cash Flow, last 12m) | B34: ='Cash Flow'!$B$7 -> 0.375
A35: Actual annual savings (Cash Flow) | B35: ='Cash Flow'!$B$8 -> 36000 | C35: ="plan: "&TEXT(Settings!$B$8,"$#,##0") -> plan: $30,000

Sheet Settings
A1: SETTINGS & ASSUMPTIONS
A2: Edit the yellow cells. The rest of the workbook reads its assumptions from here.
A4: YOUR PROFILE
A5: Current age | B5: 42
A6: Current year (projection base) | B6: 2026
A7: Planned retirement age | B7: 60
A8: Annual savings ($/yr) | B8: 30000
A10: RETURN ASSUMPTIONS
A11: Annual inflation | B11: 0.025
A12: Conservative growth | B12: 0.03
A13: Moderate growth | B13: 0.05
A14: Aggressive growth | B14: 0.08
A15: Dividend yield (on portfolio) | B15: 0.04
A17: RETIREMENT TARGETS (Singapore)
A18: Target annual retirement sum ($/yr) | B18: 60000
A19: Reserve for housing / HDB ($) | B19: 330000
A21: FX TO SGD (single source of truth — the Prices tab reads these)
A22: USD -> SGD | B22: 1.2928081
A23: HKD -> SGD | B23: 0.16489949
A25: Notes:
A26: CPF (Central Provident Fund), SRS (Supplementary Retirement Scheme), SSB (Singapore Savings Bonds),
A27: BSD (Buyer Stamp Duty), HDB (public housing). Replace with your local equivalents if you are outside Singapore.
A28: ‘Current year (projection base)’ = the year that matches your current age above; the Retirement Plan projection counts up from it to age 85.
A30: SPENDING & RETIREMENT TARGETS
A31: Monthly household expenses ($/mth) | B31: 5000
A32: Safe withdrawal rate (for FI number) | B32: 0.04
A34: CHILD / EDUCATION ASSUMPTIONS (used by Balance Sheet liabilities)
A35: Education inflation | B35: 0.03
A36: Years until university | B36: 14
A37: Degree cost per year (today's $) | B37: 33000
A38: Degree length (years) | B38: 5
A39: Allowance during studies ($/mth) | B39: 1500

Sheet Balance Sheet
A1: As at today — values update live from the other tabs
A2: Assets | D2: Liabilities and Net Worth
A4: Liquid Assets | D4: Current Liabilities
A5: POSB Cash | B5: 8500 | D5: OCBC Credit Balance | E5: 1800
A6: e$aver (Closed) | B6: 0 | D6: Maribank + POSB | E6: 950
A7: XtraSaver (Closed) | B7: 0 | D7: UOB | E7: 1200
A8: DASH by Standchart (Closed) | B8: 0
A9: Maybank | B9: 15000 | D9: Total | E9: =SUM(E5:E7) -> 3950
A10: Trust Bank | B10: 12000
A11: Super Salary Acct (Closed) | B11: 0
A12: Maribank + Funds | B12: 20000
A13: POSB Joint | B13: 6500
A14: UOB ONE Account | B14: 38000
A15: UOB Savings | B15: 0
A16: OCBC 360 + Joint Account | B16: 28000
A17: DBS Multicurrency + MooMoo Cash Account + Webull Cash | B17: 9500
A18: Total | B18: =SUM(B5:B17) -> 137500
D19: Long Term Liabilities
D20: Child Savings | E20: 12000
A21: Investments (Cap Protected 2-3%) | D21: University Study Fund | E21: 0
A22: AIA Endowment Deposit (4% p.a.) | B22: =Insurance!H21 -> 0 | D22: UOB Home Loan | E22: =Housing!B21 -> 578266.97
A23: Prudential Savings (Projected $100,000 @ 52) | B23: =Insurance!H18 -> 60000
A24: UOB/Prudential Savings (Projected $46,000 @ 52) | B24: =Insurance!H19 -> 28000 | D24: Total | E24: =SUM(E20:E22) -> 590266.97
A25: Prudential Saving (2%PA till 2022 using SRS) (Closed) | D25: Child University Fund (e.g. degree @ $33k/yr) | E25: =((1+Settings!$B$35)^Settings!$B$36)*Settings!$B$37*Settings!$B$38 -> 249577.3
A26: NTUC Savings/Insurance (Projected $40,000 @ 55) | B26: =Insurance!H15+Insurance!H16 -> 22000 | D26: Child Allowance during studies (e.g. $1,500/mth) | E26: =((1+Settings!$B$35)^Settings!$B$36)*Settings!$B$39*12*Settings!$B$38 -> 136133.08
A27: SRS Account (Supplementary Retirement Scheme) | B27: 120000
A28: CPF Cash Top-ups for Family Members (tax relief) | B28: 35000
A29: Child Development Account (CDA) Contributions | B29: 9000
A30: Singapore Savings Bond (1.89% coupon, using SRS) | B30: 18000 | J30: Asset Allocation
A31: Temasek Bond (2.7% coupon) | K31: Amount | L31: Percentage
A32: AIA ILP | B32: =Insurance!H20 -> 25000 | J32: Cash | K32: =B18 -> 137500 | L32: =K32/SUM($K$32:$K$44) -> 0.11466958
A33: Total | B33: =SUM(B22:B32) -> 317000 | J33: =$A$21 -> Investments (Cap Protected 2-3%) | K33: =$B$33 -> 317000 | L33: =K33/SUM($K$32:$K$44) -> 0.2643655
J34: =A37 -> Crypto | K34: =$B$37 -> 13252.532 | L34: =K34/SUM($K$32:$K$44) -> 0.011052089
A35: Equities/Crypto/High Risk Loans | J35: =A40 -> Small Cap | K35: =$B$40 -> 8150 | L35: =K35/SUM($K$32:$K$44) -> 0.0067967785
A36: Personal Loan to Friend | B36: 5000 | J36: =A38 -> US/HK Growth | K36: =$B$38 -> 39594.911 | L36: =K36/SUM($K$32:$K$44) -> 0.033020594
A37: =Shares!S7 -> Crypto | B37: =Shares!T7 -> 13252.532 | J37: =A39 -> Reit/Dividend | K37: =$B$39 -> 38740 | L37: =K37/SUM($K$32:$K$44) -> 0.032307632 | M37: =SUM(L34:L37) -> 0.083177094 | N37: <- high-risk subtotal (rows 34-37)
A38: =Shares!S3 -> US/HK Growth | B38: =Shares!T3 -> 39594.911 | J38: Bonds | K38: =$B$46 -> 40000 | L38: =K38/SUM($K$32:$K$44) -> 0.033358422
A39: =Shares!S4 -> Reit/Dividend | B39: =Shares!T4 -> 38740 | J39: Gold/Silver | K39: =B48 -> 78127 | L39: =K39/SUM($K$32:$K$44) -> 0.065154836
A40: =Shares!S5 -> Small Cap | B40: =Shares!T5 -> 8150 | J40: =A49 -> Commodities | K40: =B49 -> 0 | L40: =K40/SUM($K$32:$K$44) -> 0
A41: Total | B41: =SUM(B36:B40) -> 104737.44 | J41: =$A$53 -> CPF OA (2.5%) | K41: =$B$53 -> 95000 | L41: =K41/SUM($K$32:$K$44) -> 0.079226253
J42: CPF SA Medisave | K42: =$B54+$B55 -> 180000 | L42: =K42/SUM($K$32:$K$44) -> 0.1501129
A43: Bonds (Min Yield at 3.16%) | J43: =$A$59 -> Real Properties | K43: =$B$60-E22 -> 246733.03 | L43: =K43/SUM($K$32:$K$44) -> 0.20576562
A44: Singapore Savings Bond (Cash) | B44: 25000 | J44: =$A$36 -> Personal Loan to Friend | K44: =$B$36 -> 5000 | L44: =K44/SUM($K$32:$K$44) -> 0.0041698028
A45: Singapore Savings Bond (SRS) | B45: 15000 | J45: Total | K45: =SUM(K32:K44) -> 1199097.5 | L45: =SUM(L32:L44) -> 1
A46: Total | B46: =SUM(B44:B45) -> 40000
A48: Gold+Silver | B48: =Shares!T8 -> 78127
A49: =Shares!S6 -> Commodities | B49: =Shares!T6 -> 0
A50: Total | B50: =SUM(B48:B49) -> 78127
A52: CPF
A53: CPF OA (2.5%) | B53: 95000
A54: CPF SA (4%) | B54: 130000
A55: CPF Medisave | B55: 50000
A56: Investment | B56: 0
A57: Total | B57: =SUM(B53:B56) -> 275000
A59: Real Properties
A60: Primary Residence (Condo) | B60: =Housing!B20 -> 825000
A62: Personal Properties
A63: Car | B63: 45000
A67: Total Assets | B67: =B18+B33+B46+B57+B63+B50+B41+B60 -> 1822364.4 | D67: Total Liabilities | E67: =E9+E24 -> 594216.97
A68: Total Assets (excl House/Car) | B68: =B18+B33+B46+B50+B57+B41 -> 952364.44 | D68: Net Worth | E68: =B67-E67 -> 1228147.5 | F68: =E68-E25-E26 -> 842437.1 | G68: <- net worth after reserving child education costs (E25:E26)
A69: Emergency Cash | B69: =B18 -> 137500 | D69: 3% dividend out of networth | E69: =0.03*E68 -> 36844.424 | F69: =0.03*F68 -> 25273.113
D70: 3% dividend out of networth / mth | E70: =E69/12 -> 3070.3687 | F70: =F69/12 -> 2106.0927

Sheet Cash Flow
A1: CASH FLOW (monthly income & spending — your measured savings rate)
A2: One row per month, yellow cells only. The averages below use your last 12 months of entries and are compared against the plan numbers in Settings.
A4: ACTUALS (last 12 months of entries)
A5: Average monthly take-home income | B5: =IFERROR(AVERAGEIFS($B$13:$B$60,$A$13:$A$60,">"&EDATE(TODAY(),-12)),"") -> 8000
A6: Average monthly expenses | B6: =IFERROR(AVERAGEIFS($E$13:$E$60,$A$13:$A$60,">"&EDATE(TODAY(),-12)),"") -> 5000 | C6: ="plan (Settings): "&TEXT(Settings!$B$31,"$#,##0") -> plan (Settings): $5,000
A7: Average savings rate | B7: =IFERROR(1-B6/B5,"") -> 0.375
A8: Implied annual savings (actual) | B8: =IFERROR((B5-B6)*12,"") -> 36000 | C8: ="plan (Settings): "&TEXT(Settings!$B$8,"$#,##0") -> plan (Settings): $30,000
A10: Tip: once a few months are entered, consider updating the yellow plan numbers in Settings to match reality.
A12: Month | B12: Take-home income | C12: Fixed expenses | D12: Variable expenses | E12: Total expenses | F12: Saved | G12: Savings rate | H12: Notes
A13: 46174 | B13: 8000 | C13: 3500 | D13: 1500 | E13: =IF($A13="","",$C13+$D13) -> 5000 | F13: =IF($A13="","",$B13-$E13) -> 3000 | G13: =IF(OR($A13="",$B13="",$B13=0),"",$F13/$B13) -> 0.375 | H13: [Sample] replace with your own
E14: =IF($A14="","",$C14+$D14) | F14: =IF($A14="","",$B14-$E14) | G14: =IF(OR($A14="",$B14="",$B14=0),"",$F14/$B14)
E15: =IF($A15="","",$C15+$D15) | F15: =IF($A15="","",$B15-$E15) | G15: =IF(OR($A15="",$B15="",$B15=0),"",$F15/$B15)
E16: =IF($A16="","",$C16+$D16) | F16: =IF($A16="","",$B16-$E16) | G16: =IF(OR($A16="",$B16="",$B16=0),"",$F16/$B16)
E17: =IF($A17="","",$C17+$D17) | F17: =IF($A17="","",$B17-$E17) | G17: =IF(OR($A17="",$B17="",$B17=0),"",$F17/$B17)
E18: =IF($A18="","",$C18+$D18) | F18: =IF($A18="","",$B18-$E18) | G18: =IF(OR($A18="",$B18="",$B18=0),"",$F18/$B18)
E19: =IF($A19="","",$C19+$D19) | F19: =IF($A19="","",$B19-$E19) | G19: =IF(OR($A19="",$B19="",$B19=0),"",$F19/$B19)
E20: =IF($A20="","",$C20+$D20) | F20: =IF($A20="","",$B20-$E20) | G20: =IF(OR($A20="",$B20="",$B20=0),"",$F20/$B20)
E21: =IF($A21="","",$C21+$D21) | F21: =IF($A21="","",$B21-$E21) | G21: =IF(OR($A21="",$B21="",$B21=0),"",$F21/$B21)
E22: =IF($A22="","",$C22+$D22) | F22: =IF($A22="","",$B22-$E22) | G22: =IF(OR($A22="",$B22="",$B22=0),"",$F22/$B22)
E23: =IF($A23="","",$C23+$D23) | F23: =IF($A23="","",$B23-$E23) | G23: =IF(OR($A23="",$B23="",$B23=0),"",$F23/$B23)
E24: =IF($A24="","",$C24+$D24) | F24: =IF($A24="","",$B24-$E24) | G24: =IF(OR($A24="",$B24="",$B24=0),"",$F24/$B24)
E25: =IF($A25="","",$C25+$D25) | F25: =IF($A25="","",$B25-$E25) | G25: =IF(OR($A25="",$B25="",$B25=0),"",$F25/$B25)
... E60: =IF($A60="","",$C60+$D60) | F60: =IF($A60="","",$B60-$E60) | G60: =IF(OR($A60="",$B60="",$B60=0),"",$F60/$B60)

Sheet Net Worth History
A1: NET WORTH HISTORY
A2: Each month, record your net worth (copy the value from Balance Sheet cell E68). Add new rows at the bottom; the formulas will extend if you copy them down. (Sample rows are quarterly just to demonstrate the formulas — monthly is better.)
A4: Date | B4: Net Worth | C4: MoM Change | D4: YoY Change | E4: YoY % | F4: 12-mo Avg (MoM) | G4: Notes
A5: 45627 | B5: 1050000 | G5: Starting point
A6: 45717 | B6: 1082000 | C6: =IF(OR($A6="",$B6=""),"",IF($B5="","",$B6-$B5)) -> 32000 | D6: =IF(OR($A6="",$B6=""),"",IFERROR($B6-LOOKUP(EDATE($A6,-12),$A$5:$A5,$B$5:$B5),"")) | E6: =IF($D6="","",IFERROR($D6/($B6-$D6),"")) | F6: =IF(OR($A6="",$B6=""),"",IFERROR(AVERAGEIFS($C$5:$C6,$A$5:$A6,">"&EDATE($A6,-12),$A$5:$A6,"<="&$A6),"")) -> 32000
A7: 45809 | B7: 1068000 | C7: =IF(OR($A7="",$B7=""),"",IF($B6="","",$B7-$B6)) -> -14000 | D7: =IF(OR($A7="",$B7=""),"",IFERROR($B7-LOOKUP(EDATE($A7,-12),$A$5:$A6,$B$5:$B6),"")) | E7: =IF($D7="","",IFERROR($D7/($B7-$D7),"")) | F7: =IF(OR($A7="",$B7=""),"",IFERROR(AVERAGEIFS($C$5:$C7,$A$5:$A7,">"&EDATE($A7,-12),$A$5:$A7,"<="&$A7),"")) -> 9000 | G7: Market dip
A8: 45901 | B8: 1120000 | C8: =IF(OR($A8="",$B8=""),"",IF($B7="","",$B8-$B7)) -> 52000 | D8: =IF(OR($A8="",$B8=""),"",IFERROR($B8-LOOKUP(EDATE($A8,-12),$A$5:$A7,$B$5:$B7),"")) | E8: =IF($D8="","",IFERROR($D8/($B8-$D8),"")) | F8: =IF(OR($A8="",$B8=""),"",IFERROR(AVERAGEIFS($C$5:$C8,$A$5:$A8,">"&EDATE($A8,-12),$A$5:$A8,"<="&$A8),"")) -> 23333.333
A9: 45992 | B9: 1168000 | C9: =IF(OR($A9="",$B9=""),"",IF($B8="","",$B9-$B8)) -> 48000 | D9: =IF(OR($A9="",$B9=""),"",IFERROR($B9-LOOKUP(EDATE($A9,-12),$A$5:$A8,$B$5:$B8),"")) -> 118000 | E9: =IF($D9="","",IFERROR($D9/($B9-$D9),"")) -> 0.11238095 | F9: =IF(OR($A9="",$B9=""),"",IFERROR(AVERAGEIFS($C$5:$C9,$A$5:$A9,">"&EDATE($A9,-12),$A$5:$A9,"<="&$A9),"")) -> 29500 | G9: Year-end bonus saved
A10: 46082 | B10: 1196000 | C10: =IF(OR($A10="",$B10=""),"",IF($B9="","",$B10-$B9)) -> 28000 | D10: =IF(OR($A10="",$B10=""),"",IFERROR($B10-LOOKUP(EDATE($A10,-12),$A$5:$A9,$B$5:$B9),"")) -> 114000 | E10: =IF($D10="","",IFERROR($D10/($B10-$D10),"")) -> 0.10536044 | F10: =IF(OR($A10="",$B10=""),"",IFERROR(AVERAGEIFS($C$5:$C10,$A$5:$A10,">"&EDATE($A10,-12),$A$5:$A10,"<="&$A10),"")) -> 28500
A11: 46174 | B11: 1224000 | C11: =IF(OR($A11="",$B11=""),"",IF($B10="","",$B11-$B10)) -> 28000 | D11: =IF(OR($A11="",$B11=""),"",IFERROR($B11-LOOKUP(EDATE($A11,-12),$A$5:$A10,$B$5:$B10),"")) -> 156000 | E11: =IF($D11="","",IFERROR($D11/($B11-$D11),"")) -> 0.14606742 | F11: =IF(OR($A11="",$B11=""),"",IFERROR(AVERAGEIFS($C$5:$C11,$A$5:$A11,">"&EDATE($A11,-12),$A$5:$A11,"<="&$A11),"")) -> 39000
C12: =IF(OR($A12="",$B12=""),"",IF($B11="","",$B12-$B11)) | D12: =IF(OR($A12="",$B12=""),"",IFERROR($B12-LOOKUP(EDATE($A12,-12),$A$5:$A11,$B$5:$B11),"")) | E12: =IF($D12="","",IFERROR($D12/($B12-$D12),"")) | F12: =IF(OR($A12="",$B12=""),"",IFERROR(AVERAGEIFS($C$5:$C12,$A$5:$A12,">"&EDATE($A12,-12),$A$5:$A12,"<="&$A12),""))
C13: =IF(OR($A13="",$B13=""),"",IF($B12="","",$B13-$B12)) | D13: =IF(OR($A13="",$B13=""),"",IFERROR($B13-LOOKUP(EDATE($A13,-12),$A$5:$A12,$B$5:$B12),"")) | E13: =IF($D13="","",IFERROR($D13/($B13-$D13),"")) | F13: =IF(OR($A13="",$B13=""),"",IFERROR(AVERAGEIFS($C$5:$C13,$A$5:$A13,">"&EDATE($A13,-12),$A$5:$A13,"<="&$A13),""))
C14: =IF(OR($A14="",$B14=""),"",IF($B13="","",$B14-$B13)) | D14: =IF(OR($A14="",$B14=""),"",IFERROR($B14-LOOKUP(EDATE($A14,-12),$A$5:$A13,$B$5:$B13),"")) | E14: =IF($D14="","",IFERROR($D14/($B14-$D14),"")) | F14: =IF(OR($A14="",$B14=""),"",IFERROR(AVERAGEIFS($C$5:$C14,$A$5:$A14,">"&EDATE($A14,-12),$A$5:$A14,"<="&$A14),""))
C15: =IF(OR($A15="",$B15=""),"",IF($B14="","",$B15-$B14)) | D15: =IF(OR($A15="",$B15=""),"",IFERROR($B15-LOOKUP(EDATE($A15,-12),$A$5:$A14,$B$5:$B14),"")) | E15: =IF($D15="","",IFERROR($D15/($B15-$D15),"")) | F15: =IF(OR($A15="",$B15=""),"",IFERROR(AVERAGEIFS($C$5:$C15,$A$5:$A15,">"&EDATE($A15,-12),$A$5:$A15,"<="&$A15),""))
C16: =IF(OR($A16="",$B16=""),"",IF($B15="","",$B16-$B15)) | D16: =IF(OR($A16="",$B16=""),"",IFERROR($B16-LOOKUP(EDATE($A16,-12),$A$5:$A15,$B$5:$B15),"")) | E16: =IF($D16="","",IFERROR($D16/($B16-$D16),"")) | F16: =IF(OR($A16="",$B16=""),"",IFERROR(AVERAGEIFS($C$5:$C16,$A$5:$A16,">"&EDATE($A16,-12),$A$5:$A16,"<="&$A16),""))
C17: =IF(OR($A17="",$B17=""),"",IF($B16="","",$B17-$B16)) | D17: =IF(OR($A17="",$B17=""),"",IFERROR($B17-LOOKUP(EDATE($A17,-12),$A$5:$A16,$B$5:$B16),"")) | E17: =IF($D17="","",IFERROR($D17/($B17-$D17),"")) | F17: =IF(OR($A17="",$B17=""),"",IFERROR(AVERAGEIFS($C$5:$C17,$A$5:$A17,">"&EDATE($A17,-12),$A$5:$A17,"<="&$A17),""))
C18: =IF(OR($A18="",$B18=""),"",IF($B17="","",$B18-$B17)) | D18: =IF(OR($A18="",$B18=""),"",IFERROR($B18-LOOKUP(EDATE($A18,-12),$A$5:$A17,$B$5:$B17),"")) | E18: =IF($D18="","",IFERROR($D18/($B18-$D18),"")) | F18: =IF(OR($A18="",$B18=""),"",IFERROR(AVERAGEIFS($C$5:$C18,$A$5:$A18,">"&EDATE($A18,-12),$A$5:$A18,"<="&$A18),""))
C19: =IF(OR($A19="",$B19=""),"",IF($B18="","",$B19-$B18)) | D19: =IF(OR($A19="",$B19=""),"",IFERROR($B19-LOOKUP(EDATE($A19,-12),$A$5:$A18,$B$5:$B18),"")) | E19: =IF($D19="","",IFERROR($D19/($B19-$D19),"")) | F19: =IF(OR($A19="",$B19=""),"",IFERROR(AVERAGEIFS($C$5:$C19,$A$5:$A19,">"&EDATE($A19,-12),$A$5:$A19,"<="&$A19),""))
C20: =IF(OR($A20="",$B20=""),"",IF($B19="","",$B20-$B19)) | D20: =IF(OR($A20="",$B20=""),"",IFERROR($B20-LOOKUP(EDATE($A20,-12),$A$5:$A19,$B$5:$B19),"")) | E20: =IF($D20="","",IFERROR($D20/($B20-$D20),"")) | F20: =IF(OR($A20="",$B20=""),"",IFERROR(AVERAGEIFS($C$5:$C20,$A$5:$A20,">"&EDATE($A20,-12),$A$5:$A20,"<="&$A20),""))
C21: =IF(OR($A21="",$B21=""),"",IF($B20="","",$B21-$B20)) | D21: =IF(OR($A21="",$B21=""),"",IFERROR($B21-LOOKUP(EDATE($A21,-12),$A$5:$A20,$B$5:$B20),"")) | E21: =IF($D21="","",IFERROR($D21/($B21-$D21),"")) | F21: =IF(OR($A21="",$B21=""),"",IFERROR(AVERAGEIFS($C$5:$C21,$A$5:$A21,">"&EDATE($A21,-12),$A$5:$A21,"<="&$A21),""))
C22: =IF(OR($A22="",$B22=""),"",IF($B21="","",$B22-$B21)) | D22: =IF(OR($A22="",$B22=""),"",IFERROR($B22-LOOKUP(EDATE($A22,-12),$A$5:$A21,$B$5:$B21),"")) | E22: =IF($D22="","",IFERROR($D22/($B22-$D22),"")) | F22: =IF(OR($A22="",$B22=""),"",IFERROR(AVERAGEIFS($C$5:$C22,$A$5:$A22,">"&EDATE($A22,-12),$A$5:$A22,"<="&$A22),""))
C23: =IF(OR($A23="",$B23=""),"",IF($B22="","",$B23-$B22)) | D23: =IF(OR($A23="",$B23=""),"",IFERROR($B23-LOOKUP(EDATE($A23,-12),$A$5:$A22,$B$5:$B22),"")) | E23: =IF($D23="","",IFERROR($D23/($B23-$D23),"")) | F23: =IF(OR($A23="",$B23=""),"",IFERROR(AVERAGEIFS($C$5:$C23,$A$5:$A23,">"&EDATE($A23,-12),$A$5:$A23,"<="&$A23),""))
... C40: =IF(OR($A40="",$B40=""),"",IF($B39="","",$B40-$B39)) | D40: =IF(OR($A40="",$B40=""),"",IFERROR($B40-LOOKUP(EDATE($A40,-12),$A$5:$A39,$B$5:$B39),"")) | E40: =IF($D40="","",IFERROR($D40/($B40-$D40),"")) | F40: =IF(OR($A40="",$B40=""),"",IFERROR(AVERAGEIFS($C$5:$C40,$A$5:$A40,">"&EDATE($A40,-12),$A$5:$A40,"<="&$A40),""))

Sheet Insurance
A1: INSURANCE
A2: One row per policy. Yellow cells = type your own number. Current cash/surrender value flows to the Balance Sheet; projected maturity value feeds the Retirement Plan. Coverage is protection, not an asset.
A4: SUMMARY
A5: Current cash / surrender value (asset today) | B5: =SUM(H15:H21) -> 135000 | C5: <- flows to the Balance Sheet
A6: Projected maturity value (future) | B6: =SUM(I15:I21) -> 237422 | C6: <- feeds the Retirement Plan
A7: Total annual premium | B7: =SUM(L15:L21) -> 5048.88
A8: Total life / death coverage | B8: =SUM(N15:N21) -> 710000
A9: Total TPD coverage | B9: =SUM(O15:O21) -> 710000
A10: Total critical illness coverage | B10: =SUM(P15:P21) -> 410000
A11: Number of policies | B11: =COUNTA(A15:A21) -> 7
A14: Policy | B14: Company | C14: Policy No. | D14: Plan Type / Name | E14: Category | F14: Commencement | G14: Maturity Age | H14: Current Cash / Surrender Value | I14: Projected Maturity Value | J14: Premium Amount | K14: Frequency | L14: Annual Premium | M14: Sum Assured (Basic) | N14: Death Benefit | O14: TPD Benefit | P14: Critical Illness Benefit | Q14: Remarks
A15: Policy 1 | B15: NTUC | C15: POL-0001 | D15: Living Policy (Whole Life) | E15: Protection | F15: 37012 | G15: 60 | H15: 10000 | I15: 39188 | J15: 33.1 | K15: Monthly | L15: =IF(K15="Monthly",J15*12,IF(K15="Quarterly",J15*4,J15)) -> 397.2 | M15: 20000 | N15: 20000 | O15: 20000 | P15: 20000 | Q15: Participating whole life. TPD: 10% of S/A+bonus yrs1-4, 60% yr5 (till age 60). Convertible to annuity @60 +5%. Hosp benefit $30/day.
A16: Policy 2 | B16: NTUC | C16: POL-0002 | D16: Living Policy (Whole Life) | E16: Protection | F16: 38987 | G16: 60 | H16: 12000 | I16: 42234 | J16: 62.3 | K16: Monthly | L16: =IF(K16="Monthly",J16*12,IF(K16="Quarterly",J16*4,J16)) -> 747.6 | M16: 30000 | N16: 30000 | O16: 30000 | P16: 30000 | Q16: Whole life + term rider 13/20 x $100k (till age 45). Disability income: TPD $6k/yr from 6th yr (till 65); Major illness $500/mth 20 yrs. Convertible to annuity @60 +5%.
A17: Policy 3 | B17: Aviva | C17: POL-C1 / POL-C2 | D17: Group Term Life + Living Care | E17: Term | F17: 40934 | G17: 65 | H17: 0 | I17: 0 | J17: 106.8 | K17: Monthly | L17: =IF(K17="Monthly",J17*12,IF(K17="Quarterly",J17*4,J17)) -> 1281.6 | M17: 600000 | N17: 600000 | O17: 600000 | P17: 300000 | Q17: Term to 65, no cash value. Critical illness $300k. Hosp benefit $120/day (day 11-30).
A18: Policy 4 | B18: Prudential | C18: POL-0004 | D18: PruSave (Endowment) | E18: Endowment/Savings | F18: 39499 | G18: 60 | H18: 60000 | I18: 110000 | J18: 218.54 | K18: Monthly | L18: =IF(K18="Monthly",J18*12,IF(K18="Quarterly",J18*4,J18)) -> 2622.48 | M18: 60000 | N18: 60000 | O18: 60000 | P18: 60000 | Q18: Endowment/savings plan. Projected maturity ~$110k @60. Convertible to annuity @60 +5%.
A19: Policy 5 | B19: Prudential | C19: (UOB/Pru) | D19: UOB/Prudential Savings | E19: Endowment/Savings | G19: 52 | H19: 28000 | I19: 46000 | K19: Monthly | L19: =IF(K19="Monthly",J19*12,IF(K19="Quarterly",J19*4,J19)) -> 0 | Q19: Savings plan projected ~$46k @52. Update premium/coverage from your policy document.
A20: Policy 6 | B20: AIA | C20: (ILP) | D20: Investment-Linked Policy | E20: Investment-Linked | H20: 25000 | K20: Monthly | L20: =IF(K20="Monthly",J20*12,IF(K20="Quarterly",J20*4,J20)) -> 0 | Q20: Market-linked policy; cash value moves with fund NAV. Not capital-guaranteed.
A21: Policy 7 | B21: AIA | C21: (Endowment) | D21: Endowment Deposit (4% p.a.) | E21: Endowment/Savings | H21: 0 | K21: Monthly | L21: =IF(K21="Monthly",J21*12,IF(K21="Quarterly",J21*4,J21)) -> 0 | Q21: AIA endowment deposit, ~4% p.a. Enter current surrender value when available.
A23: Notes: Cash/surrender value = what you'd realise if you cashed out today (the asset figure). Term/protection-only policies have no cash value. Add more policies on new rows below the table - the SUMMARY and linked sheets update automatically.

Sheet Housing
A1: HOUSING & MORTGAGE
A2: Yellow = type your own number. Loan terms & the full repayment schedule live on the Loan Calculator tab. Your ownership share of the property value and loan flows to the Balance Sheet.
A4: PROPERTY
A5: Current market value (100%) | B5: 1500000
A6: Original purchase price (100%) | B6: 1500000
A7: Purchase date | B7: 45658
A8: Your ownership share | B8: 0.55
A9: Spouse ownership share | B9: =1-B8 -> 0.45
A11: MORTGAGE (set loan terms on the Loan Calculator tab)
A12: Original loan amount | B12: ='Loan Calculator'!D5 -> 1125000
A13: Interest rate (p.a.) | B13: ='Loan Calculator'!D6 -> 0.02
A14: Loan tenure (years) | B14: ='Loan Calculator'!D7 -> 20
A15: Loan start date | B15: ='Loan Calculator'!D8 -> 45658
A16: Monthly repayment | B16: ='Loan Calculator'!D11 -> 5691.1875
A17: Outstanding balance (today, 100%) | B17: ='Loan Calculator'!D15 -> 1051394.5
A19: YOUR POSITION (flows to Balance Sheet)
A20: Property value - your share | B20: =B5*B8 -> 825000 | D20: <- Balance Sheet asset
A21: Outstanding loan - your share | B21: =B17*B8 -> 578266.97 | D21: <- Balance Sheet liability
A22: Home equity - your share | B22: =B20-B21 -> 246733.03
A23: Home equity - full (100%) | B23: =B5-B17 -> 448605.52
A25: PAYDOWN PLAN (optional target)
A26: Target loan balance (100%) | B26: 1000000
A27: Target date | B27: 47118
A28: Amount still to pay down (100%) | B28: =MAX(0,B17-B26) -> 51394.483
A29: - your share | B29: =B28*B8 -> 28266.966
A30: - spouse share | B30: =B28*B9 -> 23127.517
A31: Years to target (approx) | B31: =MAX(0,(B27-TODAY())/365) -> 2.4109589
A32: Annual paydown needed - your share | B32: =IFERROR(B29/B31,0) -> 11724.366
A34: CPF FUNDING (planning)
A35: Current CPF OA balance | B35: ='Balance Sheet'!B53 -> 95000
A36: CPF OA contribution / month | B36: 2200
A37: CPF OA contribution / year (13 mths) | B37: =B36*13 -> 28600
A38: Emergency CPF buffer to keep | B38: 236000
A39: CPF OA available after buffer | B39: =B35-B38 -> -141000
A41: PURCHASE FUNDING (one-time record of how the purchase was paid)
A42: Funding source | B42: Spouse (45%) | C42: Self (55%) | D42: Total
A43: CPF used | B43: 90000 | C43: 120000 | D43: =B43+C43 -> 210000
A44: Cash used | B44: 170000 | C44: 120000 | D44: =B44+C44 -> 290000
A45: Total upfront paid | B45: =SUM(B43:B44) -> 260000 | C45: =SUM(C43:C44) -> 240000 | D45: =SUM(D43:D44) -> 500000
A47: Note: 'Your Position' (rows 20-22) are the only figures used by the Balance Sheet. Paydown, CPF and purchase-funding sections are planning/records and do not affect net worth.

Sheet Loan Calculator
B2: Simple loan calculator | M2: Annual summary (auto-updates from the schedule below)
B4: Loan details | M4: Year | N4: Principal Paid | O4: Interest Paid | P4: Total Paid
C5: Loan amount | D5: 1125000 | M5: =YEAR($D$8) -> 2025 | N5: =SUMPRODUCT(($M5=YEAR($C$17:$C$256))*$F$17:$F$256) -> 42329.635 | O5: =SUMPRODUCT(($M5=YEAR($C$17:$C$256))*$H$17:$H$256) -> 20273.428 | P5: =N5+O5 -> 62603.063
C6: Annual interest rate | D6: 0.02 | M6: =M5+1 -> 2026 | N6: =SUMPRODUCT(($M6=YEAR($C$17:$C$256))*$F$17:$F$256) -> 47070.768 | O6: =SUMPRODUCT(($M6=YEAR($C$17:$C$256))*$H$17:$H$256) -> 21223.482 | P6: =N6+O6 -> 68294.25
C7: Loan period in years | D7: 20 | M7: =M6+1 -> 2027 | N7: =SUMPRODUCT(($M7=YEAR($C$17:$C$256))*$F$17:$F$256) -> 48020.861 | O7: =SUMPRODUCT(($M7=YEAR($C$17:$C$256))*$H$17:$H$256) -> 20273.389 | P7: =N7+O7 -> 68294.25
C8: Start date of loan | D8: 45658 | M8: =M7+1 -> 2028 | N8: =SUMPRODUCT(($M8=YEAR($C$17:$C$256))*$F$17:$F$256) -> 48990.131 | O8: =SUMPRODUCT(($M8=YEAR($C$17:$C$256))*$H$17:$H$256) -> 19304.119 | P8: =N8+O8 -> 68294.25
M9: =M8+1 -> 2029 | N9: =SUMPRODUCT(($M9=YEAR($C$17:$C$256))*$F$17:$F$256) -> 49978.966 | O9: =SUMPRODUCT(($M9=YEAR($C$17:$C$256))*$H$17:$H$256) -> 18315.285 | P9: =N9+O9 -> 68294.25
B10: Loan summary | M10: =M9+1 -> 2030 | N10: =SUMPRODUCT(($M10=YEAR($C$17:$C$256))*$F$17:$F$256) -> 50987.759 | O10: =SUMPRODUCT(($M10=YEAR($C$17:$C$256))*$H$17:$H$256) -> 17306.491 | P10: =N10+O10 -> 68294.25
C11: Monthly payment | D11: =IFERROR(IF(LoanIsGood,MonthlyPayment,""), "") -> 5691.1875 | M11: =M10+1 -> 2031 | N11: =SUMPRODUCT(($M11=YEAR($C$17:$C$256))*$F$17:$F$256) -> 52016.914 | O11: =SUMPRODUCT(($M11=YEAR($C$17:$C$256))*$H$17:$H$256) -> 16277.336 | P11: =N11+O11 -> 68294.25
C12: Number of payments | D12: =IFERROR(IF(LoanIsGood,LoanYears*12,""), "") -> 240 | M12: =M11+1 -> 2032 | N12: =SUMPRODUCT(($M12=YEAR($C$17:$C$256))*$F$17:$F$256) -> 53066.842 | O12: =SUMPRODUCT(($M12=YEAR($C$17:$C$256))*$H$17:$H$256) -> 15227.408 | P12: =N12+O12 -> 68294.25
C13: Total interest | D13: =IFERROR(IF(LoanIsGood,TotalLoanCost-LoanAmount,""), "") -> 240885 | M13: =M12+1 -> 2033 | N13: =SUMPRODUCT(($M13=YEAR($C$17:$C$256))*$F$17:$F$256) -> 54137.962 | O13: =SUMPRODUCT(($M13=YEAR($C$17:$C$256))*$H$17:$H$256) -> 14156.288 | P13: =N13+O13 -> 68294.25
C14: Total cost of loan | D14: =IFERROR(IF(LoanIsGood,MonthlyPayment*NumberOfPayments,""), "") -> 1365885 | M14: =M13+1 -> 2034 | N14: =SUMPRODUCT(($M14=YEAR($C$17:$C$256))*$F$17:$F$256) -> 55230.702 | O14: =SUMPRODUCT(($M14=YEAR($C$17:$C$256))*$H$17:$H$256) -> 13063.549 | P14: =N14+O14 -> 68294.25
C15: Outstanding balance (today) | D15: =IFERROR(LOOKUP(2,1/($C$17:$C$256<=TODAY()),$J$17:$J$256),D5) -> 1051394.5 | M15: =M14+1 -> 2035 | N15: =SUMPRODUCT(($M15=YEAR($C$17:$C$256))*$F$17:$F$256) -> 56345.498 | O15: =SUMPRODUCT(($M15=YEAR($C$17:$C$256))*$H$17:$H$256) -> 11948.752 | P15: =N15+O15 -> 68294.25
B16: Pmt no. | C16: Payment date | D16: Beginning balance | E16: Payment | F16: Principal | G16: Cumulative Principal | H16: Interest | I16: Cumulative Interest | J16: Ending balance | M16: =M15+1 -> 2036 | N16: =SUMPRODUCT(($M16=YEAR($C$17:$C$256))*$F$17:$F$256) -> 57482.795 | O16: =SUMPRODUCT(($M16=YEAR($C$17:$C$256))*$H$17:$H$256) -> 10811.455 | P16: =N16+O16 -> 68294.25
B17: =IFERROR(IF(LoanIsNotPaid*LoanIsGood,PaymentNumber,""), "") -> 1 | C17: =IFERROR(IF(LoanIsNotPaid*LoanIsGood,PaymentDate,LoanStartDate), LoanStartDate) -> 45689 | D17: =IFERROR(IF(LoanIsNotPaid*LoanIsGood,LoanValue,""), "") -> 1125000 | E17: =IFERROR(IF(LoanIsNotPaid*LoanIsGood,MonthlyPayment,0), 0) -> 5691.1875 | F17: =IFERROR(IF(LoanIsNotPaid*LoanIsGood,Principal,0), 0) -> 3816.1875 | G17: =SUM($F$17:F17) -> 3816.1875 | H17: =IFERROR(IF(LoanIsNotPaid*LoanIsGood,InterestAmt,0), 0) -> 1875 | I17: =SUM($H$17:H17) -> 1875 | J17: =IFERROR(IF(LoanIsNotPaid*LoanIsGood,EndingBalance,0), 0) -> 1121183.8 | M17: =M16+1 -> 2037 | N17: =SUMPRODUCT(($M17=YEAR($C$17:$C$256))*$F$17:$F$256) -> 58643.049 | O17: =SUMPRODUCT(($M17=YEAR($C$17:$C$256))*$H$17:$H$256) -> 9651.2016 | P17: =N17+O17 -> 68294.25
B18: =IFERROR(IF(LoanIsNotPaid*LoanIsGood,PaymentNumber,""), "") -> 2 | C18: =IFERROR(IF(LoanIsNotPaid*LoanIsGood,PaymentDate,LoanStartDate), LoanStartDate) -> 45717 | D18: =IFERROR(IF(LoanIsNotPaid*LoanIsGood,LoanValue,""), "") -> 1121183.8 | E18: =IFERROR(IF(LoanIsNotPaid*LoanIsGood,MonthlyPayment,0), 0) -> 5691.1875 | F18: =IFERROR(IF(LoanIsNotPaid*LoanIsGood,Principal,0), 0) -> 3822.5478 | G18: =SUM($F$17:F18) -> 7638.7354 | H18: =IFERROR(IF(LoanIsNotPaid*LoanIsGood,InterestAmt,0), 0) -> 1868.6397 | I18: =SUM($H$17:H18) -> 3743.6397 | J18: =IFERROR(IF(LoanIsNotPaid*LoanIsGood,EndingBalance,0), 0) -> 1117361.3 | M18: =M17+1 -> 2038 | N18: =SUMPRODUCT(($M18=YEAR($C$17:$C$256))*$F$17:$F$256) -> 59826.721 | O18: =SUMPRODUCT(($M18=YEAR($C$17:$C$256))*$H$17:$H$256) -> 8467.5295 | P18: =N18+O18 -> 68294.25
B19: =IFERROR(IF(LoanIsNotPaid*LoanIsGood,PaymentNumber,""), "") -> 3 | C19: =IFERROR(IF(LoanIsNotPaid*LoanIsGood,PaymentDate,LoanStartDate), LoanStartDate) -> 45748 | D19: =IFERROR(IF(LoanIsNotPaid*LoanIsGood,LoanValue,""), "") -> 1117361.3 | E19: =IFERROR(IF(LoanIsNotPaid*LoanIsGood,MonthlyPayment,0), 0) -> 5691.1875 | F19: =IFERROR(IF(LoanIsNotPaid*LoanIsGood,Principal,0), 0) -> 3828.9187 | G19: =SUM($F$17:F19) -> 11467.654 | H19: =IFERROR(IF(LoanIsNotPaid*LoanIsGood,InterestAmt,0), 0) -> 1862.2688 | I19: =SUM($H$17:H19) -> 5605.9085 | J19: =IFERROR(IF(LoanIsNotPaid*LoanIsGood,EndingBalance,0), 0) -> 1113532.3 | M19: =M18+1 -> 2039 | N19: =SUMPRODUCT(($M19=YEAR($C$17:$C$256))*$F$17:$F$256) -> 61034.285 | O19: =SUMPRODUCT(($M19=YEAR($C$17:$C$256))*$H$17:$H$256) -> 7259.9657 | P19: =N19+O19 -> 68294.25
B20: =IFERROR(IF(LoanIsNotPaid*LoanIsGood,PaymentNumber,""), "") -> 4 | C20: =IFERROR(IF(LoanIsNotPaid*LoanIsGood,PaymentDate,LoanStartDate), LoanStartDate) -> 45778 | D20: =IFERROR(IF(LoanIsNotPaid*LoanIsGood,LoanValue,""), "") -> 1113532.3 | E20: =IFERROR(IF(LoanIsNotPaid*LoanIsGood,MonthlyPayment,0), 0) -> 5691.1875 | F20: =IFERROR(IF(LoanIsNotPaid*LoanIsGood,Principal,0), 0) -> 3835.3003 | G20: =SUM($F$17:F20) -> 15302.954 | H20: =IFERROR(IF(LoanIsNotPaid*LoanIsGood,InterestAmt,0), 0) -> 1855.8872 | I20: =SUM($H$17:H20) -> 7461.7957 | J20: =IFERROR(IF(LoanIsNotPaid*LoanIsGood,EndingBalance,0), 0) -> 1109697 | M20: =M19+1 -> 2040 | N20: =SUMPRODUCT(($M20=YEAR($C$17:$C$256))*$F$17:$F$256) -> 62266.222 | O20: =SUMPRODUCT(($M20=YEAR($C$17:$C$256))*$H$17:$H$256) -> 6028.028 | P20: =N20+O20 -> 68294.25
B21: =IFERROR(IF(LoanIsNotPaid*LoanIsGood,PaymentNumber,""), "") -> 5 | C21: =IFERROR(IF(LoanIsNotPaid*LoanIsGood,PaymentDate,LoanStartDate), LoanStartDate) -> 45809 | D21: =IFERROR(IF(LoanIsNotPaid*LoanIsGood,LoanValue,""), "") -> 1109697 | E21: =IFERROR(IF(LoanIsNotPaid*LoanIsGood,MonthlyPayment,0), 0) -> 5691.1875 | F21: =IFERROR(IF(LoanIsNotPaid*LoanIsGood,Principal,0), 0) -> 3841.6924 | G21: =SUM($F$17:F21) -> 19144.647 | H21: =IFERROR(IF(LoanIsNotPaid*LoanIsGood,InterestAmt,0), 0) -> 1849.4951 | I21: =SUM($H$17:H21) -> 9311.2908 | J21: =IFERROR(IF(LoanIsNotPaid*LoanIsGood,EndingBalance,0), 0) -> 1105855.4 | M21: =M20+1 -> 2041 | N21: =SUMPRODUCT(($M21=YEAR($C$17:$C$256))*$F$17:$F$256) -> 63523.026 | O21: =SUMPRODUCT(($M21=YEAR($C$17:$C$256))*$H$17:$H$256) -> 4771.2244 | P21: =N21+O21 -> 68294.25
B22: =IFERROR(IF(LoanIsNotPaid*LoanIsGood,PaymentNumber,""), "") -> 6 | C22: =IFERROR(IF(LoanIsNotPaid*LoanIsGood,PaymentDate,LoanStartDate), LoanStartDate) -> 45839 | D22: =IFERROR(IF(LoanIsNotPaid*LoanIsGood,LoanValue,""), "") -> 1105855.4 | E22: =IFERROR(IF(LoanIsNotPaid*LoanIsGood,MonthlyPayment,0), 0) -> 5691.1875 | F22: =IFERROR(IF(LoanIsNotPaid*LoanIsGood,Principal,0), 0) -> 3848.0953 | G22: =SUM($F$17:F22) -> 22992.742 | H22: =IFERROR(IF(LoanIsNotPaid*LoanIsGood,InterestAmt,0), 0) -> 1843.0923 | I22: =SUM($H$17:H22) -> 11154.383 | J22: =IFERROR(IF(LoanIsNotPaid*LoanIsGood,EndingBalance,0), 0) -> 1102007.3 | M22: =M21+1 -> 2042 | N22: =SUMPRODUCT(($M22=YEAR($C$17:$C$256))*$F$17:$F$256) -> 64805.197 | O22: =SUMPRODUCT(($M22=YEAR($C$17:$C$256))*$H$17:$H$256) -> 3489.053 | P22: =N22+O22 -> 68294.25
B23: =IFERROR(IF(LoanIsNotPaid*LoanIsGood,PaymentNumber,""), "") -> 7 | C23: =IFERROR(IF(LoanIsNotPaid*LoanIsGood,PaymentDate,LoanStartDate), LoanStartDate) -> 45870 | D23: =IFERROR(IF(LoanIsNotPaid*LoanIsGood,LoanValue,""), "") -> 1102007.3 | E23: =IFERROR(IF(LoanIsNotPaid*LoanIsGood,MonthlyPayment,0), 0) -> 5691.1875 | F23: =IFERROR(IF(LoanIsNotPaid*LoanIsGood,Principal,0), 0) -> 3854.5088 | G23: =SUM($F$17:F23) -> 26847.251 | H23: =IFERROR(IF(LoanIsNotPaid*LoanIsGood,InterestAmt,0), 0) -> 1836.6788 | I23: =SUM($H$17:H23) -> 12991.062 | J23: =IFERROR(IF(LoanIsNotPaid*LoanIsGood,EndingBalance,0), 0) -> 1098152.7 | M23: =M22+1 -> 2043 | N23: =SUMPRODUCT(($M23=YEAR($C$17:$C$256))*$F$17:$F$256) -> 66113.248 | O23: =SUMPRODUCT(($M23=YEAR($C$17:$C$256))*$H$17:$H$256) -> 2181.0019 | P23: =N23+O23 -> 68294.25
B24: =IFERROR(IF(LoanIsNotPaid*LoanIsGood,PaymentNumber,""), "") -> 8 | C24: =IFERROR(IF(LoanIsNotPaid*LoanIsGood,PaymentDate,LoanStartDate), LoanStartDate) -> 45901 | D24: =IFERROR(IF(LoanIsNotPaid*LoanIsGood,LoanValue,""), "") -> 1098152.7 | E24: =IFERROR(IF(LoanIsNotPaid*LoanIsGood,MonthlyPayment,0), 0) -> 5691.1875 | F24: =IFERROR(IF(LoanIsNotPaid*LoanIsGood,Principal,0), 0) -> 3860.9329 | G24: =SUM($F$17:F24) -> 30708.184 | H24: =IFERROR(IF(LoanIsNotPaid*LoanIsGood,InterestAmt,0), 0) -> 1830.2546 | I24: =SUM($H$17:H24) -> 14821.316 | J24: =IFERROR(IF(LoanIsNotPaid*LoanIsGood,EndingBalance,0), 0) -> 1094291.8 | M24: =M23+1 -> 2044 | N24: =SUMPRODUCT(($M24=YEAR($C$17:$C$256))*$F$17:$F$256) -> 67447.702 | O24: =SUMPRODUCT(($M24=YEAR($C$17:$C$256))*$H$17:$H$256) -> 846.54856 | P24: =N24+O24 -> 68294.25
B25: =IFERROR(IF(LoanIsNotPaid*LoanIsGood,PaymentNumber,""), "") -> 9 | C25: =IFERROR(IF(LoanIsNotPaid*LoanIsGood,PaymentDate,LoanStartDate), LoanStartDate) -> 45931 | D25: =IFERROR(IF(LoanIsNotPaid*LoanIsGood,LoanValue,""), "") -> 1094291.8 | E25: =IFERROR(IF(LoanIsNotPaid*LoanIsGood,MonthlyPayment,0), 0) -> 5691.1875 | F25: =IFERROR(IF(LoanIsNotPaid*LoanIsGood,Principal,0), 0) -> 3867.3678 | G25: =SUM($F$17:F25) -> 34575.552 | H25: =IFERROR(IF(LoanIsNotPaid*LoanIsGood,InterestAmt,0), 0) -> 1823.8197 | I25: =SUM($H$17:H25) -> 16645.136 | J25: =IFERROR(IF(LoanIsNotPaid*LoanIsGood,EndingBalance,0), 0) -> 1090424.4 | M25: =M24+1 -> 2045 | N25: =SUMPRODUCT(($M25=YEAR($C$17:$C$256))*$F$17:$F$256) -> 5681.718 | O25: =SUMPRODUCT(($M25=YEAR($C$17:$C$256))*$H$17:$H$256) -> 9.46953 | P25: =N25+O25 -> 5691.1875
B26: =IFERROR(IF(LoanIsNotPaid*LoanIsGood,PaymentNumber,""), "") -> 10 | C26: =IFERROR(IF(LoanIsNotPaid*LoanIsGood,PaymentDate,LoanStartDate), LoanStartDate) -> 45962 | D26: =IFERROR(IF(LoanIsNotPaid*LoanIsGood,LoanValue,""), "") -> 1090424.4 | E26: =IFERROR(IF(LoanIsNotPaid*LoanIsGood,MonthlyPayment,0), 0) -> 5691.1875 | F26: =IFERROR(IF(LoanIsNotPaid*LoanIsGood,Principal,0), 0) -> 3873.8134 | G26: =SUM($F$17:F26) -> 38449.365 | H26: =IFERROR(IF(LoanIsNotPaid*LoanIsGood,InterestAmt,0), 0) -> 1817.3741 | I26: =SUM($H$17:H26) -> 18462.51 | J26: =IFERROR(IF(LoanIsNotPaid*LoanIsGood,EndingBalance,0), 0) -> 1086550.6 | M26: =M25+1 -> 2046 | N26: =SUMPRODUCT(($M26=YEAR($C$17:$C$256))*$F$17:$F$256) -> 0 | O26: =SUMPRODUCT(($M26=YEAR($C$17:$C$256))*$H$17:$H$256) -> 0 | P26: =N26+O26 -> 0
B27: =IFERROR(IF(LoanIsNotPaid*LoanIsGood,PaymentNumber,""), "") -> 11 | C27: =IFERROR(IF(LoanIsNotPaid*LoanIsGood,PaymentDate,LoanStartDate), LoanStartDate) -> 45992 | D27: =IFERROR(IF(LoanIsNotPaid*LoanIsGood,LoanValue,""), "") -> 1086550.6 | E27: =IFERROR(IF(LoanIsNotPaid*LoanIsGood,MonthlyPayment,0), 0) -> 5691.1875 | F27: =IFERROR(IF(LoanIsNotPaid*LoanIsGood,Principal,0), 0) -> 3880.2698 | G27: =SUM($F$17:F27) -> 42329.635 | H27: =IFERROR(IF(LoanIsNotPaid*LoanIsGood,InterestAmt,0), 0) -> 1810.9177 | I27: =SUM($H$17:H27) -> 20273.428 | J27: =IFERROR(IF(LoanIsNotPaid*LoanIsGood,EndingBalance,0), 0) -> 1082670.4 | M27: =M26+1 -> 2047 | N27: =SUMPRODUCT(($M27=YEAR($C$17:$C$256))*$F$17:$F$256) -> 0 | O27: =SUMPRODUCT(($M27=YEAR($C$17:$C$256))*$H$17:$H$256) -> 0 | P27: =N27+O27 -> 0
B28: =IFERROR(IF(LoanIsNotPaid*LoanIsGood,PaymentNumber,""), "") -> 12 | C28: =IFERROR(IF(LoanIsNotPaid*LoanIsGood,PaymentDate,LoanStartDate), LoanStartDate) -> 46023 | D28: =IFERROR(IF(LoanIsNotPaid*LoanIsGood,LoanValue,""), "") -> 1082670.4 | E28: =IFERROR(IF(LoanIsNotPaid*LoanIsGood,MonthlyPayment,0), 0) -> 5691.1875 | F28: =IFERROR(IF(LoanIsNotPaid*LoanIsGood,Principal,0), 0) -> 3886.7369 | G28: =SUM($F$17:F28) -> 46216.372 | H28: =IFERROR(IF(LoanIsNotPaid*LoanIsGood,InterestAmt,0), 0) -> 1804.4506 | I28: =SUM($H$17:H28) -> 22077.878 | J28: =IFERROR(IF(LoanIsNotPaid*LoanIsGood,EndingBalance,0), 0) -> 1078783.6 | M28: =M27+1 -> 2048 | N28: =SUMPRODUCT(($M28=YEAR($C$17:$C$256))*$F$17:$F$256) -> 0 | O28: =SUMPRODUCT(($M28=YEAR($C$17:$C$256))*$H$17:$H$256) -> 0 | P28: =N28+O28 -> 0
B29: =IFERROR(IF(LoanIsNotPaid*LoanIsGood,PaymentNumber,""), "") -> 13 | C29: =IFERROR(IF(LoanIsNotPaid*LoanIsGood,PaymentDate,LoanStartDate), LoanStartDate) -> 46054 | D29: =IFERROR(IF(LoanIsNotPaid*LoanIsGood,LoanValue,""), "") -> 1078783.6 | E29: =IFERROR(IF(LoanIsNotPaid*LoanIsGood,MonthlyPayment,0), 0) -> 5691.1875 | F29: =IFERROR(IF(LoanIsNotPaid*LoanIsGood,Principal,0), 0) -> 3893.2148 | G29: =SUM($F$17:F29) -> 50109.587 | H29: =IFERROR(IF(LoanIsNotPaid*LoanIsGood,InterestAmt,0), 0) -> 1797.9727 | I29: =SUM($H$17:H29) -> 23875.851 | J29: =IFERROR(IF(LoanIsNotPaid*LoanIsGood,EndingBalance,0), 0) -> 1074890.4 | M29: =M28+1 -> 2049 | N29: =SUMPRODUCT(($M29=YEAR($C$17:$C$256))*$F$17:$F$256) -> 0 | O29: =SUMPRODUCT(($M29=YEAR($C$17:$C$256))*$H$17:$H$256) -> 0 | P29: =N29+O29 -> 0
B30: =IFERROR(IF(LoanIsNotPaid*LoanIsGood,PaymentNumber,""), "") -> 14 | C30: =IFERROR(IF(LoanIsNotPaid*LoanIsGood,PaymentDate,LoanStartDate), LoanStartDate) -> 46082 | D30: =IFERROR(IF(LoanIsNotPaid*LoanIsGood,LoanValue,""), "") -> 1074890.4 | E30: =IFERROR(IF(LoanIsNotPaid*LoanIsGood,MonthlyPayment,0), 0) -> 5691.1875 | F30: =IFERROR(IF(LoanIsNotPaid*LoanIsGood,Principal,0), 0) -> 3899.7035 | G30: =SUM($F$17:F30) -> 54009.29 | H30: =IFERROR(IF(LoanIsNotPaid*LoanIsGood,InterestAmt,0), 0) -> 1791.484 | I30: =SUM($H$17:H30) -> 25667.335 | J30: =IFERROR(IF(LoanIsNotPaid*LoanIsGood,EndingBalance,0), 0) -> 1070990.7
B31: =IFERROR(IF(LoanIsNotPaid*LoanIsGood,PaymentNumber,""), "") -> 15 | C31: =IFERROR(IF(LoanIsNotPaid*LoanIsGood,PaymentDate,LoanStartDate), LoanStartDate) -> 46113 | D31: =IFERROR(IF(LoanIsNotPaid*LoanIsGood,LoanValue,""), "") -> 1070990.7 | E31: =IFERROR(IF(LoanIsNotPaid*LoanIsGood,MonthlyPayment,0), 0) -> 5691.1875 | F31: =IFERROR(IF(LoanIsNotPaid*LoanIsGood,Principal,0), 0) -> 3906.203 | G31: =SUM($F$17:F31) -> 57915.493 | H31: =IFERROR(IF(LoanIsNotPaid*LoanIsGood,InterestAmt,0), 0) -> 1784.9845 | I31: =SUM($H$17:H31) -> 27452.32 | J31: =IFERROR(IF(LoanIsNotPaid*LoanIsGood,EndingBalance,0), 0) -> 1067084.5
B32: =IFERROR(IF(LoanIsNotPaid*LoanIsGood,PaymentNumber,""), "") -> 16 | C32: =IFERROR(IF(LoanIsNotPaid*LoanIsGood,PaymentDate,LoanStartDate), LoanStartDate) -> 46143 | D32: =IFERROR(IF(LoanIsNotPaid*LoanIsGood,LoanValue,""), "") -> 1067084.5 | E32: =IFERROR(IF(LoanIsNotPaid*LoanIsGood,MonthlyPayment,0), 0) -> 5691.1875 | F32: =IFERROR(IF(LoanIsNotPaid*LoanIsGood,Principal,0), 0) -> 3912.7133 | G32: =SUM($F$17:F32) -> 61828.206 | H32: =IFERROR(IF(LoanIsNotPaid*LoanIsGood,InterestAmt,0), 0) -> 1778.4742 | I32: =SUM($H$17:H32) -> 29230.794 | J32: =IFERROR(IF(LoanIsNotPaid*LoanIsGood,EndingBalance,0), 0) -> 1063171.8
B33: =IFERROR(IF(LoanIsNotPaid*LoanIsGood,PaymentNumber,""), "") -> 17 | C33: =IFERROR(IF(LoanIsNotPaid*LoanIsGood,PaymentDate,LoanStartDate), LoanStartDate) -> 46174 | D33: =IFERROR(IF(LoanIsNotPaid*LoanIsGood,LoanValue,""), "") -> 1063171.8 | E33: =IFERROR(IF(LoanIsNotPaid*LoanIsGood,MonthlyPayment,0), 0) -> 5691.1875 | F33: =IFERROR(IF(LoanIsNotPaid*LoanIsGood,Principal,0), 0) -> 3919.2345 | G33: =SUM($F$17:F33) -> 65747.441 | H33: =IFERROR(IF(LoanIsNotPaid*LoanIsGood,InterestAmt,0), 0) -> 1771.953 | I33: =SUM($H$17:H33) -> 31002.747 | J33: =IFERROR(IF(LoanIsNotPaid*LoanIsGood,EndingBalance,0), 0) -> 1059252.6
B34: =IFERROR(IF(LoanIsNotPaid*LoanIsGood,PaymentNumber,""), "") -> 18 | C34: =IFERROR(IF(LoanIsNotPaid*LoanIsGood,PaymentDate,LoanStartDate), LoanStartDate) -> 46204 | D34: =IFERROR(IF(LoanIsNotPaid*LoanIsGood,LoanValue,""), "") -> 1059252.6 | E34: =IFERROR(IF(LoanIsNotPaid*LoanIsGood,MonthlyPayment,0), 0) -> 5691.1875 | F34: =IFERROR(IF(LoanIsNotPaid*LoanIsGood,Principal,0), 0) -> 3925.7666 | G34: =SUM($F$17:F34) -> 69673.208 | H34: =IFERROR(IF(LoanIsNotPaid*LoanIsGood,InterestAmt,0), 0) -> 1765.4209 | I34: =SUM($H$17:H34) -> 32768.168 | J34: =IFERROR(IF(LoanIsNotPaid*LoanIsGood,EndingBalance,0), 0) -> 1055326.8
B35: =IFERROR(IF(LoanIsNotPaid*LoanIsGood,PaymentNumber,""), "") -> 19 | C35: =IFERROR(IF(LoanIsNotPaid*LoanIsGood,PaymentDate,LoanStartDate), LoanStartDate) -> 46235 | D35: =IFERROR(IF(LoanIsNotPaid*LoanIsGood,LoanValue,""), "") -> 1055326.8 | E35: =IFERROR(IF(LoanIsNotPaid*LoanIsGood,MonthlyPayment,0), 0) -> 5691.1875 | F35: =IFERROR(IF(LoanIsNotPaid*LoanIsGood,Principal,0), 0) -> 3932.3095 | G35: =SUM($F$17:F35) -> 73605.517 | H35: =IFERROR(IF(LoanIsNotPaid*LoanIsGood,InterestAmt,0), 0) -> 1758.878 | I35: =SUM($H$17:H35) -> 34527.046 | J35: =IFERROR(IF(LoanIsNotPaid*LoanIsGood,EndingBalance,0), 0) -> 1051394.5
B36: =IFERROR(IF(LoanIsNotPaid*LoanIsGood,PaymentNumber,""), "") -> 20 | C36: =IFERROR(IF(LoanIsNotPaid*LoanIsGood,PaymentDate,LoanStartDate), LoanStartDate) -> 46266 | D36: =IFERROR(IF(LoanIsNotPaid*LoanIsGood,LoanValue,""), "") -> 1051394.5 | E36: =IFERROR(IF(LoanIsNotPaid*LoanIsGood,MonthlyPayment,0), 0) -> 5691.1875 | F36: =IFERROR(IF(LoanIsNotPaid*LoanIsGood,Principal,0), 0) -> 3938.8634 | G36: =SUM($F$17:F36) -> 77544.38 | H36: =IFERROR(IF(LoanIsNotPaid*LoanIsGood,InterestAmt,0), 0) -> 1752.3241 | I36: =SUM($H$17:H36) -> 36279.37 | J36: =IFERROR(IF(LoanIsNotPaid*LoanIsGood,EndingBalance,0), 0) -> 1047455.6
B37: =IFERROR(IF(LoanIsNotPaid*LoanIsGood,PaymentNumber,""), "") -> 21 | C37: =IFERROR(IF(LoanIsNotPaid*LoanIsGood,PaymentDate,LoanStartDate), LoanStartDate) -> 46296 | D37: =IFERROR(IF(LoanIsNotPaid*LoanIsGood,LoanValue,""), "") -> 1047455.6 | E37: =IFERROR(IF(LoanIsNotPaid*LoanIsGood,MonthlyPayment,0), 0) -> 5691.1875 | F37: =IFERROR(IF(LoanIsNotPaid*LoanIsGood,Principal,0), 0) -> 3945.4282 | G37: =SUM($F$17:F37) -> 81489.809 | H37: =IFERROR(IF(LoanIsNotPaid*LoanIsGood,InterestAmt,0), 0) -> 1745.7594 | I37: =SUM($H$17:H37) -> 38025.129 | J37: =IFERROR(IF(LoanIsNotPaid*LoanIsGood,EndingBalance,0), 0) -> 1043510.2
B38: =IFERROR(IF(LoanIsNotPaid*LoanIsGood,PaymentNumber,""), "") -> 22 | C38: =IFERROR(IF(LoanIsNotPaid*LoanIsGood,PaymentDate,LoanStartDate), LoanStartDate) -> 46327 | D38: =IFERROR(IF(LoanIsNotPaid*LoanIsGood,LoanValue,""), "") -> 1043510.2 | E38: =IFERROR(IF(LoanIsNotPaid*LoanIsGood,MonthlyPayment,0), 0) -> 5691.1875 | F38: =IFERROR(IF(LoanIsNotPaid*LoanIsGood,Principal,0), 0) -> 3952.0039 | G38: =SUM($F$17:F38) -> 85441.812 | H38: =IFERROR(IF(LoanIsNotPaid*LoanIsGood,InterestAmt,0), 0) -> 1739.1837 | I38: =SUM($H$17:H38) -> 39764.313 | J38: =IFERROR(IF(LoanIsNotPaid*LoanIsGood,EndingBalance,0), 0) -> 1039558.2
B39: =IFERROR(IF(LoanIsNotPaid*LoanIsGood,PaymentNumber,""), "") -> 23 | C39: =IFERROR(IF(LoanIsNotPaid*LoanIsGood,PaymentDate,LoanStartDate), LoanStartDate) -> 46357 | D39: =IFERROR(IF(LoanIsNotPaid*LoanIsGood,LoanValue,""), "") -> 1039558.2 | E39: =IFERROR(IF(LoanIsNotPaid*LoanIsGood,MonthlyPayment,0), 0) -> 5691.1875 | F39: =IFERROR(IF(LoanIsNotPaid*LoanIsGood,Principal,0), 0) -> 3958.5905 | G39: =SUM($F$17:F39) -> 89400.403 | H39: =IFERROR(IF(LoanIsNotPaid*LoanIsGood,InterestAmt,0), 0) -> 1732.597 | I39: =SUM($H$17:H39) -> 41496.91 | J39: =IFERROR(IF(LoanIsNotPaid*LoanIsGood,EndingBalance,0), 0) -> 1035599.6
B40: =IFERROR(IF(LoanIsNotPaid*LoanIsGood,PaymentNumber,""), "") -> 24 | C40: =IFERROR(IF(LoanIsNotPaid*LoanIsGood,PaymentDate,LoanStartDate), LoanStartDate) -> 46388 | D40: =IFERROR(IF(LoanIsNotPaid*LoanIsGood,LoanValue,""), "") -> 1035599.6 | E40: =IFERROR(IF(LoanIsNotPaid*LoanIsGood,MonthlyPayment,0), 0) -> 5691.1875 | F40: =IFERROR(IF(LoanIsNotPaid*LoanIsGood,Principal,0), 0) -> 3965.1882 | G40: =SUM($F$17:F40) -> 93365.591 | H40: =IFERROR(IF(LoanIsNotPaid*LoanIsGood,InterestAmt,0), 0) -> 1725.9993 | I40: =SUM($H$17:H40) -> 43222.909 | J40: =IFERROR(IF(LoanIsNotPaid*LoanIsGood,EndingBalance,0), 0) -> 1031634.4
B41: =IFERROR(IF(LoanIsNotPaid*LoanIsGood,PaymentNumber,""), "") -> 25 | C41: =IFERROR(IF(LoanIsNotPaid*LoanIsGood,PaymentDate,LoanStartDate), LoanStartDate) -> 46419 | D41: =IFERROR(IF(LoanIsNotPaid*LoanIsGood,LoanValue,""), "") -> 1031634.4 | E41: =IFERROR(IF(LoanIsNotPaid*LoanIsGood,MonthlyPayment,0), 0) -> 5691.1875 | F41: =IFERROR(IF(LoanIsNotPaid*LoanIsGood,Principal,0), 0) -> 3971.7968 | G41: =SUM($F$17:F41) -> 97337.388 | H41: =IFERROR(IF(LoanIsNotPaid*LoanIsGood,InterestAmt,0), 0) -> 1719.3907 | I41: =SUM($H$17:H41) -> 44942.3 | J41: =IFERROR(IF(LoanIsNotPaid*LoanIsGood,EndingBalance,0), 0) -> 1027662.6
... B256: =IFERROR(IF(LoanIsNotPaid*LoanIsGood,PaymentNumber,""), "") -> 240 | C256: =IFERROR(IF(LoanIsNotPaid*LoanIsGood,PaymentDate,LoanStartDate), LoanStartDate) -> 52963 | D256: =IFERROR(IF(LoanIsNotPaid*LoanIsGood,LoanValue,""), "") -> 5681.718 | E256: =IFERROR(IF(LoanIsNotPaid*LoanIsGood,MonthlyPayment,0), 0) -> 5691.1875 | F256: =IFERROR(IF(LoanIsNotPaid*LoanIsGood,Principal,0), 0) -> 5681.718 | G256: =SUM($F$17:F256) -> 1125000 | H256: =IFERROR(IF(LoanIsNotPaid*LoanIsGood,InterestAmt,0), 0) -> 9.46953 | I256: =SUM($H$17:H256) -> 240885 | J256: =IFERROR(IF(LoanIsNotPaid*LoanIsGood,EndingBalance,0), 0) -> -5.6345016e-08

Sheet Retirement Plan
A1: Annual Inflation | B1: =Settings!B11 -> 0.025 | E1: (assumptions are set on the Settings tab)
A2: Current Asset linked to Balance Sheet Latest | B2: =IF($B$8="",'Balance Sheet'!E68,$B$8) -> 1228147.5 | C2: ='Balance Sheet'!F68 -> 842437.1
A3: Annual Savings Rate | B3: =Settings!B8 -> 30000
A4: 3% Growth | B4: =Settings!B12 -> 0.03 | D4: PROPERTY (from Housing)
A5: 5% Growth | B5: =Settings!B13 -> 0.05 | D5: Home equity - your share | E5: =Housing!B22 -> 246733.03
A6: 8% Growth | B6: =Settings!B14 -> 0.08 | D6: Property value - your share | E6: =Housing!B20 -> 825000
A7: Dividend % | B7: =Settings!B15 -> 0.04 | D7: Outstanding mortgage - your share | E7: =Housing!B21 -> 578266.97
A8: Starting balance (blank = use Balance Sheet) | D8: Starting age (blank = use Settings)
A9: Amount to reserve for HDB | B9: =Settings!B19 -> 330000
A10: Amount still in CPF @55 estimated | B10: ='Balance Sheet'!B53 -> 95000
A11: Amount still in CPF @65 estimated | B11: ='Balance Sheet'!B54+'Balance Sheet'!B55 -> 180000
A12: Current SRS Amount (disburse @62) | B12: ='Balance Sheet'!B27 -> 120000
A13: Insurance/Endowment projected maturity (from Insurance) | B13: =Insurance!B6 -> 237422
A14: Age | B14: Year | C14: Retirement Sum (inflated) | D14: Actual Assets (Dec) | E14: Actual Cash (Dec) | F14: Assets @3% | G14: Accessible @3% | H14: Dividends @3% | I14: Assets @5% | J14: Accessible @5% | K14: Dividends @5% | L14: Assets @8% | M14: Accessible @8% | N14: Dividends @8%
A15: =IF($E$8="",Settings!B5,$E$8) -> 42 | B15: =Settings!B6 -> 2026 | C15: =Settings!B18 -> 60000 | D15: 1225000 | F15: =$B$2 -> 1228147.5 | G15: =MAX(0,$B$2-SUM($C$64:$C$66)) -> 376147.48 | H15: =G15*$B$7 -> 15045.899 | I15: =$B$2 -> 1228147.5 | J15: =MAX(0,$B$2-SUM($C$64:$C$66)) -> 376147.48 | K15: =J15*$B$7 -> 15045.899 | L15: =$B$2 -> 1228147.5 | M15: =MAX(0,$B$2-SUM($C$64:$C$66)) -> 376147.48 | N15: =M15*$B$7 -> 15045.899
A16: =A15+1 -> 43 | B16: =B15+1 -> 2027 | C16: =(1+$B$1)*C15 -> 61500 | F16: =(1+$B$4)*F15+IF($A16<=Settings!$B$7,$B$3,-$C16) -> 1294991.9 | G16: =(1+$B$4)*G15+IF($A16<=Settings!$B$7,$B$3,-$C16)+SUMIFS($E$64:$E$66,$A$64:$A$66,$A16) -> 417431.9 | H16: =G16*$B$7 -> 16697.276 | I16: =(1+$B$5)*I15+IF($A16<=Settings!$B$7,$B$3,-$C16) -> 1319554.9 | J16: =(1+$B$5)*J15+IF($A16<=Settings!$B$7,$B$3,-$C16)+SUMIFS($E$64:$E$66,$A$64:$A$66,$A16) -> 424954.85 | K16: =J16*$B$7 -> 16998.194 | L16: =(1+$B$6)*L15+IF($A16<=Settings!$B$7,$B$3,-$C16) -> 1356399.3 | M16: =(1+$B$6)*M15+IF($A16<=Settings!$B$7,$B$3,-$C16)+SUMIFS($E$64:$E$66,$A$64:$A$66,$A16) -> 436239.28 | N16: =M16*$B$7 -> 17449.571
A17: =A16+1 -> 44 | B17: =B16+1 -> 2028 | C17: =(1+$B$1)*C16 -> 63037.5 | F17: =(1+$B$4)*F16+IF($A17<=Settings!$B$7,$B$3,-$C17) -> 1363841.7 | G17: =(1+$B$4)*G16+IF($A17<=Settings!$B$7,$B$3,-$C17)+SUMIFS($E$64:$E$66,$A$64:$A$66,$A17) -> 459954.86 | H17: =G17*$B$7 -> 18398.194 | I17: =(1+$B$5)*I16+IF($A17<=Settings!$B$7,$B$3,-$C17) -> 1415532.6 | J17: =(1+$B$5)*J16+IF($A17<=Settings!$B$7,$B$3,-$C17)+SUMIFS($E$64:$E$66,$A$64:$A$66,$A17) -> 476202.59 | K17: =J17*$B$7 -> 19048.104 | L17: =(1+$B$6)*L16+IF($A17<=Settings!$B$7,$B$3,-$C17) -> 1494911.2 | M17: =(1+$B$6)*M16+IF($A17<=Settings!$B$7,$B$3,-$C17)+SUMIFS($E$64:$E$66,$A$64:$A$66,$A17) -> 501138.42 | N17: =M17*$B$7 -> 20045.537
A18: =A17+1 -> 45 | B18: =B17+1 -> 2029 | C18: =(1+$B$1)*C17 -> 64613.437 | F18: =(1+$B$4)*F17+IF($A18<=Settings!$B$7,$B$3,-$C18) -> 1434756.9 | G18: =(1+$B$4)*G17+IF($A18<=Settings!$B$7,$B$3,-$C18)+SUMIFS($E$64:$E$66,$A$64:$A$66,$A18) -> 503753.5 | H18: =G18*$B$7 -> 20150.14 | I18: =(1+$B$5)*I17+IF($A18<=Settings!$B$7,$B$3,-$C18) -> 1516309.2 | J18: =(1+$B$5)*J17+IF($A18<=Settings!$B$7,$B$3,-$C18)+SUMIFS($E$64:$E$66,$A$64:$A$66,$A18) -> 530012.72 | K18: =J18*$B$7 -> 21200.509 | L18: =(1+$B$6)*L17+IF($A18<=Settings!$B$7,$B$3,-$C18) -> 1644504.1 | M18: =(1+$B$6)*M17+IF($A18<=Settings!$B$7,$B$3,-$C18)+SUMIFS($E$64:$E$66,$A$64:$A$66,$A18) -> 571229.49 | N18: =M18*$B$7 -> 22849.18
A19: =A18+1 -> 46 | B19: =B18+1 -> 2030 | C19: =(1+$B$1)*C18 -> 66228.773 | F19: =(1+$B$4)*F18+IF($A19<=Settings!$B$7,$B$3,-$C19) -> 1507799.6 | G19: =(1+$B$4)*G18+IF($A19<=Settings!$B$7,$B$3,-$C19)+SUMIFS($E$64:$E$66,$A$64:$A$66,$A19) -> 548866.11 | H19: =G19*$B$7 -> 21954.644 | I19: =(1+$B$5)*I18+IF($A19<=Settings!$B$7,$B$3,-$C19) -> 1622124.7 | J19: =(1+$B$5)*J18+IF($A19<=Settings!$B$7,$B$3,-$C19)+SUMIFS($E$64:$E$66,$A$64:$A$66,$A19) -> 586513.36 | K19: =J19*$B$7 -> 23460.534 | L19: =(1+$B$6)*L18+IF($A19<=Settings!$B$7,$B$3,-$C19) -> 1806064.4 | M19: =(1+$B$6)*M18+IF($A19<=Settings!$B$7,$B$3,-$C19)+SUMIFS($E$64:$E$66,$A$64:$A$66,$A19) -> 646927.85 | N19: =M19*$B$7 -> 25877.114
A20: =A19+1 -> 47 | B20: =B19+1 -> 2031 | C20: =(1+$B$1)*C19 -> 67884.493 | F20: =(1+$B$4)*F19+IF($A20<=Settings!$B$7,$B$3,-$C20) -> 1583033.6 | G20: =(1+$B$4)*G19+IF($A20<=Settings!$B$7,$B$3,-$C20)+SUMIFS($E$64:$E$66,$A$64:$A$66,$A20) -> 595332.09 | H20: =G20*$B$7 -> 23813.284 | I20: =(1+$B$5)*I19+IF($A20<=Settings!$B$7,$B$3,-$C20) -> 1733230.9 | J20: =(1+$B$5)*J19+IF($A20<=Settings!$B$7,$B$3,-$C20)+SUMIFS($E$64:$E$66,$A$64:$A$66,$A20) -> 645839.03 | K20: =J20*$B$7 -> 25833.561 | L20: =(1+$B$6)*L19+IF($A20<=Settings!$B$7,$B$3,-$C20) -> 1980549.6 | M20: =(1+$B$6)*M19+IF($A20<=Settings!$B$7,$B$3,-$C20)+SUMIFS($E$64:$E$66,$A$64:$A$66,$A20) -> 728682.08 | N20: =M20*$B$7 -> 29147.283
A21: =A20+1 -> 48 | B21: =B20+1 -> 2032 | C21: =(1+$B$1)*C20 -> 69581.605 | F21: =(1+$B$4)*F20+IF($A21<=Settings!$B$7,$B$3,-$C21) -> 1660524.6 | G21: =(1+$B$4)*G20+IF($A21<=Settings!$B$7,$B$3,-$C21)+SUMIFS($E$64:$E$66,$A$64:$A$66,$A21) -> 643192.06 | H21: =G21*$B$7 -> 25727.682 | I21: =(1+$B$5)*I20+IF($A21<=Settings!$B$7,$B$3,-$C21) -> 1849892.5 | J21: =(1+$B$5)*J20+IF($A21<=Settings!$B$7,$B$3,-$C21)+SUMIFS($E$64:$E$66,$A$64:$A$66,$A21) -> 708130.98 | K21: =J21*$B$7 -> 28325.239 | L21: =(1+$B$6)*L20+IF($A21<=Settings!$B$7,$B$3,-$C21) -> 2168993.6 | M21: =(1+$B$6)*M20+IF($A21<=Settings!$B$7,$B$3,-$C21)+SUMIFS($E$64:$E$66,$A$64:$A$66,$A21) -> 816976.64 | N21: =M21*$B$7 -> 32679.066
A22: =A21+1 -> 49 | B22: =B21+1 -> 2033 | C22: =(1+$B$1)*C21 -> 71321.145 | F22: =(1+$B$4)*F21+IF($A22<=Settings!$B$7,$B$3,-$C22) -> 1740340.4 | G22: =(1+$B$4)*G21+IF($A22<=Settings!$B$7,$B$3,-$C22)+SUMIFS($E$64:$E$66,$A$64:$A$66,$A22) -> 692487.82 | H22: =G22*$B$7 -> 27699.513 | I22: =(1+$B$5)*I21+IF($A22<=Settings!$B$7,$B$3,-$C22) -> 1972387.1 | J22: =(1+$B$5)*J21+IF($A22<=Settings!$B$7,$B$3,-$C22)+SUMIFS($E$64:$E$66,$A$64:$A$66,$A22) -> 773537.53 | K22: =J22*$B$7 -> 30941.501 | L22: =(1+$B$6)*L21+IF($A22<=Settings!$B$7,$B$3,-$C22) -> 2372513.1 | M22: =(1+$B$6)*M21+IF($A22<=Settings!$B$7,$B$3,-$C22)+SUMIFS($E$64:$E$66,$A$64:$A$66,$A22) -> 912334.78 | N22: =M22*$B$7 -> 36493.391
A23: =A22+1 -> 50 | B23: =B22+1 -> 2034 | C23: =(1+$B$1)*C22 -> 73104.174 | F23: =(1+$B$4)*F22+IF($A23<=Settings!$B$7,$B$3,-$C23) -> 1822550.6 | G23: =(1+$B$4)*G22+IF($A23<=Settings!$B$7,$B$3,-$C23)+SUMIFS($E$64:$E$66,$A$64:$A$66,$A23) -> 743262.45 | H23: =G23*$B$7 -> 29730.498 | I23: =(1+$B$5)*I22+IF($A23<=Settings!$B$7,$B$3,-$C23) -> 2101006.4 | J23: =(1+$B$5)*J22+IF($A23<=Settings!$B$7,$B$3,-$C23)+SUMIFS($E$64:$E$66,$A$64:$A$66,$A23) -> 842214.4 | K23: =J23*$B$7 -> 33688.576 | L23: =(1+$B$6)*L22+IF($A23<=Settings!$B$7,$B$3,-$C23) -> 2592314.1 | M23: =(1+$B$6)*M22+IF($A23<=Settings!$B$7,$B$3,-$C23)+SUMIFS($E$64:$E$66,$A$64:$A$66,$A23) -> 1015321.6 | N23: =M23*$B$7 -> 40612.862
A24: =A23+1 -> 51 | B24: =B23+1 -> 2035 | C24: =(1+$B$1)*C23 -> 74931.778 | F24: =(1+$B$4)*F23+IF($A24<=Settings!$B$7,$B$3,-$C24) -> 1907227.1 | G24: =(1+$B$4)*G23+IF($A24<=Settings!$B$7,$B$3,-$C24)+SUMIFS($E$64:$E$66,$A$64:$A$66,$A24) -> 795560.33 | H24: =G24*$B$7 -> 31822.413 | I24: =(1+$B$5)*I23+IF($A24<=Settings!$B$7,$B$3,-$C24) -> 2236056.8 | J24: =(1+$B$5)*J23+IF($A24<=Settings!$B$7,$B$3,-$C24)+SUMIFS($E$64:$E$66,$A$64:$A$66,$A24) -> 914325.12 | K24: =J24*$B$7 -> 36573.005 | L24: =(1+$B$6)*L23+IF($A24<=Settings!$B$7,$B$3,-$C24) -> 2829699.2 | M24: =(1+$B$6)*M23+IF($A24<=Settings!$B$7,$B$3,-$C24)+SUMIFS($E$64:$E$66,$A$64:$A$66,$A24) -> 1126547.3 | N24: =M24*$B$7 -> 45061.891
A25: =A24+1 -> 52 | B25: =B24+1 -> 2036 | C25: =(1+$B$1)*C24 -> 76805.073 | F25: =(1+$B$4)*F24+IF($A25<=Settings!$B$7,$B$3,-$C25) -> 1994443.9 | G25: =(1+$B$4)*G24+IF($A25<=Settings!$B$7,$B$3,-$C25)+SUMIFS($E$64:$E$66,$A$64:$A$66,$A25) -> 849427.14 | H25: =G25*$B$7 -> 33977.085 | I25: =(1+$B$5)*I24+IF($A25<=Settings!$B$7,$B$3,-$C25) -> 2377859.6 | J25: =(1+$B$5)*J24+IF($A25<=Settings!$B$7,$B$3,-$C25)+SUMIFS($E$64:$E$66,$A$64:$A$66,$A25) -> 990041.38 | K25: =J25*$B$7 -> 39601.655 | L25: =(1+$B$6)*L24+IF($A25<=Settings!$B$7,$B$3,-$C25) -> 3086075.2 | M25: =(1+$B$6)*M24+IF($A25<=Settings!$B$7,$B$3,-$C25)+SUMIFS($E$64:$E$66,$A$64:$A$66,$A25) -> 1246671.1 | N25: =M25*$B$7 -> 49866.843
A26: =A25+1 -> 53 | B26: =B25+1 -> 2037 | C26: =(1+$B$1)*C25 -> 78725.199 | F26: =(1+$B$4)*F25+IF($A26<=Settings!$B$7,$B$3,-$C26) -> 2084277.2 | G26: =(1+$B$4)*G25+IF($A26<=Settings!$B$7,$B$3,-$C26)+SUMIFS($E$64:$E$66,$A$64:$A$66,$A26) -> 904909.95 | H26: =G26*$B$7 -> 36196.398 | I26: =(1+$B$5)*I25+IF($A26<=Settings!$B$7,$B$3,-$C26) -> 2526752.6 | J26: =(1+$B$5)*J25+IF($A26<=Settings!$B$7,$B$3,-$C26)+SUMIFS($E$64:$E$66,$A$64:$A$66,$A26) -> 1069543.5 | K26: =J26*$B$7 -> 42781.738 | L26: =(1+$B$6)*L25+IF($A26<=Settings!$B$7,$B$3,-$C26) -> 3362961.2 | M26: =(1+$B$6)*M25+IF($A26<=Settings!$B$7,$B$3,-$C26)+SUMIFS($E$64:$E$66,$A$64:$A$66,$A26) -> 1376404.8 | N26: =M26*$B$7 -> 55056.19
A27: =A26+1 -> 54 | B27: =B26+1 -> 2038 | C27: =(1+$B$1)*C26 -> 80693.329 | F27: =(1+$B$4)*F26+IF($A27<=Settings!$B$7,$B$3,-$C27) -> 2176805.5 | G27: =(1+$B$4)*G26+IF($A27<=Settings!$B$7,$B$3,-$C27)+SUMIFS($E$64:$E$66,$A$64:$A$66,$A27) -> 962057.25 | H27: =G27*$B$7 -> 38482.29 | I27: =(1+$B$5)*I26+IF($A27<=Settings!$B$7,$B$3,-$C27) -> 2683090.2 | J27: =(1+$B$5)*J26+IF($A27<=Settings!$B$7,$B$3,-$C27)+SUMIFS($E$64:$E$66,$A$64:$A$66,$A27) -> 1153020.6 | K27: =J27*$B$7 -> 46120.825 | L27: =(1+$B$6)*L26+IF($A27<=Settings!$B$7,$B$3,-$C27) -> 3661998.1 | M27: =(1+$B$6)*M26+IF($A27<=Settings!$B$7,$B$3,-$C27)+SUMIFS($E$64:$E$66,$A$64:$A$66,$A27) -> 1516517.1 | N27: =M27*$B$7 -> 60660.685
... A58: =A57+1 -> 85 | B58: =B57+1 -> 2069 | C58: =(1+$B$1)*C57 -> 173491.2 | F58: =(1+$B$4)*F57+IF($A58<=Settings!$B$7,$B$3,-$C58) -> 1247566.3 | G58: =(1+$B$4)*G57+IF($A58<=Settings!$B$7,$B$3,-$C58)+SUMIFS($E$64:$E$66,$A$64:$A$66,$A58) -> 1381640.3 | H58: =G58*$B$7 -> 55265.61 | I58: =(1+$B$5)*I57+IF($A58<=Settings!$B$7,$B$3,-$C58) -> 6987486.8 | J58: =(1+$B$5)*J57+IF($A58<=Settings!$B$7,$B$3,-$C58)+SUMIFS($E$64:$E$66,$A$64:$A$66,$A58) -> 5215034.3 | K58: =J58*$B$7 -> 208601.37 | L58: =(1+$B$6)*L57+IF($A58<=Settings!$B$7,$B$3,-$C58) -> 32594210 | M58: =(1+$B$6)*M57+IF($A58<=Settings!$B$7,$B$3,-$C58)+SUMIFS($E$64:$E$66,$A$64:$A$66,$A58) -> 20014471 | N58: =M58*$B$7 -> 800578.83
A60: v8: Savings are added until the planned retirement age (Settings), then the inflated Annual Retirement Sum (col C) is withdrawn each year. Locked assets below unlock into the accessible-cash columns at the given age.
A62: FUTURE CASH-IN EVENTS (yellow = edit; replaces v7's hardcoded CPF/SRS/endowment formulas)
A63: Age | B63: Description | C63: Amount (today's $) | D63: Growth p.a. | E63: Value at unlock
A64: 55 | B64: CPF withdrawable at 55 | C64: 450000 | D64: 0.025 | E64: =C64*(1+D64)^(A64-Settings!$B$5) -> 620329.97
A65: 62 | B65: SRS disbursement | C65: 140000 | D65: 0.03 | E65: =C65*(1+D65)^(A65-Settings!$B$5) -> 252855.57
A66: 65 | B66: CPF payout eligibility + endowment | C66: 262000 | D66: 0.04 | E66: =C66*(1+D66)^(A66-Settings!$B$5) -> 645755.47

Sheet Savings Goal Calculator
A1: SAVINGS GOAL CALCULATOR
A2: How much to set aside — and over how long, at what return — to reach a savings goal. Four ways to solve it.
A3: Contributions are assumed at the start of each year (annuity-due). Returns are nominal annual; taxes and fees are not modelled. The figures below are an illustrative worked example — edit the yellow cells to make it yours.
A4: Expected-return cells pull from Settings (moderate growth, currently 5%). Type a % over any of them for a one-off what-if; Settings also holds conservative (3%) and aggressive (8%).
A6: 1 · What will my savings grow to?
A7: Initial lump sum now | B7: 50000 | C7: $
A8: Annual savings added | B8: 10000 | C8: $/yr
A9: Years to accumulate | B9: 28 | C9: yrs
A10: Expected annual return (from Settings) | B10: =Settings!$B$13 -> 0.05 | C10: %/yr
A11: → Projected total at maturity | B11: =FV(B10,B9,-B8,-B7,1) -> 809233.58
A13: 2 · What return do I need to hit a target?
A14: Initial lump sum now | B14: 50000 | C14: $
A15: Annual savings added | B15: 10000 | C15: $/yr
A16: Years to accumulate | B16: 28 | C16: yrs
A17: Target amount at maturity | B17: 800000 | C17: $
A18: → Required annual return | B18: =IFERROR(RATE(B16,-B15,-B14,B17,1),"") -> 0.04940044 | C18: %/yr
A20: 3 · How many years must I save?
A21: Initial lump sum now | B21: 50000 | C21: $
A22: Annual savings added | B22: 16000 | C22: $/yr
A23: Target amount at maturity | B23: 800000 | C23: $
A24: Expected annual return (from Settings) | B24: =Settings!$B$13 -> 0.05 | C24: %/yr
A25: → Years needed | B25: =IFERROR(NPER(B24,-B22,-B21,B23,1),"") -> 22.123952 | C25: yrs
A27: 4 · How much must I set aside for a goal?
A28: Target amount at maturity | B28: 800000 | C28: $
A29: Years to accumulate | B29: 28 | C29: yrs
A30: Expected annual return (from Settings) | B30: =Settings!$B$13 -> 0.05 | C30: %/yr
A31: A) Either one of these on its own:
A32: → Lump sum now only | B32: =-PV(B30,B29,0,B28) -> 204074.91 | C32: $
A33: → Or annual savings only | B33: =-PMT(B30,B29,0,B28,1) -> 13045.737 | C33: $/yr
A34: B) Or combine a lump sum with annual savings:
A35: If my lump sum now is | B35: 25000 | C35: $
A36: → Annual savings I will also need | B36: =-PMT(B30,B29,-B35,B28,1) -> 11447.582 | C36: $/yr
A37: If my annual savings is | B37: 8000 | C37: $/yr
A38: → Lump sum I will also need | B38: =-PV(B30,B29,-B37,B28,1) -> 78930.641 | C38: $
A40: Not financial advice — a simplified compound-growth model for personal planning. Verify anything important with a qualified professional.

Sheet Transactions
A1: Sell (-1) Buy (1) Fees (0) Dividend (2) | B1: Exchange | C1: Symbol | D1: Units Purchased or Sold | E1: Currency | F1: Price Paid or Received | G1: Date of transaction (YYYY-MM-DD) | H1: Fee | I1: FX Rate | J1: Total after fees | K1: Transaction Details (Optional) | L1: Key | M1: Signed Units | N1: Buy Cost | O1: Sell Proceeds | P1: FX to SGD | Q1: Flow SGD | R1: Dividend SGD | S1: Running Units | T1: Sort Key | U1: In Cycle | V1: =IF((COUNTIF($L:$L,"?*")-1)>COUNT($U:$U),"WARNING: "&TEXT((COUNTIF($L:$L,"?*")-1)-COUNT($U:$U),"#,##0")&" transaction(s) are missing helper formulas (In Cycle is blank) and are ignored by Shares. Select a filled cell in columns S-U and drag down over every row.",IF((COUNTIF($L:$L,"?*")-1)>COUNTIF(Txn[Key],"?*"),"WARNING: "&TEXT((COUNTIF($L:$L,"?*")-1)-COUNTIF(Txn[Key],"?*"),"#,##0")&" transaction(s) sit OUTSIDE the ledger table and are ignored by Shares and the Dashboard. Click any ledger cell, then Table Design > Resize Table to include every row.",IF(COUNTIF(Txn[Key],"?*")>10000,"WARNING: over 10,000 transactions - the XIRR engine on Portfolio Analysis covers 10,000. Extend columns B and F there or XIRR will ignore the excess.","Ledger capacity OK ("&TEXT(COUNTIF(Txn[Key],"?*"),"#,##0")&" of 10,000 transactions)"))) -> Ledger capacity OK (20 of 10,000 transactions)
A2: 1 | B2: CA | C2: GOLD | D2: 400 | E2: SGD | F2: 75 | G2: 43525 | J2: 30000 | K2: [Sample] Gold via pseudo-ticker | L2: =IF(OR(B2="",C2="",E2=""),"",B2&":"&C2&":"&E2) -> CA:GOLD:SGD | M2: =IF(A2="","",IF(A2=1,D2,IF(A2=-1,-D2,0))) -> 400 | N2: =IF(A2="","",IF(OR(A2=1,A2=0),J2,0)) -> 30000 | O2: =IF(A2="","",IF(A2=-1,J2,0)) -> 0 | P2: =IF($I2<>"",$I2,IF($E2="SGD",1,IF($E2="USD",Settings!$B$22,IF($E2="HKD",Settings!$B$23,1)))) -> 1 | Q2: =IF($L2="",0,($O2-$N2+IF($A2=2,$J2,0))*$P2) -> -30000 | R2: =IF($L2="",0,IF($A2=2,$J2*$P2,0)) -> 0 | S2: =IF(L2="","",SUMIFS($M:$M,$L:$L,L2,$T:$T,"<="&T2)) -> 400 | T2: =IF(L2="","",INT(G2)*100000+ROW()) -> 4352500002 | U2: =IF(L2="","",IF(AND(COUNTIFS($L:$L,L2,$S:$S,">-0.000001",$S:$S,"<0.000001",$T:$T,">"&T2)=0,ABS(S2)>0.000001),1,0)) -> 1 | V2: Paste new rows only into columns A–K — never over J–S (these are formulas). If J–S go blank, select a filled row and drag them down. Details on the Start Here tab.
A3: 1 | B3: SGX | C3: Z74 | D3: 3000 | E3: SGD | F3: 3.1 | G3: 43770 | J3: 9325 | L3: =IF(OR(B3="",C3="",E3=""),"",B3&":"&C3&":"&E3) -> SGX:Z74:SGD | M3: =IF(A3="","",IF(A3=1,D3,IF(A3=-1,-D3,0))) -> 3000 | N3: =IF(A3="","",IF(OR(A3=1,A3=0),J3,0)) -> 9325 | O3: =IF(A3="","",IF(A3=-1,J3,0)) -> 0 | P3: =IF($I3<>"",$I3,IF($E3="SGD",1,IF($E3="USD",Settings!$B$22,IF($E3="HKD",Settings!$B$23,1)))) -> 1 | Q3: =IF($L3="",0,($O3-$N3+IF($A3=2,$J3,0))*$P3) -> -9325 | R3: =IF($L3="",0,IF($A3=2,$J3*$P3,0)) -> 0 | S3: =IF(L3="","",SUMIFS($M:$M,$L:$L,L3,$T:$T,"<="&T3)) -> 3000 | T3: =IF(L3="","",INT(G3)*100000+ROW()) -> 4377000003 | U3: =IF(L3="","",IF(AND(COUNTIFS($L:$L,L3,$S:$S,">-0.000001",$S:$S,"<0.000001",$T:$T,">"&T3)=0,ABS(S3)>0.000001),1,0)) -> 1
A4: 1 | B4: USX | C4: AAPL | D4: 50 | E4: USD | F4: 80 | G4: 43966 | J4: 4005 | L4: =IF(OR(B4="",C4="",E4=""),"",B4&":"&C4&":"&E4) -> USX:AAPL:USD | M4: =IF(A4="","",IF(A4=1,D4,IF(A4=-1,-D4,0))) -> 50 | N4: =IF(A4="","",IF(OR(A4=1,A4=0),J4,0)) -> 4005 | O4: =IF(A4="","",IF(A4=-1,J4,0)) -> 0 | P4: =IF($I4<>"",$I4,IF($E4="SGD",1,IF($E4="USD",Settings!$B$22,IF($E4="HKD",Settings!$B$23,1)))) -> 1.2928081 | Q4: =IF($L4="",0,($O4-$N4+IF($A4=2,$J4,0))*$P4) -> -5177.6965 | R4: =IF($L4="",0,IF($A4=2,$J4*$P4,0)) -> 0 | S4: =IF(L4="","",SUMIFS($M:$M,$L:$L,L4,$T:$T,"<="&T4)) -> 50 | T4: =IF(L4="","",INT(G4)*100000+ROW()) -> 4396600004 | U4: =IF(L4="","",IF(AND(COUNTIFS($L:$L,L4,$S:$S,">-0.000001",$S:$S,"<0.000001",$T:$T,">"&T4)=0,ABS(S4)>0.000001),1,0)) -> 1
A5: 1 | B5: SGX | C5: C38U | D5: 5000 | E5: SGD | F5: 1.9 | G5: 44046 | J5: 9525 | L5: =IF(OR(B5="",C5="",E5=""),"",B5&":"&C5&":"&E5) -> SGX:C38U:SGD | M5: =IF(A5="","",IF(A5=1,D5,IF(A5=-1,-D5,0))) -> 5000 | N5: =IF(A5="","",IF(OR(A5=1,A5=0),J5,0)) -> 9525 | O5: =IF(A5="","",IF(A5=-1,J5,0)) -> 0 | P5: =IF($I5<>"",$I5,IF($E5="SGD",1,IF($E5="USD",Settings!$B$22,IF($E5="HKD",Settings!$B$23,1)))) -> 1 | Q5: =IF($L5="",0,($O5-$N5+IF($A5=2,$J5,0))*$P5) -> -9525 | R5: =IF($L5="",0,IF($A5=2,$J5*$P5,0)) -> 0 | S5: =IF(L5="","",SUMIFS($M:$M,$L:$L,L5,$T:$T,"<="&T5)) -> 5000 | T5: =IF(L5="","",INT(G5)*100000+ROW()) -> 4404600005 | U5: =IF(L5="","",IF(AND(COUNTIFS($L:$L,L5,$S:$S,">-0.000001",$S:$S,"<0.000001",$T:$T,">"&T5)=0,ABS(S5)>0.000001),1,0)) -> 1
A6: 1 | B6: CG | C6: BITCOIN | D6: 0.05 | E6: USD | F6: 20000 | G6: 44166 | J6: 1000 | L6: =IF(OR(B6="",C6="",E6=""),"",B6&":"&C6&":"&E6) -> CG:BITCOIN:USD | M6: =IF(A6="","",IF(A6=1,D6,IF(A6=-1,-D6,0))) -> 0.05 | N6: =IF(A6="","",IF(OR(A6=1,A6=0),J6,0)) -> 1000 | O6: =IF(A6="","",IF(A6=-1,J6,0)) -> 0 | P6: =IF($I6<>"",$I6,IF($E6="SGD",1,IF($E6="USD",Settings!$B$22,IF($E6="HKD",Settings!$B$23,1)))) -> 1.2928081 | Q6: =IF($L6="",0,($O6-$N6+IF($A6=2,$J6,0))*$P6) -> -1292.8081 | R6: =IF($L6="",0,IF($A6=2,$J6*$P6,0)) -> 0 | S6: =IF(L6="","",SUMIFS($M:$M,$L:$L,L6,$T:$T,"<="&T6)) -> 0.05 | T6: =IF(L6="","",INT(G6)*100000+ROW()) -> 4416600006 | U6: =IF(L6="","",IF(AND(COUNTIFS($L:$L,L6,$S:$S,">-0.000001",$S:$S,"<0.000001",$T:$T,">"&T6)=0,ABS(S6)>0.000001),1,0)) -> 1
A7: 1 | B7: HKEX | C7: 700 | D7: 100 | E7: HKD | F7: 600 | G7: 44228 | J7: 60100 | K7: [Sample] HKD position, currently at a loss | L7: =IF(OR(B7="",C7="",E7=""),"",B7&":"&C7&":"&E7) -> HKEX:700:HKD | M7: =IF(A7="","",IF(A7=1,D7,IF(A7=-1,-D7,0))) -> 100 | N7: =IF(A7="","",IF(OR(A7=1,A7=0),J7,0)) -> 60100 | O7: =IF(A7="","",IF(A7=-1,J7,0)) -> 0 | P7: =IF($I7<>"",$I7,IF($E7="SGD",1,IF($E7="USD",Settings!$B$22,IF($E7="HKD",Settings!$B$23,1)))) -> 0.16489949 | Q7: =IF($L7="",0,($O7-$N7+IF($A7=2,$J7,0))*$P7) -> -9910.4596 | R7: =IF($L7="",0,IF($A7=2,$J7*$P7,0)) -> 0 | S7: =IF(L7="","",SUMIFS($M:$M,$L:$L,L7,$T:$T,"<="&T7)) -> 100 | T7: =IF(L7="","",INT(G7)*100000+ROW()) -> 4422800007 | U7: =IF(L7="","",IF(AND(COUNTIFS($L:$L,L7,$S:$S,">-0.000001",$S:$S,"<0.000001",$T:$T,">"&T7)=0,ABS(S7)>0.000001),1,0)) -> 1
A8: 1 | B8: USX | C8: MSFT | D8: 20 | E8: USD | F8: 230 | G8: 44256 | J8: 4605 | L8: =IF(OR(B8="",C8="",E8=""),"",B8&":"&C8&":"&E8) -> USX:MSFT:USD | M8: =IF(A8="","",IF(A8=1,D8,IF(A8=-1,-D8,0))) -> 20 | N8: =IF(A8="","",IF(OR(A8=1,A8=0),J8,0)) -> 4605 | O8: =IF(A8="","",IF(A8=-1,J8,0)) -> 0 | P8: =IF($I8<>"",$I8,IF($E8="SGD",1,IF($E8="USD",Settings!$B$22,IF($E8="HKD",Settings!$B$23,1)))) -> 1.2928081 | Q8: =IF($L8="",0,($O8-$N8+IF($A8=2,$J8,0))*$P8) -> -5953.3813 | R8: =IF($L8="",0,IF($A8=2,$J8*$P8,0)) -> 0 | S8: =IF(L8="","",SUMIFS($M:$M,$L:$L,L8,$T:$T,"<="&T8)) -> 20 | T8: =IF(L8="","",INT(G8)*100000+ROW()) -> 4425600008 | U8: =IF(L8="","",IF(AND(COUNTIFS($L:$L,L8,$S:$S,">-0.000001",$S:$S,"<0.000001",$T:$T,">"&T8)=0,ABS(S8)>0.000001),1,0)) -> 1
A9: 1 | B9: SGX | C9: A17U | D9: 4000 | E9: SGD | F9: 2.95 | G9: 44326 | J9: 11825 | L9: =IF(OR(B9="",C9="",E9=""),"",B9&":"&C9&":"&E9) -> SGX:A17U:SGD | M9: =IF(A9="","",IF(A9=1,D9,IF(A9=-1,-D9,0))) -> 4000 | N9: =IF(A9="","",IF(OR(A9=1,A9=0),J9,0)) -> 11825 | O9: =IF(A9="","",IF(A9=-1,J9,0)) -> 0 | P9: =IF($I9<>"",$I9,IF($E9="SGD",1,IF($E9="USD",Settings!$B$22,IF($E9="HKD",Settings!$B$23,1)))) -> 1 | Q9: =IF($L9="",0,($O9-$N9+IF($A9=2,$J9,0))*$P9) -> -11825 | R9: =IF($L9="",0,IF($A9=2,$J9*$P9,0)) -> 0 | S9: =IF(L9="","",SUMIFS($M:$M,$L:$L,L9,$T:$T,"<="&T9)) -> 4000 | T9: =IF(L9="","",INT(G9)*100000+ROW()) -> 4432600009 | U9: =IF(L9="","",IF(AND(COUNTIFS($L:$L,L9,$S:$S,">-0.000001",$S:$S,"<0.000001",$T:$T,">"&T9)=0,ABS(S9)>0.000001),1,0)) -> 1
A10: 0 | B10: SGX | C10: A17U | D10: 0 | E10: SGD | F10: 0 | G10: 44326 | J10: 25 | K10: [Sample] Brokerage fee — action 0, zero units | L10: =IF(OR(B10="",C10="",E10=""),"",B10&":"&C10&":"&E10) -> SGX:A17U:SGD | M10: =IF(A10="","",IF(A10=1,D10,IF(A10=-1,-D10,0))) -> 0 | N10: =IF(A10="","",IF(OR(A10=1,A10=0),J10,0)) -> 25 | O10: =IF(A10="","",IF(A10=-1,J10,0)) -> 0 | P10: =IF($I10<>"",$I10,IF($E10="SGD",1,IF($E10="USD",Settings!$B$22,IF($E10="HKD",Settings!$B$23,1)))) -> 1 | Q10: =IF($L10="",0,($O10-$N10+IF($A10=2,$J10,0))*$P10) -> -25 | R10: =IF($L10="",0,IF($A10=2,$J10*$P10,0)) -> 0 | S10: =IF(L10="","",SUMIFS($M:$M,$L:$L,L10,$T:$T,"<="&T10)) -> 4000 | T10: =IF(L10="","",INT(G10)*100000+ROW()) -> 4432600010 | U10: =IF(L10="","",IF(AND(COUNTIFS($L:$L,L10,$S:$S,">-0.000001",$S:$S,"<0.000001",$T:$T,">"&T10)=0,ABS(S10)>0.000001),1,0)) -> 1
A11: 1 | B11: CA | C11: GOLD | D11: 300 | E11: SGD | F11: 85 | G11: 44348 | J11: 25500 | L11: =IF(OR(B11="",C11="",E11=""),"",B11&":"&C11&":"&E11) -> CA:GOLD:SGD | M11: =IF(A11="","",IF(A11=1,D11,IF(A11=-1,-D11,0))) -> 300 | N11: =IF(A11="","",IF(OR(A11=1,A11=0),J11,0)) -> 25500 | O11: =IF(A11="","",IF(A11=-1,J11,0)) -> 0 | P11: =IF($I11<>"",$I11,IF($E11="SGD",1,IF($E11="USD",Settings!$B$22,IF($E11="HKD",Settings!$B$23,1)))) -> 1 | Q11: =IF($L11="",0,($O11-$N11+IF($A11=2,$J11,0))*$P11) -> -25500 | R11: =IF($L11="",0,IF($A11=2,$J11*$P11,0)) -> 0 | S11: =IF(L11="","",SUMIFS($M:$M,$L:$L,L11,$T:$T,"<="&T11)) -> 700 | T11: =IF(L11="","",INT(G11)*100000+ROW()) -> 4434800011 | U11: =IF(L11="","",IF(AND(COUNTIFS($L:$L,L11,$S:$S,">-0.000001",$S:$S,"<0.000001",$T:$T,">"&T11)=0,ABS(S11)>0.000001),1,0)) -> 1
A12: 1 | B12: USX | C12: AAPL | D12: 30 | E12: USD | F12: 170 | G12: 44571 | J12: 5105 | L12: =IF(OR(B12="",C12="",E12=""),"",B12&":"&C12&":"&E12) -> USX:AAPL:USD | M12: =IF(A12="","",IF(A12=1,D12,IF(A12=-1,-D12,0))) -> 30 | N12: =IF(A12="","",IF(OR(A12=1,A12=0),J12,0)) -> 5105 | O12: =IF(A12="","",IF(A12=-1,J12,0)) -> 0 | P12: =IF($I12<>"",$I12,IF($E12="SGD",1,IF($E12="USD",Settings!$B$22,IF($E12="HKD",Settings!$B$23,1)))) -> 1.2928081 | Q12: =IF($L12="",0,($O12-$N12+IF($A12=2,$J12,0))*$P12) -> -6599.7854 | R12: =IF($L12="",0,IF($A12=2,$J12*$P12,0)) -> 0 | S12: =IF(L12="","",SUMIFS($M:$M,$L:$L,L12,$T:$T,"<="&T12)) -> 80 | T12: =IF(L12="","",INT(G12)*100000+ROW()) -> 4457100012 | U12: =IF(L12="","",IF(AND(COUNTIFS($L:$L,L12,$S:$S,">-0.000001",$S:$S,"<0.000001",$T:$T,">"&T12)=0,ABS(S12)>0.000001),1,0)) -> 1
A13: 1 | B13: SGX | C13: C38U | D13: 3000 | E13: SGD | F13: 2.2 | G13: 44621 | J13: 6625 | L13: =IF(OR(B13="",C13="",E13=""),"",B13&":"&C13&":"&E13) -> SGX:C38U:SGD | M13: =IF(A13="","",IF(A13=1,D13,IF(A13=-1,-D13,0))) -> 3000 | N13: =IF(A13="","",IF(OR(A13=1,A13=0),J13,0)) -> 6625 | O13: =IF(A13="","",IF(A13=-1,J13,0)) -> 0 | P13: =IF($I13<>"",$I13,IF($E13="SGD",1,IF($E13="USD",Settings!$B$22,IF($E13="HKD",Settings!$B$23,1)))) -> 1 | Q13: =IF($L13="",0,($O13-$N13+IF($A13=2,$J13,0))*$P13) -> -6625 | R13: =IF($L13="",0,IF($A13=2,$J13*$P13,0)) -> 0 | S13: =IF(L13="","",SUMIFS($M:$M,$L:$L,L13,$T:$T,"<="&T13)) -> 8000 | T13: =IF(L13="","",INT(G13)*100000+ROW()) -> 4462100013 | U13: =IF(L13="","",IF(AND(COUNTIFS($L:$L,L13,$S:$S,">-0.000001",$S:$S,"<0.000001",$T:$T,">"&T13)=0,ABS(S13)>0.000001),1,0)) -> 1
A14: 1 | B14: USX | C14: NVDA | D14: 40 | E14: USD | F14: 120 | G14: 44837 | J14: 4805 | L14: =IF(OR(B14="",C14="",E14=""),"",B14&":"&C14&":"&E14) -> USX:NVDA:USD | M14: =IF(A14="","",IF(A14=1,D14,IF(A14=-1,-D14,0))) -> 40 | N14: =IF(A14="","",IF(OR(A14=1,A14=0),J14,0)) -> 4805 | O14: =IF(A14="","",IF(A14=-1,J14,0)) -> 0 | P14: =IF($I14<>"",$I14,IF($E14="SGD",1,IF($E14="USD",Settings!$B$22,IF($E14="HKD",Settings!$B$23,1)))) -> 1.2928081 | Q14: =IF($L14="",0,($O14-$N14+IF($A14=2,$J14,0))*$P14) -> -6211.943 | R14: =IF($L14="",0,IF($A14=2,$J14*$P14,0)) -> 0 | S14: =IF(L14="","",SUMIFS($M:$M,$L:$L,L14,$T:$T,"<="&T14)) -> 40 | T14: =IF(L14="","",INT(G14)*100000+ROW()) -> 4483700014 | U14: =IF(L14="","",IF(AND(COUNTIFS($L:$L,L14,$S:$S,">-0.000001",$S:$S,"<0.000001",$T:$T,">"&T14)=0,ABS(S14)>0.000001),1,0)) -> 0
A15: 1 | B15: CG | C15: BITCOIN | D15: 0.05 | E15: USD | F15: 17000 | G15: 44942 | J15: 850 | L15: =IF(OR(B15="",C15="",E15=""),"",B15&":"&C15&":"&E15) -> CG:BITCOIN:USD | M15: =IF(A15="","",IF(A15=1,D15,IF(A15=-1,-D15,0))) -> 0.05 | N15: =IF(A15="","",IF(OR(A15=1,A15=0),J15,0)) -> 850 | O15: =IF(A15="","",IF(A15=-1,J15,0)) -> 0 | P15: =IF($I15<>"",$I15,IF($E15="SGD",1,IF($E15="USD",Settings!$B$22,IF($E15="HKD",Settings!$B$23,1)))) -> 1.2928081 | Q15: =IF($L15="",0,($O15-$N15+IF($A15=2,$J15,0))*$P15) -> -1098.8869 | R15: =IF($L15="",0,IF($A15=2,$J15*$P15,0)) -> 0 | S15: =IF(L15="","",SUMIFS($M:$M,$L:$L,L15,$T:$T,"<="&T15)) -> 0.1 | T15: =IF(L15="","",INT(G15)*100000+ROW()) -> 4494200015 | U15: =IF(L15="","",IF(AND(COUNTIFS($L:$L,L15,$S:$S,">-0.000001",$S:$S,"<0.000001",$T:$T,">"&T15)=0,ABS(S15)>0.000001),1,0)) -> 1
A16: 1 | B16: SGX | C16: CLR | D16: 10000 | E16: SGD | F16: 0.7 | G16: 45019 | J16: 7025 | L16: =IF(OR(B16="",C16="",E16=""),"",B16&":"&C16&":"&E16) -> SGX:CLR:SGD | M16: =IF(A16="","",IF(A16=1,D16,IF(A16=-1,-D16,0))) -> 10000 | N16: =IF(A16="","",IF(OR(A16=1,A16=0),J16,0)) -> 7025 | O16: =IF(A16="","",IF(A16=-1,J16,0)) -> 0 | P16: =IF($I16<>"",$I16,IF($E16="SGD",1,IF($E16="USD",Settings!$B$22,IF($E16="HKD",Settings!$B$23,1)))) -> 1 | Q16: =IF($L16="",0,($O16-$N16+IF($A16=2,$J16,0))*$P16) -> -7025 | R16: =IF($L16="",0,IF($A16=2,$J16*$P16,0)) -> 0 | S16: =IF(L16="","",SUMIFS($M:$M,$L:$L,L16,$T:$T,"<="&T16)) -> 10000 | T16: =IF(L16="","",INT(G16)*100000+ROW()) -> 4501900016 | U16: =IF(L16="","",IF(AND(COUNTIFS($L:$L,L16,$S:$S,">-0.000001",$S:$S,"<0.000001",$T:$T,">"&T16)=0,ABS(S16)>0.000001),1,0)) -> 1
A17: -1 | B17: USX | C17: NVDA | D17: 40 | E17: USD | F17: 450 | G17: 45446 | J17: 17995 | K17: [Sample] Sold — a closed position (see All Ticker P&L) | L17: =IF(OR(B17="",C17="",E17=""),"",B17&":"&C17&":"&E17) -> USX:NVDA:USD | M17: =IF(A17="","",IF(A17=1,D17,IF(A17=-1,-D17,0))) -> -40 | N17: =IF(A17="","",IF(OR(A17=1,A17=0),J17,0)) -> 0 | O17: =IF(A17="","",IF(A17=-1,J17,0)) -> 17995 | P17: =IF($I17<>"",$I17,IF($E17="SGD",1,IF($E17="USD",Settings!$B$22,IF($E17="HKD",Settings!$B$23,1)))) -> 1.2928081 | Q17: =IF($L17="",0,($O17-$N17+IF($A17=2,$J17,0))*$P17) -> 23264.082 | R17: =IF($L17="",0,IF($A17=2,$J17*$P17,0)) -> 0 | S17: =IF(L17="","",SUMIFS($M:$M,$L:$L,L17,$T:$T,"<="&T17)) -> 0 | T17: =IF(L17="","",INT(G17)*100000+ROW()) -> 4544600017 | U17: =IF(L17="","",IF(AND(COUNTIFS($L:$L,L17,$S:$S,">-0.000001",$S:$S,"<0.000001",$T:$T,">"&T17)=0,ABS(S17)>0.000001),1,0)) -> 0
A18: 2 | B18: SGX | C18: C38U | D18: 0 | E18: SGD | F18: 0 | G18: 45889 | J18: 280 | K18: [Sample] Dividend received — action 2, Total = amount | L18: =IF(OR(B18="",C18="",E18=""),"",B18&":"&C18&":"&E18) -> SGX:C38U:SGD | M18: =IF(A18="","",IF(A18=1,D18,IF(A18=-1,-D18,0))) -> 0 | N18: =IF(A18="","",IF(OR(A18=1,A18=0),J18,0)) -> 0 | O18: =IF(A18="","",IF(A18=-1,J18,0)) -> 0 | P18: =IF($I18<>"",$I18,IF($E18="SGD",1,IF($E18="USD",Settings!$B$22,IF($E18="HKD",Settings!$B$23,1)))) -> 1 | Q18: =IF($L18="",0,($O18-$N18+IF($A18=2,$J18,0))*$P18) -> 280 | R18: =IF($L18="",0,IF($A18=2,$J18*$P18,0)) -> 280 | S18: =IF(L18="","",SUMIFS($M:$M,$L:$L,L18,$T:$T,"<="&T18)) -> 8000 | T18: =IF(L18="","",INT(G18)*100000+ROW()) -> 4588900018 | U18: =IF(L18="","",IF(AND(COUNTIFS($L:$L,L18,$S:$S,">-0.000001",$S:$S,"<0.000001",$T:$T,">"&T18)=0,ABS(S18)>0.000001),1,0)) -> 1
A19: 2 | B19: SGX | C19: Z74 | D19: 0 | E19: SGD | F19: 0 | G19: 46037 | J19: 200 | K19: [Sample] Dividend received | L19: =IF(OR(B19="",C19="",E19=""),"",B19&":"&C19&":"&E19) -> SGX:Z74:SGD | M19: =IF(A19="","",IF(A19=1,D19,IF(A19=-1,-D19,0))) -> 0 | N19: =IF(A19="","",IF(OR(A19=1,A19=0),J19,0)) -> 0 | O19: =IF(A19="","",IF(A19=-1,J19,0)) -> 0 | P19: =IF($I19<>"",$I19,IF($E19="SGD",1,IF($E19="USD",Settings!$B$22,IF($E19="HKD",Settings!$B$23,1)))) -> 1 | Q19: =IF($L19="",0,($O19-$N19+IF($A19=2,$J19,0))*$P19) -> 200 | R19: =IF($L19="",0,IF($A19=2,$J19*$P19,0)) -> 200 | S19: =IF(L19="","",SUMIFS($M:$M,$L:$L,L19,$T:$T,"<="&T19)) -> 3000 | T19: =IF(L19="","",INT(G19)*100000+ROW()) -> 4603700019 | U19: =IF(L19="","",IF(AND(COUNTIFS($L:$L,L19,$S:$S,">-0.000001",$S:$S,"<0.000001",$T:$T,">"&T19)=0,ABS(S19)>0.000001),1,0)) -> 1
A20: 2 | B20: SGX | C20: C38U | D20: 0 | E20: SGD | F20: 0 | G20: 46073 | J20: 300 | K20: [Sample] Dividend received | L20: =IF(OR(B20="",C20="",E20=""),"",B20&":"&C20&":"&E20) -> SGX:C38U:SGD | M20: =IF(A20="","",IF(A20=1,D20,IF(A20=-1,-D20,0))) -> 0 | N20: =IF(A20="","",IF(OR(A20=1,A20=0),J20,0)) -> 0 | O20: =IF(A20="","",IF(A20=-1,J20,0)) -> 0 | P20: =IF($I20<>"",$I20,IF($E20="SGD",1,IF($E20="USD",Settings!$B$22,IF($E20="HKD",Settings!$B$23,1)))) -> 1 | Q20: =IF($L20="",0,($O20-$N20+IF($A20=2,$J20,0))*$P20) -> 300 | R20: =IF($L20="",0,IF($A20=2,$J20*$P20,0)) -> 300 | S20: =IF(L20="","",SUMIFS($M:$M,$L:$L,L20,$T:$T,"<="&T20)) -> 8000 | T20: =IF(L20="","",INT(G20)*100000+ROW()) -> 4607300020 | U20: =IF(L20="","",IF(AND(COUNTIFS($L:$L,L20,$S:$S,">-0.000001",$S:$S,"<0.000001",$T:$T,">"&T20)=0,ABS(S20)>0.000001),1,0)) -> 1
A21: 2 | B21: SGX | C21: A17U | D21: 0 | E21: SGD | F21: 0 | G21: 46203 | J21: 310 | K21: [Sample] Dividend received | L21: =IF(OR(B21="",C21="",E21=""),"",B21&":"&C21&":"&E21) -> SGX:A17U:SGD | M21: =IF(A21="","",IF(A21=1,D21,IF(A21=-1,-D21,0))) -> 0 | N21: =IF(A21="","",IF(OR(A21=1,A21=0),J21,0)) -> 0 | O21: =IF(A21="","",IF(A21=-1,J21,0)) -> 0 | P21: =IF($I21<>"",$I21,IF($E21="SGD",1,IF($E21="USD",Settings!$B$22,IF($E21="HKD",Settings!$B$23,1)))) -> 1 | Q21: =IF($L21="",0,($O21-$N21+IF($A21=2,$J21,0))*$P21) -> 310 | R21: =IF($L21="",0,IF($A21=2,$J21*$P21,0)) -> 310 | S21: =IF(L21="","",SUMIFS($M:$M,$L:$L,L21,$T:$T,"<="&T21)) -> 4000 | T21: =IF(L21="","",INT(G21)*100000+ROW()) -> 4620300021 | U21: =IF(L21="","",IF(AND(COUNTIFS($L:$L,L21,$S:$S,">-0.000001",$S:$S,"<0.000001",$T:$T,">"&T21)=0,ABS(S21)>0.000001),1,0)) -> 1
L22: =IF(OR(B22="",C22="",E22=""),"",B22&":"&C22&":"&E22) | M22: =IF(A22="","",IF(A22=1,D22,IF(A22=-1,-D22,0))) | N22: =IF(A22="","",IF(OR(A22=1,A22=0),J22,0)) | O22: =IF(A22="","",IF(A22=-1,J22,0)) | P22: =IF($I22<>"",$I22,IF($E22="SGD",1,IF($E22="USD",Settings!$B$22,IF($E22="HKD",Settings!$B$23,1)))) -> 1 | Q22: =IF($L22="",0,($O22-$N22+IF($A22=2,$J22,0))*$P22) -> 0 | R22: =IF($L22="",0,IF($A22=2,$J22*$P22,0)) -> 0 | S22: =IF(L22="","",SUMIFS($M:$M,$L:$L,L22,$T:$T,"<="&T22)) | T22: =IF(L22="","",INT(G22)*100000+ROW()) | U22: =IF(L22="","",IF(AND(COUNTIFS($L:$L,L22,$S:$S,">-0.000001",$S:$S,"<0.000001",$T:$T,">"&T22)=0,ABS(S22)>0.000001),1,0))
L23: =IF(OR(B23="",C23="",E23=""),"",B23&":"&C23&":"&E23) | M23: =IF(A23="","",IF(A23=1,D23,IF(A23=-1,-D23,0))) | N23: =IF(A23="","",IF(OR(A23=1,A23=0),J23,0)) | O23: =IF(A23="","",IF(A23=-1,J23,0)) | P23: =IF($I23<>"",$I23,IF($E23="SGD",1,IF($E23="USD",Settings!$B$22,IF($E23="HKD",Settings!$B$23,1)))) -> 1 | Q23: =IF($L23="",0,($O23-$N23+IF($A23=2,$J23,0))*$P23) -> 0 | R23: =IF($L23="",0,IF($A23=2,$J23*$P23,0)) -> 0 | S23: =IF(L23="","",SUMIFS($M:$M,$L:$L,L23,$T:$T,"<="&T23)) | T23: =IF(L23="","",INT(G23)*100000+ROW()) | U23: =IF(L23="","",IF(AND(COUNTIFS($L:$L,L23,$S:$S,">-0.000001",$S:$S,"<0.000001",$T:$T,">"&T23)=0,ABS(S23)>0.000001),1,0))
L24: =IF(OR(B24="",C24="",E24=""),"",B24&":"&C24&":"&E24) | M24: =IF(A24="","",IF(A24=1,D24,IF(A24=-1,-D24,0))) | N24: =IF(A24="","",IF(OR(A24=1,A24=0),J24,0)) | O24: =IF(A24="","",IF(A24=-1,J24,0)) | P24: =IF($I24<>"",$I24,IF($E24="SGD",1,IF($E24="USD",Settings!$B$22,IF($E24="HKD",Settings!$B$23,1)))) -> 1 | Q24: =IF($L24="",0,($O24-$N24+IF($A24=2,$J24,0))*$P24) -> 0 | R24: =IF($L24="",0,IF($A24=2,$J24*$P24,0)) -> 0 | S24: =IF(L24="","",SUMIFS($M:$M,$L:$L,L24,$T:$T,"<="&T24)) | T24: =IF(L24="","",INT(G24)*100000+ROW()) | U24: =IF(L24="","",IF(AND(COUNTIFS($L:$L,L24,$S:$S,">-0.000001",$S:$S,"<0.000001",$T:$T,">"&T24)=0,ABS(S24)>0.000001),1,0))
L25: =IF(OR(B25="",C25="",E25=""),"",B25&":"&C25&":"&E25) | M25: =IF(A25="","",IF(A25=1,D25,IF(A25=-1,-D25,0))) | N25: =IF(A25="","",IF(OR(A25=1,A25=0),J25,0)) | O25: =IF(A25="","",IF(A25=-1,J25,0)) | P25: =IF($I25<>"",$I25,IF($E25="SGD",1,IF($E25="USD",Settings!$B$22,IF($E25="HKD",Settings!$B$23,1)))) -> 1 | Q25: =IF($L25="",0,($O25-$N25+IF($A25=2,$J25,0))*$P25) -> 0 | R25: =IF($L25="",0,IF($A25=2,$J25*$P25,0)) -> 0 | S25: =IF(L25="","",SUMIFS($M:$M,$L:$L,L25,$T:$T,"<="&T25)) | T25: =IF(L25="","",INT(G25)*100000+ROW()) | U25: =IF(L25="","",IF(AND(COUNTIFS($L:$L,L25,$S:$S,">-0.000001",$S:$S,"<0.000001",$T:$T,">"&T25)=0,ABS(S25)>0.000001),1,0))
L26: =IF(OR(B26="",C26="",E26=""),"",B26&":"&C26&":"&E26) | M26: =IF(A26="","",IF(A26=1,D26,IF(A26=-1,-D26,0))) | N26: =IF(A26="","",IF(OR(A26=1,A26=0),J26,0)) | O26: =IF(A26="","",IF(A26=-1,J26,0)) | P26: =IF($I26<>"",$I26,IF($E26="SGD",1,IF($E26="USD",Settings!$B$22,IF($E26="HKD",Settings!$B$23,1)))) -> 1 | Q26: =IF($L26="",0,($O26-$N26+IF($A26=2,$J26,0))*$P26) -> 0 | R26: =IF($L26="",0,IF($A26=2,$J26*$P26,0)) -> 0 | S26: =IF(L26="","",SUMIFS($M:$M,$L:$L,L26,$T:$T,"<="&T26)) | T26: =IF(L26="","",INT(G26)*100000+ROW()) | U26: =IF(L26="","",IF(AND(COUNTIFS($L:$L,L26,$S:$S,">-0.000001",$S:$S,"<0.000001",$T:$T,">"&T26)=0,ABS(S26)>0.000001),1,0))
L27: =IF(OR(B27="",C27="",E27=""),"",B27&":"&C27&":"&E27) | M27: =IF(A27="","",IF(A27=1,D27,IF(A27=-1,-D27,0))) | N27: =IF(A27="","",IF(OR(A27=1,A27=0),J27,0)) | O27: =IF(A27="","",IF(A27=-1,J27,0)) | P27: =IF($I27<>"",$I27,IF($E27="SGD",1,IF($E27="USD",Settings!$B$22,IF($E27="HKD",Settings!$B$23,1)))) -> 1 | Q27: =IF($L27="",0,($O27-$N27+IF($A27=2,$J27,0))*$P27) -> 0 | R27: =IF($L27="",0,IF($A27=2,$J27*$P27,0)) -> 0 | S27: =IF(L27="","",SUMIFS($M:$M,$L:$L,L27,$T:$T,"<="&T27)) | T27: =IF(L27="","",INT(G27)*100000+ROW()) | U27: =IF(L27="","",IF(AND(COUNTIFS($L:$L,L27,$S:$S,">-0.000001",$S:$S,"<0.000001",$T:$T,">"&T27)=0,ABS(S27)>0.000001),1,0))
L28: =IF(OR(B28="",C28="",E28=""),"",B28&":"&C28&":"&E28) | M28: =IF(A28="","",IF(A28=1,D28,IF(A28=-1,-D28,0))) | N28: =IF(A28="","",IF(OR(A28=1,A28=0),J28,0)) | O28: =IF(A28="","",IF(A28=-1,J28,0)) | P28: =IF($I28<>"",$I28,IF($E28="SGD",1,IF($E28="USD",Settings!$B$22,IF($E28="HKD",Settings!$B$23,1)))) -> 1 | Q28: =IF($L28="",0,($O28-$N28+IF($A28=2,$J28,0))*$P28) -> 0 | R28: =IF($L28="",0,IF($A28=2,$J28*$P28,0)) -> 0 | S28: =IF(L28="","",SUMIFS($M:$M,$L:$L,L28,$T:$T,"<="&T28)) | T28: =IF(L28="","",INT(G28)*100000+ROW()) | U28: =IF(L28="","",IF(AND(COUNTIFS($L:$L,L28,$S:$S,">-0.000001",$S:$S,"<0.000001",$T:$T,">"&T28)=0,ABS(S28)>0.000001),1,0))
L29: =IF(OR(B29="",C29="",E29=""),"",B29&":"&C29&":"&E29) | M29: =IF(A29="","",IF(A29=1,D29,IF(A29=-1,-D29,0))) | N29: =IF(A29="","",IF(OR(A29=1,A29=0),J29,0)) | O29: =IF(A29="","",IF(A29=-1,J29,0)) | P29: =IF($I29<>"",$I29,IF($E29="SGD",1,IF($E29="USD",Settings!$B$22,IF($E29="HKD",Settings!$B$23,1)))) -> 1 | Q29: =IF($L29="",0,($O29-$N29+IF($A29=2,$J29,0))*$P29) -> 0 | R29: =IF($L29="",0,IF($A29=2,$J29*$P29,0)) -> 0 | S29: =IF(L29="","",SUMIFS($M:$M,$L:$L,L29,$T:$T,"<="&T29)) | T29: =IF(L29="","",INT(G29)*100000+ROW()) | U29: =IF(L29="","",IF(AND(COUNTIFS($L:$L,L29,$S:$S,">-0.000001",$S:$S,"<0.000001",$T:$T,">"&T29)=0,ABS(S29)>0.000001),1,0))
L30: =IF(OR(B30="",C30="",E30=""),"",B30&":"&C30&":"&E30) | M30: =IF(A30="","",IF(A30=1,D30,IF(A30=-1,-D30,0))) | N30: =IF(A30="","",IF(OR(A30=1,A30=0),J30,0)) | O30: =IF(A30="","",IF(A30=-1,J30,0)) | P30: =IF($I30<>"",$I30,IF($E30="SGD",1,IF($E30="USD",Settings!$B$22,IF($E30="HKD",Settings!$B$23,1)))) -> 1 | Q30: =IF($L30="",0,($O30-$N30+IF($A30=2,$J30,0))*$P30) -> 0 | R30: =IF($L30="",0,IF($A30=2,$J30*$P30,0)) -> 0 | S30: =IF(L30="","",SUMIFS($M:$M,$L:$L,L30,$T:$T,"<="&T30)) | T30: =IF(L30="","",INT(G30)*100000+ROW()) | U30: =IF(L30="","",IF(AND(COUNTIFS($L:$L,L30,$S:$S,">-0.000001",$S:$S,"<0.000001",$T:$T,">"&T30)=0,ABS(S30)>0.000001),1,0))
L31: =IF(OR(B31="",C31="",E31=""),"",B31&":"&C31&":"&E31) | M31: =IF(A31="","",IF(A31=1,D31,IF(A31=-1,-D31,0))) | N31: =IF(A31="","",IF(OR(A31=1,A31=0),J31,0)) | O31: =IF(A31="","",IF(A31=-1,J31,0)) | P31: =IF($I31<>"",$I31,IF($E31="SGD",1,IF($E31="USD",Settings!$B$22,IF($E31="HKD",Settings!$B$23,1)))) -> 1 | Q31: =IF($L31="",0,($O31-$N31+IF($A31=2,$J31,0))*$P31) -> 0 | R31: =IF($L31="",0,IF($A31=2,$J31*$P31,0)) -> 0 | S31: =IF(L31="","",SUMIFS($M:$M,$L:$L,L31,$T:$T,"<="&T31)) | T31: =IF(L31="","",INT(G31)*100000+ROW()) | U31: =IF(L31="","",IF(AND(COUNTIFS($L:$L,L31,$S:$S,">-0.000001",$S:$S,"<0.000001",$T:$T,">"&T31)=0,ABS(S31)>0.000001),1,0))
L32: =IF(OR(B32="",C32="",E32=""),"",B32&":"&C32&":"&E32) | M32: =IF(A32="","",IF(A32=1,D32,IF(A32=-1,-D32,0))) | N32: =IF(A32="","",IF(OR(A32=1,A32=0),J32,0)) | O32: =IF(A32="","",IF(A32=-1,J32,0)) | P32: =IF($I32<>"",$I32,IF($E32="SGD",1,IF($E32="USD",Settings!$B$22,IF($E32="HKD",Settings!$B$23,1)))) -> 1 | Q32: =IF($L32="",0,($O32-$N32+IF($A32=2,$J32,0))*$P32) -> 0 | R32: =IF($L32="",0,IF($A32=2,$J32*$P32,0)) -> 0 | S32: =IF(L32="","",SUMIFS($M:$M,$L:$L,L32,$T:$T,"<="&T32)) | T32: =IF(L32="","",INT(G32)*100000+ROW()) | U32: =IF(L32="","",IF(AND(COUNTIFS($L:$L,L32,$S:$S,">-0.000001",$S:$S,"<0.000001",$T:$T,">"&T32)=0,ABS(S32)>0.000001),1,0))
L33: =IF(OR(B33="",C33="",E33=""),"",B33&":"&C33&":"&E33) | M33: =IF(A33="","",IF(A33=1,D33,IF(A33=-1,-D33,0))) | N33: =IF(A33="","",IF(OR(A33=1,A33=0),J33,0)) | O33: =IF(A33="","",IF(A33=-1,J33,0)) | P33: =IF($I33<>"",$I33,IF($E33="SGD",1,IF($E33="USD",Settings!$B$22,IF($E33="HKD",Settings!$B$23,1)))) -> 1 | Q33: =IF($L33="",0,($O33-$N33+IF($A33=2,$J33,0))*$P33) -> 0 | R33: =IF($L33="",0,IF($A33=2,$J33*$P33,0)) -> 0 | S33: =IF(L33="","",SUMIFS($M:$M,$L:$L,L33,$T:$T,"<="&T33)) | T33: =IF(L33="","",INT(G33)*100000+ROW()) | U33: =IF(L33="","",IF(AND(COUNTIFS($L:$L,L33,$S:$S,">-0.000001",$S:$S,"<0.000001",$T:$T,">"&T33)=0,ABS(S33)>0.000001),1,0))
... L10001: =IF(OR(B10001="",C10001="",E10001=""),"",B10001&":"&C10001&":"&E10001) | M10001: =IF(A10001="","",IF(A10001=1,D10001,IF(A10001=-1,-D10001,0))) | N10001: =IF(A10001="","",IF(OR(A10001=1,A10001=0),J10001,0)) | O10001: =IF(A10001="","",IF(A10001=-1,J10001,0)) | P10001: =IF($I10001<>"",$I10001,IF($E10001="SGD",1,IF($E10001="USD",Settings!$B$22,IF($E10001="HKD",Settings!$B$23,1)))) -> 1 | Q10001: =IF($L10001="",0,($O10001-$N10001+IF($A10001=2,$J10001,0))*$P10001) -> 0 | R10001: =IF($L10001="",0,IF($A10001=2,$J10001*$P10001,0)) -> 0 | S10001: =IF(L10001="","",SUMIFS($M:$M,$L:$L,L10001,$T:$T,"<="&T10001)) | T10001: =IF(L10001="","",INT(G10001)*100000+ROW()) | U10001: =IF(L10001="","",IF(AND(COUNTIFS($L:$L,L10001,$S:$S,">-0.000001",$S:$S,"<0.000001",$T:$T,">"&T10001)=0,ABS(S10001)>0.000001),1,0))

Sheet Prices
A1: Key | B1: Exchange | C1: Symbol | D1: Currency | E1: Current Price | F1: FX to SGD | G1: Notes | H1: Category | J1: TICKER SYNC (live) | M1: Missing: | N1: =COUNTIF($N$4:$N$501,"ADD TO PRICES") -> 0 | P1: Stale: | Q1: =COUNTIF($Q$4:$Q$501,"NOT HELD - review") -> 0 | S1: HOW TO USE THIS PANEL
A2: CA:GOLD:SGD | B2: CA | C2: GOLD | D2: SGD | E2: 111.61 | F2: =IF($D2="SGD",1,IF($D2="USD",Settings!$B$22,IF($D2="HKD",Settings!$B$23,1))) -> 1 | G2: Sample price — update manually | H2: Gold & Silver | J2: Held now -> in Prices? | P2: Prices rows -> still held? | S2: Green = fine. Red 'ADD TO PRICES' = you hold it but it isn't in the price list on the left — add a row (paste the ticker into column A as values, then type the price).
A3: CG:BITCOIN:USD | B3: CG | C3: BITCOIN | D3: USD | E3: 102509.66 | F3: =IF($D3="SGD",1,IF($D3="USD",Settings!$B$22,IF($D3="HKD",Settings!$B$23,1))) -> 1.2928081 | G3: Sample price — update manually | H3: Crypto | J3: Key | K3: Exchange | L3: Symbol | M3: Currency | N3: Status | P3: Key | Q3: Status | S3: Red 'NOT HELD - review' = you have fully sold it — delete that price row.
A4: HKEX:700:HKD | B4: HKEX | C4: 700 | D4: HKD | E4: 488.2 | F4: =IF($D4="SGD",1,IF($D4="USD",Settings!$B$22,IF($D4="HKD",Settings!$B$23,1))) -> 0.16489949 | G4: Sample price — update manually | H4: US/HK Growth | J4: =IF(Shares!$A2="","",Shares!$A2) -> CA:GOLD:SGD | K4: =IF($J4="","",LEFT($J4,FIND(":",$J4)-1)) -> CA | L4: =IF($J4="","",MID($J4,FIND(":",$J4)+1,FIND(":",$J4,FIND(":",$J4)+1)-FIND(":",$J4)-1)) -> GOLD | M4: =IF($J4="","",RIGHT($J4,LEN($J4)-FIND(":",$J4,FIND(":",$J4)+1))) -> SGD | N4: =IF($J4="","",IF(ISNUMBER(MATCH($J4,Prices[Key],0)),"OK - in Prices","ADD TO PRICES")) -> OK - in Prices | P4: =IFERROR(INDEX(Prices[Key],ROWS($P$4:P4)),"") -> CA:GOLD:SGD | Q4: =IF($P4="","",IF(ISNUMBER(MATCH($P4,Shares!$A$2:$A$1001,0)),"held","NOT HELD - review")) -> held | S4: The Missing / Stale counts at the top should both read 0 when the price list matches your holdings.
A5: SGX:A17U:SGD | B5: SGX | C5: A17U | D5: SGD | E5: 2.74 | F5: =IF($D5="SGD",1,IF($D5="USD",Settings!$B$22,IF($D5="HKD",Settings!$B$23,1))) -> 1 | G5: Sample price — update manually | H5: Reit/Dividend | J5: =IF(Shares!$A3="","",Shares!$A3) -> SGX:Z74:SGD | K5: =IF($J5="","",LEFT($J5,FIND(":",$J5)-1)) -> SGX | L5: =IF($J5="","",MID($J5,FIND(":",$J5)+1,FIND(":",$J5,FIND(":",$J5)+1)-FIND(":",$J5)-1)) -> Z74 | M5: =IF($J5="","",RIGHT($J5,LEN($J5)-FIND(":",$J5,FIND(":",$J5)+1))) -> SGD | N5: =IF($J5="","",IF(ISNUMBER(MATCH($J5,Prices[Key],0)),"OK - in Prices","ADD TO PRICES")) -> OK - in Prices | P5: =IFERROR(INDEX(Prices[Key],ROWS($P$4:P5)),"") -> CG:BITCOIN:USD | Q5: =IF($P5="","",IF(ISNUMBER(MATCH($P5,Shares!$A$2:$A$1001,0)),"held","NOT HELD - review")) -> held | S5: Holdings look missing here? The Transactions helper columns (J–S) were probably cleared by a paste — go to Transactions and drag J–S down. See Start Here.
A6: SGX:C38U:SGD | B6: SGX | C6: C38U | D6: SGD | E6: 2.04 | F6: =IF($D6="SGD",1,IF($D6="USD",Settings!$B$22,IF($D6="HKD",Settings!$B$23,1))) -> 1 | G6: Sample price — update manually | H6: Reit/Dividend | J6: =IF(Shares!$A4="","",Shares!$A4) -> USX:AAPL:USD | K6: =IF($J6="","",LEFT($J6,FIND(":",$J6)-1)) -> USX | L6: =IF($J6="","",MID($J6,FIND(":",$J6)+1,FIND(":",$J6,FIND(":",$J6)+1)-FIND(":",$J6)-1)) -> AAPL | M6: =IF($J6="","",RIGHT($J6,LEN($J6)-FIND(":",$J6,FIND(":",$J6)+1))) -> USD | N6: =IF($J6="","",IF(ISNUMBER(MATCH($J6,Prices[Key],0)),"OK - in Prices","ADD TO PRICES")) -> OK - in Prices | P6: =IFERROR(INDEX(Prices[Key],ROWS($P$4:P6)),"") -> HKEX:700:HKD | Q6: =IF($P6="","",IF(ISNUMBER(MATCH($P6,Shares!$A$2:$A$1001,0)),"held","NOT HELD - review")) -> held | S6: Every held ticker also needs a Category (column H). A blank Category leaves that holding unclassified on the Allocation tab (which flags it) - fill it in.
A7: SGX:CLR:SGD | B7: SGX | C7: CLR | D7: SGD | E7: 0.815 | F7: =IF($D7="SGD",1,IF($D7="USD",Settings!$B$22,IF($D7="HKD",Settings!$B$23,1))) -> 1 | G7: Sample price — update manually | H7: Small Cap | J7: =IF(Shares!$A5="","",Shares!$A5) -> SGX:C38U:SGD | K7: =IF($J7="","",LEFT($J7,FIND(":",$J7)-1)) -> SGX | L7: =IF($J7="","",MID($J7,FIND(":",$J7)+1,FIND(":",$J7,FIND(":",$J7)+1)-FIND(":",$J7)-1)) -> C38U | M7: =IF($J7="","",RIGHT($J7,LEN($J7)-FIND(":",$J7,FIND(":",$J7)+1))) -> SGD | N7: =IF($J7="","",IF(ISNUMBER(MATCH($J7,Prices[Key],0)),"OK - in Prices","ADD TO PRICES")) -> OK - in Prices | P7: =IFERROR(INDEX(Prices[Key],ROWS($P$4:P7)),"") -> SGX:A17U:SGD | Q7: =IF($P7="","",IF(ISNUMBER(MATCH($P7,Shares!$A$2:$A$1001,0)),"held","NOT HELD - review")) -> held
A8: SGX:Z74:SGD | B8: SGX | C8: Z74 | D8: SGD | E8: 3.82 | F8: =IF($D8="SGD",1,IF($D8="USD",Settings!$B$22,IF($D8="HKD",Settings!$B$23,1))) -> 1 | G8: Sample price — update manually | H8: Reit/Dividend | J8: =IF(Shares!$A6="","",Shares!$A6) -> CG:BITCOIN:USD | K8: =IF($J8="","",LEFT($J8,FIND(":",$J8)-1)) -> CG | L8: =IF($J8="","",MID($J8,FIND(":",$J8)+1,FIND(":",$J8,FIND(":",$J8)+1)-FIND(":",$J8)-1)) -> BITCOIN | M8: =IF($J8="","",RIGHT($J8,LEN($J8)-FIND(":",$J8,FIND(":",$J8)+1))) -> USD | N8: =IF($J8="","",IF(ISNUMBER(MATCH($J8,Prices[Key],0)),"OK - in Prices","ADD TO PRICES")) -> OK - in Prices | P8: =IFERROR(INDEX(Prices[Key],ROWS($P$4:P8)),"") -> SGX:C38U:SGD | Q8: =IF($P8="","",IF(ISNUMBER(MATCH($P8,Shares!$A$2:$A$1001,0)),"held","NOT HELD - review")) -> held
A9: USX:AAPL:USD | B9: USX | C9: AAPL | D9: USD | E9: 200 | F9: =IF($D9="SGD",1,IF($D9="USD",Settings!$B$22,IF($D9="HKD",Settings!$B$23,1))) -> 1.2928081 | G9: Sample price — update manually | H9: US/HK Growth | J9: =IF(Shares!$A7="","",Shares!$A7) -> HKEX:700:HKD | K9: =IF($J9="","",LEFT($J9,FIND(":",$J9)-1)) -> HKEX | L9: =IF($J9="","",MID($J9,FIND(":",$J9)+1,FIND(":",$J9,FIND(":",$J9)+1)-FIND(":",$J9)-1)) -> 700 | M9: =IF($J9="","",RIGHT($J9,LEN($J9)-FIND(":",$J9,FIND(":",$J9)+1))) -> HKD | N9: =IF($J9="","",IF(ISNUMBER(MATCH($J9,Prices[Key],0)),"OK - in Prices","ADD TO PRICES")) -> OK - in Prices | P9: =IFERROR(INDEX(Prices[Key],ROWS($P$4:P9)),"") -> SGX:CLR:SGD | Q9: =IF($P9="","",IF(ISNUMBER(MATCH($P9,Shares!$A$2:$A$1001,0)),"held","NOT HELD - review")) -> held
A10: USX:MSFT:USD | B10: USX | C10: MSFT | D10: USD | E10: 420 | F10: =IF($D10="SGD",1,IF($D10="USD",Settings!$B$22,IF($D10="HKD",Settings!$B$23,1))) -> 1.2928081 | G10: Sample price — update manually | H10: US/HK Growth | J10: =IF(Shares!$A8="","",Shares!$A8) -> USX:MSFT:USD | K10: =IF($J10="","",LEFT($J10,FIND(":",$J10)-1)) -> USX | L10: =IF($J10="","",MID($J10,FIND(":",$J10)+1,FIND(":",$J10,FIND(":",$J10)+1)-FIND(":",$J10)-1)) -> MSFT | M10: =IF($J10="","",RIGHT($J10,LEN($J10)-FIND(":",$J10,FIND(":",$J10)+1))) -> USD | N10: =IF($J10="","",IF(ISNUMBER(MATCH($J10,Prices[Key],0)),"OK - in Prices","ADD TO PRICES")) -> OK - in Prices | P10: =IFERROR(INDEX(Prices[Key],ROWS($P$4:P10)),"") -> SGX:Z74:SGD | Q10: =IF($P10="","",IF(ISNUMBER(MATCH($P10,Shares!$A$2:$A$1001,0)),"held","NOT HELD - review")) -> held
J11: =IF(Shares!$A9="","",Shares!$A9) -> SGX:A17U:SGD | K11: =IF($J11="","",LEFT($J11,FIND(":",$J11)-1)) -> SGX | L11: =IF($J11="","",MID($J11,FIND(":",$J11)+1,FIND(":",$J11,FIND(":",$J11)+1)-FIND(":",$J11)-1)) -> A17U | M11: =IF($J11="","",RIGHT($J11,LEN($J11)-FIND(":",$J11,FIND(":",$J11)+1))) -> SGD | N11: =IF($J11="","",IF(ISNUMBER(MATCH($J11,Prices[Key],0)),"OK - in Prices","ADD TO PRICES")) -> OK - in Prices | P11: =IFERROR(INDEX(Prices[Key],ROWS($P$4:P11)),"") -> USX:AAPL:USD | Q11: =IF($P11="","",IF(ISNUMBER(MATCH($P11,Shares!$A$2:$A$1001,0)),"held","NOT HELD - review")) -> held
J12: =IF(Shares!$A10="","",Shares!$A10) -> SGX:CLR:SGD | K12: =IF($J12="","",LEFT($J12,FIND(":",$J12)-1)) -> SGX | L12: =IF($J12="","",MID($J12,FIND(":",$J12)+1,FIND(":",$J12,FIND(":",$J12)+1)-FIND(":",$J12)-1)) -> CLR | M12: =IF($J12="","",RIGHT($J12,LEN($J12)-FIND(":",$J12,FIND(":",$J12)+1))) -> SGD | N12: =IF($J12="","",IF(ISNUMBER(MATCH($J12,Prices[Key],0)),"OK - in Prices","ADD TO PRICES")) -> OK - in Prices | P12: =IFERROR(INDEX(Prices[Key],ROWS($P$4:P12)),"") -> USX:MSFT:USD | Q12: =IF($P12="","",IF(ISNUMBER(MATCH($P12,Shares!$A$2:$A$1001,0)),"held","NOT HELD - review")) -> held
J13: =IF(Shares!$A11="","",Shares!$A11) | K13: =IF($J13="","",LEFT($J13,FIND(":",$J13)-1)) | L13: =IF($J13="","",MID($J13,FIND(":",$J13)+1,FIND(":",$J13,FIND(":",$J13)+1)-FIND(":",$J13)-1)) | M13: =IF($J13="","",RIGHT($J13,LEN($J13)-FIND(":",$J13,FIND(":",$J13)+1))) | N13: =IF($J13="","",IF(ISNUMBER(MATCH($J13,Prices[Key],0)),"OK - in Prices","ADD TO PRICES")) | P13: =IFERROR(INDEX(Prices[Key],ROWS($P$4:P13)),"") | Q13: =IF($P13="","",IF(ISNUMBER(MATCH($P13,Shares!$A$2:$A$1001,0)),"held","NOT HELD - review"))
J14: =IF(Shares!$A12="","",Shares!$A12) | K14: =IF($J14="","",LEFT($J14,FIND(":",$J14)-1)) | L14: =IF($J14="","",MID($J14,FIND(":",$J14)+1,FIND(":",$J14,FIND(":",$J14)+1)-FIND(":",$J14)-1)) | M14: =IF($J14="","",RIGHT($J14,LEN($J14)-FIND(":",$J14,FIND(":",$J14)+1))) | N14: =IF($J14="","",IF(ISNUMBER(MATCH($J14,Prices[Key],0)),"OK - in Prices","ADD TO PRICES")) | P14: =IFERROR(INDEX(Prices[Key],ROWS($P$4:P14)),"") | Q14: =IF($P14="","",IF(ISNUMBER(MATCH($P14,Shares!$A$2:$A$1001,0)),"held","NOT HELD - review"))
J15: =IF(Shares!$A13="","",Shares!$A13) | K15: =IF($J15="","",LEFT($J15,FIND(":",$J15)-1)) | L15: =IF($J15="","",MID($J15,FIND(":",$J15)+1,FIND(":",$J15,FIND(":",$J15)+1)-FIND(":",$J15)-1)) | M15: =IF($J15="","",RIGHT($J15,LEN($J15)-FIND(":",$J15,FIND(":",$J15)+1))) | N15: =IF($J15="","",IF(ISNUMBER(MATCH($J15,Prices[Key],0)),"OK - in Prices","ADD TO PRICES")) | P15: =IFERROR(INDEX(Prices[Key],ROWS($P$4:P15)),"") | Q15: =IF($P15="","",IF(ISNUMBER(MATCH($P15,Shares!$A$2:$A$1001,0)),"held","NOT HELD - review"))
J16: =IF(Shares!$A14="","",Shares!$A14) | K16: =IF($J16="","",LEFT($J16,FIND(":",$J16)-1)) | L16: =IF($J16="","",MID($J16,FIND(":",$J16)+1,FIND(":",$J16,FIND(":",$J16)+1)-FIND(":",$J16)-1)) | M16: =IF($J16="","",RIGHT($J16,LEN($J16)-FIND(":",$J16,FIND(":",$J16)+1))) | N16: =IF($J16="","",IF(ISNUMBER(MATCH($J16,Prices[Key],0)),"OK - in Prices","ADD TO PRICES")) | P16: =IFERROR(INDEX(Prices[Key],ROWS($P$4:P16)),"") | Q16: =IF($P16="","",IF(ISNUMBER(MATCH($P16,Shares!$A$2:$A$1001,0)),"held","NOT HELD - review"))
J17: =IF(Shares!$A15="","",Shares!$A15) | K17: =IF($J17="","",LEFT($J17,FIND(":",$J17)-1)) | L17: =IF($J17="","",MID($J17,FIND(":",$J17)+1,FIND(":",$J17,FIND(":",$J17)+1)-FIND(":",$J17)-1)) | M17: =IF($J17="","",RIGHT($J17,LEN($J17)-FIND(":",$J17,FIND(":",$J17)+1))) | N17: =IF($J17="","",IF(ISNUMBER(MATCH($J17,Prices[Key],0)),"OK - in Prices","ADD TO PRICES")) | P17: =IFERROR(INDEX(Prices[Key],ROWS($P$4:P17)),"") | Q17: =IF($P17="","",IF(ISNUMBER(MATCH($P17,Shares!$A$2:$A$1001,0)),"held","NOT HELD - review"))
J18: =IF(Shares!$A16="","",Shares!$A16) | K18: =IF($J18="","",LEFT($J18,FIND(":",$J18)-1)) | L18: =IF($J18="","",MID($J18,FIND(":",$J18)+1,FIND(":",$J18,FIND(":",$J18)+1)-FIND(":",$J18)-1)) | M18: =IF($J18="","",RIGHT($J18,LEN($J18)-FIND(":",$J18,FIND(":",$J18)+1))) | N18: =IF($J18="","",IF(ISNUMBER(MATCH($J18,Prices[Key],0)),"OK - in Prices","ADD TO PRICES")) | P18: =IFERROR(INDEX(Prices[Key],ROWS($P$4:P18)),"") | Q18: =IF($P18="","",IF(ISNUMBER(MATCH($P18,Shares!$A$2:$A$1001,0)),"held","NOT HELD - review"))
J19: =IF(Shares!$A17="","",Shares!$A17) | K19: =IF($J19="","",LEFT($J19,FIND(":",$J19)-1)) | L19: =IF($J19="","",MID($J19,FIND(":",$J19)+1,FIND(":",$J19,FIND(":",$J19)+1)-FIND(":",$J19)-1)) | M19: =IF($J19="","",RIGHT($J19,LEN($J19)-FIND(":",$J19,FIND(":",$J19)+1))) | N19: =IF($J19="","",IF(ISNUMBER(MATCH($J19,Prices[Key],0)),"OK - in Prices","ADD TO PRICES")) | P19: =IFERROR(INDEX(Prices[Key],ROWS($P$4:P19)),"") | Q19: =IF($P19="","",IF(ISNUMBER(MATCH($P19,Shares!$A$2:$A$1001,0)),"held","NOT HELD - review"))
J20: =IF(Shares!$A18="","",Shares!$A18) | K20: =IF($J20="","",LEFT($J20,FIND(":",$J20)-1)) | L20: =IF($J20="","",MID($J20,FIND(":",$J20)+1,FIND(":",$J20,FIND(":",$J20)+1)-FIND(":",$J20)-1)) | M20: =IF($J20="","",RIGHT($J20,LEN($J20)-FIND(":",$J20,FIND(":",$J20)+1))) | N20: =IF($J20="","",IF(ISNUMBER(MATCH($J20,Prices[Key],0)),"OK - in Prices","ADD TO PRICES")) | P20: =IFERROR(INDEX(Prices[Key],ROWS($P$4:P20)),"") | Q20: =IF($P20="","",IF(ISNUMBER(MATCH($P20,Shares!$A$2:$A$1001,0)),"held","NOT HELD - review"))
J21: =IF(Shares!$A19="","",Shares!$A19) | K21: =IF($J21="","",LEFT($J21,FIND(":",$J21)-1)) | L21: =IF($J21="","",MID($J21,FIND(":",$J21)+1,FIND(":",$J21,FIND(":",$J21)+1)-FIND(":",$J21)-1)) | M21: =IF($J21="","",RIGHT($J21,LEN($J21)-FIND(":",$J21,FIND(":",$J21)+1))) | N21: =IF($J21="","",IF(ISNUMBER(MATCH($J21,Prices[Key],0)),"OK - in Prices","ADD TO PRICES")) | P21: =IFERROR(INDEX(Prices[Key],ROWS($P$4:P21)),"") | Q21: =IF($P21="","",IF(ISNUMBER(MATCH($P21,Shares!$A$2:$A$1001,0)),"held","NOT HELD - review"))
J22: =IF(Shares!$A20="","",Shares!$A20) | K22: =IF($J22="","",LEFT($J22,FIND(":",$J22)-1)) | L22: =IF($J22="","",MID($J22,FIND(":",$J22)+1,FIND(":",$J22,FIND(":",$J22)+1)-FIND(":",$J22)-1)) | M22: =IF($J22="","",RIGHT($J22,LEN($J22)-FIND(":",$J22,FIND(":",$J22)+1))) | N22: =IF($J22="","",IF(ISNUMBER(MATCH($J22,Prices[Key],0)),"OK - in Prices","ADD TO PRICES")) | P22: =IFERROR(INDEX(Prices[Key],ROWS($P$4:P22)),"") | Q22: =IF($P22="","",IF(ISNUMBER(MATCH($P22,Shares!$A$2:$A$1001,0)),"held","NOT HELD - review"))
... J501: =IF(Shares!$A499="","",Shares!$A499) | K501: =IF($J501="","",LEFT($J501,FIND(":",$J501)-1)) | L501: =IF($J501="","",MID($J501,FIND(":",$J501)+1,FIND(":",$J501,FIND(":",$J501)+1)-FIND(":",$J501)-1)) | M501: =IF($J501="","",RIGHT($J501,LEN($J501)-FIND(":",$J501,FIND(":",$J501)+1))) | N501: =IF($J501="","",IF(ISNUMBER(MATCH($J501,Prices[Key],0)),"OK - in Prices","ADD TO PRICES")) | P501: =IFERROR(INDEX(Prices[Key],ROWS($P$4:P501)),"") | Q501: =IF($P501="","",IF(ISNUMBER(MATCH($P501,Shares!$A$2:$A$1001,0)),"held","NOT HELD - review"))

Sheet Allocation
A1: PORTFOLIO ALLOCATION | N1: CATEGORY -> ASSET CLASS (edit)
A2: Weights across three lenses (Total / Investible / Risk). Edit the yellow maps at right; everything else recalculates from Shares and the Other assets block. | N2: Category | O2: Asset Class
N3: US/HK Growth | O3: Equity
A4: Lens | B4: Value (S$) | C4: Definition | N4: Small Cap | O4: Equity
A5: Total assets | B5: =SUM($H$30:$H$279)+SUM($C$22:$C$26) -> 208487.97 | C5: everything, incl. property | N5: Commodities | O5: Equity
A6: Investible | B6: =SUMIFS($B$11:$B$16,$T$11:$T$16,"Yes") -> 208487.97 | C6: total - real estate | N6: Reit/Dividend | O6: REIT
A7: Risk portfolio | B7: =SUMIFS($B$11:$B$16,$S$11:$S$16,"Yes") -> 120110 | C7: equity + REIT only | N7: Crypto | O7: Store of Value
N8: Gold & Silver | O8: Store of Value
A9: ALLOCATION BY ASSET CLASS
A10: Asset class | B10: Market value | C10: % Risk | D10: % Investible | E10: % Total | S10: Risk? | T10: Inv?
A11: Equity | B11: =SUMIFS($H$30:$H$279,$E$30:$E$279,$A11)+SUMIFS($C$22:$C$26,$B$22:$B$26,$A11) -> 81370 | C11: =IF($S11="Yes",IFERROR($B11/$B$7,""),"") -> 0.67746233 | D11: =IF($T11="Yes",IFERROR($B11/$B$6,""),"") -> 0.39028632 | E11: =IFERROR($B11/$B$5,"") -> 0.39028632 | S11: =IFERROR(INDEX($P$16:$P$21,MATCH($A11,$N$16:$N$21,0)),"No") -> Yes | T11: =IFERROR(INDEX($O$16:$O$21,MATCH($A11,$N$16:$N$21,0)),"No") -> Yes
A12: REIT | B12: =SUMIFS($H$30:$H$279,$E$30:$E$279,$A12)+SUMIFS($C$22:$C$26,$B$22:$B$26,$A12) -> 38740 | C12: =IF($S12="Yes",IFERROR($B12/$B$7,""),"") -> 0.32253767 | D12: =IF($T12="Yes",IFERROR($B12/$B$6,""),"") -> 0.18581408 | E12: =IFERROR($B12/$B$5,"") -> 0.18581408 | S12: =IFERROR(INDEX($P$16:$P$21,MATCH($A12,$N$16:$N$21,0)),"No") -> Yes | T12: =IFERROR(INDEX($O$16:$O$21,MATCH($A12,$N$16:$N$21,0)),"No") -> Yes
A13: Bond | B13: =SUMIFS($H$30:$H$279,$E$30:$E$279,$A13)+SUMIFS($C$22:$C$26,$B$22:$B$26,$A13) -> 0 | C13: =IF($S13="Yes",IFERROR($B13/$B$7,""),"") | D13: =IF($T13="Yes",IFERROR($B13/$B$6,""),"") -> 0 | E13: =IFERROR($B13/$B$5,"") -> 0 | S13: =IFERROR(INDEX($P$16:$P$21,MATCH($A13,$N$16:$N$21,0)),"No") -> No | T13: =IFERROR(INDEX($O$16:$O$21,MATCH($A13,$N$16:$N$21,0)),"No") -> Yes
A14: Store of Value | B14: =SUMIFS($H$30:$H$279,$E$30:$E$279,$A14)+SUMIFS($C$22:$C$26,$B$22:$B$26,$A14) -> 88377.966 | C14: =IF($S14="Yes",IFERROR($B14/$B$7,""),"") | D14: =IF($T14="Yes",IFERROR($B14/$B$6,""),"") -> 0.4238996 | E14: =IFERROR($B14/$B$5,"") -> 0.4238996 | N14: ASSET CLASS -> LENS (edit Yes/No) | S14: =IFERROR(INDEX($P$16:$P$21,MATCH($A14,$N$16:$N$21,0)),"No") -> No | T14: =IFERROR(INDEX($O$16:$O$21,MATCH($A14,$N$16:$N$21,0)),"No") -> Yes
A15: Cash/CPF | B15: =SUMIFS($H$30:$H$279,$E$30:$E$279,$A15)+SUMIFS($C$22:$C$26,$B$22:$B$26,$A15) -> 0 | C15: =IF($S15="Yes",IFERROR($B15/$B$7,""),"") | D15: =IF($T15="Yes",IFERROR($B15/$B$6,""),"") -> 0 | E15: =IFERROR($B15/$B$5,"") -> 0 | N15: Asset Class | O15: Investible? | P15: Risk? | S15: =IFERROR(INDEX($P$16:$P$21,MATCH($A15,$N$16:$N$21,0)),"No") -> No | T15: =IFERROR(INDEX($O$16:$O$21,MATCH($A15,$N$16:$N$21,0)),"No") -> Yes
A16: Real Estate | B16: =SUMIFS($H$30:$H$279,$E$30:$E$279,$A16)+SUMIFS($C$22:$C$26,$B$22:$B$26,$A16) -> 0 | C16: =IF($S16="Yes",IFERROR($B16/$B$7,""),"") | D16: =IF($T16="Yes",IFERROR($B16/$B$6,""),"") | E16: =IFERROR($B16/$B$5,"") -> 0 | N16: Equity | O16: Yes | P16: Yes | S16: =IFERROR(INDEX($P$16:$P$21,MATCH($A16,$N$16:$N$21,0)),"No") -> No | T16: =IFERROR(INDEX($O$16:$O$21,MATCH($A16,$N$16:$N$21,0)),"No") -> No
A17: Total | B17: =SUM($B$11:$B$16) -> 208487.97 | C17: =SUM($C$11:$C$16) -> 1 | D17: =SUM($D$11:$D$16) -> 1 | E17: =SUM($E$11:$E$16) -> 1 | N17: REIT | O17: Yes | P17: Yes
A18: =IF((COUNTIF(Shares!$A:$A,"?*")-1)>COUNT($A$30:$A$279),"WARNING: more holdings than the detail table captures - extend it","OK: all Shares holdings included") -> OK: all Shares holdings included | N18: Bond | O18: Yes | P18: No
A19: =IF(ROUND($B$5-SUM($B$11:$B$16),2)=0,"OK: every holding lands in an asset class","WARNING: S$"&TEXT($B$5-SUM($B$11:$B$16),"#,##0")&" of assets are unclassified - fill the blank/unknown Category on Prices") -> OK: every holding lands in an asset class | N19: Store of Value | O19: Yes | P19: No
A20: OTHER ASSETS (enter value or link to Balance Sheet; do not double-count anything already in your ledger) | N20: Cash/CPF | O20: Yes | P20: No
A21: Asset | B21: Asset Class | C21: Market Value (S$) | N21: Real Estate | O21: No | P21: No
A22: Primary Residence | B22: Real Estate
A23: Investment Property | B23: Real Estate
A24: CPF (OA/SA/MA) | B24: Cash/CPF
A25: Cash | B25: Cash/CPF
A28: HOLDINGS DETAIL (auto from Shares)
A29: No | B29: Symbol | C29: Exchange | D29: Category | E29: Asset Class | F29: Price | G29: Avg Cost | H29: Market Value | I29: % Risk | J29: % Investible | K29: % Total
A30: =IF(Shares!$A2="","",ROW()-29) -> 1 | B30: =IF(Shares!$A2="","",Shares!$C2) -> GOLD | C30: =IF(Shares!$A2="","",Shares!$B2) -> CA | D30: =IF(Shares!$A2="","",Shares!$O2) -> Gold & Silver | E30: =IF(Shares!$A2="","",IFERROR(INDEX($O$3:$O$40,MATCH(Shares!$O2,$N$3:$N$40,0)),"UNMAPPED")) -> Store of Value | F30: =IF(Shares!$A2="","",Shares!$I2) -> 111.61 | G30: =IF(Shares!$A2="","",Shares!$G2) -> 79.285714 | H30: =IF(Shares!$A2="","",Shares!$K2*Shares!$J2) -> 78127 | I30: =IF($E30="","",IF(IFERROR(INDEX($P$16:$P$21,MATCH($E30,$N$16:$N$21,0)),"No")="Yes",IFERROR($H30/$B$7,""),"")) | J30: =IF($E30="","",IF(IFERROR(INDEX($O$16:$O$21,MATCH($E30,$N$16:$N$21,0)),"No")="Yes",IFERROR($H30/$B$6,""),"")) -> 0.37473146 | K30: =IF($E30="","",IFERROR($H30/$B$5,"")) -> 0.37473146
A31: =IF(Shares!$A3="","",ROW()-29) -> 2 | B31: =IF(Shares!$A3="","",Shares!$C3) -> Z74 | C31: =IF(Shares!$A3="","",Shares!$B3) -> SGX | D31: =IF(Shares!$A3="","",Shares!$O3) -> Reit/Dividend | E31: =IF(Shares!$A3="","",IFERROR(INDEX($O$3:$O$40,MATCH(Shares!$O3,$N$3:$N$40,0)),"UNMAPPED")) -> REIT | F31: =IF(Shares!$A3="","",Shares!$I3) -> 3.82 | G31: =IF(Shares!$A3="","",Shares!$G3) -> 3.1083333 | H31: =IF(Shares!$A3="","",Shares!$K3*Shares!$J3) -> 11460 | I31: =IF($E31="","",IF(IFERROR(INDEX($P$16:$P$21,MATCH($E31,$N$16:$N$21,0)),"No")="Yes",IFERROR($H31/$B$7,""),"")) -> 0.095412539 | J31: =IF($E31="","",IF(IFERROR(INDEX($O$16:$O$21,MATCH($E31,$N$16:$N$21,0)),"No")="Yes",IFERROR($H31/$B$6,""),"")) -> 0.054967201 | K31: =IF($E31="","",IFERROR($H31/$B$5,"")) -> 0.054967201
A32: =IF(Shares!$A4="","",ROW()-29) -> 3 | B32: =IF(Shares!$A4="","",Shares!$C4) -> AAPL | C32: =IF(Shares!$A4="","",Shares!$B4) -> USX | D32: =IF(Shares!$A4="","",Shares!$O4) -> US/HK Growth | E32: =IF(Shares!$A4="","",IFERROR(INDEX($O$3:$O$40,MATCH(Shares!$O4,$N$3:$N$40,0)),"UNMAPPED")) -> Equity | F32: =IF(Shares!$A4="","",Shares!$I4) -> 200 | G32: =IF(Shares!$A4="","",Shares!$G4) -> 113.875 | H32: =IF(Shares!$A4="","",Shares!$K4*Shares!$J4) -> 16000 | I32: =IF($E32="","",IF(IFERROR(INDEX($P$16:$P$21,MATCH($E32,$N$16:$N$21,0)),"No")="Yes",IFERROR($H32/$B$7,""),"")) -> 0.13321122 | J32: =IF($E32="","",IF(IFERROR(INDEX($O$16:$O$21,MATCH($E32,$N$16:$N$21,0)),"No")="Yes",IFERROR($H32/$B$6,""),"")) -> 0.076743038 | K32: =IF($E32="","",IFERROR($H32/$B$5,"")) -> 0.076743038
A33: =IF(Shares!$A5="","",ROW()-29) -> 4 | B33: =IF(Shares!$A5="","",Shares!$C5) -> C38U | C33: =IF(Shares!$A5="","",Shares!$B5) -> SGX | D33: =IF(Shares!$A5="","",Shares!$O5) -> Reit/Dividend | E33: =IF(Shares!$A5="","",IFERROR(INDEX($O$3:$O$40,MATCH(Shares!$O5,$N$3:$N$40,0)),"UNMAPPED")) -> REIT | F33: =IF(Shares!$A5="","",Shares!$I5) -> 2.04 | G33: =IF(Shares!$A5="","",Shares!$G5) -> 2.01875 | H33: =IF(Shares!$A5="","",Shares!$K5*Shares!$J5) -> 16320 | I33: =IF($E33="","",IF(IFERROR(INDEX($P$16:$P$21,MATCH($E33,$N$16:$N$21,0)),"No")="Yes",IFERROR($H33/$B$7,""),"")) -> 0.13587545 | J33: =IF($E33="","",IF(IFERROR(INDEX($O$16:$O$21,MATCH($E33,$N$16:$N$21,0)),"No")="Yes",IFERROR($H33/$B$6,""),"")) -> 0.078277899 | K33: =IF($E33="","",IFERROR($H33/$B$5,"")) -> 0.078277899
A34: =IF(Shares!$A6="","",ROW()-29) -> 5 | B34: =IF(Shares!$A6="","",Shares!$C6) -> BITCOIN | C34: =IF(Shares!$A6="","",Shares!$B6) -> CG | D34: =IF(Shares!$A6="","",Shares!$O6) -> Crypto | E34: =IF(Shares!$A6="","",IFERROR(INDEX($O$3:$O$40,MATCH(Shares!$O6,$N$3:$N$40,0)),"UNMAPPED")) -> Store of Value | F34: =IF(Shares!$A6="","",Shares!$I6) -> 102509.66 | G34: =IF(Shares!$A6="","",Shares!$G6) -> 18500 | H34: =IF(Shares!$A6="","",Shares!$K6*Shares!$J6) -> 10250.966 | I34: =IF($E34="","",IF(IFERROR(INDEX($P$16:$P$21,MATCH($E34,$N$16:$N$21,0)),"No")="Yes",IFERROR($H34/$B$7,""),"")) | J34: =IF($E34="","",IF(IFERROR(INDEX($O$16:$O$21,MATCH($E34,$N$16:$N$21,0)),"No")="Yes",IFERROR($H34/$B$6,""),"")) -> 0.049168142 | K34: =IF($E34="","",IFERROR($H34/$B$5,"")) -> 0.049168142
A35: =IF(Shares!$A7="","",ROW()-29) -> 6 | B35: =IF(Shares!$A7="","",Shares!$C7) -> 700 | C35: =IF(Shares!$A7="","",Shares!$B7) -> HKEX | D35: =IF(Shares!$A7="","",Shares!$O7) -> US/HK Growth | E35: =IF(Shares!$A7="","",IFERROR(INDEX($O$3:$O$40,MATCH(Shares!$O7,$N$3:$N$40,0)),"UNMAPPED")) -> Equity | F35: =IF(Shares!$A7="","",Shares!$I7) -> 488.2 | G35: =IF(Shares!$A7="","",Shares!$G7) -> 601 | H35: =IF(Shares!$A7="","",Shares!$K7*Shares!$J7) -> 48820 | I35: =IF($E35="","",IF(IFERROR(INDEX($P$16:$P$21,MATCH($E35,$N$16:$N$21,0)),"No")="Yes",IFERROR($H35/$B$7,""),"")) -> 0.40646074 | J35: =IF($E35="","",IF(IFERROR(INDEX($O$16:$O$21,MATCH($E35,$N$16:$N$21,0)),"No")="Yes",IFERROR($H35/$B$6,""),"")) -> 0.2341622 | K35: =IF($E35="","",IFERROR($H35/$B$5,"")) -> 0.2341622
A36: =IF(Shares!$A8="","",ROW()-29) -> 7 | B36: =IF(Shares!$A8="","",Shares!$C8) -> MSFT | C36: =IF(Shares!$A8="","",Shares!$B8) -> USX | D36: =IF(Shares!$A8="","",Shares!$O8) -> US/HK Growth | E36: =IF(Shares!$A8="","",IFERROR(INDEX($O$3:$O$40,MATCH(Shares!$O8,$N$3:$N$40,0)),"UNMAPPED")) -> Equity | F36: =IF(Shares!$A8="","",Shares!$I8) -> 420 | G36: =IF(Shares!$A8="","",Shares!$G8) -> 230.25 | H36: =IF(Shares!$A8="","",Shares!$K8*Shares!$J8) -> 8400 | I36: =IF($E36="","",IF(IFERROR(INDEX($P$16:$P$21,MATCH($E36,$N$16:$N$21,0)),"No")="Yes",IFERROR($H36/$B$7,""),"")) -> 0.069935892 | J36: =IF($E36="","",IF(IFERROR(INDEX($O$16:$O$21,MATCH($E36,$N$16:$N$21,0)),"No")="Yes",IFERROR($H36/$B$6,""),"")) -> 0.040290095 | K36: =IF($E36="","",IFERROR($H36/$B$5,"")) -> 0.040290095
A37: =IF(Shares!$A9="","",ROW()-29) -> 8 | B37: =IF(Shares!$A9="","",Shares!$C9) -> A17U | C37: =IF(Shares!$A9="","",Shares!$B9) -> SGX | D37: =IF(Shares!$A9="","",Shares!$O9) -> Reit/Dividend | E37: =IF(Shares!$A9="","",IFERROR(INDEX($O$3:$O$40,MATCH(Shares!$O9,$N$3:$N$40,0)),"UNMAPPED")) -> REIT | F37: =IF(Shares!$A9="","",Shares!$I9) -> 2.74 | G37: =IF(Shares!$A9="","",Shares!$G9) -> 2.9625 | H37: =IF(Shares!$A9="","",Shares!$K9*Shares!$J9) -> 10960 | I37: =IF($E37="","",IF(IFERROR(INDEX($P$16:$P$21,MATCH($E37,$N$16:$N$21,0)),"No")="Yes",IFERROR($H37/$B$7,""),"")) -> 0.091249688 | J37: =IF($E37="","",IF(IFERROR(INDEX($O$16:$O$21,MATCH($E37,$N$16:$N$21,0)),"No")="Yes",IFERROR($H37/$B$6,""),"")) -> 0.052568981 | K37: =IF($E37="","",IFERROR($H37/$B$5,"")) -> 0.052568981
A38: =IF(Shares!$A10="","",ROW()-29) -> 9 | B38: =IF(Shares!$A10="","",Shares!$C10) -> CLR | C38: =IF(Shares!$A10="","",Shares!$B10) -> SGX | D38: =IF(Shares!$A10="","",Shares!$O10) -> Small Cap | E38: =IF(Shares!$A10="","",IFERROR(INDEX($O$3:$O$40,MATCH(Shares!$O10,$N$3:$N$40,0)),"UNMAPPED")) -> Equity | F38: =IF(Shares!$A10="","",Shares!$I10) -> 0.815 | G38: =IF(Shares!$A10="","",Shares!$G10) -> 0.7025 | H38: =IF(Shares!$A10="","",Shares!$K10*Shares!$J10) -> 8150 | I38: =IF($E38="","",IF(IFERROR(INDEX($P$16:$P$21,MATCH($E38,$N$16:$N$21,0)),"No")="Yes",IFERROR($H38/$B$7,""),"")) -> 0.067854467 | J38: =IF($E38="","",IF(IFERROR(INDEX($O$16:$O$21,MATCH($E38,$N$16:$N$21,0)),"No")="Yes",IFERROR($H38/$B$6,""),"")) -> 0.039090985 | K38: =IF($E38="","",IFERROR($H38/$B$5,"")) -> 0.039090985
A39: =IF(Shares!$A11="","",ROW()-29) | B39: =IF(Shares!$A11="","",Shares!$C11) | C39: =IF(Shares!$A11="","",Shares!$B11) | D39: =IF(Shares!$A11="","",Shares!$O11) | E39: =IF(Shares!$A11="","",IFERROR(INDEX($O$3:$O$40,MATCH(Shares!$O11,$N$3:$N$40,0)),"UNMAPPED")) | F39: =IF(Shares!$A11="","",Shares!$I11) | G39: =IF(Shares!$A11="","",Shares!$G11) | H39: =IF(Shares!$A11="","",Shares!$K11*Shares!$J11) | I39: =IF($E39="","",IF(IFERROR(INDEX($P$16:$P$21,MATCH($E39,$N$16:$N$21,0)),"No")="Yes",IFERROR($H39/$B$7,""),"")) | J39: =IF($E39="","",IF(IFERROR(INDEX($O$16:$O$21,MATCH($E39,$N$16:$N$21,0)),"No")="Yes",IFERROR($H39/$B$6,""),"")) | K39: =IF($E39="","",IFERROR($H39/$B$5,""))
A40: =IF(Shares!$A12="","",ROW()-29) | B40: =IF(Shares!$A12="","",Shares!$C12) | C40: =IF(Shares!$A12="","",Shares!$B12) | D40: =IF(Shares!$A12="","",Shares!$O12) | E40: =IF(Shares!$A12="","",IFERROR(INDEX($O$3:$O$40,MATCH(Shares!$O12,$N$3:$N$40,0)),"UNMAPPED")) | F40: =IF(Shares!$A12="","",Shares!$I12) | G40: =IF(Shares!$A12="","",Shares!$G12) | H40: =IF(Shares!$A12="","",Shares!$K12*Shares!$J12) | I40: =IF($E40="","",IF(IFERROR(INDEX($P$16:$P$21,MATCH($E40,$N$16:$N$21,0)),"No")="Yes",IFERROR($H40/$B$7,""),"")) | J40: =IF($E40="","",IF(IFERROR(INDEX($O$16:$O$21,MATCH($E40,$N$16:$N$21,0)),"No")="Yes",IFERROR($H40/$B$6,""),"")) | K40: =IF($E40="","",IFERROR($H40/$B$5,""))
A41: =IF(Shares!$A13="","",ROW()-29) | B41: =IF(Shares!$A13="","",Shares!$C13) | C41: =IF(Shares!$A13="","",Shares!$B13) | D41: =IF(Shares!$A13="","",Shares!$O13) | E41: =IF(Shares!$A13="","",IFERROR(INDEX($O$3:$O$40,MATCH(Shares!$O13,$N$3:$N$40,0)),"UNMAPPED")) | F41: =IF(Shares!$A13="","",Shares!$I13) | G41: =IF(Shares!$A13="","",Shares!$G13) | H41: =IF(Shares!$A13="","",Shares!$K13*Shares!$J13) | I41: =IF($E41="","",IF(IFERROR(INDEX($P$16:$P$21,MATCH($E41,$N$16:$N$21,0)),"No")="Yes",IFERROR($H41/$B$7,""),"")) | J41: =IF($E41="","",IF(IFERROR(INDEX($O$16:$O$21,MATCH($E41,$N$16:$N$21,0)),"No")="Yes",IFERROR($H41/$B$6,""),"")) | K41: =IF($E41="","",IFERROR($H41/$B$5,""))
... A279: =IF(Shares!$A251="","",ROW()-29) | B279: =IF(Shares!$A251="","",Shares!$C251) | C279: =IF(Shares!$A251="","",Shares!$B251) | D279: =IF(Shares!$A251="","",Shares!$O251) | E279: =IF(Shares!$A251="","",IFERROR(INDEX($O$3:$O$40,MATCH(Shares!$O251,$N$3:$N$40,0)),"UNMAPPED")) | F279: =IF(Shares!$A251="","",Shares!$I251) | G279: =IF(Shares!$A251="","",Shares!$G251) | H279: =IF(Shares!$A251="","",Shares!$K251*Shares!$J251) | I279: =IF($E279="","",IF(IFERROR(INDEX($P$16:$P$21,MATCH($E279,$N$16:$N$21,0)),"No")="Yes",IFERROR($H279/$B$7,""),"")) | J279: =IF($E279="","",IF(IFERROR(INDEX($O$16:$O$21,MATCH($E279,$N$16:$N$21,0)),"No")="Yes",IFERROR($H279/$B$6,""),"")) | K279: =IF($E279="","",IFERROR($H279/$B$5,""))

Sheet Stock Dashboard
A1: Portfolio Dashboard | Z1: Live Key | AA1: Live Exchange | AB1: Live Symbol | AC1: Live Currency | AD1: Live Units | AE1: Live Market Value SGD | AF1: Live Weight | AG1: Live P&L SGD | AH1: Live P&L % | AI1: Holding Rank | AJ1: Negative Rank | AL1: All Key | AM1: All Exchange | AN1: All Symbol | AO1: All Currency | AP1: All Units | AQ1: All Market Value SGD | AR1: All P&L SGD | AS1: All P&L % | AT1: Winner Rank | AU1: Loser Rank | AV1: Negative P&L Helper
A2: Current-state performance view. Performance over time lives on the Portfolio History tab; the XIRR engine is on Portfolio Analysis. | Z2: =Shares!A2 -> CA:GOLD:SGD | AA2: =Shares!B2 -> CA | AB2: =Shares!C2 -> GOLD | AC2: =Shares!D2 -> SGD | AD2: =IF($Z2="",0,Shares!E2) -> 700 | AE2: =IF($Z2="",0,Shares!K2*Shares!J2) -> 78127 | AF2: =IFERROR(AE2/$B$5,0) -> 0.43925024 | AG2: =IF($Z2="",0,Shares!M2) -> 22627 | AH2: =IF($Z2="",0,Shares!N2) -> 0.40769369 | AI2: =IF($Z2="","",RANK(AE2,$AE$2:$AE$1001)+COUNTIF($AE$2:AE2,AE2)-1) -> 1 | AJ2: =IF($AD2<0,COUNT($AJ$1:AJ1)+1,"") | AL2: ='All Ticker P&L'!A2 -> CA:GOLD:SGD | AM2: ='All Ticker P&L'!B2 -> CA | AN2: ='All Ticker P&L'!C2 -> GOLD | AO2: ='All Ticker P&L'!D2 -> SGD | AP2: =IF($AL2="",0,'All Ticker P&L'!E2) -> 700 | AQ2: =IF($AL2="",0,'All Ticker P&L'!J2*'All Ticker P&L'!I2) -> 78127 | AR2: =IF($AL2="",0,'All Ticker P&L'!L2) -> 22627 | AS2: =IF($AL2="",0,'All Ticker P&L'!M2) -> 0.40769369 | AT2: =IF($AL2="","",RANK(AR2,$AR$2:$AR$1001)+COUNTIF($AR$2:AR2,AR2)-1) -> 1 | AU2: =IF($AL2="","",RANK(AV2,$AV$2:$AV$1001)+COUNTIF($AV$2:AV2,AV2)-1) -> 1000 | AV2: =-AR2 -> -22627
A3: Current Snapshot | D3: Top 10 Holdings by Market Value | Z3: =Shares!A3 -> SGX:Z74:SGD | AA3: =Shares!B3 -> SGX | AB3: =Shares!C3 -> Z74 | AC3: =Shares!D3 -> SGD | AD3: =IF($Z3="",0,Shares!E3) -> 3000 | AE3: =IF($Z3="",0,Shares!K3*Shares!J3) -> 11460 | AF3: =IFERROR(AE3/$B$5,0) -> 0.06443109 | AG3: =IF($Z3="",0,Shares!M3) -> 2135 | AH3: =IF($Z3="",0,Shares!N3) -> 0.22895442 | AI3: =IF($Z3="","",RANK(AE3,$AE$2:$AE$1001)+COUNTIF($AE$2:AE3,AE3)-1) -> 5 | AJ3: =IF($AD3<0,COUNT($AJ$1:AJ2)+1,"") | AL3: ='All Ticker P&L'!A3 -> SGX:Z74:SGD | AM3: ='All Ticker P&L'!B3 -> SGX | AN3: ='All Ticker P&L'!C3 -> Z74 | AO3: ='All Ticker P&L'!D3 -> SGD | AP3: =IF($AL3="",0,'All Ticker P&L'!E3) -> 3000 | AQ3: =IF($AL3="",0,'All Ticker P&L'!J3*'All Ticker P&L'!I3) -> 11460 | AR3: =IF($AL3="",0,'All Ticker P&L'!L3) -> 2135 | AS3: =IF($AL3="",0,'All Ticker P&L'!M3) -> 0.22895442 | AT3: =IF($AL3="","",RANK(AR3,$AR$2:$AR$1001)+COUNTIF($AR$2:AR3,AR3)-1) -> 6 | AU3: =IF($AL3="","",RANK(AV3,$AV$2:$AV$1001)+COUNTIF($AV$2:AV3,AV3)-1) -> 995 | AV3: =-AR3 -> -2135
A4: Open positions count | B4: =COUNTIF($Z$2:$Z$1001,"?*") -> 9 | D4: Rank | E4: Key | F4: Exchange | G4: Currency | H4: Market Value SGD | I4: Weight | J4: P&L SGD | K4: P&L % | Z4: =Shares!A4 -> USX:AAPL:USD | AA4: =Shares!B4 -> USX | AB4: =Shares!C4 -> AAPL | AC4: =Shares!D4 -> USD | AD4: =IF($Z4="",0,Shares!E4) -> 80 | AE4: =IF($Z4="",0,Shares!K4*Shares!J4) -> 20684.93 | AF4: =IFERROR(AE4/$B$5,0) -> 0.11629604 | AG4: =IF($Z4="",0,Shares!M4) -> 8907.4479 | AH4: =IF($Z4="",0,Shares!N4) -> 0.75631175 | AI4: =IF($Z4="","",RANK(AE4,$AE$2:$AE$1001)+COUNTIF($AE$2:AE4,AE4)-1) -> 2 | AJ4: =IF($AD4<0,COUNT($AJ$1:AJ3)+1,"") | AL4: ='All Ticker P&L'!A4 -> USX:AAPL:USD | AM4: ='All Ticker P&L'!B4 -> USX | AN4: ='All Ticker P&L'!C4 -> AAPL | AO4: ='All Ticker P&L'!D4 -> USD | AP4: =IF($AL4="",0,'All Ticker P&L'!E4) -> 80 | AQ4: =IF($AL4="",0,'All Ticker P&L'!J4*'All Ticker P&L'!I4) -> 20684.93 | AR4: =IF($AL4="",0,'All Ticker P&L'!L4) -> 8907.4479 | AS4: =IF($AL4="",0,'All Ticker P&L'!M4) -> 0.75631175 | AT4: =IF($AL4="","",RANK(AR4,$AR$2:$AR$1001)+COUNTIF($AR$2:AR4,AR4)-1) -> 4 | AU4: =IF($AL4="","",RANK(AV4,$AV$2:$AV$1001)+COUNTIF($AV$2:AV4,AV4)-1) -> 997 | AV4: =-AR4 -> -8907.4479
A5: Portfolio market value SGD | B5: =SUM($AE$2:$AE$1001) -> 177864.44 | D5: 1 | E5: =IFERROR(INDEX($Z$2:$Z$1001,MATCH($D5,$AI$2:$AI$1001,0)),"") -> CA:GOLD:SGD | F5: =IF($E5="","",INDEX($AA$2:$AA$1001,MATCH($D5,$AI$2:$AI$1001,0))) -> CA | G5: =IF($E5="","",INDEX($AC$2:$AC$1001,MATCH($D5,$AI$2:$AI$1001,0))) -> SGD | H5: =IF($E5="","",INDEX($AE$2:$AE$1001,MATCH($D5,$AI$2:$AI$1001,0))) -> 78127 | I5: =IF($E5="","",INDEX($AF$2:$AF$1001,MATCH($D5,$AI$2:$AI$1001,0))) -> 0.43925024 | J5: =IF($E5="","",INDEX($AG$2:$AG$1001,MATCH($D5,$AI$2:$AI$1001,0))) -> 22627 | K5: =IF($E5="","",INDEX($AH$2:$AH$1001,MATCH($D5,$AI$2:$AI$1001,0))) -> 0.40769369 | Z5: =Shares!A5 -> SGX:C38U:SGD | AA5: =Shares!B5 -> SGX | AB5: =Shares!C5 -> C38U | AC5: =Shares!D5 -> SGD | AD5: =IF($Z5="",0,Shares!E5) -> 8000 | AE5: =IF($Z5="",0,Shares!K5*Shares!J5) -> 16320 | AF5: =IFERROR(AE5/$B$5,0) -> 0.09175527 | AG5: =IF($Z5="",0,Shares!M5) -> 170 | AH5: =IF($Z5="",0,Shares!N5) -> 0.010526316 | AI5: =IF($Z5="","",RANK(AE5,$AE$2:$AE$1001)+COUNTIF($AE$2:AE5,AE5)-1) -> 3 | AJ5: =IF($AD5<0,COUNT($AJ$1:AJ4)+1,"") | AL5: ='All Ticker P&L'!A5 -> SGX:C38U:SGD | AM5: ='All Ticker P&L'!B5 -> SGX | AN5: ='All Ticker P&L'!C5 -> C38U | AO5: ='All Ticker P&L'!D5 -> SGD | AP5: =IF($AL5="",0,'All Ticker P&L'!E5) -> 8000 | AQ5: =IF($AL5="",0,'All Ticker P&L'!J5*'All Ticker P&L'!I5) -> 16320 | AR5: =IF($AL5="",0,'All Ticker P&L'!L5) -> 170 | AS5: =IF($AL5="",0,'All Ticker P&L'!M5) -> 0.010526316 | AT5: =IF($AL5="","",RANK(AR5,$AR$2:$AR$1001)+COUNTIF($AR$2:AR5,AR5)-1) -> 8 | AU5: =IF($AL5="","",RANK(AV5,$AV$2:$AV$1001)+COUNTIF($AV$2:AV5,AV5)-1) -> 993 | AV5: =-AR5 -> -170
A6: Total buy cost SGD | B6: =SUMPRODUCT('All Ticker P&L'!$F$2:$F$1001,'All Ticker P&L'!$I$2:$I$1001) -> 134688.02 | D6: 2 | E6: =IFERROR(INDEX($Z$2:$Z$1001,MATCH($D6,$AI$2:$AI$1001,0)),"") -> USX:AAPL:USD | F6: =IF($E6="","",INDEX($AA$2:$AA$1001,MATCH($D6,$AI$2:$AI$1001,0))) -> USX | G6: =IF($E6="","",INDEX($AC$2:$AC$1001,MATCH($D6,$AI$2:$AI$1001,0))) -> USD | H6: =IF($E6="","",INDEX($AE$2:$AE$1001,MATCH($D6,$AI$2:$AI$1001,0))) -> 20684.93 | I6: =IF($E6="","",INDEX($AF$2:$AF$1001,MATCH($D6,$AI$2:$AI$1001,0))) -> 0.11629604 | J6: =IF($E6="","",INDEX($AG$2:$AG$1001,MATCH($D6,$AI$2:$AI$1001,0))) -> 8907.4479 | K6: =IF($E6="","",INDEX($AH$2:$AH$1001,MATCH($D6,$AI$2:$AI$1001,0))) -> 0.75631175 | Z6: =Shares!A6 -> CG:BITCOIN:USD | AA6: =Shares!B6 -> CG | AB6: =Shares!C6 -> BITCOIN | AC6: =Shares!D6 -> USD | AD6: =IF($Z6="",0,Shares!E6) -> 0.1 | AE6: =IF($Z6="",0,Shares!K6*Shares!J6) -> 13252.532 | AF6: =IFERROR(AE6/$B$5,0) -> 0.07450917 | AG6: =IF($Z6="",0,Shares!M6) -> 10860.837 | AH6: =IF($Z6="",0,Shares!N6) -> 4.5410627 | AI6: =IF($Z6="","",RANK(AE6,$AE$2:$AE$1001)+COUNTIF($AE$2:AE6,AE6)-1) -> 4 | AJ6: =IF($AD6<0,COUNT($AJ$1:AJ5)+1,"") | AL6: ='All Ticker P&L'!A6 -> CG:BITCOIN:USD | AM6: ='All Ticker P&L'!B6 -> CG | AN6: ='All Ticker P&L'!C6 -> BITCOIN | AO6: ='All Ticker P&L'!D6 -> USD | AP6: =IF($AL6="",0,'All Ticker P&L'!E6) -> 0.1 | AQ6: =IF($AL6="",0,'All Ticker P&L'!J6*'All Ticker P&L'!I6) -> 13252.532 | AR6: =IF($AL6="",0,'All Ticker P&L'!L6) -> 10860.837 | AS6: =IF($AL6="",0,'All Ticker P&L'!M6) -> 4.5410627 | AT6: =IF($AL6="","",RANK(AR6,$AR$2:$AR$1001)+COUNTIF($AR$2:AR6,AR6)-1) -> 3 | AU6: =IF($AL6="","",RANK(AV6,$AV$2:$AV$1001)+COUNTIF($AV$2:AV6,AV6)-1) -> 998 | AV6: =-AR6 -> -10860.837
A7: Total sell proceeds SGD | B7: =SUMPRODUCT('All Ticker P&L'!$G$2:$G$1001,'All Ticker P&L'!$I$2:$I$1001) -> 17995 | D7: 3 | E7: =IFERROR(INDEX($Z$2:$Z$1001,MATCH($D7,$AI$2:$AI$1001,0)),"") -> SGX:C38U:SGD | F7: =IF($E7="","",INDEX($AA$2:$AA$1001,MATCH($D7,$AI$2:$AI$1001,0))) -> SGX | G7: =IF($E7="","",INDEX($AC$2:$AC$1001,MATCH($D7,$AI$2:$AI$1001,0))) -> SGD | H7: =IF($E7="","",INDEX($AE$2:$AE$1001,MATCH($D7,$AI$2:$AI$1001,0))) -> 16320 | I7: =IF($E7="","",INDEX($AF$2:$AF$1001,MATCH($D7,$AI$2:$AI$1001,0))) -> 0.09175527 | J7: =IF($E7="","",INDEX($AG$2:$AG$1001,MATCH($D7,$AI$2:$AI$1001,0))) -> 170 | K7: =IF($E7="","",INDEX($AH$2:$AH$1001,MATCH($D7,$AI$2:$AI$1001,0))) -> 0.010526316 | Z7: =Shares!A7 -> HKEX:700:HKD | AA7: =Shares!B7 -> HKEX | AB7: =Shares!C7 -> 700 | AC7: =Shares!D7 -> HKD | AD7: =IF($Z7="",0,Shares!E7) -> 100 | AE7: =IF($Z7="",0,Shares!K7*Shares!J7) -> 8050.3933 | AF7: =IFERROR(AE7/$B$5,0) -> 0.045261398 | AG7: =IF($Z7="",0,Shares!M7) -> -1860.0663 | AH7: =IF($Z7="",0,Shares!N7) -> -0.18768719 | AI7: =IF($Z7="","",RANK(AE7,$AE$2:$AE$1001)+COUNTIF($AE$2:AE7,AE7)-1) -> 9 | AJ7: =IF($AD7<0,COUNT($AJ$1:AJ6)+1,"") | AL7: ='All Ticker P&L'!A7 -> HKEX:700:HKD | AM7: ='All Ticker P&L'!B7 -> HKEX | AN7: ='All Ticker P&L'!C7 -> 700 | AO7: ='All Ticker P&L'!D7 -> HKD | AP7: =IF($AL7="",0,'All Ticker P&L'!E7) -> 100 | AQ7: =IF($AL7="",0,'All Ticker P&L'!J7*'All Ticker P&L'!I7) -> 8050.3933 | AR7: =IF($AL7="",0,'All Ticker P&L'!L7) -> -1860.0663 | AS7: =IF($AL7="",0,'All Ticker P&L'!M7) -> -0.18768719 | AT7: =IF($AL7="","",RANK(AR7,$AR$2:$AR$1001)+COUNTIF($AR$2:AR7,AR7)-1) -> 1000 | AU7: =IF($AL7="","",RANK(AV7,$AV$2:$AV$1001)+COUNTIF($AV$2:AV7,AV7)-1) -> 1 | AV7: =-AR7 -> 1860.0663
A8: Open positions P&L SGD | B8: =SUM($AG$2:$AG$1001) -> 47981.425 | D8: 4 | E8: =IFERROR(INDEX($Z$2:$Z$1001,MATCH($D8,$AI$2:$AI$1001,0)),"") -> CG:BITCOIN:USD | F8: =IF($E8="","",INDEX($AA$2:$AA$1001,MATCH($D8,$AI$2:$AI$1001,0))) -> CG | G8: =IF($E8="","",INDEX($AC$2:$AC$1001,MATCH($D8,$AI$2:$AI$1001,0))) -> USD | H8: =IF($E8="","",INDEX($AE$2:$AE$1001,MATCH($D8,$AI$2:$AI$1001,0))) -> 13252.532 | I8: =IF($E8="","",INDEX($AF$2:$AF$1001,MATCH($D8,$AI$2:$AI$1001,0))) -> 0.07450917 | J8: =IF($E8="","",INDEX($AG$2:$AG$1001,MATCH($D8,$AI$2:$AI$1001,0))) -> 10860.837 | K8: =IF($E8="","",INDEX($AH$2:$AH$1001,MATCH($D8,$AI$2:$AI$1001,0))) -> 4.5410627 | Z8: =Shares!A8 -> USX:MSFT:USD | AA8: =Shares!B8 -> USX | AB8: =Shares!C8 -> MSFT | AC8: =Shares!D8 -> USD | AD8: =IF($Z8="",0,Shares!E8) -> 20 | AE8: =IF($Z8="",0,Shares!K8*Shares!J8) -> 10859.588 | AF8: =IFERROR(AE8/$B$5,0) -> 0.061055419 | AG8: =IF($Z8="",0,Shares!M8) -> 4906.2068 | AH8: =IF($Z8="",0,Shares!N8) -> 0.82410423 | AI8: =IF($Z8="","",RANK(AE8,$AE$2:$AE$1001)+COUNTIF($AE$2:AE8,AE8)-1) -> 7 | AJ8: =IF($AD8<0,COUNT($AJ$1:AJ7)+1,"") | AL8: ='All Ticker P&L'!A8 -> USX:MSFT:USD | AM8: ='All Ticker P&L'!B8 -> USX | AN8: ='All Ticker P&L'!C8 -> MSFT | AO8: ='All Ticker P&L'!D8 -> USD | AP8: =IF($AL8="",0,'All Ticker P&L'!E8) -> 20 | AQ8: =IF($AL8="",0,'All Ticker P&L'!J8*'All Ticker P&L'!I8) -> 10859.588 | AR8: =IF($AL8="",0,'All Ticker P&L'!L8) -> 4906.2068 | AS8: =IF($AL8="",0,'All Ticker P&L'!M8) -> 0.82410423 | AT8: =IF($AL8="","",RANK(AR8,$AR$2:$AR$1001)+COUNTIF($AR$2:AR8,AR8)-1) -> 5 | AU8: =IF($AL8="","",RANK(AV8,$AV$2:$AV$1001)+COUNTIF($AV$2:AV8,AV8)-1) -> 996 | AV8: =-AR8 -> -4906.2068
A9: Closed positions P&L SGD | B9: =SUMIFS('All Ticker P&L'!$L$2:$L$1001,'All Ticker P&L'!$E$2:$E$1001,0) -> 13190 | D9: 5 | E9: =IFERROR(INDEX($Z$2:$Z$1001,MATCH($D9,$AI$2:$AI$1001,0)),"") -> SGX:Z74:SGD | F9: =IF($E9="","",INDEX($AA$2:$AA$1001,MATCH($D9,$AI$2:$AI$1001,0))) -> SGX | G9: =IF($E9="","",INDEX($AC$2:$AC$1001,MATCH($D9,$AI$2:$AI$1001,0))) -> SGD | H9: =IF($E9="","",INDEX($AE$2:$AE$1001,MATCH($D9,$AI$2:$AI$1001,0))) -> 11460 | I9: =IF($E9="","",INDEX($AF$2:$AF$1001,MATCH($D9,$AI$2:$AI$1001,0))) -> 0.06443109 | J9: =IF($E9="","",INDEX($AG$2:$AG$1001,MATCH($D9,$AI$2:$AI$1001,0))) -> 2135 | K9: =IF($E9="","",INDEX($AH$2:$AH$1001,MATCH($D9,$AI$2:$AI$1001,0))) -> 0.22895442 | Z9: =Shares!A9 -> SGX:A17U:SGD | AA9: =Shares!B9 -> SGX | AB9: =Shares!C9 -> A17U | AC9: =Shares!D9 -> SGD | AD9: =IF($Z9="",0,Shares!E9) -> 4000 | AE9: =IF($Z9="",0,Shares!K9*Shares!J9) -> 10960 | AF9: =IFERROR(AE9/$B$5,0) -> 0.061619961 | AG9: =IF($Z9="",0,Shares!M9) -> -890 | AH9: =IF($Z9="",0,Shares!N9) -> -0.075105485 | AI9: =IF($Z9="","",RANK(AE9,$AE$2:$AE$1001)+COUNTIF($AE$2:AE9,AE9)-1) -> 6 | AJ9: =IF($AD9<0,COUNT($AJ$1:AJ8)+1,"") | AL9: ='All Ticker P&L'!A9 -> SGX:A17U:SGD | AM9: ='All Ticker P&L'!B9 -> SGX | AN9: ='All Ticker P&L'!C9 -> A17U | AO9: ='All Ticker P&L'!D9 -> SGD | AP9: =IF($AL9="",0,'All Ticker P&L'!E9) -> 4000 | AQ9: =IF($AL9="",0,'All Ticker P&L'!J9*'All Ticker P&L'!I9) -> 10960 | AR9: =IF($AL9="",0,'All Ticker P&L'!L9) -> -890 | AS9: =IF($AL9="",0,'All Ticker P&L'!M9) -> -0.075105485 | AT9: =IF($AL9="","",RANK(AR9,$AR$2:$AR$1001)+COUNTIF($AR$2:AR9,AR9)-1) -> 999 | AU9: =IF($AL9="","",RANK(AV9,$AV$2:$AV$1001)+COUNTIF($AV$2:AV9,AV9)-1) -> 2 | AV9: =-AR9 -> 890
A10: Total P&L SGD | B10: =SUM('All Ticker P&L'!$L$2:$L$1001) -> 61171.425 | D10: 6 | E10: =IFERROR(INDEX($Z$2:$Z$1001,MATCH($D10,$AI$2:$AI$1001,0)),"") -> SGX:A17U:SGD | F10: =IF($E10="","",INDEX($AA$2:$AA$1001,MATCH($D10,$AI$2:$AI$1001,0))) -> SGX | G10: =IF($E10="","",INDEX($AC$2:$AC$1001,MATCH($D10,$AI$2:$AI$1001,0))) -> SGD | H10: =IF($E10="","",INDEX($AE$2:$AE$1001,MATCH($D10,$AI$2:$AI$1001,0))) -> 10960 | I10: =IF($E10="","",INDEX($AF$2:$AF$1001,MATCH($D10,$AI$2:$AI$1001,0))) -> 0.061619961 | J10: =IF($E10="","",INDEX($AG$2:$AG$1001,MATCH($D10,$AI$2:$AI$1001,0))) -> -890 | K10: =IF($E10="","",INDEX($AH$2:$AH$1001,MATCH($D10,$AI$2:$AI$1001,0))) -> -0.075105485 | Z10: =Shares!A10 -> SGX:CLR:SGD | AA10: =Shares!B10 -> SGX | AB10: =Shares!C10 -> CLR | AC10: =Shares!D10 -> SGD | AD10: =IF($Z10="",0,Shares!E10) -> 10000 | AE10: =IF($Z10="",0,Shares!K10*Shares!J10) -> 8150 | AF10: =IFERROR(AE10/$B$5,0) -> 0.045821412 | AG10: =IF($Z10="",0,Shares!M10) -> 1125 | AH10: =IF($Z10="",0,Shares!N10) -> 0.16014235 | AI10: =IF($Z10="","",RANK(AE10,$AE$2:$AE$1001)+COUNTIF($AE$2:AE10,AE10)-1) -> 8 | AJ10: =IF($AD10<0,COUNT($AJ$1:AJ9)+1,"") | AL10: ='All Ticker P&L'!A10 -> USX:NVDA:USD | AM10: ='All Ticker P&L'!B10 -> USX | AN10: ='All Ticker P&L'!C10 -> NVDA | AO10: ='All Ticker P&L'!D10 -> USD | AP10: =IF($AL10="",0,'All Ticker P&L'!E10) -> 0 | AQ10: =IF($AL10="",0,'All Ticker P&L'!J10*'All Ticker P&L'!I10) -> 0 | AR10: =IF($AL10="",0,'All Ticker P&L'!L10) -> 13190 | AS10: =IF($AL10="",0,'All Ticker P&L'!M10) -> 2.7450572 | AT10: =IF($AL10="","",RANK(AR10,$AR$2:$AR$1001)+COUNTIF($AR$2:AR10,AR10)-1) -> 2 | AU10: =IF($AL10="","",RANK(AV10,$AV$2:$AV$1001)+COUNTIF($AV$2:AV10,AV10)-1) -> 999 | AV10: =-AR10 -> -13190
A11: Total return on buy cost | B11: =IFERROR($B$10/$B$6,0) -> 0.45417125 | D11: 7 | E11: =IFERROR(INDEX($Z$2:$Z$1001,MATCH($D11,$AI$2:$AI$1001,0)),"") -> USX:MSFT:USD | F11: =IF($E11="","",INDEX($AA$2:$AA$1001,MATCH($D11,$AI$2:$AI$1001,0))) -> USX | G11: =IF($E11="","",INDEX($AC$2:$AC$1001,MATCH($D11,$AI$2:$AI$1001,0))) -> USD | H11: =IF($E11="","",INDEX($AE$2:$AE$1001,MATCH($D11,$AI$2:$AI$1001,0))) -> 10859.588 | I11: =IF($E11="","",INDEX($AF$2:$AF$1001,MATCH($D11,$AI$2:$AI$1001,0))) -> 0.061055419 | J11: =IF($E11="","",INDEX($AG$2:$AG$1001,MATCH($D11,$AI$2:$AI$1001,0))) -> 4906.2068 | K11: =IF($E11="","",INDEX($AH$2:$AH$1001,MATCH($D11,$AI$2:$AI$1001,0))) -> 0.82410423 | Z11: =Shares!A11 | AA11: =Shares!B11 | AB11: =Shares!C11 | AC11: =Shares!D11 | AD11: =IF($Z11="",0,Shares!E11) -> 0 | AE11: =IF($Z11="",0,Shares!K11*Shares!J11) -> 0 | AF11: =IFERROR(AE11/$B$5,0) -> 0 | AG11: =IF($Z11="",0,Shares!M11) -> 0 | AH11: =IF($Z11="",0,Shares!N11) -> 0 | AI11: =IF($Z11="","",RANK(AE11,$AE$2:$AE$1001)+COUNTIF($AE$2:AE11,AE11)-1) | AJ11: =IF($AD11<0,COUNT($AJ$1:AJ10)+1,"") | AL11: ='All Ticker P&L'!A11 -> SGX:CLR:SGD | AM11: ='All Ticker P&L'!B11 -> SGX | AN11: ='All Ticker P&L'!C11 -> CLR | AO11: ='All Ticker P&L'!D11 -> SGD | AP11: =IF($AL11="",0,'All Ticker P&L'!E11) -> 10000 | AQ11: =IF($AL11="",0,'All Ticker P&L'!J11*'All Ticker P&L'!I11) -> 8150 | AR11: =IF($AL11="",0,'All Ticker P&L'!L11) -> 1125 | AS11: =IF($AL11="",0,'All Ticker P&L'!M11) -> 0.16014235 | AT11: =IF($AL11="","",RANK(AR11,$AR$2:$AR$1001)+COUNTIF($AR$2:AR11,AR11)-1) -> 7 | AU11: =IF($AL11="","",RANK(AV11,$AV$2:$AV$1001)+COUNTIF($AV$2:AV11,AV11)-1) -> 994 | AV11: =-AR11 -> -1125
A12: Top holding concentration | B12: =IFERROR(MAX($AF$2:$AF$1001),0) -> 0.43925024 | D12: 8 | E12: =IFERROR(INDEX($Z$2:$Z$1001,MATCH($D12,$AI$2:$AI$1001,0)),"") -> SGX:CLR:SGD | F12: =IF($E12="","",INDEX($AA$2:$AA$1001,MATCH($D12,$AI$2:$AI$1001,0))) -> SGX | G12: =IF($E12="","",INDEX($AC$2:$AC$1001,MATCH($D12,$AI$2:$AI$1001,0))) -> SGD | H12: =IF($E12="","",INDEX($AE$2:$AE$1001,MATCH($D12,$AI$2:$AI$1001,0))) -> 8150 | I12: =IF($E12="","",INDEX($AF$2:$AF$1001,MATCH($D12,$AI$2:$AI$1001,0))) -> 0.045821412 | J12: =IF($E12="","",INDEX($AG$2:$AG$1001,MATCH($D12,$AI$2:$AI$1001,0))) -> 1125 | K12: =IF($E12="","",INDEX($AH$2:$AH$1001,MATCH($D12,$AI$2:$AI$1001,0))) -> 0.16014235 | Z12: =Shares!A12 | AA12: =Shares!B12 | AB12: =Shares!C12 | AC12: =Shares!D12 | AD12: =IF($Z12="",0,Shares!E12) -> 0 | AE12: =IF($Z12="",0,Shares!K12*Shares!J12) -> 0 | AF12: =IFERROR(AE12/$B$5,0) -> 0 | AG12: =IF($Z12="",0,Shares!M12) -> 0 | AH12: =IF($Z12="",0,Shares!N12) -> 0 | AI12: =IF($Z12="","",RANK(AE12,$AE$2:$AE$1001)+COUNTIF($AE$2:AE12,AE12)-1) | AJ12: =IF($AD12<0,COUNT($AJ$1:AJ11)+1,"") | AL12: ='All Ticker P&L'!A12 | AM12: ='All Ticker P&L'!B12 | AN12: ='All Ticker P&L'!C12 | AO12: ='All Ticker P&L'!D12 | AP12: =IF($AL12="",0,'All Ticker P&L'!E12) -> 0 | AQ12: =IF($AL12="",0,'All Ticker P&L'!J12*'All Ticker P&L'!I12) -> 0 | AR12: =IF($AL12="",0,'All Ticker P&L'!L12) -> 0 | AS12: =IF($AL12="",0,'All Ticker P&L'!M12) -> 0 | AT12: =IF($AL12="","",RANK(AR12,$AR$2:$AR$1001)+COUNTIF($AR$2:AR12,AR12)-1) | AU12: =IF($AL12="","",RANK(AV12,$AV$2:$AV$1001)+COUNTIF($AV$2:AV12,AV12)-1) | AV12: =-AR12 -> 0
A13: Negative / short positions | B13: =COUNTIF(Shares!$E$2:$E$1001,"<0") -> 0 | D13: 9 | E13: =IFERROR(INDEX($Z$2:$Z$1001,MATCH($D13,$AI$2:$AI$1001,0)),"") -> HKEX:700:HKD | F13: =IF($E13="","",INDEX($AA$2:$AA$1001,MATCH($D13,$AI$2:$AI$1001,0))) -> HKEX | G13: =IF($E13="","",INDEX($AC$2:$AC$1001,MATCH($D13,$AI$2:$AI$1001,0))) -> HKD | H13: =IF($E13="","",INDEX($AE$2:$AE$1001,MATCH($D13,$AI$2:$AI$1001,0))) -> 8050.3933 | I13: =IF($E13="","",INDEX($AF$2:$AF$1001,MATCH($D13,$AI$2:$AI$1001,0))) -> 0.045261398 | J13: =IF($E13="","",INDEX($AG$2:$AG$1001,MATCH($D13,$AI$2:$AI$1001,0))) -> -1860.0663 | K13: =IF($E13="","",INDEX($AH$2:$AH$1001,MATCH($D13,$AI$2:$AI$1001,0))) -> -0.18768719 | Z13: =Shares!A13 | AA13: =Shares!B13 | AB13: =Shares!C13 | AC13: =Shares!D13 | AD13: =IF($Z13="",0,Shares!E13) -> 0 | AE13: =IF($Z13="",0,Shares!K13*Shares!J13) -> 0 | AF13: =IFERROR(AE13/$B$5,0) -> 0 | AG13: =IF($Z13="",0,Shares!M13) -> 0 | AH13: =IF($Z13="",0,Shares!N13) -> 0 | AI13: =IF($Z13="","",RANK(AE13,$AE$2:$AE$1001)+COUNTIF($AE$2:AE13,AE13)-1) | AJ13: =IF($AD13<0,COUNT($AJ$1:AJ12)+1,"") | AL13: ='All Ticker P&L'!A13 | AM13: ='All Ticker P&L'!B13 | AN13: ='All Ticker P&L'!C13 | AO13: ='All Ticker P&L'!D13 | AP13: =IF($AL13="",0,'All Ticker P&L'!E13) -> 0 | AQ13: =IF($AL13="",0,'All Ticker P&L'!J13*'All Ticker P&L'!I13) -> 0 | AR13: =IF($AL13="",0,'All Ticker P&L'!L13) -> 0 | AS13: =IF($AL13="",0,'All Ticker P&L'!M13) -> 0 | AT13: =IF($AL13="","",RANK(AR13,$AR$2:$AR$1001)+COUNTIF($AR$2:AR13,AR13)-1) | AU13: =IF($AL13="","",RANK(AV13,$AV$2:$AV$1001)+COUNTIF($AV$2:AV13,AV13)-1) | AV13: =-AR13 -> 0
A14: Price / FX warnings | B14: =COUNTIFS(Shares!$A$2:$A$1001,"?*",Shares!$I$2:$I$1001,0)+COUNTIFS(Shares!$A$2:$A$1001,"?*",Shares!$J$2:$J$1001,0)+COUNTIFS(Shares!$A$2:$A$1001,"?*",Shares!$D$2:$D$1001,"<>SGD",Shares!$J$2:$J$1001,1) -> 0 | D14: 10 | E14: =IFERROR(INDEX($Z$2:$Z$1001,MATCH($D14,$AI$2:$AI$1001,0)),"") | F14: =IF($E14="","",INDEX($AA$2:$AA$1001,MATCH($D14,$AI$2:$AI$1001,0))) | G14: =IF($E14="","",INDEX($AC$2:$AC$1001,MATCH($D14,$AI$2:$AI$1001,0))) | H14: =IF($E14="","",INDEX($AE$2:$AE$1001,MATCH($D14,$AI$2:$AI$1001,0))) | I14: =IF($E14="","",INDEX($AF$2:$AF$1001,MATCH($D14,$AI$2:$AI$1001,0))) | J14: =IF($E14="","",INDEX($AG$2:$AG$1001,MATCH($D14,$AI$2:$AI$1001,0))) | K14: =IF($E14="","",INDEX($AH$2:$AH$1001,MATCH($D14,$AI$2:$AI$1001,0))) | Z14: =Shares!A14 | AA14: =Shares!B14 | AB14: =Shares!C14 | AC14: =Shares!D14 | AD14: =IF($Z14="",0,Shares!E14) -> 0 | AE14: =IF($Z14="",0,Shares!K14*Shares!J14) -> 0 | AF14: =IFERROR(AE14/$B$5,0) -> 0 | AG14: =IF($Z14="",0,Shares!M14) -> 0 | AH14: =IF($Z14="",0,Shares!N14) -> 0 | AI14: =IF($Z14="","",RANK(AE14,$AE$2:$AE$1001)+COUNTIF($AE$2:AE14,AE14)-1) | AJ14: =IF($AD14<0,COUNT($AJ$1:AJ13)+1,"") | AL14: ='All Ticker P&L'!A14 | AM14: ='All Ticker P&L'!B14 | AN14: ='All Ticker P&L'!C14 | AO14: ='All Ticker P&L'!D14 | AP14: =IF($AL14="",0,'All Ticker P&L'!E14) -> 0 | AQ14: =IF($AL14="",0,'All Ticker P&L'!J14*'All Ticker P&L'!I14) -> 0 | AR14: =IF($AL14="",0,'All Ticker P&L'!L14) -> 0 | AS14: =IF($AL14="",0,'All Ticker P&L'!M14) -> 0 | AT14: =IF($AL14="","",RANK(AR14,$AR$2:$AR$1001)+COUNTIF($AR$2:AR14,AR14)-1) | AU14: =IF($AL14="","",RANK(AV14,$AV$2:$AV$1001)+COUNTIF($AV$2:AV14,AV14)-1) | AV14: =-AR14 -> 0
A15: Portfolio XIRR p.a. (incl dividends) | B15: ='Portfolio Analysis'!$B$3 -> 0.075031766 | Z15: =Shares!A15 | AA15: =Shares!B15 | AB15: =Shares!C15 | AC15: =Shares!D15 | AD15: =IF($Z15="",0,Shares!E15) -> 0 | AE15: =IF($Z15="",0,Shares!K15*Shares!J15) -> 0 | AF15: =IFERROR(AE15/$B$5,0) -> 0 | AG15: =IF($Z15="",0,Shares!M15) -> 0 | AH15: =IF($Z15="",0,Shares!N15) -> 0 | AI15: =IF($Z15="","",RANK(AE15,$AE$2:$AE$1001)+COUNTIF($AE$2:AE15,AE15)-1) | AJ15: =IF($AD15<0,COUNT($AJ$1:AJ14)+1,"") | AL15: ='All Ticker P&L'!A15 | AM15: ='All Ticker P&L'!B15 | AN15: ='All Ticker P&L'!C15 | AO15: ='All Ticker P&L'!D15 | AP15: =IF($AL15="",0,'All Ticker P&L'!E15) -> 0 | AQ15: =IF($AL15="",0,'All Ticker P&L'!J15*'All Ticker P&L'!I15) -> 0 | AR15: =IF($AL15="",0,'All Ticker P&L'!L15) -> 0 | AS15: =IF($AL15="",0,'All Ticker P&L'!M15) -> 0 | AT15: =IF($AL15="","",RANK(AR15,$AR$2:$AR$1001)+COUNTIF($AR$2:AR15,AR15)-1) | AU15: =IF($AL15="","",RANK(AV15,$AV$2:$AV$1001)+COUNTIF($AV$2:AV15,AV15)-1) | AV15: =-AR15 -> 0
A16: Dividends collected, all time (SGD) | B16: =SUM(Txn[Dividend SGD]) -> 1090 | Z16: =Shares!A16 | AA16: =Shares!B16 | AB16: =Shares!C16 | AC16: =Shares!D16 | AD16: =IF($Z16="",0,Shares!E16) -> 0 | AE16: =IF($Z16="",0,Shares!K16*Shares!J16) -> 0 | AF16: =IFERROR(AE16/$B$5,0) -> 0 | AG16: =IF($Z16="",0,Shares!M16) -> 0 | AH16: =IF($Z16="",0,Shares!N16) -> 0 | AI16: =IF($Z16="","",RANK(AE16,$AE$2:$AE$1001)+COUNTIF($AE$2:AE16,AE16)-1) | AJ16: =IF($AD16<0,COUNT($AJ$1:AJ15)+1,"") | AL16: ='All Ticker P&L'!A16 | AM16: ='All Ticker P&L'!B16 | AN16: ='All Ticker P&L'!C16 | AO16: ='All Ticker P&L'!D16 | AP16: =IF($AL16="",0,'All Ticker P&L'!E16) -> 0 | AQ16: =IF($AL16="",0,'All Ticker P&L'!J16*'All Ticker P&L'!I16) -> 0 | AR16: =IF($AL16="",0,'All Ticker P&L'!L16) -> 0 | AS16: =IF($AL16="",0,'All Ticker P&L'!M16) -> 0 | AT16: =IF($AL16="","",RANK(AR16,$AR$2:$AR$1001)+COUNTIF($AR$2:AR16,AR16)-1) | AU16: =IF($AL16="","",RANK(AV16,$AV$2:$AV$1001)+COUNTIF($AV$2:AV16,AV16)-1) | AV16: =-AR16 -> 0
A17: Allocation by Currency | F17: Allocation by Exchange | Z17: =Shares!A17 | AA17: =Shares!B17 | AB17: =Shares!C17 | AC17: =Shares!D17 | AD17: =IF($Z17="",0,Shares!E17) -> 0 | AE17: =IF($Z17="",0,Shares!K17*Shares!J17) -> 0 | AF17: =IFERROR(AE17/$B$5,0) -> 0 | AG17: =IF($Z17="",0,Shares!M17) -> 0 | AH17: =IF($Z17="",0,Shares!N17) -> 0 | AI17: =IF($Z17="","",RANK(AE17,$AE$2:$AE$1001)+COUNTIF($AE$2:AE17,AE17)-1) | AJ17: =IF($AD17<0,COUNT($AJ$1:AJ16)+1,"") | AL17: ='All Ticker P&L'!A17 | AM17: ='All Ticker P&L'!B17 | AN17: ='All Ticker P&L'!C17 | AO17: ='All Ticker P&L'!D17 | AP17: =IF($AL17="",0,'All Ticker P&L'!E17) -> 0 | AQ17: =IF($AL17="",0,'All Ticker P&L'!J17*'All Ticker P&L'!I17) -> 0 | AR17: =IF($AL17="",0,'All Ticker P&L'!L17) -> 0 | AS17: =IF($AL17="",0,'All Ticker P&L'!M17) -> 0 | AT17: =IF($AL17="","",RANK(AR17,$AR$2:$AR$1001)+COUNTIF($AR$2:AR17,AR17)-1) | AU17: =IF($AL17="","",RANK(AV17,$AV$2:$AV$1001)+COUNTIF($AV$2:AV17,AV17)-1) | AV17: =-AR17 -> 0
A18: Currency | B18: Market Value SGD | C18: Weight | D18: Positions | F18: Exchange | G18: Market Value SGD | H18: Weight | I18: Positions | Z18: =Shares!A18 | AA18: =Shares!B18 | AB18: =Shares!C18 | AC18: =Shares!D18 | AD18: =IF($Z18="",0,Shares!E18) -> 0 | AE18: =IF($Z18="",0,Shares!K18*Shares!J18) -> 0 | AF18: =IFERROR(AE18/$B$5,0) -> 0 | AG18: =IF($Z18="",0,Shares!M18) -> 0 | AH18: =IF($Z18="",0,Shares!N18) -> 0 | AI18: =IF($Z18="","",RANK(AE18,$AE$2:$AE$1001)+COUNTIF($AE$2:AE18,AE18)-1) | AJ18: =IF($AD18<0,COUNT($AJ$1:AJ17)+1,"") | AL18: ='All Ticker P&L'!A18 | AM18: ='All Ticker P&L'!B18 | AN18: ='All Ticker P&L'!C18 | AO18: ='All Ticker P&L'!D18 | AP18: =IF($AL18="",0,'All Ticker P&L'!E18) -> 0 | AQ18: =IF($AL18="",0,'All Ticker P&L'!J18*'All Ticker P&L'!I18) -> 0 | AR18: =IF($AL18="",0,'All Ticker P&L'!L18) -> 0 | AS18: =IF($AL18="",0,'All Ticker P&L'!M18) -> 0 | AT18: =IF($AL18="","",RANK(AR18,$AR$2:$AR$1001)+COUNTIF($AR$2:AR18,AR18)-1) | AU18: =IF($AL18="","",RANK(AV18,$AV$2:$AV$1001)+COUNTIF($AV$2:AV18,AV18)-1) | AV18: =-AR18 -> 0
A19: SGD | B19: =SUMIFS($AE$2:$AE$1001,$AC$2:$AC$1001,A19) -> 125017 | C19: =IFERROR(B19/$B$5,0) -> 0.70287798 | D19: =COUNTIFS($AC$2:$AC$1001,A19,$Z$2:$Z$1001,"?*") -> 5 | F19: CA | G19: =SUMIFS($AE$2:$AE$1001,$AA$2:$AA$1001,F19) -> 78127 | H19: =IFERROR(G19/$B$5,0) -> 0.43925024 | I19: =COUNTIFS($AA$2:$AA$1001,F19,$Z$2:$Z$1001,"?*") -> 1 | Z19: =Shares!A19 | AA19: =Shares!B19 | AB19: =Shares!C19 | AC19: =Shares!D19 | AD19: =IF($Z19="",0,Shares!E19) -> 0 | AE19: =IF($Z19="",0,Shares!K19*Shares!J19) -> 0 | AF19: =IFERROR(AE19/$B$5,0) -> 0 | AG19: =IF($Z19="",0,Shares!M19) -> 0 | AH19: =IF($Z19="",0,Shares!N19) -> 0 | AI19: =IF($Z19="","",RANK(AE19,$AE$2:$AE$1001)+COUNTIF($AE$2:AE19,AE19)-1) | AJ19: =IF($AD19<0,COUNT($AJ$1:AJ18)+1,"") | AL19: ='All Ticker P&L'!A19 | AM19: ='All Ticker P&L'!B19 | AN19: ='All Ticker P&L'!C19 | AO19: ='All Ticker P&L'!D19 | AP19: =IF($AL19="",0,'All Ticker P&L'!E19) -> 0 | AQ19: =IF($AL19="",0,'All Ticker P&L'!J19*'All Ticker P&L'!I19) -> 0 | AR19: =IF($AL19="",0,'All Ticker P&L'!L19) -> 0 | AS19: =IF($AL19="",0,'All Ticker P&L'!M19) -> 0 | AT19: =IF($AL19="","",RANK(AR19,$AR$2:$AR$1001)+COUNTIF($AR$2:AR19,AR19)-1) | AU19: =IF($AL19="","",RANK(AV19,$AV$2:$AV$1001)+COUNTIF($AV$2:AV19,AV19)-1) | AV19: =-AR19 -> 0
A20: HKD | B20: =SUMIFS($AE$2:$AE$1001,$AC$2:$AC$1001,A20) -> 8050.3933 | C20: =IFERROR(B20/$B$5,0) -> 0.045261398 | D20: =COUNTIFS($AC$2:$AC$1001,A20,$Z$2:$Z$1001,"?*") -> 1 | F20: HKEX | G20: =SUMIFS($AE$2:$AE$1001,$AA$2:$AA$1001,F20) -> 8050.3933 | H20: =IFERROR(G20/$B$5,0) -> 0.045261398 | I20: =COUNTIFS($AA$2:$AA$1001,F20,$Z$2:$Z$1001,"?*") -> 1 | Z20: =Shares!A20 | AA20: =Shares!B20 | AB20: =Shares!C20 | AC20: =Shares!D20 | AD20: =IF($Z20="",0,Shares!E20) -> 0 | AE20: =IF($Z20="",0,Shares!K20*Shares!J20) -> 0 | AF20: =IFERROR(AE20/$B$5,0) -> 0 | AG20: =IF($Z20="",0,Shares!M20) -> 0 | AH20: =IF($Z20="",0,Shares!N20) -> 0 | AI20: =IF($Z20="","",RANK(AE20,$AE$2:$AE$1001)+COUNTIF($AE$2:AE20,AE20)-1) | AJ20: =IF($AD20<0,COUNT($AJ$1:AJ19)+1,"") | AL20: ='All Ticker P&L'!A20 | AM20: ='All Ticker P&L'!B20 | AN20: ='All Ticker P&L'!C20 | AO20: ='All Ticker P&L'!D20 | AP20: =IF($AL20="",0,'All Ticker P&L'!E20) -> 0 | AQ20: =IF($AL20="",0,'All Ticker P&L'!J20*'All Ticker P&L'!I20) -> 0 | AR20: =IF($AL20="",0,'All Ticker P&L'!L20) -> 0 | AS20: =IF($AL20="",0,'All Ticker P&L'!M20) -> 0 | AT20: =IF($AL20="","",RANK(AR20,$AR$2:$AR$1001)+COUNTIF($AR$2:AR20,AR20)-1) | AU20: =IF($AL20="","",RANK(AV20,$AV$2:$AV$1001)+COUNTIF($AV$2:AV20,AV20)-1) | AV20: =-AR20 -> 0
A21: USD | B21: =SUMIFS($AE$2:$AE$1001,$AC$2:$AC$1001,A21) -> 44797.05 | C21: =IFERROR(B21/$B$5,0) -> 0.25186063 | D21: =COUNTIFS($AC$2:$AC$1001,A21,$Z$2:$Z$1001,"?*") -> 3 | F21: SSB | G21: =SUMIFS($AE$2:$AE$1001,$AA$2:$AA$1001,F21) -> 0 | H21: =IFERROR(G21/$B$5,0) -> 0 | I21: =COUNTIFS($AA$2:$AA$1001,F21,$Z$2:$Z$1001,"?*") -> 0 | Z21: =Shares!A21 | AA21: =Shares!B21 | AB21: =Shares!C21 | AC21: =Shares!D21 | AD21: =IF($Z21="",0,Shares!E21) -> 0 | AE21: =IF($Z21="",0,Shares!K21*Shares!J21) -> 0 | AF21: =IFERROR(AE21/$B$5,0) -> 0 | AG21: =IF($Z21="",0,Shares!M21) -> 0 | AH21: =IF($Z21="",0,Shares!N21) -> 0 | AI21: =IF($Z21="","",RANK(AE21,$AE$2:$AE$1001)+COUNTIF($AE$2:AE21,AE21)-1) | AJ21: =IF($AD21<0,COUNT($AJ$1:AJ20)+1,"") | AL21: ='All Ticker P&L'!A21 | AM21: ='All Ticker P&L'!B21 | AN21: ='All Ticker P&L'!C21 | AO21: ='All Ticker P&L'!D21 | AP21: =IF($AL21="",0,'All Ticker P&L'!E21) -> 0 | AQ21: =IF($AL21="",0,'All Ticker P&L'!J21*'All Ticker P&L'!I21) -> 0 | AR21: =IF($AL21="",0,'All Ticker P&L'!L21) -> 0 | AS21: =IF($AL21="",0,'All Ticker P&L'!M21) -> 0 | AT21: =IF($AL21="","",RANK(AR21,$AR$2:$AR$1001)+COUNTIF($AR$2:AR21,AR21)-1) | AU21: =IF($AL21="","",RANK(AV21,$AV$2:$AV$1001)+COUNTIF($AV$2:AV21,AV21)-1) | AV21: =-AR21 -> 0
A22: Other / new categories | B22: =$B$5-SUM(B19:B21) -> 0 | C22: =IFERROR(B22/$B$5,0) -> 0 | D22: =$B$4-SUM(D19:D21) -> 0 | F22: SGX | G22: =SUMIFS($AE$2:$AE$1001,$AA$2:$AA$1001,F22) -> 46890 | H22: =IFERROR(G22/$B$5,0) -> 0.26362773 | I22: =COUNTIFS($AA$2:$AA$1001,F22,$Z$2:$Z$1001,"?*") -> 4 | Z22: =Shares!A22 | AA22: =Shares!B22 | AB22: =Shares!C22 | AC22: =Shares!D22 | AD22: =IF($Z22="",0,Shares!E22) -> 0 | AE22: =IF($Z22="",0,Shares!K22*Shares!J22) -> 0 | AF22: =IFERROR(AE22/$B$5,0) -> 0 | AG22: =IF($Z22="",0,Shares!M22) -> 0 | AH22: =IF($Z22="",0,Shares!N22) -> 0 | AI22: =IF($Z22="","",RANK(AE22,$AE$2:$AE$1001)+COUNTIF($AE$2:AE22,AE22)-1) | AJ22: =IF($AD22<0,COUNT($AJ$1:AJ21)+1,"") | AL22: ='All Ticker P&L'!A22 | AM22: ='All Ticker P&L'!B22 | AN22: ='All Ticker P&L'!C22 | AO22: ='All Ticker P&L'!D22 | AP22: =IF($AL22="",0,'All Ticker P&L'!E22) -> 0 | AQ22: =IF($AL22="",0,'All Ticker P&L'!J22*'All Ticker P&L'!I22) -> 0 | AR22: =IF($AL22="",0,'All Ticker P&L'!L22) -> 0 | AS22: =IF($AL22="",0,'All Ticker P&L'!M22) -> 0 | AT22: =IF($AL22="","",RANK(AR22,$AR$2:$AR$1001)+COUNTIF($AR$2:AR22,AR22)-1) | AU22: =IF($AL22="","",RANK(AV22,$AV$2:$AV$1001)+COUNTIF($AV$2:AV22,AV22)-1) | AV22: =-AR22 -> 0
F23: USX | G23: =SUMIFS($AE$2:$AE$1001,$AA$2:$AA$1001,F23) -> 31544.518 | H23: =IFERROR(G23/$B$5,0) -> 0.17735146 | I23: =COUNTIFS($AA$2:$AA$1001,F23,$Z$2:$Z$1001,"?*") -> 2 | Z23: =Shares!A23 | AA23: =Shares!B23 | AB23: =Shares!C23 | AC23: =Shares!D23 | AD23: =IF($Z23="",0,Shares!E23) -> 0 | AE23: =IF($Z23="",0,Shares!K23*Shares!J23) -> 0 | AF23: =IFERROR(AE23/$B$5,0) -> 0 | AG23: =IF($Z23="",0,Shares!M23) -> 0 | AH23: =IF($Z23="",0,Shares!N23) -> 0 | AI23: =IF($Z23="","",RANK(AE23,$AE$2:$AE$1001)+COUNTIF($AE$2:AE23,AE23)-1) | AJ23: =IF($AD23<0,COUNT($AJ$1:AJ22)+1,"") | AL23: ='All Ticker P&L'!A23 | AM23: ='All Ticker P&L'!B23 | AN23: ='All Ticker P&L'!C23 | AO23: ='All Ticker P&L'!D23 | AP23: =IF($AL23="",0,'All Ticker P&L'!E23) -> 0 | AQ23: =IF($AL23="",0,'All Ticker P&L'!J23*'All Ticker P&L'!I23) -> 0 | AR23: =IF($AL23="",0,'All Ticker P&L'!L23) -> 0 | AS23: =IF($AL23="",0,'All Ticker P&L'!M23) -> 0 | AT23: =IF($AL23="","",RANK(AR23,$AR$2:$AR$1001)+COUNTIF($AR$2:AR23,AR23)-1) | AU23: =IF($AL23="","",RANK(AV23,$AV$2:$AV$1001)+COUNTIF($AV$2:AV23,AV23)-1) | AV23: =-AR23 -> 0
F24: CG | G24: =SUMIFS($AE$2:$AE$1001,$AA$2:$AA$1001,F24) -> 13252.532 | H24: =IFERROR(G24/$B$5,0) -> 0.07450917 | I24: =COUNTIFS($AA$2:$AA$1001,F24,$Z$2:$Z$1001,"?*") -> 1 | Z24: =Shares!A24 | AA24: =Shares!B24 | AB24: =Shares!C24 | AC24: =Shares!D24 | AD24: =IF($Z24="",0,Shares!E24) -> 0 | AE24: =IF($Z24="",0,Shares!K24*Shares!J24) -> 0 | AF24: =IFERROR(AE24/$B$5,0) -> 0 | AG24: =IF($Z24="",0,Shares!M24) -> 0 | AH24: =IF($Z24="",0,Shares!N24) -> 0 | AI24: =IF($Z24="","",RANK(AE24,$AE$2:$AE$1001)+COUNTIF($AE$2:AE24,AE24)-1) | AJ24: =IF($AD24<0,COUNT($AJ$1:AJ23)+1,"") | AL24: ='All Ticker P&L'!A24 | AM24: ='All Ticker P&L'!B24 | AN24: ='All Ticker P&L'!C24 | AO24: ='All Ticker P&L'!D24 | AP24: =IF($AL24="",0,'All Ticker P&L'!E24) -> 0 | AQ24: =IF($AL24="",0,'All Ticker P&L'!J24*'All Ticker P&L'!I24) -> 0 | AR24: =IF($AL24="",0,'All Ticker P&L'!L24) -> 0 | AS24: =IF($AL24="",0,'All Ticker P&L'!M24) -> 0 | AT24: =IF($AL24="","",RANK(AR24,$AR$2:$AR$1001)+COUNTIF($AR$2:AR24,AR24)-1) | AU24: =IF($AL24="","",RANK(AV24,$AV$2:$AV$1001)+COUNTIF($AV$2:AV24,AV24)-1) | AV24: =-AR24 -> 0
F25: Other / new categories | G25: =$B$5-SUM(G19:G24) -> 0 | H25: =IFERROR(G25/$B$5,0) -> 0 | I25: =$B$4-SUM(I19:I24) -> 0 | Z25: =Shares!A25 | AA25: =Shares!B25 | AB25: =Shares!C25 | AC25: =Shares!D25 | AD25: =IF($Z25="",0,Shares!E25) -> 0 | AE25: =IF($Z25="",0,Shares!K25*Shares!J25) -> 0 | AF25: =IFERROR(AE25/$B$5,0) -> 0 | AG25: =IF($Z25="",0,Shares!M25) -> 0 | AH25: =IF($Z25="",0,Shares!N25) -> 0 | AI25: =IF($Z25="","",RANK(AE25,$AE$2:$AE$1001)+COUNTIF($AE$2:AE25,AE25)-1) | AJ25: =IF($AD25<0,COUNT($AJ$1:AJ24)+1,"") | AL25: ='All Ticker P&L'!A25 | AM25: ='All Ticker P&L'!B25 | AN25: ='All Ticker P&L'!C25 | AO25: ='All Ticker P&L'!D25 | AP25: =IF($AL25="",0,'All Ticker P&L'!E25) -> 0 | AQ25: =IF($AL25="",0,'All Ticker P&L'!J25*'All Ticker P&L'!I25) -> 0 | AR25: =IF($AL25="",0,'All Ticker P&L'!L25) -> 0 | AS25: =IF($AL25="",0,'All Ticker P&L'!M25) -> 0 | AT25: =IF($AL25="","",RANK(AR25,$AR$2:$AR$1001)+COUNTIF($AR$2:AR25,AR25)-1) | AU25: =IF($AL25="","",RANK(AV25,$AV$2:$AV$1001)+COUNTIF($AV$2:AV25,AV25)-1) | AV25: =-AR25 -> 0
Z26: =Shares!A26 | AA26: =Shares!B26 | AB26: =Shares!C26 | AC26: =Shares!D26 | AD26: =IF($Z26="",0,Shares!E26) -> 0 | AE26: =IF($Z26="",0,Shares!K26*Shares!J26) -> 0 | AF26: =IFERROR(AE26/$B$5,0) -> 0 | AG26: =IF($Z26="",0,Shares!M26) -> 0 | AH26: =IF($Z26="",0,Shares!N26) -> 0 | AI26: =IF($Z26="","",RANK(AE26,$AE$2:$AE$1001)+COUNTIF($AE$2:AE26,AE26)-1) | AJ26: =IF($AD26<0,COUNT($AJ$1:AJ25)+1,"") | AL26: ='All Ticker P&L'!A26 | AM26: ='All Ticker P&L'!B26 | AN26: ='All Ticker P&L'!C26 | AO26: ='All Ticker P&L'!D26 | AP26: =IF($AL26="",0,'All Ticker P&L'!E26) -> 0 | AQ26: =IF($AL26="",0,'All Ticker P&L'!J26*'All Ticker P&L'!I26) -> 0 | AR26: =IF($AL26="",0,'All Ticker P&L'!L26) -> 0 | AS26: =IF($AL26="",0,'All Ticker P&L'!M26) -> 0 | AT26: =IF($AL26="","",RANK(AR26,$AR$2:$AR$1001)+COUNTIF($AR$2:AR26,AR26)-1) | AU26: =IF($AL26="","",RANK(AV26,$AV$2:$AV$1001)+COUNTIF($AV$2:AV26,AV26)-1) | AV26: =-AR26 -> 0
Z27: =Shares!A27 | AA27: =Shares!B27 | AB27: =Shares!C27 | AC27: =Shares!D27 | AD27: =IF($Z27="",0,Shares!E27) -> 0 | AE27: =IF($Z27="",0,Shares!K27*Shares!J27) -> 0 | AF27: =IFERROR(AE27/$B$5,0) -> 0 | AG27: =IF($Z27="",0,Shares!M27) -> 0 | AH27: =IF($Z27="",0,Shares!N27) -> 0 | AI27: =IF($Z27="","",RANK(AE27,$AE$2:$AE$1001)+COUNTIF($AE$2:AE27,AE27)-1) | AJ27: =IF($AD27<0,COUNT($AJ$1:AJ26)+1,"") | AL27: ='All Ticker P&L'!A27 | AM27: ='All Ticker P&L'!B27 | AN27: ='All Ticker P&L'!C27 | AO27: ='All Ticker P&L'!D27 | AP27: =IF($AL27="",0,'All Ticker P&L'!E27) -> 0 | AQ27: =IF($AL27="",0,'All Ticker P&L'!J27*'All Ticker P&L'!I27) -> 0 | AR27: =IF($AL27="",0,'All Ticker P&L'!L27) -> 0 | AS27: =IF($AL27="",0,'All Ticker P&L'!M27) -> 0 | AT27: =IF($AL27="","",RANK(AR27,$AR$2:$AR$1001)+COUNTIF($AR$2:AR27,AR27)-1) | AU27: =IF($AL27="","",RANK(AV27,$AV$2:$AV$1001)+COUNTIF($AV$2:AV27,AV27)-1) | AV27: =-AR27 -> 0
Z28: =Shares!A28 | AA28: =Shares!B28 | AB28: =Shares!C28 | AC28: =Shares!D28 | AD28: =IF($Z28="",0,Shares!E28) -> 0 | AE28: =IF($Z28="",0,Shares!K28*Shares!J28) -> 0 | AF28: =IFERROR(AE28/$B$5,0) -> 0 | AG28: =IF($Z28="",0,Shares!M28) -> 0 | AH28: =IF($Z28="",0,Shares!N28) -> 0 | AI28: =IF($Z28="","",RANK(AE28,$AE$2:$AE$1001)+COUNTIF($AE$2:AE28,AE28)-1) | AJ28: =IF($AD28<0,COUNT($AJ$1:AJ27)+1,"") | AL28: ='All Ticker P&L'!A28 | AM28: ='All Ticker P&L'!B28 | AN28: ='All Ticker P&L'!C28 | AO28: ='All Ticker P&L'!D28 | AP28: =IF($AL28="",0,'All Ticker P&L'!E28) -> 0 | AQ28: =IF($AL28="",0,'All Ticker P&L'!J28*'All Ticker P&L'!I28) -> 0 | AR28: =IF($AL28="",0,'All Ticker P&L'!L28) -> 0 | AS28: =IF($AL28="",0,'All Ticker P&L'!M28) -> 0 | AT28: =IF($AL28="","",RANK(AR28,$AR$2:$AR$1001)+COUNTIF($AR$2:AR28,AR28)-1) | AU28: =IF($AL28="","",RANK(AV28,$AV$2:$AV$1001)+COUNTIF($AV$2:AV28,AV28)-1) | AV28: =-AR28 -> 0
Z29: =Shares!A29 | AA29: =Shares!B29 | AB29: =Shares!C29 | AC29: =Shares!D29 | AD29: =IF($Z29="",0,Shares!E29) -> 0 | AE29: =IF($Z29="",0,Shares!K29*Shares!J29) -> 0 | AF29: =IFERROR(AE29/$B$5,0) -> 0 | AG29: =IF($Z29="",0,Shares!M29) -> 0 | AH29: =IF($Z29="",0,Shares!N29) -> 0 | AI29: =IF($Z29="","",RANK(AE29,$AE$2:$AE$1001)+COUNTIF($AE$2:AE29,AE29)-1) | AJ29: =IF($AD29<0,COUNT($AJ$1:AJ28)+1,"") | AL29: ='All Ticker P&L'!A29 | AM29: ='All Ticker P&L'!B29 | AN29: ='All Ticker P&L'!C29 | AO29: ='All Ticker P&L'!D29 | AP29: =IF($AL29="",0,'All Ticker P&L'!E29) -> 0 | AQ29: =IF($AL29="",0,'All Ticker P&L'!J29*'All Ticker P&L'!I29) -> 0 | AR29: =IF($AL29="",0,'All Ticker P&L'!L29) -> 0 | AS29: =IF($AL29="",0,'All Ticker P&L'!M29) -> 0 | AT29: =IF($AL29="","",RANK(AR29,$AR$2:$AR$1001)+COUNTIF($AR$2:AR29,AR29)-1) | AU29: =IF($AL29="","",RANK(AV29,$AV$2:$AV$1001)+COUNTIF($AV$2:AV29,AV29)-1) | AV29: =-AR29 -> 0
Z30: =Shares!A30 | AA30: =Shares!B30 | AB30: =Shares!C30 | AC30: =Shares!D30 | AD30: =IF($Z30="",0,Shares!E30) -> 0 | AE30: =IF($Z30="",0,Shares!K30*Shares!J30) -> 0 | AF30: =IFERROR(AE30/$B$5,0) -> 0 | AG30: =IF($Z30="",0,Shares!M30) -> 0 | AH30: =IF($Z30="",0,Shares!N30) -> 0 | AI30: =IF($Z30="","",RANK(AE30,$AE$2:$AE$1001)+COUNTIF($AE$2:AE30,AE30)-1) | AJ30: =IF($AD30<0,COUNT($AJ$1:AJ29)+1,"") | AL30: ='All Ticker P&L'!A30 | AM30: ='All Ticker P&L'!B30 | AN30: ='All Ticker P&L'!C30 | AO30: ='All Ticker P&L'!D30 | AP30: =IF($AL30="",0,'All Ticker P&L'!E30) -> 0 | AQ30: =IF($AL30="",0,'All Ticker P&L'!J30*'All Ticker P&L'!I30) -> 0 | AR30: =IF($AL30="",0,'All Ticker P&L'!L30) -> 0 | AS30: =IF($AL30="",0,'All Ticker P&L'!M30) -> 0 | AT30: =IF($AL30="","",RANK(AR30,$AR$2:$AR$1001)+COUNTIF($AR$2:AR30,AR30)-1) | AU30: =IF($AL30="","",RANK(AV30,$AV$2:$AV$1001)+COUNTIF($AV$2:AV30,AV30)-1) | AV30: =-AR30 -> 0
Z31: =Shares!A31 | AA31: =Shares!B31 | AB31: =Shares!C31 | AC31: =Shares!D31 | AD31: =IF($Z31="",0,Shares!E31) -> 0 | AE31: =IF($Z31="",0,Shares!K31*Shares!J31) -> 0 | AF31: =IFERROR(AE31/$B$5,0) -> 0 | AG31: =IF($Z31="",0,Shares!M31) -> 0 | AH31: =IF($Z31="",0,Shares!N31) -> 0 | AI31: =IF($Z31="","",RANK(AE31,$AE$2:$AE$1001)+COUNTIF($AE$2:AE31,AE31)-1) | AJ31: =IF($AD31<0,COUNT($AJ$1:AJ30)+1,"") | AL31: ='All Ticker P&L'!A31 | AM31: ='All Ticker P&L'!B31 | AN31: ='All Ticker P&L'!C31 | AO31: ='All Ticker P&L'!D31 | AP31: =IF($AL31="",0,'All Ticker P&L'!E31) -> 0 | AQ31: =IF($AL31="",0,'All Ticker P&L'!J31*'All Ticker P&L'!I31) -> 0 | AR31: =IF($AL31="",0,'All Ticker P&L'!L31) -> 0 | AS31: =IF($AL31="",0,'All Ticker P&L'!M31) -> 0 | AT31: =IF($AL31="","",RANK(AR31,$AR$2:$AR$1001)+COUNTIF($AR$2:AR31,AR31)-1) | AU31: =IF($AL31="","",RANK(AV31,$AV$2:$AV$1001)+COUNTIF($AV$2:AV31,AV31)-1) | AV31: =-AR31 -> 0
Z32: =Shares!A32 | AA32: =Shares!B32 | AB32: =Shares!C32 | AC32: =Shares!D32 | AD32: =IF($Z32="",0,Shares!E32) -> 0 | AE32: =IF($Z32="",0,Shares!K32*Shares!J32) -> 0 | AF32: =IFERROR(AE32/$B$5,0) -> 0 | AG32: =IF($Z32="",0,Shares!M32) -> 0 | AH32: =IF($Z32="",0,Shares!N32) -> 0 | AI32: =IF($Z32="","",RANK(AE32,$AE$2:$AE$1001)+COUNTIF($AE$2:AE32,AE32)-1) | AJ32: =IF($AD32<0,COUNT($AJ$1:AJ31)+1,"") | AL32: ='All Ticker P&L'!A32 | AM32: ='All Ticker P&L'!B32 | AN32: ='All Ticker P&L'!C32 | AO32: ='All Ticker P&L'!D32 | AP32: =IF($AL32="",0,'All Ticker P&L'!E32) -> 0 | AQ32: =IF($AL32="",0,'All Ticker P&L'!J32*'All Ticker P&L'!I32) -> 0 | AR32: =IF($AL32="",0,'All Ticker P&L'!L32) -> 0 | AS32: =IF($AL32="",0,'All Ticker P&L'!M32) -> 0 | AT32: =IF($AL32="","",RANK(AR32,$AR$2:$AR$1001)+COUNTIF($AR$2:AR32,AR32)-1) | AU32: =IF($AL32="","",RANK(AV32,$AV$2:$AV$1001)+COUNTIF($AV$2:AV32,AV32)-1) | AV32: =-AR32 -> 0
A33: Top 10 Winners by Total P&L | J33: Top 10 Losers by Total P&L | Z33: =Shares!A33 | AA33: =Shares!B33 | AB33: =Shares!C33 | AC33: =Shares!D33 | AD33: =IF($Z33="",0,Shares!E33) -> 0 | AE33: =IF($Z33="",0,Shares!K33*Shares!J33) -> 0 | AF33: =IFERROR(AE33/$B$5,0) -> 0 | AG33: =IF($Z33="",0,Shares!M33) -> 0 | AH33: =IF($Z33="",0,Shares!N33) -> 0 | AI33: =IF($Z33="","",RANK(AE33,$AE$2:$AE$1001)+COUNTIF($AE$2:AE33,AE33)-1) | AJ33: =IF($AD33<0,COUNT($AJ$1:AJ32)+1,"") | AL33: ='All Ticker P&L'!A33 | AM33: ='All Ticker P&L'!B33 | AN33: ='All Ticker P&L'!C33 | AO33: ='All Ticker P&L'!D33 | AP33: =IF($AL33="",0,'All Ticker P&L'!E33) -> 0 | AQ33: =IF($AL33="",0,'All Ticker P&L'!J33*'All Ticker P&L'!I33) -> 0 | AR33: =IF($AL33="",0,'All Ticker P&L'!L33) -> 0 | AS33: =IF($AL33="",0,'All Ticker P&L'!M33) -> 0 | AT33: =IF($AL33="","",RANK(AR33,$AR$2:$AR$1001)+COUNTIF($AR$2:AR33,AR33)-1) | AU33: =IF($AL33="","",RANK(AV33,$AV$2:$AV$1001)+COUNTIF($AV$2:AV33,AV33)-1) | AV33: =-AR33 -> 0
A34: Rank | B34: Key | C34: Exchange | D34: Currency | E34: Units Held | F34: P&L SGD | G34: P&L % | H34: Status | J34: Rank | K34: Key | L34: Exchange | M34: Currency | N34: Units Held | O34: P&L SGD | P34: P&L % | Q34: Status | Z34: =Shares!A34 | AA34: =Shares!B34 | AB34: =Shares!C34 | AC34: =Shares!D34 | AD34: =IF($Z34="",0,Shares!E34) -> 0 | AE34: =IF($Z34="",0,Shares!K34*Shares!J34) -> 0 | AF34: =IFERROR(AE34/$B$5,0) -> 0 | AG34: =IF($Z34="",0,Shares!M34) -> 0 | AH34: =IF($Z34="",0,Shares!N34) -> 0 | AI34: =IF($Z34="","",RANK(AE34,$AE$2:$AE$1001)+COUNTIF($AE$2:AE34,AE34)-1) | AJ34: =IF($AD34<0,COUNT($AJ$1:AJ33)+1,"") | AL34: ='All Ticker P&L'!A34 | AM34: ='All Ticker P&L'!B34 | AN34: ='All Ticker P&L'!C34 | AO34: ='All Ticker P&L'!D34 | AP34: =IF($AL34="",0,'All Ticker P&L'!E34) -> 0 | AQ34: =IF($AL34="",0,'All Ticker P&L'!J34*'All Ticker P&L'!I34) -> 0 | AR34: =IF($AL34="",0,'All Ticker P&L'!L34) -> 0 | AS34: =IF($AL34="",0,'All Ticker P&L'!M34) -> 0 | AT34: =IF($AL34="","",RANK(AR34,$AR$2:$AR$1001)+COUNTIF($AR$2:AR34,AR34)-1) | AU34: =IF($AL34="","",RANK(AV34,$AV$2:$AV$1001)+COUNTIF($AV$2:AV34,AV34)-1) | AV34: =-AR34 -> 0
A35: 1 | B35: =IFERROR(INDEX($AL$2:$AL$1001,MATCH($A35,$AT$2:$AT$1001,0)),"") -> CA:GOLD:SGD | C35: =IF($B35="","",INDEX($AM$2:$AM$1001,MATCH($A35,$AT$2:$AT$1001,0))) -> CA | D35: =IF($B35="","",INDEX($AO$2:$AO$1001,MATCH($A35,$AT$2:$AT$1001,0))) -> SGD | E35: =IF($B35="","",INDEX($AP$2:$AP$1001,MATCH($A35,$AT$2:$AT$1001,0))) -> 700 | F35: =IF($B35="","",INDEX($AR$2:$AR$1001,MATCH($A35,$AT$2:$AT$1001,0))) -> 22627 | G35: =IF($B35="","",INDEX($AS$2:$AS$1001,MATCH($A35,$AT$2:$AT$1001,0))) -> 0.40769369 | H35: =IF($B35="","",IF(E35=0,"Closed","Open")) -> Open | J35: 1 | K35: =IFERROR(INDEX($AL$2:$AL$1001,MATCH($J35,$AU$2:$AU$1001,0)),"") -> HKEX:700:HKD | L35: =IF($K35="","",INDEX($AM$2:$AM$1001,MATCH($J35,$AU$2:$AU$1001,0))) -> HKEX | M35: =IF($K35="","",INDEX($AO$2:$AO$1001,MATCH($J35,$AU$2:$AU$1001,0))) -> HKD | N35: =IF($K35="","",INDEX($AP$2:$AP$1001,MATCH($J35,$AU$2:$AU$1001,0))) -> 100 | O35: =IF($K35="","",INDEX($AR$2:$AR$1001,MATCH($J35,$AU$2:$AU$1001,0))) -> -1860.0663 | P35: =IF($K35="","",INDEX($AS$2:$AS$1001,MATCH($J35,$AU$2:$AU$1001,0))) -> -0.18768719 | Q35: =IF($K35="","",IF(N35=0,"Closed","Open")) -> Open | Z35: =Shares!A35 | AA35: =Shares!B35 | AB35: =Shares!C35 | AC35: =Shares!D35 | AD35: =IF($Z35="",0,Shares!E35) -> 0 | AE35: =IF($Z35="",0,Shares!K35*Shares!J35) -> 0 | AF35: =IFERROR(AE35/$B$5,0) -> 0 | AG35: =IF($Z35="",0,Shares!M35) -> 0 | AH35: =IF($Z35="",0,Shares!N35) -> 0 | AI35: =IF($Z35="","",RANK(AE35,$AE$2:$AE$1001)+COUNTIF($AE$2:AE35,AE35)-1) | AJ35: =IF($AD35<0,COUNT($AJ$1:AJ34)+1,"") | AL35: ='All Ticker P&L'!A35 | AM35: ='All Ticker P&L'!B35 | AN35: ='All Ticker P&L'!C35 | AO35: ='All Ticker P&L'!D35 | AP35: =IF($AL35="",0,'All Ticker P&L'!E35) -> 0 | AQ35: =IF($AL35="",0,'All Ticker P&L'!J35*'All Ticker P&L'!I35) -> 0 | AR35: =IF($AL35="",0,'All Ticker P&L'!L35) -> 0 | AS35: =IF($AL35="",0,'All Ticker P&L'!M35) -> 0 | AT35: =IF($AL35="","",RANK(AR35,$AR$2:$AR$1001)+COUNTIF($AR$2:AR35,AR35)-1) | AU35: =IF($AL35="","",RANK(AV35,$AV$2:$AV$1001)+COUNTIF($AV$2:AV35,AV35)-1) | AV35: =-AR35 -> 0
A36: 2 | B36: =IFERROR(INDEX($AL$2:$AL$1001,MATCH($A36,$AT$2:$AT$1001,0)),"") -> USX:NVDA:USD | C36: =IF($B36="","",INDEX($AM$2:$AM$1001,MATCH($A36,$AT$2:$AT$1001,0))) -> USX | D36: =IF($B36="","",INDEX($AO$2:$AO$1001,MATCH($A36,$AT$2:$AT$1001,0))) -> USD | E36: =IF($B36="","",INDEX($AP$2:$AP$1001,MATCH($A36,$AT$2:$AT$1001,0))) -> 0 | F36: =IF($B36="","",INDEX($AR$2:$AR$1001,MATCH($A36,$AT$2:$AT$1001,0))) -> 13190 | G36: =IF($B36="","",INDEX($AS$2:$AS$1001,MATCH($A36,$AT$2:$AT$1001,0))) -> 2.7450572 | H36: =IF($B36="","",IF(E36=0,"Closed","Open")) -> Closed | J36: 2 | K36: =IFERROR(INDEX($AL$2:$AL$1001,MATCH($J36,$AU$2:$AU$1001,0)),"") -> SGX:A17U:SGD | L36: =IF($K36="","",INDEX($AM$2:$AM$1001,MATCH($J36,$AU$2:$AU$1001,0))) -> SGX | M36: =IF($K36="","",INDEX($AO$2:$AO$1001,MATCH($J36,$AU$2:$AU$1001,0))) -> SGD | N36: =IF($K36="","",INDEX($AP$2:$AP$1001,MATCH($J36,$AU$2:$AU$1001,0))) -> 4000 | O36: =IF($K36="","",INDEX($AR$2:$AR$1001,MATCH($J36,$AU$2:$AU$1001,0))) -> -890 | P36: =IF($K36="","",INDEX($AS$2:$AS$1001,MATCH($J36,$AU$2:$AU$1001,0))) -> -0.075105485 | Q36: =IF($K36="","",IF(N36=0,"Closed","Open")) -> Open | Z36: =Shares!A36 | AA36: =Shares!B36 | AB36: =Shares!C36 | AC36: =Shares!D36 | AD36: =IF($Z36="",0,Shares!E36) -> 0 | AE36: =IF($Z36="",0,Shares!K36*Shares!J36) -> 0 | AF36: =IFERROR(AE36/$B$5,0) -> 0 | AG36: =IF($Z36="",0,Shares!M36) -> 0 | AH36: =IF($Z36="",0,Shares!N36) -> 0 | AI36: =IF($Z36="","",RANK(AE36,$AE$2:$AE$1001)+COUNTIF($AE$2:AE36,AE36)-1) | AJ36: =IF($AD36<0,COUNT($AJ$1:AJ35)+1,"") | AL36: ='All Ticker P&L'!A36 | AM36: ='All Ticker P&L'!B36 | AN36: ='All Ticker P&L'!C36 | AO36: ='All Ticker P&L'!D36 | AP36: =IF($AL36="",0,'All Ticker P&L'!E36) -> 0 | AQ36: =IF($AL36="",0,'All Ticker P&L'!J36*'All Ticker P&L'!I36) -> 0 | AR36: =IF($AL36="",0,'All Ticker P&L'!L36) -> 0 | AS36: =IF($AL36="",0,'All Ticker P&L'!M36) -> 0 | AT36: =IF($AL36="","",RANK(AR36,$AR$2:$AR$1001)+COUNTIF($AR$2:AR36,AR36)-1) | AU36: =IF($AL36="","",RANK(AV36,$AV$2:$AV$1001)+COUNTIF($AV$2:AV36,AV36)-1) | AV36: =-AR36 -> 0
A37: 3 | B37: =IFERROR(INDEX($AL$2:$AL$1001,MATCH($A37,$AT$2:$AT$1001,0)),"") -> CG:BITCOIN:USD | C37: =IF($B37="","",INDEX($AM$2:$AM$1001,MATCH($A37,$AT$2:$AT$1001,0))) -> CG | D37: =IF($B37="","",INDEX($AO$2:$AO$1001,MATCH($A37,$AT$2:$AT$1001,0))) -> USD | E37: =IF($B37="","",INDEX($AP$2:$AP$1001,MATCH($A37,$AT$2:$AT$1001,0))) -> 0.1 | F37: =IF($B37="","",INDEX($AR$2:$AR$1001,MATCH($A37,$AT$2:$AT$1001,0))) -> 10860.837 | G37: =IF($B37="","",INDEX($AS$2:$AS$1001,MATCH($A37,$AT$2:$AT$1001,0))) -> 4.5410627 | H37: =IF($B37="","",IF(E37=0,"Closed","Open")) -> Open | J37: 3 | K37: =IFERROR(INDEX($AL$2:$AL$1001,MATCH($J37,$AU$2:$AU$1001,0)),"") | L37: =IF($K37="","",INDEX($AM$2:$AM$1001,MATCH($J37,$AU$2:$AU$1001,0))) | M37: =IF($K37="","",INDEX($AO$2:$AO$1001,MATCH($J37,$AU$2:$AU$1001,0))) | N37: =IF($K37="","",INDEX($AP$2:$AP$1001,MATCH($J37,$AU$2:$AU$1001,0))) | O37: =IF($K37="","",INDEX($AR$2:$AR$1001,MATCH($J37,$AU$2:$AU$1001,0))) | P37: =IF($K37="","",INDEX($AS$2:$AS$1001,MATCH($J37,$AU$2:$AU$1001,0))) | Q37: =IF($K37="","",IF(N37=0,"Closed","Open")) | Z37: =Shares!A37 | AA37: =Shares!B37 | AB37: =Shares!C37 | AC37: =Shares!D37 | AD37: =IF($Z37="",0,Shares!E37) -> 0 | AE37: =IF($Z37="",0,Shares!K37*Shares!J37) -> 0 | AF37: =IFERROR(AE37/$B$5,0) -> 0 | AG37: =IF($Z37="",0,Shares!M37) -> 0 | AH37: =IF($Z37="",0,Shares!N37) -> 0 | AI37: =IF($Z37="","",RANK(AE37,$AE$2:$AE$1001)+COUNTIF($AE$2:AE37,AE37)-1) | AJ37: =IF($AD37<0,COUNT($AJ$1:AJ36)+1,"") | AL37: ='All Ticker P&L'!A37 | AM37: ='All Ticker P&L'!B37 | AN37: ='All Ticker P&L'!C37 | AO37: ='All Ticker P&L'!D37 | AP37: =IF($AL37="",0,'All Ticker P&L'!E37) -> 0 | AQ37: =IF($AL37="",0,'All Ticker P&L'!J37*'All Ticker P&L'!I37) -> 0 | AR37: =IF($AL37="",0,'All Ticker P&L'!L37) -> 0 | AS37: =IF($AL37="",0,'All Ticker P&L'!M37) -> 0 | AT37: =IF($AL37="","",RANK(AR37,$AR$2:$AR$1001)+COUNTIF($AR$2:AR37,AR37)-1) | AU37: =IF($AL37="","",RANK(AV37,$AV$2:$AV$1001)+COUNTIF($AV$2:AV37,AV37)-1) | AV37: =-AR37 -> 0
A38: 4 | B38: =IFERROR(INDEX($AL$2:$AL$1001,MATCH($A38,$AT$2:$AT$1001,0)),"") -> USX:AAPL:USD | C38: =IF($B38="","",INDEX($AM$2:$AM$1001,MATCH($A38,$AT$2:$AT$1001,0))) -> USX | D38: =IF($B38="","",INDEX($AO$2:$AO$1001,MATCH($A38,$AT$2:$AT$1001,0))) -> USD | E38: =IF($B38="","",INDEX($AP$2:$AP$1001,MATCH($A38,$AT$2:$AT$1001,0))) -> 80 | F38: =IF($B38="","",INDEX($AR$2:$AR$1001,MATCH($A38,$AT$2:$AT$1001,0))) -> 8907.4479 | G38: =IF($B38="","",INDEX($AS$2:$AS$1001,MATCH($A38,$AT$2:$AT$1001,0))) -> 0.75631175 | H38: =IF($B38="","",IF(E38=0,"Closed","Open")) -> Open | J38: 4 | K38: =IFERROR(INDEX($AL$2:$AL$1001,MATCH($J38,$AU$2:$AU$1001,0)),"") | L38: =IF($K38="","",INDEX($AM$2:$AM$1001,MATCH($J38,$AU$2:$AU$1001,0))) | M38: =IF($K38="","",INDEX($AO$2:$AO$1001,MATCH($J38,$AU$2:$AU$1001,0))) | N38: =IF($K38="","",INDEX($AP$2:$AP$1001,MATCH($J38,$AU$2:$AU$1001,0))) | O38: =IF($K38="","",INDEX($AR$2:$AR$1001,MATCH($J38,$AU$2:$AU$1001,0))) | P38: =IF($K38="","",INDEX($AS$2:$AS$1001,MATCH($J38,$AU$2:$AU$1001,0))) | Q38: =IF($K38="","",IF(N38=0,"Closed","Open")) | Z38: =Shares!A38 | AA38: =Shares!B38 | AB38: =Shares!C38 | AC38: =Shares!D38 | AD38: =IF($Z38="",0,Shares!E38) -> 0 | AE38: =IF($Z38="",0,Shares!K38*Shares!J38) -> 0 | AF38: =IFERROR(AE38/$B$5,0) -> 0 | AG38: =IF($Z38="",0,Shares!M38) -> 0 | AH38: =IF($Z38="",0,Shares!N38) -> 0 | AI38: =IF($Z38="","",RANK(AE38,$AE$2:$AE$1001)+COUNTIF($AE$2:AE38,AE38)-1) | AJ38: =IF($AD38<0,COUNT($AJ$1:AJ37)+1,"") | AL38: ='All Ticker P&L'!A38 | AM38: ='All Ticker P&L'!B38 | AN38: ='All Ticker P&L'!C38 | AO38: ='All Ticker P&L'!D38 | AP38: =IF($AL38="",0,'All Ticker P&L'!E38) -> 0 | AQ38: =IF($AL38="",0,'All Ticker P&L'!J38*'All Ticker P&L'!I38) -> 0 | AR38: =IF($AL38="",0,'All Ticker P&L'!L38) -> 0 | AS38: =IF($AL38="",0,'All Ticker P&L'!M38) -> 0 | AT38: =IF($AL38="","",RANK(AR38,$AR$2:$AR$1001)+COUNTIF($AR$2:AR38,AR38)-1) | AU38: =IF($AL38="","",RANK(AV38,$AV$2:$AV$1001)+COUNTIF($AV$2:AV38,AV38)-1) | AV38: =-AR38 -> 0
A39: 5 | B39: =IFERROR(INDEX($AL$2:$AL$1001,MATCH($A39,$AT$2:$AT$1001,0)),"") -> USX:MSFT:USD | C39: =IF($B39="","",INDEX($AM$2:$AM$1001,MATCH($A39,$AT$2:$AT$1001,0))) -> USX | D39: =IF($B39="","",INDEX($AO$2:$AO$1001,MATCH($A39,$AT$2:$AT$1001,0))) -> USD | E39: =IF($B39="","",INDEX($AP$2:$AP$1001,MATCH($A39,$AT$2:$AT$1001,0))) -> 20 | F39: =IF($B39="","",INDEX($AR$2:$AR$1001,MATCH($A39,$AT$2:$AT$1001,0))) -> 4906.2068 | G39: =IF($B39="","",INDEX($AS$2:$AS$1001,MATCH($A39,$AT$2:$AT$1001,0))) -> 0.82410423 | H39: =IF($B39="","",IF(E39=0,"Closed","Open")) -> Open | J39: 5 | K39: =IFERROR(INDEX($AL$2:$AL$1001,MATCH($J39,$AU$2:$AU$1001,0)),"") | L39: =IF($K39="","",INDEX($AM$2:$AM$1001,MATCH($J39,$AU$2:$AU$1001,0))) | M39: =IF($K39="","",INDEX($AO$2:$AO$1001,MATCH($J39,$AU$2:$AU$1001,0))) | N39: =IF($K39="","",INDEX($AP$2:$AP$1001,MATCH($J39,$AU$2:$AU$1001,0))) | O39: =IF($K39="","",INDEX($AR$2:$AR$1001,MATCH($J39,$AU$2:$AU$1001,0))) | P39: =IF($K39="","",INDEX($AS$2:$AS$1001,MATCH($J39,$AU$2:$AU$1001,0))) | Q39: =IF($K39="","",IF(N39=0,"Closed","Open")) | Z39: =Shares!A39 | AA39: =Shares!B39 | AB39: =Shares!C39 | AC39: =Shares!D39 | AD39: =IF($Z39="",0,Shares!E39) -> 0 | AE39: =IF($Z39="",0,Shares!K39*Shares!J39) -> 0 | AF39: =IFERROR(AE39/$B$5,0) -> 0 | AG39: =IF($Z39="",0,Shares!M39) -> 0 | AH39: =IF($Z39="",0,Shares!N39) -> 0 | AI39: =IF($Z39="","",RANK(AE39,$AE$2:$AE$1001)+COUNTIF($AE$2:AE39,AE39)-1) | AJ39: =IF($AD39<0,COUNT($AJ$1:AJ38)+1,"") | AL39: ='All Ticker P&L'!A39 | AM39: ='All Ticker P&L'!B39 | AN39: ='All Ticker P&L'!C39 | AO39: ='All Ticker P&L'!D39 | AP39: =IF($AL39="",0,'All Ticker P&L'!E39) -> 0 | AQ39: =IF($AL39="",0,'All Ticker P&L'!J39*'All Ticker P&L'!I39) -> 0 | AR39: =IF($AL39="",0,'All Ticker P&L'!L39) -> 0 | AS39: =IF($AL39="",0,'All Ticker P&L'!M39) -> 0 | AT39: =IF($AL39="","",RANK(AR39,$AR$2:$AR$1001)+COUNTIF($AR$2:AR39,AR39)-1) | AU39: =IF($AL39="","",RANK(AV39,$AV$2:$AV$1001)+COUNTIF($AV$2:AV39,AV39)-1) | AV39: =-AR39 -> 0
A40: 6 | B40: =IFERROR(INDEX($AL$2:$AL$1001,MATCH($A40,$AT$2:$AT$1001,0)),"") -> SGX:Z74:SGD | C40: =IF($B40="","",INDEX($AM$2:$AM$1001,MATCH($A40,$AT$2:$AT$1001,0))) -> SGX | D40: =IF($B40="","",INDEX($AO$2:$AO$1001,MATCH($A40,$AT$2:$AT$1001,0))) -> SGD | E40: =IF($B40="","",INDEX($AP$2:$AP$1001,MATCH($A40,$AT$2:$AT$1001,0))) -> 3000 | F40: =IF($B40="","",INDEX($AR$2:$AR$1001,MATCH($A40,$AT$2:$AT$1001,0))) -> 2135 | G40: =IF($B40="","",INDEX($AS$2:$AS$1001,MATCH($A40,$AT$2:$AT$1001,0))) -> 0.22895442 | H40: =IF($B40="","",IF(E40=0,"Closed","Open")) -> Open | J40: 6 | K40: =IFERROR(INDEX($AL$2:$AL$1001,MATCH($J40,$AU$2:$AU$1001,0)),"") | L40: =IF($K40="","",INDEX($AM$2:$AM$1001,MATCH($J40,$AU$2:$AU$1001,0))) | M40: =IF($K40="","",INDEX($AO$2:$AO$1001,MATCH($J40,$AU$2:$AU$1001,0))) | N40: =IF($K40="","",INDEX($AP$2:$AP$1001,MATCH($J40,$AU$2:$AU$1001,0))) | O40: =IF($K40="","",INDEX($AR$2:$AR$1001,MATCH($J40,$AU$2:$AU$1001,0))) | P40: =IF($K40="","",INDEX($AS$2:$AS$1001,MATCH($J40,$AU$2:$AU$1001,0))) | Q40: =IF($K40="","",IF(N40=0,"Closed","Open")) | Z40: =Shares!A40 | AA40: =Shares!B40 | AB40: =Shares!C40 | AC40: =Shares!D40 | AD40: =IF($Z40="",0,Shares!E40) -> 0 | AE40: =IF($Z40="",0,Shares!K40*Shares!J40) -> 0 | AF40: =IFERROR(AE40/$B$5,0) -> 0 | AG40: =IF($Z40="",0,Shares!M40) -> 0 | AH40: =IF($Z40="",0,Shares!N40) -> 0 | AI40: =IF($Z40="","",RANK(AE40,$AE$2:$AE$1001)+COUNTIF($AE$2:AE40,AE40)-1) | AJ40: =IF($AD40<0,COUNT($AJ$1:AJ39)+1,"") | AL40: ='All Ticker P&L'!A40 | AM40: ='All Ticker P&L'!B40 | AN40: ='All Ticker P&L'!C40 | AO40: ='All Ticker P&L'!D40 | AP40: =IF($AL40="",0,'All Ticker P&L'!E40) -> 0 | AQ40: =IF($AL40="",0,'All Ticker P&L'!J40*'All Ticker P&L'!I40) -> 0 | AR40: =IF($AL40="",0,'All Ticker P&L'!L40) -> 0 | AS40: =IF($AL40="",0,'All Ticker P&L'!M40) -> 0 | AT40: =IF($AL40="","",RANK(AR40,$AR$2:$AR$1001)+COUNTIF($AR$2:AR40,AR40)-1) | AU40: =IF($AL40="","",RANK(AV40,$AV$2:$AV$1001)+COUNTIF($AV$2:AV40,AV40)-1) | AV40: =-AR40 -> 0
A41: 7 | B41: =IFERROR(INDEX($AL$2:$AL$1001,MATCH($A41,$AT$2:$AT$1001,0)),"") -> SGX:CLR:SGD | C41: =IF($B41="","",INDEX($AM$2:$AM$1001,MATCH($A41,$AT$2:$AT$1001,0))) -> SGX | D41: =IF($B41="","",INDEX($AO$2:$AO$1001,MATCH($A41,$AT$2:$AT$1001,0))) -> SGD | E41: =IF($B41="","",INDEX($AP$2:$AP$1001,MATCH($A41,$AT$2:$AT$1001,0))) -> 10000 | F41: =IF($B41="","",INDEX($AR$2:$AR$1001,MATCH($A41,$AT$2:$AT$1001,0))) -> 1125 | G41: =IF($B41="","",INDEX($AS$2:$AS$1001,MATCH($A41,$AT$2:$AT$1001,0))) -> 0.16014235 | H41: =IF($B41="","",IF(E41=0,"Closed","Open")) -> Open | J41: 7 | K41: =IFERROR(INDEX($AL$2:$AL$1001,MATCH($J41,$AU$2:$AU$1001,0)),"") | L41: =IF($K41="","",INDEX($AM$2:$AM$1001,MATCH($J41,$AU$2:$AU$1001,0))) | M41: =IF($K41="","",INDEX($AO$2:$AO$1001,MATCH($J41,$AU$2:$AU$1001,0))) | N41: =IF($K41="","",INDEX($AP$2:$AP$1001,MATCH($J41,$AU$2:$AU$1001,0))) | O41: =IF($K41="","",INDEX($AR$2:$AR$1001,MATCH($J41,$AU$2:$AU$1001,0))) | P41: =IF($K41="","",INDEX($AS$2:$AS$1001,MATCH($J41,$AU$2:$AU$1001,0))) | Q41: =IF($K41="","",IF(N41=0,"Closed","Open")) | Z41: =Shares!A41 | AA41: =Shares!B41 | AB41: =Shares!C41 | AC41: =Shares!D41 | AD41: =IF($Z41="",0,Shares!E41) -> 0 | AE41: =IF($Z41="",0,Shares!K41*Shares!J41) -> 0 | AF41: =IFERROR(AE41/$B$5,0) -> 0 | AG41: =IF($Z41="",0,Shares!M41) -> 0 | AH41: =IF($Z41="",0,Shares!N41) -> 0 | AI41: =IF($Z41="","",RANK(AE41,$AE$2:$AE$1001)+COUNTIF($AE$2:AE41,AE41)-1) | AJ41: =IF($AD41<0,COUNT($AJ$1:AJ40)+1,"") | AL41: ='All Ticker P&L'!A41 | AM41: ='All Ticker P&L'!B41 | AN41: ='All Ticker P&L'!C41 | AO41: ='All Ticker P&L'!D41 | AP41: =IF($AL41="",0,'All Ticker P&L'!E41) -> 0 | AQ41: =IF($AL41="",0,'All Ticker P&L'!J41*'All Ticker P&L'!I41) -> 0 | AR41: =IF($AL41="",0,'All Ticker P&L'!L41) -> 0 | AS41: =IF($AL41="",0,'All Ticker P&L'!M41) -> 0 | AT41: =IF($AL41="","",RANK(AR41,$AR$2:$AR$1001)+COUNTIF($AR$2:AR41,AR41)-1) | AU41: =IF($AL41="","",RANK(AV41,$AV$2:$AV$1001)+COUNTIF($AV$2:AV41,AV41)-1) | AV41: =-AR41 -> 0
A42: 8 | B42: =IFERROR(INDEX($AL$2:$AL$1001,MATCH($A42,$AT$2:$AT$1001,0)),"") -> SGX:C38U:SGD | C42: =IF($B42="","",INDEX($AM$2:$AM$1001,MATCH($A42,$AT$2:$AT$1001,0))) -> SGX | D42: =IF($B42="","",INDEX($AO$2:$AO$1001,MATCH($A42,$AT$2:$AT$1001,0))) -> SGD | E42: =IF($B42="","",INDEX($AP$2:$AP$1001,MATCH($A42,$AT$2:$AT$1001,0))) -> 8000 | F42: =IF($B42="","",INDEX($AR$2:$AR$1001,MATCH($A42,$AT$2:$AT$1001,0))) -> 170 | G42: =IF($B42="","",INDEX($AS$2:$AS$1001,MATCH($A42,$AT$2:$AT$1001,0))) -> 0.010526316 | H42: =IF($B42="","",IF(E42=0,"Closed","Open")) -> Open | J42: 8 | K42: =IFERROR(INDEX($AL$2:$AL$1001,MATCH($J42,$AU$2:$AU$1001,0)),"") | L42: =IF($K42="","",INDEX($AM$2:$AM$1001,MATCH($J42,$AU$2:$AU$1001,0))) | M42: =IF($K42="","",INDEX($AO$2:$AO$1001,MATCH($J42,$AU$2:$AU$1001,0))) | N42: =IF($K42="","",INDEX($AP$2:$AP$1001,MATCH($J42,$AU$2:$AU$1001,0))) | O42: =IF($K42="","",INDEX($AR$2:$AR$1001,MATCH($J42,$AU$2:$AU$1001,0))) | P42: =IF($K42="","",INDEX($AS$2:$AS$1001,MATCH($J42,$AU$2:$AU$1001,0))) | Q42: =IF($K42="","",IF(N42=0,"Closed","Open")) | Z42: =Shares!A42 | AA42: =Shares!B42 | AB42: =Shares!C42 | AC42: =Shares!D42 | AD42: =IF($Z42="",0,Shares!E42) -> 0 | AE42: =IF($Z42="",0,Shares!K42*Shares!J42) -> 0 | AF42: =IFERROR(AE42/$B$5,0) -> 0 | AG42: =IF($Z42="",0,Shares!M42) -> 0 | AH42: =IF($Z42="",0,Shares!N42) -> 0 | AI42: =IF($Z42="","",RANK(AE42,$AE$2:$AE$1001)+COUNTIF($AE$2:AE42,AE42)-1) | AJ42: =IF($AD42<0,COUNT($AJ$1:AJ41)+1,"") | AL42: ='All Ticker P&L'!A42 | AM42: ='All Ticker P&L'!B42 | AN42: ='All Ticker P&L'!C42 | AO42: ='All Ticker P&L'!D42 | AP42: =IF($AL42="",0,'All Ticker P&L'!E42) -> 0 | AQ42: =IF($AL42="",0,'All Ticker P&L'!J42*'All Ticker P&L'!I42) -> 0 | AR42: =IF($AL42="",0,'All Ticker P&L'!L42) -> 0 | AS42: =IF($AL42="",0,'All Ticker P&L'!M42) -> 0 | AT42: =IF($AL42="","",RANK(AR42,$AR$2:$AR$1001)+COUNTIF($AR$2:AR42,AR42)-1) | AU42: =IF($AL42="","",RANK(AV42,$AV$2:$AV$1001)+COUNTIF($AV$2:AV42,AV42)-1) | AV42: =-AR42 -> 0
A43: 9 | B43: =IFERROR(INDEX($AL$2:$AL$1001,MATCH($A43,$AT$2:$AT$1001,0)),"") | C43: =IF($B43="","",INDEX($AM$2:$AM$1001,MATCH($A43,$AT$2:$AT$1001,0))) | D43: =IF($B43="","",INDEX($AO$2:$AO$1001,MATCH($A43,$AT$2:$AT$1001,0))) | E43: =IF($B43="","",INDEX($AP$2:$AP$1001,MATCH($A43,$AT$2:$AT$1001,0))) | F43: =IF($B43="","",INDEX($AR$2:$AR$1001,MATCH($A43,$AT$2:$AT$1001,0))) | G43: =IF($B43="","",INDEX($AS$2:$AS$1001,MATCH($A43,$AT$2:$AT$1001,0))) | H43: =IF($B43="","",IF(E43=0,"Closed","Open")) | J43: 9 | K43: =IFERROR(INDEX($AL$2:$AL$1001,MATCH($J43,$AU$2:$AU$1001,0)),"") | L43: =IF($K43="","",INDEX($AM$2:$AM$1001,MATCH($J43,$AU$2:$AU$1001,0))) | M43: =IF($K43="","",INDEX($AO$2:$AO$1001,MATCH($J43,$AU$2:$AU$1001,0))) | N43: =IF($K43="","",INDEX($AP$2:$AP$1001,MATCH($J43,$AU$2:$AU$1001,0))) | O43: =IF($K43="","",INDEX($AR$2:$AR$1001,MATCH($J43,$AU$2:$AU$1001,0))) | P43: =IF($K43="","",INDEX($AS$2:$AS$1001,MATCH($J43,$AU$2:$AU$1001,0))) | Q43: =IF($K43="","",IF(N43=0,"Closed","Open")) | Z43: =Shares!A43 | AA43: =Shares!B43 | AB43: =Shares!C43 | AC43: =Shares!D43 | AD43: =IF($Z43="",0,Shares!E43) -> 0 | AE43: =IF($Z43="",0,Shares!K43*Shares!J43) -> 0 | AF43: =IFERROR(AE43/$B$5,0) -> 0 | AG43: =IF($Z43="",0,Shares!M43) -> 0 | AH43: =IF($Z43="",0,Shares!N43) -> 0 | AI43: =IF($Z43="","",RANK(AE43,$AE$2:$AE$1001)+COUNTIF($AE$2:AE43,AE43)-1) | AJ43: =IF($AD43<0,COUNT($AJ$1:AJ42)+1,"") | AL43: ='All Ticker P&L'!A43 | AM43: ='All Ticker P&L'!B43 | AN43: ='All Ticker P&L'!C43 | AO43: ='All Ticker P&L'!D43 | AP43: =IF($AL43="",0,'All Ticker P&L'!E43) -> 0 | AQ43: =IF($AL43="",0,'All Ticker P&L'!J43*'All Ticker P&L'!I43) -> 0 | AR43: =IF($AL43="",0,'All Ticker P&L'!L43) -> 0 | AS43: =IF($AL43="",0,'All Ticker P&L'!M43) -> 0 | AT43: =IF($AL43="","",RANK(AR43,$AR$2:$AR$1001)+COUNTIF($AR$2:AR43,AR43)-1) | AU43: =IF($AL43="","",RANK(AV43,$AV$2:$AV$1001)+COUNTIF($AV$2:AV43,AV43)-1) | AV43: =-AR43 -> 0
A44: 10 | B44: =IFERROR(INDEX($AL$2:$AL$1001,MATCH($A44,$AT$2:$AT$1001,0)),"") | C44: =IF($B44="","",INDEX($AM$2:$AM$1001,MATCH($A44,$AT$2:$AT$1001,0))) | D44: =IF($B44="","",INDEX($AO$2:$AO$1001,MATCH($A44,$AT$2:$AT$1001,0))) | E44: =IF($B44="","",INDEX($AP$2:$AP$1001,MATCH($A44,$AT$2:$AT$1001,0))) | F44: =IF($B44="","",INDEX($AR$2:$AR$1001,MATCH($A44,$AT$2:$AT$1001,0))) | G44: =IF($B44="","",INDEX($AS$2:$AS$1001,MATCH($A44,$AT$2:$AT$1001,0))) | H44: =IF($B44="","",IF(E44=0,"Closed","Open")) | J44: 10 | K44: =IFERROR(INDEX($AL$2:$AL$1001,MATCH($J44,$AU$2:$AU$1001,0)),"") | L44: =IF($K44="","",INDEX($AM$2:$AM$1001,MATCH($J44,$AU$2:$AU$1001,0))) | M44: =IF($K44="","",INDEX($AO$2:$AO$1001,MATCH($J44,$AU$2:$AU$1001,0))) | N44: =IF($K44="","",INDEX($AP$2:$AP$1001,MATCH($J44,$AU$2:$AU$1001,0))) | O44: =IF($K44="","",INDEX($AR$2:$AR$1001,MATCH($J44,$AU$2:$AU$1001,0))) | P44: =IF($K44="","",INDEX($AS$2:$AS$1001,MATCH($J44,$AU$2:$AU$1001,0))) | Q44: =IF($K44="","",IF(N44=0,"Closed","Open")) | Z44: =Shares!A44 | AA44: =Shares!B44 | AB44: =Shares!C44 | AC44: =Shares!D44 | AD44: =IF($Z44="",0,Shares!E44) -> 0 | AE44: =IF($Z44="",0,Shares!K44*Shares!J44) -> 0 | AF44: =IFERROR(AE44/$B$5,0) -> 0 | AG44: =IF($Z44="",0,Shares!M44) -> 0 | AH44: =IF($Z44="",0,Shares!N44) -> 0 | AI44: =IF($Z44="","",RANK(AE44,$AE$2:$AE$1001)+COUNTIF($AE$2:AE44,AE44)-1) | AJ44: =IF($AD44<0,COUNT($AJ$1:AJ43)+1,"") | AL44: ='All Ticker P&L'!A44 | AM44: ='All Ticker P&L'!B44 | AN44: ='All Ticker P&L'!C44 | AO44: ='All Ticker P&L'!D44 | AP44: =IF($AL44="",0,'All Ticker P&L'!E44) -> 0 | AQ44: =IF($AL44="",0,'All Ticker P&L'!J44*'All Ticker P&L'!I44) -> 0 | AR44: =IF($AL44="",0,'All Ticker P&L'!L44) -> 0 | AS44: =IF($AL44="",0,'All Ticker P&L'!M44) -> 0 | AT44: =IF($AL44="","",RANK(AR44,$AR$2:$AR$1001)+COUNTIF($AR$2:AR44,AR44)-1) | AU44: =IF($AL44="","",RANK(AV44,$AV$2:$AV$1001)+COUNTIF($AV$2:AV44,AV44)-1) | AV44: =-AR44 -> 0
Z45: =Shares!A45 | AA45: =Shares!B45 | AB45: =Shares!C45 | AC45: =Shares!D45 | AD45: =IF($Z45="",0,Shares!E45) -> 0 | AE45: =IF($Z45="",0,Shares!K45*Shares!J45) -> 0 | AF45: =IFERROR(AE45/$B$5,0) -> 0 | AG45: =IF($Z45="",0,Shares!M45) -> 0 | AH45: =IF($Z45="",0,Shares!N45) -> 0 | AI45: =IF($Z45="","",RANK(AE45,$AE$2:$AE$1001)+COUNTIF($AE$2:AE45,AE45)-1) | AJ45: =IF($AD45<0,COUNT($AJ$1:AJ44)+1,"") | AL45: ='All Ticker P&L'!A45 | AM45: ='All Ticker P&L'!B45 | AN45: ='All Ticker P&L'!C45 | AO45: ='All Ticker P&L'!D45 | AP45: =IF($AL45="",0,'All Ticker P&L'!E45) -> 0 | AQ45: =IF($AL45="",0,'All Ticker P&L'!J45*'All Ticker P&L'!I45) -> 0 | AR45: =IF($AL45="",0,'All Ticker P&L'!L45) -> 0 | AS45: =IF($AL45="",0,'All Ticker P&L'!M45) -> 0 | AT45: =IF($AL45="","",RANK(AR45,$AR$2:$AR$1001)+COUNTIF($AR$2:AR45,AR45)-1) | AU45: =IF($AL45="","",RANK(AV45,$AV$2:$AV$1001)+COUNTIF($AV$2:AV45,AV45)-1) | AV45: =-AR45 -> 0
Z46: =Shares!A46 | AA46: =Shares!B46 | AB46: =Shares!C46 | AC46: =Shares!D46 | AD46: =IF($Z46="",0,Shares!E46) -> 0 | AE46: =IF($Z46="",0,Shares!K46*Shares!J46) -> 0 | AF46: =IFERROR(AE46/$B$5,0) -> 0 | AG46: =IF($Z46="",0,Shares!M46) -> 0 | AH46: =IF($Z46="",0,Shares!N46) -> 0 | AI46: =IF($Z46="","",RANK(AE46,$AE$2:$AE$1001)+COUNTIF($AE$2:AE46,AE46)-1) | AJ46: =IF($AD46<0,COUNT($AJ$1:AJ45)+1,"") | AL46: ='All Ticker P&L'!A46 | AM46: ='All Ticker P&L'!B46 | AN46: ='All Ticker P&L'!C46 | AO46: ='All Ticker P&L'!D46 | AP46: =IF($AL46="",0,'All Ticker P&L'!E46) -> 0 | AQ46: =IF($AL46="",0,'All Ticker P&L'!J46*'All Ticker P&L'!I46) -> 0 | AR46: =IF($AL46="",0,'All Ticker P&L'!L46) -> 0 | AS46: =IF($AL46="",0,'All Ticker P&L'!M46) -> 0 | AT46: =IF($AL46="","",RANK(AR46,$AR$2:$AR$1001)+COUNTIF($AR$2:AR46,AR46)-1) | AU46: =IF($AL46="","",RANK(AV46,$AV$2:$AV$1001)+COUNTIF($AV$2:AV46,AV46)-1) | AV46: =-AR46 -> 0
A47: Negative / Short Position Watchlist | J47: Data Checks | Z47: =Shares!A47 | AA47: =Shares!B47 | AB47: =Shares!C47 | AC47: =Shares!D47 | AD47: =IF($Z47="",0,Shares!E47) -> 0 | AE47: =IF($Z47="",0,Shares!K47*Shares!J47) -> 0 | AF47: =IFERROR(AE47/$B$5,0) -> 0 | AG47: =IF($Z47="",0,Shares!M47) -> 0 | AH47: =IF($Z47="",0,Shares!N47) -> 0 | AI47: =IF($Z47="","",RANK(AE47,$AE$2:$AE$1001)+COUNTIF($AE$2:AE47,AE47)-1) | AJ47: =IF($AD47<0,COUNT($AJ$1:AJ46)+1,"") | AL47: ='All Ticker P&L'!A47 | AM47: ='All Ticker P&L'!B47 | AN47: ='All Ticker P&L'!C47 | AO47: ='All Ticker P&L'!D47 | AP47: =IF($AL47="",0,'All Ticker P&L'!E47) -> 0 | AQ47: =IF($AL47="",0,'All Ticker P&L'!J47*'All Ticker P&L'!I47) -> 0 | AR47: =IF($AL47="",0,'All Ticker P&L'!L47) -> 0 | AS47: =IF($AL47="",0,'All Ticker P&L'!M47) -> 0 | AT47: =IF($AL47="","",RANK(AR47,$AR$2:$AR$1001)+COUNTIF($AR$2:AR47,AR47)-1) | AU47: =IF($AL47="","",RANK(AV47,$AV$2:$AV$1001)+COUNTIF($AV$2:AV47,AV47)-1) | AV47: =-AR47 -> 0
A48: Rank | B48: Key | C48: Exchange | D48: Currency | E48: Units Held | F48: Market Value SGD | G48: P&L SGD | H48: Weight | J48: Negative / short positions | K48: =$B$13 -> 0 | Z48: =Shares!A48 | AA48: =Shares!B48 | AB48: =Shares!C48 | AC48: =Shares!D48 | AD48: =IF($Z48="",0,Shares!E48) -> 0 | AE48: =IF($Z48="",0,Shares!K48*Shares!J48) -> 0 | AF48: =IFERROR(AE48/$B$5,0) -> 0 | AG48: =IF($Z48="",0,Shares!M48) -> 0 | AH48: =IF($Z48="",0,Shares!N48) -> 0 | AI48: =IF($Z48="","",RANK(AE48,$AE$2:$AE$1001)+COUNTIF($AE$2:AE48,AE48)-1) | AJ48: =IF($AD48<0,COUNT($AJ$1:AJ47)+1,"") | AL48: ='All Ticker P&L'!A48 | AM48: ='All Ticker P&L'!B48 | AN48: ='All Ticker P&L'!C48 | AO48: ='All Ticker P&L'!D48 | AP48: =IF($AL48="",0,'All Ticker P&L'!E48) -> 0 | AQ48: =IF($AL48="",0,'All Ticker P&L'!J48*'All Ticker P&L'!I48) -> 0 | AR48: =IF($AL48="",0,'All Ticker P&L'!L48) -> 0 | AS48: =IF($AL48="",0,'All Ticker P&L'!M48) -> 0 | AT48: =IF($AL48="","",RANK(AR48,$AR$2:$AR$1001)+COUNTIF($AR$2:AR48,AR48)-1) | AU48: =IF($AL48="","",RANK(AV48,$AV$2:$AV$1001)+COUNTIF($AV$2:AV48,AV48)-1) | AV48: =-AR48 -> 0
A49: 1 | B49: =IFERROR(INDEX($Z$2:$Z$1001,MATCH($A49,$AJ$2:$AJ$1001,0)),"") | C49: =IF($B49="","",INDEX($AA$2:$AA$1001,MATCH($A49,$AJ$2:$AJ$1001,0))) | D49: =IF($B49="","",INDEX($AC$2:$AC$1001,MATCH($A49,$AJ$2:$AJ$1001,0))) | E49: =IF($B49="","",INDEX($AD$2:$AD$1001,MATCH($A49,$AJ$2:$AJ$1001,0))) | F49: =IF($B49="","",INDEX($AE$2:$AE$1001,MATCH($A49,$AJ$2:$AJ$1001,0))) | G49: =IF($B49="","",INDEX($AG$2:$AG$1001,MATCH($A49,$AJ$2:$AJ$1001,0))) | H49: =IF($B49="","",INDEX($AF$2:$AF$1001,MATCH($A49,$AJ$2:$AJ$1001,0))) | J49: Missing price or FX warnings | K49: =$B$14 -> 0 | Z49: =Shares!A49 | AA49: =Shares!B49 | AB49: =Shares!C49 | AC49: =Shares!D49 | AD49: =IF($Z49="",0,Shares!E49) -> 0 | AE49: =IF($Z49="",0,Shares!K49*Shares!J49) -> 0 | AF49: =IFERROR(AE49/$B$5,0) -> 0 | AG49: =IF($Z49="",0,Shares!M49) -> 0 | AH49: =IF($Z49="",0,Shares!N49) -> 0 | AI49: =IF($Z49="","",RANK(AE49,$AE$2:$AE$1001)+COUNTIF($AE$2:AE49,AE49)-1) | AJ49: =IF($AD49<0,COUNT($AJ$1:AJ48)+1,"") | AL49: ='All Ticker P&L'!A49 | AM49: ='All Ticker P&L'!B49 | AN49: ='All Ticker P&L'!C49 | AO49: ='All Ticker P&L'!D49 | AP49: =IF($AL49="",0,'All Ticker P&L'!E49) -> 0 | AQ49: =IF($AL49="",0,'All Ticker P&L'!J49*'All Ticker P&L'!I49) -> 0 | AR49: =IF($AL49="",0,'All Ticker P&L'!L49) -> 0 | AS49: =IF($AL49="",0,'All Ticker P&L'!M49) -> 0 | AT49: =IF($AL49="","",RANK(AR49,$AR$2:$AR$1001)+COUNTIF($AR$2:AR49,AR49)-1) | AU49: =IF($AL49="","",RANK(AV49,$AV$2:$AV$1001)+COUNTIF($AV$2:AV49,AV49)-1) | AV49: =-AR49 -> 0
A50: 2 | B50: =IFERROR(INDEX($Z$2:$Z$1001,MATCH($A50,$AJ$2:$AJ$1001,0)),"") | C50: =IF($B50="","",INDEX($AA$2:$AA$1001,MATCH($A50,$AJ$2:$AJ$1001,0))) | D50: =IF($B50="","",INDEX($AC$2:$AC$1001,MATCH($A50,$AJ$2:$AJ$1001,0))) | E50: =IF($B50="","",INDEX($AD$2:$AD$1001,MATCH($A50,$AJ$2:$AJ$1001,0))) | F50: =IF($B50="","",INDEX($AE$2:$AE$1001,MATCH($A50,$AJ$2:$AJ$1001,0))) | G50: =IF($B50="","",INDEX($AG$2:$AG$1001,MATCH($A50,$AJ$2:$AJ$1001,0))) | H50: =IF($B50="","",INDEX($AF$2:$AF$1001,MATCH($A50,$AJ$2:$AJ$1001,0))) | J50: Open positions with zero market value | K50: =COUNTIFS($Z$2:$Z$1001,"?*",$AE$2:$AE$1001,0) -> 0 | Z50: =Shares!A50 | AA50: =Shares!B50 | AB50: =Shares!C50 | AC50: =Shares!D50 | AD50: =IF($Z50="",0,Shares!E50) -> 0 | AE50: =IF($Z50="",0,Shares!K50*Shares!J50) -> 0 | AF50: =IFERROR(AE50/$B$5,0) -> 0 | AG50: =IF($Z50="",0,Shares!M50) -> 0 | AH50: =IF($Z50="",0,Shares!N50) -> 0 | AI50: =IF($Z50="","",RANK(AE50,$AE$2:$AE$1001)+COUNTIF($AE$2:AE50,AE50)-1) | AJ50: =IF($AD50<0,COUNT($AJ$1:AJ49)+1,"") | AL50: ='All Ticker P&L'!A50 | AM50: ='All Ticker P&L'!B50 | AN50: ='All Ticker P&L'!C50 | AO50: ='All Ticker P&L'!D50 | AP50: =IF($AL50="",0,'All Ticker P&L'!E50) -> 0 | AQ50: =IF($AL50="",0,'All Ticker P&L'!J50*'All Ticker P&L'!I50) -> 0 | AR50: =IF($AL50="",0,'All Ticker P&L'!L50) -> 0 | AS50: =IF($AL50="",0,'All Ticker P&L'!M50) -> 0 | AT50: =IF($AL50="","",RANK(AR50,$AR$2:$AR$1001)+COUNTIF($AR$2:AR50,AR50)-1) | AU50: =IF($AL50="","",RANK(AV50,$AV$2:$AV$1001)+COUNTIF($AV$2:AV50,AV50)-1) | AV50: =-AR50 -> 0
A51: 3 | B51: =IFERROR(INDEX($Z$2:$Z$1001,MATCH($A51,$AJ$2:$AJ$1001,0)),"") | C51: =IF($B51="","",INDEX($AA$2:$AA$1001,MATCH($A51,$AJ$2:$AJ$1001,0))) | D51: =IF($B51="","",INDEX($AC$2:$AC$1001,MATCH($A51,$AJ$2:$AJ$1001,0))) | E51: =IF($B51="","",INDEX($AD$2:$AD$1001,MATCH($A51,$AJ$2:$AJ$1001,0))) | F51: =IF($B51="","",INDEX($AE$2:$AE$1001,MATCH($A51,$AJ$2:$AJ$1001,0))) | G51: =IF($B51="","",INDEX($AG$2:$AG$1001,MATCH($A51,$AJ$2:$AJ$1001,0))) | H51: =IF($B51="","",INDEX($AF$2:$AF$1001,MATCH($A51,$AJ$2:$AJ$1001,0))) | J51: Top holding concentration | K51: =$B$12 -> 0.43925024 | Z51: =Shares!A51 | AA51: =Shares!B51 | AB51: =Shares!C51 | AC51: =Shares!D51 | AD51: =IF($Z51="",0,Shares!E51) -> 0 | AE51: =IF($Z51="",0,Shares!K51*Shares!J51) -> 0 | AF51: =IFERROR(AE51/$B$5,0) -> 0 | AG51: =IF($Z51="",0,Shares!M51) -> 0 | AH51: =IF($Z51="",0,Shares!N51) -> 0 | AI51: =IF($Z51="","",RANK(AE51,$AE$2:$AE$1001)+COUNTIF($AE$2:AE51,AE51)-1) | AJ51: =IF($AD51<0,COUNT($AJ$1:AJ50)+1,"") | AL51: ='All Ticker P&L'!A51 | AM51: ='All Ticker P&L'!B51 | AN51: ='All Ticker P&L'!C51 | AO51: ='All Ticker P&L'!D51 | AP51: =IF($AL51="",0,'All Ticker P&L'!E51) -> 0 | AQ51: =IF($AL51="",0,'All Ticker P&L'!J51*'All Ticker P&L'!I51) -> 0 | AR51: =IF($AL51="",0,'All Ticker P&L'!L51) -> 0 | AS51: =IF($AL51="",0,'All Ticker P&L'!M51) -> 0 | AT51: =IF($AL51="","",RANK(AR51,$AR$2:$AR$1001)+COUNTIF($AR$2:AR51,AR51)-1) | AU51: =IF($AL51="","",RANK(AV51,$AV$2:$AV$1001)+COUNTIF($AV$2:AV51,AV51)-1) | AV51: =-AR51 -> 0
A52: 4 | B52: =IFERROR(INDEX($Z$2:$Z$1001,MATCH($A52,$AJ$2:$AJ$1001,0)),"") | C52: =IF($B52="","",INDEX($AA$2:$AA$1001,MATCH($A52,$AJ$2:$AJ$1001,0))) | D52: =IF($B52="","",INDEX($AC$2:$AC$1001,MATCH($A52,$AJ$2:$AJ$1001,0))) | E52: =IF($B52="","",INDEX($AD$2:$AD$1001,MATCH($A52,$AJ$2:$AJ$1001,0))) | F52: =IF($B52="","",INDEX($AE$2:$AE$1001,MATCH($A52,$AJ$2:$AJ$1001,0))) | G52: =IF($B52="","",INDEX($AG$2:$AG$1001,MATCH($A52,$AJ$2:$AJ$1001,0))) | H52: =IF($B52="","",INDEX($AF$2:$AF$1001,MATCH($A52,$AJ$2:$AJ$1001,0))) | Z52: =Shares!A52 | AA52: =Shares!B52 | AB52: =Shares!C52 | AC52: =Shares!D52 | AD52: =IF($Z52="",0,Shares!E52) -> 0 | AE52: =IF($Z52="",0,Shares!K52*Shares!J52) -> 0 | AF52: =IFERROR(AE52/$B$5,0) -> 0 | AG52: =IF($Z52="",0,Shares!M52) -> 0 | AH52: =IF($Z52="",0,Shares!N52) -> 0 | AI52: =IF($Z52="","",RANK(AE52,$AE$2:$AE$1001)+COUNTIF($AE$2:AE52,AE52)-1) | AJ52: =IF($AD52<0,COUNT($AJ$1:AJ51)+1,"") | AL52: ='All Ticker P&L'!A52 | AM52: ='All Ticker P&L'!B52 | AN52: ='All Ticker P&L'!C52 | AO52: ='All Ticker P&L'!D52 | AP52: =IF($AL52="",0,'All Ticker P&L'!E52) -> 0 | AQ52: =IF($AL52="",0,'All Ticker P&L'!J52*'All Ticker P&L'!I52) -> 0 | AR52: =IF($AL52="",0,'All Ticker P&L'!L52) -> 0 | AS52: =IF($AL52="",0,'All Ticker P&L'!M52) -> 0 | AT52: =IF($AL52="","",RANK(AR52,$AR$2:$AR$1001)+COUNTIF($AR$2:AR52,AR52)-1) | AU52: =IF($AL52="","",RANK(AV52,$AV$2:$AV$1001)+COUNTIF($AV$2:AV52,AV52)-1) | AV52: =-AR52 -> 0
A53: 5 | B53: =IFERROR(INDEX($Z$2:$Z$1001,MATCH($A53,$AJ$2:$AJ$1001,0)),"") | C53: =IF($B53="","",INDEX($AA$2:$AA$1001,MATCH($A53,$AJ$2:$AJ$1001,0))) | D53: =IF($B53="","",INDEX($AC$2:$AC$1001,MATCH($A53,$AJ$2:$AJ$1001,0))) | E53: =IF($B53="","",INDEX($AD$2:$AD$1001,MATCH($A53,$AJ$2:$AJ$1001,0))) | F53: =IF($B53="","",INDEX($AE$2:$AE$1001,MATCH($A53,$AJ$2:$AJ$1001,0))) | G53: =IF($B53="","",INDEX($AG$2:$AG$1001,MATCH($A53,$AJ$2:$AJ$1001,0))) | H53: =IF($B53="","",INDEX($AF$2:$AF$1001,MATCH($A53,$AJ$2:$AJ$1001,0))) | Z53: =Shares!A53 | AA53: =Shares!B53 | AB53: =Shares!C53 | AC53: =Shares!D53 | AD53: =IF($Z53="",0,Shares!E53) -> 0 | AE53: =IF($Z53="",0,Shares!K53*Shares!J53) -> 0 | AF53: =IFERROR(AE53/$B$5,0) -> 0 | AG53: =IF($Z53="",0,Shares!M53) -> 0 | AH53: =IF($Z53="",0,Shares!N53) -> 0 | AI53: =IF($Z53="","",RANK(AE53,$AE$2:$AE$1001)+COUNTIF($AE$2:AE53,AE53)-1) | AJ53: =IF($AD53<0,COUNT($AJ$1:AJ52)+1,"") | AL53: ='All Ticker P&L'!A53 | AM53: ='All Ticker P&L'!B53 | AN53: ='All Ticker P&L'!C53 | AO53: ='All Ticker P&L'!D53 | AP53: =IF($AL53="",0,'All Ticker P&L'!E53) -> 0 | AQ53: =IF($AL53="",0,'All Ticker P&L'!J53*'All Ticker P&L'!I53) -> 0 | AR53: =IF($AL53="",0,'All Ticker P&L'!L53) -> 0 | AS53: =IF($AL53="",0,'All Ticker P&L'!M53) -> 0 | AT53: =IF($AL53="","",RANK(AR53,$AR$2:$AR$1001)+COUNTIF($AR$2:AR53,AR53)-1) | AU53: =IF($AL53="","",RANK(AV53,$AV$2:$AV$1001)+COUNTIF($AV$2:AV53,AV53)-1) | AV53: =-AR53 -> 0
A54: 6 | B54: =IFERROR(INDEX($Z$2:$Z$1001,MATCH($A54,$AJ$2:$AJ$1001,0)),"") | C54: =IF($B54="","",INDEX($AA$2:$AA$1001,MATCH($A54,$AJ$2:$AJ$1001,0))) | D54: =IF($B54="","",INDEX($AC$2:$AC$1001,MATCH($A54,$AJ$2:$AJ$1001,0))) | E54: =IF($B54="","",INDEX($AD$2:$AD$1001,MATCH($A54,$AJ$2:$AJ$1001,0))) | F54: =IF($B54="","",INDEX($AE$2:$AE$1001,MATCH($A54,$AJ$2:$AJ$1001,0))) | G54: =IF($B54="","",INDEX($AG$2:$AG$1001,MATCH($A54,$AJ$2:$AJ$1001,0))) | H54: =IF($B54="","",INDEX($AF$2:$AF$1001,MATCH($A54,$AJ$2:$AJ$1001,0))) | Z54: =Shares!A54 | AA54: =Shares!B54 | AB54: =Shares!C54 | AC54: =Shares!D54 | AD54: =IF($Z54="",0,Shares!E54) -> 0 | AE54: =IF($Z54="",0,Shares!K54*Shares!J54) -> 0 | AF54: =IFERROR(AE54/$B$5,0) -> 0 | AG54: =IF($Z54="",0,Shares!M54) -> 0 | AH54: =IF($Z54="",0,Shares!N54) -> 0 | AI54: =IF($Z54="","",RANK(AE54,$AE$2:$AE$1001)+COUNTIF($AE$2:AE54,AE54)-1) | AJ54: =IF($AD54<0,COUNT($AJ$1:AJ53)+1,"") | AL54: ='All Ticker P&L'!A54 | AM54: ='All Ticker P&L'!B54 | AN54: ='All Ticker P&L'!C54 | AO54: ='All Ticker P&L'!D54 | AP54: =IF($AL54="",0,'All Ticker P&L'!E54) -> 0 | AQ54: =IF($AL54="",0,'All Ticker P&L'!J54*'All Ticker P&L'!I54) -> 0 | AR54: =IF($AL54="",0,'All Ticker P&L'!L54) -> 0 | AS54: =IF($AL54="",0,'All Ticker P&L'!M54) -> 0 | AT54: =IF($AL54="","",RANK(AR54,$AR$2:$AR$1001)+COUNTIF($AR$2:AR54,AR54)-1) | AU54: =IF($AL54="","",RANK(AV54,$AV$2:$AV$1001)+COUNTIF($AV$2:AV54,AV54)-1) | AV54: =-AR54 -> 0
A55: 7 | B55: =IFERROR(INDEX($Z$2:$Z$1001,MATCH($A55,$AJ$2:$AJ$1001,0)),"") | C55: =IF($B55="","",INDEX($AA$2:$AA$1001,MATCH($A55,$AJ$2:$AJ$1001,0))) | D55: =IF($B55="","",INDEX($AC$2:$AC$1001,MATCH($A55,$AJ$2:$AJ$1001,0))) | E55: =IF($B55="","",INDEX($AD$2:$AD$1001,MATCH($A55,$AJ$2:$AJ$1001,0))) | F55: =IF($B55="","",INDEX($AE$2:$AE$1001,MATCH($A55,$AJ$2:$AJ$1001,0))) | G55: =IF($B55="","",INDEX($AG$2:$AG$1001,MATCH($A55,$AJ$2:$AJ$1001,0))) | H55: =IF($B55="","",INDEX($AF$2:$AF$1001,MATCH($A55,$AJ$2:$AJ$1001,0))) | Z55: =Shares!A55 | AA55: =Shares!B55 | AB55: =Shares!C55 | AC55: =Shares!D55 | AD55: =IF($Z55="",0,Shares!E55) -> 0 | AE55: =IF($Z55="",0,Shares!K55*Shares!J55) -> 0 | AF55: =IFERROR(AE55/$B$5,0) -> 0 | AG55: =IF($Z55="",0,Shares!M55) -> 0 | AH55: =IF($Z55="",0,Shares!N55) -> 0 | AI55: =IF($Z55="","",RANK(AE55,$AE$2:$AE$1001)+COUNTIF($AE$2:AE55,AE55)-1) | AJ55: =IF($AD55<0,COUNT($AJ$1:AJ54)+1,"") | AL55: ='All Ticker P&L'!A55 | AM55: ='All Ticker P&L'!B55 | AN55: ='All Ticker P&L'!C55 | AO55: ='All Ticker P&L'!D55 | AP55: =IF($AL55="",0,'All Ticker P&L'!E55) -> 0 | AQ55: =IF($AL55="",0,'All Ticker P&L'!J55*'All Ticker P&L'!I55) -> 0 | AR55: =IF($AL55="",0,'All Ticker P&L'!L55) -> 0 | AS55: =IF($AL55="",0,'All Ticker P&L'!M55) -> 0 | AT55: =IF($AL55="","",RANK(AR55,$AR$2:$AR$1001)+COUNTIF($AR$2:AR55,AR55)-1) | AU55: =IF($AL55="","",RANK(AV55,$AV$2:$AV$1001)+COUNTIF($AV$2:AV55,AV55)-1) | AV55: =-AR55 -> 0
A56: 8 | B56: =IFERROR(INDEX($Z$2:$Z$1001,MATCH($A56,$AJ$2:$AJ$1001,0)),"") | C56: =IF($B56="","",INDEX($AA$2:$AA$1001,MATCH($A56,$AJ$2:$AJ$1001,0))) | D56: =IF($B56="","",INDEX($AC$2:$AC$1001,MATCH($A56,$AJ$2:$AJ$1001,0))) | E56: =IF($B56="","",INDEX($AD$2:$AD$1001,MATCH($A56,$AJ$2:$AJ$1001,0))) | F56: =IF($B56="","",INDEX($AE$2:$AE$1001,MATCH($A56,$AJ$2:$AJ$1001,0))) | G56: =IF($B56="","",INDEX($AG$2:$AG$1001,MATCH($A56,$AJ$2:$AJ$1001,0))) | H56: =IF($B56="","",INDEX($AF$2:$AF$1001,MATCH($A56,$AJ$2:$AJ$1001,0))) | Z56: =Shares!A56 | AA56: =Shares!B56 | AB56: =Shares!C56 | AC56: =Shares!D56 | AD56: =IF($Z56="",0,Shares!E56) -> 0 | AE56: =IF($Z56="",0,Shares!K56*Shares!J56) -> 0 | AF56: =IFERROR(AE56/$B$5,0) -> 0 | AG56: =IF($Z56="",0,Shares!M56) -> 0 | AH56: =IF($Z56="",0,Shares!N56) -> 0 | AI56: =IF($Z56="","",RANK(AE56,$AE$2:$AE$1001)+COUNTIF($AE$2:AE56,AE56)-1) | AJ56: =IF($AD56<0,COUNT($AJ$1:AJ55)+1,"") | AL56: ='All Ticker P&L'!A56 | AM56: ='All Ticker P&L'!B56 | AN56: ='All Ticker P&L'!C56 | AO56: ='All Ticker P&L'!D56 | AP56: =IF($AL56="",0,'All Ticker P&L'!E56) -> 0 | AQ56: =IF($AL56="",0,'All Ticker P&L'!J56*'All Ticker P&L'!I56) -> 0 | AR56: =IF($AL56="",0,'All Ticker P&L'!L56) -> 0 | AS56: =IF($AL56="",0,'All Ticker P&L'!M56) -> 0 | AT56: =IF($AL56="","",RANK(AR56,$AR$2:$AR$1001)+COUNTIF($AR$2:AR56,AR56)-1) | AU56: =IF($AL56="","",RANK(AV56,$AV$2:$AV$1001)+COUNTIF($AV$2:AV56,AV56)-1) | AV56: =-AR56 -> 0
A57: 9 | B57: =IFERROR(INDEX($Z$2:$Z$1001,MATCH($A57,$AJ$2:$AJ$1001,0)),"") | C57: =IF($B57="","",INDEX($AA$2:$AA$1001,MATCH($A57,$AJ$2:$AJ$1001,0))) | D57: =IF($B57="","",INDEX($AC$2:$AC$1001,MATCH($A57,$AJ$2:$AJ$1001,0))) | E57: =IF($B57="","",INDEX($AD$2:$AD$1001,MATCH($A57,$AJ$2:$AJ$1001,0))) | F57: =IF($B57="","",INDEX($AE$2:$AE$1001,MATCH($A57,$AJ$2:$AJ$1001,0))) | G57: =IF($B57="","",INDEX($AG$2:$AG$1001,MATCH($A57,$AJ$2:$AJ$1001,0))) | H57: =IF($B57="","",INDEX($AF$2:$AF$1001,MATCH($A57,$AJ$2:$AJ$1001,0))) | Z57: =Shares!A57 | AA57: =Shares!B57 | AB57: =Shares!C57 | AC57: =Shares!D57 | AD57: =IF($Z57="",0,Shares!E57) -> 0 | AE57: =IF($Z57="",0,Shares!K57*Shares!J57) -> 0 | AF57: =IFERROR(AE57/$B$5,0) -> 0 | AG57: =IF($Z57="",0,Shares!M57) -> 0 | AH57: =IF($Z57="",0,Shares!N57) -> 0 | AI57: =IF($Z57="","",RANK(AE57,$AE$2:$AE$1001)+COUNTIF($AE$2:AE57,AE57)-1) | AJ57: =IF($AD57<0,COUNT($AJ$1:AJ56)+1,"") | AL57: ='All Ticker P&L'!A57 | AM57: ='All Ticker P&L'!B57 | AN57: ='All Ticker P&L'!C57 | AO57: ='All Ticker P&L'!D57 | AP57: =IF($AL57="",0,'All Ticker P&L'!E57) -> 0 | AQ57: =IF($AL57="",0,'All Ticker P&L'!J57*'All Ticker P&L'!I57) -> 0 | AR57: =IF($AL57="",0,'All Ticker P&L'!L57) -> 0 | AS57: =IF($AL57="",0,'All Ticker P&L'!M57) -> 0 | AT57: =IF($AL57="","",RANK(AR57,$AR$2:$AR$1001)+COUNTIF($AR$2:AR57,AR57)-1) | AU57: =IF($AL57="","",RANK(AV57,$AV$2:$AV$1001)+COUNTIF($AV$2:AV57,AV57)-1) | AV57: =-AR57 -> 0
A58: 10 | B58: =IFERROR(INDEX($Z$2:$Z$1001,MATCH($A58,$AJ$2:$AJ$1001,0)),"") | C58: =IF($B58="","",INDEX($AA$2:$AA$1001,MATCH($A58,$AJ$2:$AJ$1001,0))) | D58: =IF($B58="","",INDEX($AC$2:$AC$1001,MATCH($A58,$AJ$2:$AJ$1001,0))) | E58: =IF($B58="","",INDEX($AD$2:$AD$1001,MATCH($A58,$AJ$2:$AJ$1001,0))) | F58: =IF($B58="","",INDEX($AE$2:$AE$1001,MATCH($A58,$AJ$2:$AJ$1001,0))) | G58: =IF($B58="","",INDEX($AG$2:$AG$1001,MATCH($A58,$AJ$2:$AJ$1001,0))) | H58: =IF($B58="","",INDEX($AF$2:$AF$1001,MATCH($A58,$AJ$2:$AJ$1001,0))) | Z58: =Shares!A58 | AA58: =Shares!B58 | AB58: =Shares!C58 | AC58: =Shares!D58 | AD58: =IF($Z58="",0,Shares!E58) -> 0 | AE58: =IF($Z58="",0,Shares!K58*Shares!J58) -> 0 | AF58: =IFERROR(AE58/$B$5,0) -> 0 | AG58: =IF($Z58="",0,Shares!M58) -> 0 | AH58: =IF($Z58="",0,Shares!N58) -> 0 | AI58: =IF($Z58="","",RANK(AE58,$AE$2:$AE$1001)+COUNTIF($AE$2:AE58,AE58)-1) | AJ58: =IF($AD58<0,COUNT($AJ$1:AJ57)+1,"") | AL58: ='All Ticker P&L'!A58 | AM58: ='All Ticker P&L'!B58 | AN58: ='All Ticker P&L'!C58 | AO58: ='All Ticker P&L'!D58 | AP58: =IF($AL58="",0,'All Ticker P&L'!E58) -> 0 | AQ58: =IF($AL58="",0,'All Ticker P&L'!J58*'All Ticker P&L'!I58) -> 0 | AR58: =IF($AL58="",0,'All Ticker P&L'!L58) -> 0 | AS58: =IF($AL58="",0,'All Ticker P&L'!M58) -> 0 | AT58: =IF($AL58="","",RANK(AR58,$AR$2:$AR$1001)+COUNTIF($AR$2:AR58,AR58)-1) | AU58: =IF($AL58="","",RANK(AV58,$AV$2:$AV$1001)+COUNTIF($AV$2:AV58,AV58)-1) | AV58: =-AR58 -> 0
